Workbook
Name Clinical_Performance: #REF!
Name Clinical_Performance: #REF!
Name DataRange: #REF!
Name DataRange: #REF!
Name DataRange: #REF!
Name DataRange: #REF!
Name DataRange: #REF!
Name DataRange: #REF!
Name DataRange: #REF!
Name DataRange: #REF!
Name DataRange: #REF!
Name DataRange: #REF!
Name DataRange: #REF!
Name DataRange: #REF!
Name DataRange: #REF!
Name DataRange: #REF!
Name DataRange: #REF!
Name DataRange: #REF!
Name DataRange: #REF!
Name DataRange: #REF!
Name DataRange: #REF!
Name DataRange: #REF!
Name DataRange: #REF!
Name DataRange: #REF!
Name DataRange: #REF!
Name DataRange: #REF!
Name DataRange: #REF!
Name DataRange: #REF!
Name HeaderRange: #REF!
Name HeaderRange: #REF!
Name HeaderRange: #REF!
Name HeaderRange: #REF!
Name HeaderRange: #REF!
Name HeaderRange: #REF!
Name HeaderRange: #REF!
Name HeaderRange: #REF!
Name HeaderRange: #REF!
Name HeaderRange: #REF!
Name HeaderRange: #REF!
Name HeaderRange: #REF!
Name HeaderRange: #REF!
Name HeaderRange: #REF!
Name HeaderRange: #REF!
Name HeaderRange: #REF!
Name HeaderRange: #REF!
Name HeaderRange: #REF!
Name HeaderRange: #REF!
Name HeaderRange: #REF!
Name HeaderRange: #REF!
Name HeaderRange: #REF!
Name HeaderRange: #REF!
Name HeaderRange: #REF!
Name HeaderRange: #REF!
Name HeaderRange: #REF!
Name SortRange: #REF!
Name SortRange: #REF!
Name SortRange: #REF!
Name SortRange: #REF!
Name SortRange: #REF!
Name SortRange: #REF!

Sheet JV QUARTER
B1: 42370 | C1: 42401 | D1: 42430 | E1: Q1 | H1: 42461 | I1: 42491 | J1: 42522 | K1: Q2
A2: Kendall | G2: Kendall
M3: Joint Venture - Q4 2015
A4: Total Patients | B4: 7558 | C4: 7752 | D4: 8404 | E4: =SUM(B4:D4) -> 23714 | G4: Total Patients | K4: =SUM(H4:J4) -> 0 | M4: Total Pts | N4: Arrival to Provider Greet | O4: Duplicate MSE | P4: Admitted Pts ALOS | Q4: Departed pts ALOS | R4: LPMSE + LPT | S4: AMA
A5: Arrival to Provider Greet | B5: 16 | C5: 16 | D5: 11 | E5: =((B5*B4)+(C5*C4)+(D5*D4))/SUM(B4:D4) -> 14.228051 | G5: Arrival to Provider Greet | K5: =SUMPRODUCT(H5:J5,H4:J4)/SUM(H4:J4) -> #DIV/0!
A6: Duplicate MSE | B6: 143 | C6: 171 | D6: 142 | E6: =SUM(B6:D6) -> 456 | G6: Duplicate MSE | K6: =SUM(H6:J6) -> 0 | M6: =SUM(K4,K37,K53,K69) -> 0 | N6: =((H5*H$4)+(I5*I$4)+(J5*J$4)+(H38*H$37)+(I38*I$37)+(J38*J$37)+(H54*H$53)+(I54*I$53)+(J54*J$53)+(H70*H$69)+(I70*I$69)+(J70*J$69))/SUM(E$4,E$37,E$53,E$69) -> 0 | O6: =SUM(K6,K39,K55,K71) -> 0 | P6: =((H10*H8)+(I10*I8)+(J10*J8)+(H43*H41)+(I43*I41)+(J43*J41)+(H59*H57)+(I59*I57)+(J59*J57)+(H75*H73)+(I75*I73)+(J75*J73))/SUM(K$8,K$41,K$57,K$73) -> #DIV/0! | Q6: =((H12*H13)+(I12*I13)+(J12*J13)+(H45*H46)+(I45*I46)+(J45*J46)+(H61*H62)+(I61*I62)+(J61*J62)+(H77*H78)+(I77*I78)+(J77*J78))/SUM(K$12,K$45,K$61,K$77) -> #DIV/0! | R6: =SUM(K14,K47,K63,K79) -> 0 | S6: =SUM(K16,K49,K65,K81) -> 0
A7: Duplicate MSE % | B7: =B6/B4 -> 0.018920349 | C7: =C6/C4 -> 0.022058824 | D7: =D6/D4 -> 0.016896716 | E7: =E6/E4 -> 0.019229147 | G7: Duplicate MSE % | H7: =H6/H4 -> #DIV/0! | I7: =I6/I4 -> #DIV/0! | J7: =J6/J4 -> #DIV/0! | K7: =K6/K4 -> #DIV/0! | O7: =(O6/M6) -> #DIV/0! | R7: =R6/M6 -> #DIV/0! | S7: =S6/M6 -> #DIV/0!
A8: Admitted Pts | B8: 1599 | C8: 1326 | D8: 1773 | E8: =SUM(B8:D8) -> 4698 | G8: Admitted Pts | K8: =SUM(H8:J8) -> 0
A9: Admitted Pts % | B9: =B8/B4 -> 0.21156391 | C9: =C8/C4 -> 0.17105263 | D9: =D8/D4 -> 0.21097097 | E9: =E8/E4 -> 0.19811082 | G9: Admitted Pts % | H9: =H8/H4 -> #DIV/0! | I9: =I8/I4 -> #DIV/0! | J9: =J8/J4 -> #DIV/0! | K9: =K8/K4 -> #DIV/0!
A10: Admitted Pts ALOS | B10: 459 | C10: 448 | D10: 362 | E10: =((B10*B8)+(C10*C8)+(D10*D8))/SUM(B8:D8) -> 419.28799 | G10: Admitted Pts ALOS | K10: =SUM(H10:J10) -> 0 | M10: Joint Venture - Q3 2015
A11: Departed Pts % | B11: =B12/B4 -> 0.78843609 | C11: =C12/C4 -> 0.82894737 | D11: =D12/D4 -> 0.78902903 | E11: =E12/E4 -> 0.80188918 | G11: Departed Pts % | H11: =H12/H4 -> #DIV/0! | I11: =I12/I4 -> #DIV/0! | J11: =J12/J4 -> #DIV/0! | K11: =K12/K4 -> #DIV/0! | M11: Total Pts | N11: Arrival to Provider Greet | O11: Duplicate MSE | P11: Admitted Pts ALOS | Q11: Departed pts ALOS | R11: LPMSE + LPT | S11: AMA
A12: Departed Pts | B12: =B4-B8 -> 5959 | C12: =C4-C8 -> 6426 | D12: =D4-D8 -> 6631 | E12: =SUM(B12:D12) -> 19016 | G12: Departed Pts | K12: =SUM(H12:J12) -> 0
A13: Departed pts ALOS | B13: 186 | C13: 194 | D13: 173 | E13: =((B13*B12)+(C13*C12)+(D13*D12))/SUM(B12:D12) -> 184.17023 | G13: Departed pts ALOS | K13: =SUMPRODUCT(H13:J13,H12:J12)/SUM(H12:J12) -> #DIV/0! | M13: =SUM(E4+E37+E53+E69) -> 50880 | N13: =((B5*B$4)+(C5*C$4)+(D5*D$4)+(B38*B$37)+(C38*C$37)+(D38*D$37)+(B54*B$53)+(C54*C$53)+(D54*D$53)+(B70*B$69)+(C70*C$69)+(D70*D$69))/SUM(E$69,E$53,E$37,E$4) -> 11.658943 | O13: =SUM(E6,E39,E55,E71) -> 1280 | P13: =((B10*B8)+(C10*C8)+(D10*D8)+(B43*B41)+(C43*C41)+(D43*D41)+(B59*B57)+(C59*C57)+(D59*D57)+(B75*B73)+(C75*C73)+(D75*D73))/SUM(E$73,E$57,E$41,E$8) -> 384.60894 | Q13: =((B12*B13)+(C12*C13)+(D12*D13)+(B45*B46)+(C45*C46)+(D45*D46)+(B61*B62)+(C61*C62)+(D61*D62)+(B77*B78)+(C77*C78)+(D77*D78))/SUM(E$12,E$45,E$61,E$77) -> 170.38159 | R13: =SUM(E14,E47,E63,E79) -> 1323 | S13: =SUM(E16,E49,E65,E81) -> 664
A14: LPMSE + LPT | B14: =3+284 -> 287 | C14: 305 | D14: 146 | E14: =SUM(B14:D14) -> 738 | G14: LPMSE + LPT | K14: =SUM(H14:J14) -> 0 | O14: =(O13/M13) -> 0.025157233 | R14: =R13/M13 -> 0.026002358 | S14: =S13/M13 -> 0.013050314
A15: LPMSE + LPT % | B15: =B14/B4 -> 0.037973009 | C15: =C14/C4 -> 0.039344685 | D15: =D14/D4 -> 0.01737268 | E15: =E14/E4 -> 0.031120857 | G15: LPMSE + LPT % | H15: =H14/H4 -> #DIV/0! | I15: =I14/I4 -> #DIV/0! | J15: =J14/J4 -> #DIV/0! | K15: =K14/K4 -> #DIV/0!
A16: AMA | B16: 54 | C16: 47 | D16: 55 | E16: =SUM(B16:D16) -> 156 | G16: AMA | K16: =SUM(H16:J16) -> 0
A17: AMA % | B17: =B16/B4 -> 0.0071447473 | C17: =C16/C4 -> 0.0060629515 | D17: =D16/D4 -> 0.0065445026 | E17: =E16/E4 -> 0.0065783925 | G17: AMA % | H17: =H16/H4 -> #DIV/0! | I17: =I16/I4 -> #DIV/0! | J17: =J16/J4 -> #DIV/0! | K17: =K16/K4 -> #DIV/0!
A18: Kendall PEDS | G18: Kendall PEDS
A20: Total Patients | B20: 1713 | C20: 2067 | D20: 2197 | E20: =SUM(B20:D20) -> 5977 | G20: Total Patients | K20: =SUM(H20:J20) -> 0
A21: Arrival to Provider Greet | E21: =((B21*B20)+(C21*C20)+(D21*D20))/SUM(B20:D20) -> 0 | G21: Arrival to Provider Greet | K21: =SUMPRODUCT(H21:J21,H20:J20)/SUM(H20:J20) -> #DIV/0!
A22: Duplicate MSE | E22: =SUM(B22:D22) -> 0 | G22: Duplicate MSE | K22: =SUM(H22:J22) -> 0
A23: Duplicate MSE % | B23: =B22/B20 -> 0 | C23: =C22/C20 -> 0 | D23: =D22/D20 -> 0 | E23: =E22/E20 -> 0 | G23: Duplicate MSE % | H23: =H22/H20 -> #DIV/0! | I23: =I22/I20 -> #DIV/0! | J23: =J22/J20 -> #DIV/0! | K23: =K22/K20 -> #DIV/0!
A24: Admitted Pts | E24: =SUM(B24:D24) -> 0 | G24: Admitted Pts | K24: =SUM(H24:J24) -> 0
A25: Admitted Pts % | B25: =B24/B20 -> 0 | C25: =C24/C20 -> 0 | D25: =D24/D20 -> 0 | E25: =E24/E20 -> 0 | G25: Admitted Pts % | H25: =H24/H20 -> #DIV/0! | I25: =I24/I20 -> #DIV/0! | J25: =J24/J20 -> #DIV/0! | K25: =K24/K20 -> #DIV/0!
A26: Admitted Pts ALOS | E26: =((B26*B24)+(C26*C24)+(D26*D24))/SUM(B24:D24) -> #DIV/0! | G26: Admitted Pts ALOS | K26: =SUM(H26:J26) -> 0
A27: Departed Pts % | B27: =B28/B20 -> 0 | C27: =C28/C20 -> 0 | D27: =D28/D20 -> 0 | E27: =E28/E20 -> 0 | G27: Departed Pts % | H27: =H28/H20 -> #DIV/0! | I27: =I28/I20 -> #DIV/0! | J27: =J28/J20 -> #DIV/0! | K27: =K28/K20 -> #DIV/0!
A28: Departed Pts | E28: =SUM(B28:D28) -> 0 | G28: Departed Pts | K28: =SUM(H28:J28) -> 0
A29: Departed pts ALOS | E29: =((B29*B28)+(C29*C28)+(D29*D28))/SUM(B28:D28) -> #DIV/0! | G29: Departed pts ALOS | K29: =SUMPRODUCT(H29:J29,H28:J28)/SUM(H28:J28) -> #DIV/0!
A30: LPMSE + LPT | E30: =SUM(B30:D30) -> 0 | G30: LPMSE + LPT | K30: =SUM(H30:J30) -> 0
A31: LPMSE + LPT % | B31: =B30/B20 -> 0 | C31: =C30/C20 -> 0 | D31: =D30/D20 -> 0 | E31: =E30/E20 -> 0 | G31: LPMSE + LPT % | H31: =H30/H20 -> #DIV/0! | I31: =I30/I20 -> #DIV/0! | J31: =J30/J20 -> #DIV/0! | K31: =K30/K20 -> #DIV/0!
A32: AMA | E32: =SUM(B32:D32) -> 0 | G32: AMA | K32: =SUM(H32:J32) -> 0
A33: AMA % | B33: =B32/B20 -> 0 | C33: =C32/C20 -> 0 | D33: =D32/D20 -> 0 | E33: =E32/E20 -> 0 | G33: AMA % | H33: =H32/H20 -> #DIV/0! | I33: =I32/I20 -> #DIV/0! | J33: =J32/J20 -> #DIV/0! | K33: =K32/K20 -> #DIV/0!
A35: JFK Main | G35: JFK Main
A37: Total Pts | B37: 7515 | C37: 7460 | D37: 8153 | E37: =SUM(B37:D37) -> 23128 | G37: Total Pts | K37: =SUM(H37:J37) -> 0
A38: Arrival to Provider Greet | B38: 10 | C38: 9 | D38: 10 | E38: =((B38*B37)+(C38*C37)+(D38*D37))/SUM(B37:D37) -> 9.6774473 | G38: Arrival to Provider Greet | K38: =SUMPRODUCT(H38:J38,H37:J37)/SUM(H37:J37) -> #DIV/0!
A39: Duplicate MSE | B39: 303 | C39: 308 | D39: 143 | E39: =SUM(B39:D39) -> 754 | G39: Duplicate MSE | K39: =SUM(H39:J39) -> 0
A40: Duplicate MSE % | B40: =B39/B37 -> 0.040319361 | C40: =C39/C37 -> 0.041286863 | D40: =D39/D37 -> 0.017539556 | E40: =E39/E37 -> 0.032601176 | G40: Duplicate MSE % | H40: =H39/H37 -> #DIV/0! | I40: =I39/I37 -> #DIV/0! | J40: =J39/J37 -> #DIV/0! | K40: =K39/K37 -> #DIV/0!
A41: Admitted Pts | B41: 3008 | C41: 2853 | D41: 3055 | E41: =SUM(B41:D41) -> 8916 | G41: Admitted Pts | K41: =SUM(H41:J41) -> 0
A42: Admitted Pts % | B42: =B41/B37 -> 0.40026613 | C42: =C41/C37 -> 0.38243968 | D42: =D41/D37 -> 0.3747087 | E42: =E41/E37 -> 0.38550675 | G42: Admitted Pts % | H42: =H41/H37 -> #DIV/0! | I42: =I41/I37 -> #DIV/0! | J42: =J41/J37 -> #DIV/0! | K42: =K41/K37 -> #DIV/0!
A43: Admitted Pts ALOS | B43: 352 | C43: 392 | D43: 367 | E43: =((B43*B41)+(C43*C41)+(D43*D41))/SUM(B41:D41) -> 369.9391 | G43: Admitted Pts ALOS | K43: =SUM(H43:J43) -> 0
A44: Departed Pts % | B44: =B45/B37 -> 0.59973387 | C44: =C45/C37 -> 0.61756032 | D44: =D45/D37 -> 0.6252913 | E44: =E45/E37 -> 0.61449325 | G44: Departed Pts % | H44: =H45/H37 -> #DIV/0! | I44: =I45/I37 -> #DIV/0! | J44: =J45/J37 -> #DIV/0! | K44: =K45/K37 -> #DIV/0!
A45: Departed Pts | B45: =B37-B41 -> 4507 | C45: =C37-C41 -> 4607 | D45: =D37-D41 -> 5098 | E45: =SUM(B45:D45) -> 14212 | G45: Departed Pts | K45: =SUM(H45:J45) -> 0
A46: Departed pts ALOS | B46: 165 | C46: 175 | D46: 177 | E46: =((B46*B45)+(C46*C45)+(D46*D45))/SUM(B45:D45) -> 172.54616 | G46: Departed pts ALOS | K46: =SUMPRODUCT(H46:J46,H45:J45)/SUM(H45:J45) -> #DIV/0!
A47: LPMSE + LPT | B47: =3+88 -> 91 | C47: 180 | D47: 304 | E47: =SUM(B47:D47) -> 575 | G47: LPMSE + LPT | K47: =SUM(H47:J47) -> 0
A48: LPMSE + LPT % | B48: =B47/B37 -> 0.012109115 | C48: =C47/C37 -> 0.024128686 | D48: =D47/D37 -> 0.037286888 | E48: =E47/E37 -> 0.02486164 | G48: LPMSE + LPT % | H48: =H47/H37 -> #DIV/0! | I48: =I47/I37 -> #DIV/0! | J48: =J47/J37 -> #DIV/0! | K48: =K47/K37 -> #DIV/0!
A49: AMA | B49: 129 | C49: 177 | D49: 155 | E49: =SUM(B49:D49) -> 461 | G49: AMA | K49: =SUM(H49:J49) -> 0
A50: AMA % | B50: =B49/B37 -> 0.017165669 | C50: =C49/C37 -> 0.023726542 | D50: =D49/D37 -> 0.019011407 | E50: =E49/E37 -> 0.019932549 | G50: AMA % | H50: =H49/H37 -> #DIV/0! | I50: =I49/I37 -> #DIV/0! | J50: =J49/J37 -> #DIV/0! | K50: =K49/K37 -> #DIV/0!
A51: JFK BB | G51: JFK BB
A53: Total Pts | B53: 863 | C53: 827 | D53: 806 | E53: =SUM(B53:D53) -> 2496 | G53: Total Pts | K53: =SUM(H53:J53) -> 0
A54: Arrival to Provider Greet | B54: 9 | C54: 9 | D54: 8 | E54: =((B54*B53)+(C54*C53)+(D54*D53))/SUM(B53:D53) -> 8.6770833 | G54: Arrival to Provider Greet | K54: =SUMPRODUCT(H54:J54,H53:J53)/SUM(H53:J53) -> #DIV/0!
A55: Duplicate MSE | B55: 26 | C55: 20 | D55: 10 | E55: =SUM(B55:D55) -> 56 | G55: Duplicate MSE | K55: =SUM(H55:J55) -> 0
A56: Duplicate MSE % | B56: =B55/B53 -> 0.030127462 | C56: =C55/C53 -> 0.024183797 | D56: =D55/D53 -> 0.012406948 | E56: =E55/E53 -> 0.022435897 | G56: Duplicate MSE % | H56: ='JV DATA YTD'!K39 -> 0 | I56: ='JV DATA YTD'!L39 -> 0 | J56: ='JV DATA YTD'!M39 -> 0 | K56: =K55/K53 -> #DIV/0!
A57: Admitted Pts | B57: 100 | C57: 88 | D57: 74 | E57: =SUM(B57:D57) -> 262 | G57: Admitted Pts | K57: =SUM(H57:J57) -> 0
A58: Admitted Pts % | B58: =B57/B53 -> 0.11587486 | C58: =C57/C53 -> 0.10640871 | D58: =D57/D53 -> 0.091811414 | E58: =E57/E53 -> 0.10496795 | G58: Admitted Pts % | H58: ='JV DATA YTD'!K41 -> 0 | I58: ='JV DATA YTD'!L41 -> 0 | J58: ='JV DATA YTD'!M41 -> 0 | K58: =K57/K53 -> #DIV/0!
A59: Admitted Pts ALOS | B59: 269 | C59: 270 | D59: 279 | E59: =((B59*B57)+(C59*C57)+(D59*D57))/SUM(B57:D57) -> 272.16031 | G59: Admitted Pts ALOS | K59: =SUM(H59:J59) -> 0
A60: Departed Pts % | B60: =B61/B53 -> 0.88412514 | C60: =C61/C53 -> 0.89359129 | D60: =D61/D53 -> 0.90818859 | E60: =E61/E53 -> 0.89503205 | G60: Departed Pts % | H60: ='JV DATA YTD'!K43 -> 0 | I60: ='JV DATA YTD'!L43 -> 0 | J60: ='JV DATA YTD'!M43 -> 0 | K60: =K61/K53 -> #DIV/0!
A61: Departed Pts | B61: =B53-B57 -> 763 | C61: =C53-C57 -> 739 | D61: =D53-D57 -> 732 | E61: =SUM(B61:D61) -> 2234 | G61: Departed Pts | K61: =SUM(H61:J61) -> 0
A62: Departed pts ALOS | B62: 92 | C62: 98 | D62: 99 | E62: =((B62*B61)+(C62*C61)+(D62*D61))/SUM(B61:D61) -> 96.278424 | G62: Departed pts ALOS | K62: =SUMPRODUCT(H62:J62,H61:J61)/SUM(H61:J61) -> #DIV/0!
A63: LPMSE + LPT | B63: =3+1 -> 4 | C63: 0 | D63: 4 | E63: =SUM(B63:D63) -> 8 | G63: LPMSE + LPT | K63: =SUM(H63:J63) -> 0
A64: LPMSE + LPT % | B64: =B63/B53 -> 0.0046349942 | C64: =C63/C53 -> 0 | D64: =D63/D53 -> 0.0049627792 | E64: =E63/E53 -> 0.0032051282 | G64: LPMSE + LPT % | H64: =H63/H53 -> #DIV/0! | I64: =I63/I53 -> #DIV/0! | J64: =J63/J53 -> #DIV/0! | K64: =K63/K53 -> #DIV/0!
A65: AMA | B65: 9 | C65: 9 | D65: 11 | E65: =SUM(B65:D65) -> 29 | G65: AMA | K65: =SUM(H65:J65) -> 0
A66: AMA % | B66: =B65/B53 -> 0.010428737 | C66: =C65/C53 -> 0.010882709 | D66: =D65/D53 -> 0.013647643 | E66: =E65/E53 -> 0.01161859 | G66: AMA % | H66: =H65/H53 -> #DIV/0! | I66: =I65/I53 -> #DIV/0! | J66: =J65/J53 -> #DIV/0! | K66: =K65/K53 -> #DIV/0!
A67: JFK PBG | G67: JFK PBG
A69: Total Pts | B69: 469 | C69: 502 | D69: 571 | E69: =SUM(B69:D69) -> 1542 | G69: Total Pts | K69: =SUM(H69:J69) -> 0
A70: Arrival to Provider Greet | B70: 6 | C70: 7 | D70: 7 | E70: =((B70*B69)+(C70*C69)+(D70*D69))/SUM(B69:D69) -> 6.6958495 | G70: Arrival to Provider Greet | K70: =SUMPRODUCT(H70:J70,H69:J69)/SUM(H69:J69) -> #DIV/0!
A71: Duplicate MSE | B71: 8 | C71: 2 | D71: 4 | E71: =SUM(B71:D71) -> 14 | G71: Duplicate MSE | K71: =SUM(H71:J71) -> 0
A72: Duplicate MSE % | B72: =B71/B69 -> 0.017057569 | C72: =C71/C69 -> 0.0039840637 | D72: =D71/D69 -> 0.0070052539 | E72: =E71/E69 -> 0.009079118 | G72: Duplicate MSE % | H72: =H71/H69 -> #DIV/0! | I72: =I71/I69 -> #DIV/0! | J72: =J71/J69 -> #DIV/0! | K72: =K71/K69 -> #DIV/0!
A73: Admitted Pts | B73: 13 | C73: 1 | D73: 8 | E73: =SUM(B73:D73) -> 22 | G73: Admitted Pts | K73: =SUM(H73:J73) -> 0
A74: Admitted Pts % | B74: =B73/B69 -> 0.02771855 | C74: =C73/C69 -> 0.0019920319 | D74: =D73/D69 -> 0.014010508 | E74: =E73/E69 -> 0.014267185 | G74: Admitted Pts % | H74: =H73/H69 -> #DIV/0! | I74: =I73/I69 -> #DIV/0! | J74: =J73/J69 -> #DIV/0! | K74: =K73/K69 -> #DIV/0!
A75: Admitted Pts ALOS | B75: 261 | C75: 204 | D75: 275 | E75: =((B75*B73)+(C75*C73)+(D75*D73))/SUM(B73:D73) -> 263.5 | G75: Admitted Pts ALOS | K75: =SUM(H75:J75) -> 0
A76: Departed Pts % | B76: =B77/B69 -> 0.97228145 | C76: =C77/C69 -> 0.99800797 | D76: =D77/D69 -> 0.98598949 | E76: =E77/E69 -> 0.98573281 | G76: Departed Pts % | H76: =H77/H69 -> #DIV/0! | I76: =I77/I69 -> #DIV/0! | J76: =J77/J69 -> #DIV/0! | K76: =K77/K69 -> #DIV/0!
A77: Departed Pts | B77: =B69-B73 -> 456 | C77: =C69-C73 -> 501 | D77: =D69-D73 -> 563 | E77: =SUM(B77:D77) -> 1520 | G77: Departed Pts | K77: =SUM(H77:J77) -> 0
A78: Departed pts ALOS | B78: 77 | C78: 88 | D78: 93 | E78: =((B78*B77)+(C78*C77)+(D78*D77))/SUM(B77:D77) -> 86.551974 | G78: Departed pts ALOS | K78: =SUMPRODUCT(H78:J78,H77:J77)/SUM(H77:J77) -> #DIV/0!
A79: LPMSE + LPT | B79: =0+1 -> 1 | C79: 0 | D79: 1 | E79: =SUM(B79:D79) -> 2 | G79: LPMSE + LPT | K79: =SUM(H79:J79) -> 0
A80: LPMSE + LPT % | B80: =B79/B69 -> 0.0021321962 | C80: =C79/C69 -> 0 | D80: =D79/D69 -> 0.0017513135 | E80: =E79/E69 -> 0.0012970169 | G80: LPMSE + LPT % | H80: =H79/H69 -> #DIV/0! | I80: =I79/I69 -> #DIV/0! | J80: =J79/J69 -> #DIV/0! | K80: =K79/K69 -> #DIV/0!
A81: AMA | B81: 5 | C81: 7 | D81: 6 | E81: =SUM(B81:D81) -> 18 | G81: AMA | K81: =SUM(H81:J81) -> 0
A82: AMA % | B82: =B81/B69 -> 0.010660981 | C82: =C81/C69 -> 0.013944223 | D82: =D81/D69 -> 0.010507881 | E82: =E81/E69 -> 0.011673152 | G82: AMA % | H82: =H81/H69 -> #DIV/0! | I82: =I81/I69 -> #DIV/0! | J82: =J81/J69 -> #DIV/0! | K82: =K81/K69 -> #DIV/0!

Sheet JV DATA YTD
B1: 42370 | C1: 42401 | D1: 42430 | E1: 42461 | F1: 42491 | G1: 42522 | H1: 42552 | I1: 42583 | J1: 42614 | K1: 42644 | L1: 42675 | M1: 42705 | N1: 2016 YTD
A2: Kendall
P3: YTD
A4: Total Pts | B4: 7558 | C4: 7752 | D4: 8404 | N4: =SUM(B4:M4) -> 23714 | P4: Total Pts | Q4: Arr to Greet | R4: Duplicate MSE | S4: Departed pts ALOS | T4: LPMSE + LPT | U4: AMA
A5: Arrival to Provider Greet (Min) | B5: 16 | C5: 16 | D5: 11 | N5: =SUMPRODUCT(B5:K5,B4:K4)/SUM(B4:K4) -> 14.228051
A6: Duplicate MSE | B6: 143 | C6: 171 | D6: 142 | N6: =SUM(B6:M6) -> 456 | P6: =SUM(N4,N36,N52,N68) -> 50880 | Q6: =((N5*N4)+(N37*N36)+(N53*N52)+(N69*N68))/SUM(N68,N52,N36,N4) -> 11.658943 | R6: =SUM(N6,N38,N54,N70) -> 1280 | S6: =((N13*N12)+(N45*N44)+(N61*N60)+(N77*N76))/SUM(N76,N60,N44,N12) -> 170.38159 | T6: =SUM(N14,N46,N62,N78) -> 1323 | U6: =SUM(N16,N48,N64,N80) -> 664
A7: Duplicate MSE % | B7: =B6/B4 -> 0.018920349 | C7: =IFERROR(C6/C4,0) -> 0.022058824 | D7: =IFERROR(D6/D4,0) -> 0.016896716 | E7: =IFERROR(E6/E4,0) -> 0 | F7: =IFERROR(F6/F4,0) -> 0 | G7: =IFERROR(G6/G4,0) -> 0 | H7: =IFERROR(H6/H4,0) -> 0 | I7: =IFERROR(I6/I4,0) -> 0 | J7: =IFERROR(J6/J4,0) -> 0 | ... M7: =IFERROR(M6/M4,0) -> 0 | N7: =N6/N4 -> 0.019229147 | R7: =R6/P6 -> 0.025157233 | T7: =T6/P6 -> 0.026002358 | U7: =U6/P6 -> 0.013050314
A8: Admitted Pts (HCA Dashboard) | B8: 1599 | C8: 1326 | D8: 1773 | N8: =SUM(B8:M8) -> 4698
A9: % Admitted Pts (HCA Dashboard) | B9: =B8/B4 -> 0.21156391 | C9: =IFERROR(C8/C4,0) -> 0.17105263 | D9: =IFERROR(D8/D4,0) -> 0.21097097 | E9: =IFERROR(E8/E4,0) -> 0 | F9: =IFERROR(F8/F4,0) -> 0 | G9: =IFERROR(G8/G4,0) -> 0 | H9: =IFERROR(H8/H4,0) -> 0 | I9: =IFERROR(I8/I4,0) -> 0 | J9: =IFERROR(J8/J4,0) -> 0 | ... M9: =IFERROR(M8/M4,0) -> 0 | N9: =N8/N4 -> 0.19811082
A10: Admitted Pts ALOS (HCA Dashboard) | B10: 459 | C10: 448 | D10: 362 | N10: =SUM(B10:M10) -> 1269 | P10: As of January
A11: Departed Pts % | B11: =B12/B4 -> 0.78843609 | C11: =IFERROR(C12/C4,0) -> 0.82894737 | D11: =IFERROR(D12/D4,0) -> 0.78902903 | E11: =IFERROR(E12/E4,0) -> 0 | F11: =IFERROR(F12/F4,0) -> 0 | G11: =IFERROR(G12/G4,0) -> 0 | H11: =IFERROR(H12/H4,0) -> 0 | I11: =IFERROR(I12/I4,0) -> 0 | J11: =IFERROR(J12/J4,0) -> 0 | ... M11: =IFERROR(M12/M4,0) -> 0 | N11: =N12/N4 -> 0.80188918 | P11: Total Pts | Q11: Arr to Greet | R11: Duplicate MSE | S11: Departed pts ALOS | T11: LPMSE + LPT | U11: AMA
A12: Departed Pts | B12: =B4-B8 -> 5959 | C12: =C4-C8 -> 6426 | D12: =D4-D8 -> 6631 | N12: =SUM(B12:M12) -> 19016
A13: Departed pts ALOS | B13: 186 | C13: 194 | D13: 173 | N13: =SUMPRODUCT(B13:M13,B12:M12)/SUM(B12:M12) -> 184.17023 | P13: =SUM(B4,B36,B52,B68) -> 16405 | Q13: =((B5*B4)+(B37*B36)+(B53*B52)+(B69*B68))/SUM(B68,B52,B36,B4) -> 12.597318 | R13: =SUM(B6,B38,B54,B70) -> 480 | S13: =((B13*B12)+(B45*B44)+(B61*B60)+(B77*B76))/SUM(B76,B60,B44,B12) -> 167.50852 | T13: =SUM(B14,B46,B62,B78) -> 383 | U13: =SUM(B16,B48,B64,B80) -> 197
A14: LPMSE + LPT (HCA Dashboard) | B14: =3+284 -> 287 | C14: 305 | D14: 146 | N14: =SUM(B14:M14) -> 738 | R14: =R13/P13 -> 0.029259372 | T14: =T13/P13 -> 0.023346541 | U14: =U13/P13 -> 0.012008534
A15: LPMSE + LPT % | B15: =B14/B4 -> 0.037973009 | C15: =IFERROR(C14/C4,0) -> 0.039344685 | D15: =IFERROR(D14/D4,0) -> 0.01737268 | E15: =IFERROR(E14/E4,0) -> 0 | F15: =IFERROR(F14/F4,0) -> 0 | G15: =IFERROR(G14/G4,0) -> 0 | H15: =IFERROR(H14/H4,0) -> 0 | I15: =IFERROR(I14/I4,0) -> 0 | J15: =IFERROR(J14/J4,0) -> 0 | ... M15: =IFERROR(M14/M4,0) -> 0 | N15: =N14/N4 -> 0.031120857
A16: AMA | B16: 54 | C16: 47 | D16: 55 | N16: =SUM(B16:M16) -> 156
A17: AMA % | B17: =B16/B4 -> 0.0071447473 | C17: =IFERROR(C16/C4,0) -> 0.0060629515 | D17: =IFERROR(D16/D4,0) -> 0.0065445026 | E17: =IFERROR(E16/E4,0) -> 0 | F17: =IFERROR(F16/F4,0) -> 0 | G17: =IFERROR(G16/G4,0) -> 0 | H17: =IFERROR(H16/H4,0) -> 0 | I17: =IFERROR(I16/I4,0) -> 0 | J17: =IFERROR(J16/J4,0) -> 0 | ... M17: =IFERROR(M16/M4,0) -> 0 | N17: =N16/N4 -> 0.0065783925
A18: Kendall PEDS
A20: Total Pts | B20: 7558 | C20: 2067 | D20: 2197 | N20: =SUM(B20:M20) -> 11822
A21: Arrival to Provider Greet (Min) | N21: =SUMPRODUCT(B21:K21,B20:K20)/SUM(B20:K20) -> 0
A22: Duplicate MSE | N22: =SUM(B22:M22) -> 0
A23: Duplicate MSE % | B23: =B22/B20 -> 0 | C23: =IFERROR(C22/C20,0) -> 0 | D23: =IFERROR(D22/D20,0) -> 0 | E23: =IFERROR(E22/E20,0) -> 0 | F23: =IFERROR(F22/F20,0) -> 0 | G23: =IFERROR(G22/G20,0) -> 0 | H23: =IFERROR(H22/H20,0) -> 0 | I23: =IFERROR(I22/I20,0) -> 0 | J23: =IFERROR(J22/J20,0) -> 0 | ... M23: =IFERROR(M22/M20,0) -> 0 | N23: =N22/N20 -> 0
A24: Admitted Pts (HCA Dashboard) | N24: =SUM(B24:M24) -> 0
A25: % Admitted Pts (HCA Dashboard) | B25: =B24/B20 -> 0 | C25: =IFERROR(C24/C20,0) -> 0 | D25: =IFERROR(D24/D20,0) -> 0 | E25: =IFERROR(E24/E20,0) -> 0 | F25: =IFERROR(F24/F20,0) -> 0 | G25: =IFERROR(G24/G20,0) -> 0 | H25: =IFERROR(H24/H20,0) -> 0 | I25: =IFERROR(I24/I20,0) -> 0 | J25: =IFERROR(J24/J20,0) -> 0 | ... M25: =IFERROR(M24/M20,0) -> 0 | N25: =N24/N20 -> 0
A26: Admitted Pts ALOS (HCA Dashboard) | N26: =SUM(B26:M26) -> 0
A27: Departed Pts % | B27: =B28/B20 -> 1 | C27: =IFERROR(C28/C20,0) -> 1 | D27: =IFERROR(D28/D20,0) -> 1 | E27: =IFERROR(E28/E20,0) -> 0 | F27: =IFERROR(F28/F20,0) -> 0 | G27: =IFERROR(G28/G20,0) -> 0 | H27: =IFERROR(H28/H20,0) -> 0 | I27: =IFERROR(I28/I20,0) -> 0 | J27: =IFERROR(J28/J20,0) -> 0 | ... M27: =IFERROR(M28/M20,0) -> 0 | N27: =N28/N20 -> 1
A28: Departed Pts | B28: =B20-B24 -> 7558 | C28: =C20-C24 -> 2067 | D28: =D20-D24 -> 2197 | N28: =SUM(B28:M28) -> 11822
A29: Departed pts ALOS | N29: =SUMPRODUCT(B29:M29,B28:M28)/SUM(B28:M28) -> 0
A30: LPMSE + LPT (HCA Dashboard) | N30: =SUM(B30:M30) -> 0
A31: LPMSE + LPT % | B31: =B30/B20 -> 0 | C31: =IFERROR(C30/C20,0) -> 0 | D31: =IFERROR(D30/D20,0) -> 0 | E31: =IFERROR(E30/E20,0) -> 0 | F31: =IFERROR(F30/F20,0) -> 0 | G31: =IFERROR(G30/G20,0) -> 0 | H31: =IFERROR(H30/H20,0) -> 0 | I31: =IFERROR(I30/I20,0) -> 0 | J31: =IFERROR(J30/J20,0) -> 0 | ... M31: =IFERROR(M30/M20,0) -> 0 | N31: =N30/N20 -> 0
A32: AMA | N32: =SUM(B32:M32) -> 0
A33: AMA % | B33: =B32/B20 -> 0 | C33: =IFERROR(C32/C20,0) -> 0 | D33: =IFERROR(D32/D20,0) -> 0 | E33: =IFERROR(E32/E20,0) -> 0 | F33: =IFERROR(F32/F20,0) -> 0 | G33: =IFERROR(G32/G20,0) -> 0 | H33: =IFERROR(H32/H20,0) -> 0 | I33: =IFERROR(I32/I20,0) -> 0 | J33: =IFERROR(J32/J20,0) -> 0 | ... M33: =IFERROR(M32/M20,0) -> 0 | N33: =N32/N20 -> 0
A34: JFK Main
A36: Total Pts | B36: 7515 | C36: 7460 | D36: 8153 | N36: =SUM(B36:M36) -> 23128
A37: Arrival to Provider Greet (Min) | B37: 10 | C37: 9 | D37: 10 | N37: =SUMPRODUCT(B37:M37,B36:M36)/SUM(B36:M36) -> 9.6774473
A38: Duplicate MSE | B38: 303 | C38: 308 | D38: 143 | N38: =SUM(B38:M38) -> 754
A39: Duplicate MSE % | B39: =B38/B36 -> 0.040319361 | C39: =IFERROR(C38/C36,0) -> 0.041286863 | D39: =IFERROR(D38/D36,0) -> 0.017539556 | E39: =IFERROR(E38/E36,0) -> 0 | F39: =IFERROR(F38/F36,0) -> 0 | G39: =IFERROR(G38/G36,0) -> 0 | H39: =IFERROR(H38/H36,0) -> 0 | I39: =IFERROR(I38/I36,0) -> 0 | J39: =IFERROR(J38/J36,0) -> 0 | ... M39: =IFERROR(M38/M36,0) -> 0 | N39: =N38/N36 -> 0.032601176
A40: Admitted Pts (HCA Dashboard) | B40: 3008 | C40: 2853 | D40: 3055 | N40: =SUM(B40:M40) -> 8916
A41: Admitted Pts % (HCA Dashboard) | B41: =B40/B36 -> 0.40026613 | C41: =IFERROR(C40/C36,0) -> 0.38243968 | D41: =IFERROR(D40/D36,0) -> 0.3747087 | E41: =IFERROR(E40/E36,0) -> 0 | F41: =IFERROR(F40/F36,0) -> 0 | G41: =IFERROR(G40/G36,0) -> 0 | H41: =IFERROR(H40/H36,0) -> 0 | I41: =IFERROR(I40/I36,0) -> 0 | J41: =IFERROR(J40/J36,0) -> 0 | ... M41: =IFERROR(M40/M36,0) -> 0 | N41: =N40/N36 -> 0.38550675
A42: Admitted Pts ALOS (HCA Dashboard) | B42: 352 | C42: 392 | D42: 367 | N42: =SUM(B42:M42) -> 1111
A43: Departed Pts % | B43: =B44/B36 -> 0.59973387 | C43: =IFERROR(C44/C36,0) -> 0.61756032 | D43: =IFERROR(D44/D36,0) -> 0.6252913 | E43: =IFERROR(E44/E36,0) -> 0 | F43: =IFERROR(F44/F36,0) -> 0 | G43: =IFERROR(G44/G36,0) -> 0 | H43: =IFERROR(H44/H36,0) -> 0 | I43: =IFERROR(I44/I36,0) -> 0 | J43: =IFERROR(J44/J36,0) -> 0 | ... M43: =IFERROR(M44/M36,0) -> 0 | N43: =N44/N36 -> 0.61449325
A44: Departed Pts | B44: =B36-B40 -> 4507 | C44: =C36-C40 -> 4607 | D44: =D36-D40 -> 5098 | N44: =SUM(B44:M44) -> 14212
A45: Departed pts ALOS | B45: 165 | C45: 175 | D45: 177 | N45: =SUMPRODUCT(B45:M45,B44:M44)/SUM(B44:M44) -> 172.54616
A46: LPMSE + LPT | B46: =3+88 -> 91 | C46: 180 | D46: 304 | N46: =SUM(B46:M46) -> 575
A47: LPMSE + LPT % | B47: =B46/B36 -> 0.012109115 | C47: =IFERROR(C46/C36,0) -> 0.024128686 | D47: =IFERROR(D46/D36,0) -> 0.037286888 | E47: =IFERROR(E46/E36,0) -> 0 | F47: =IFERROR(F46/F36,0) -> 0 | G47: =IFERROR(G46/G36,0) -> 0 | H47: =IFERROR(H46/H36,0) -> 0 | I47: =IFERROR(I46/I36,0) -> 0 | J47: =IFERROR(J46/J36,0) -> 0 | ... M47: =IFERROR(M46/M36,0) -> 0 | N47: =N46/N36 -> 0.02486164
A48: AMA | B48: 129 | C48: 177 | D48: 155 | N48: =SUM(B48:M48) -> 461
A49: AMA % | B49: =B48/B36 -> 0.017165669 | C49: =IFERROR(C48/C36,0) -> 0.023726542 | D49: =IFERROR(D48/D36,0) -> 0.019011407 | E49: =IFERROR(E48/E36,0) -> 0 | F49: =IFERROR(F48/F36,0) -> 0 | G49: =IFERROR(G48/G36,0) -> 0 | H49: =IFERROR(H48/H36,0) -> 0 | I49: =IFERROR(I48/I36,0) -> 0 | J49: =IFERROR(J48/J36,0) -> 0 | ... M49: =IFERROR(M48/M36,0) -> 0 | N49: =N48/N36 -> 0.019932549
A50: JFK BB
A52: Total Pts | B52: 863 | C52: 827 | D52: 806 | N52: =SUM(B52:M52) -> 2496
A53: Arrival to Provider Greet (Min) | B53: 9 | C53: 9 | D53: 8 | N53: =SUMPRODUCT(B53:K53,B52:K52)/SUM(B52:K52) -> 8.6770833
A54: Duplicate MSE | B54: 26 | C54: 20 | D54: 10 | N54: =SUM(B54:M54) -> 56
A55: Duplicate MSE % | B55: =B54/B52 -> 0.030127462 | C55: =IFERROR(C54/C52,0) -> 0.024183797 | D55: =IFERROR(D54/D52,0) -> 0.012406948 | E55: =IFERROR(E54/E52,0) -> 0 | F55: =IFERROR(F54/F52,0) -> 0 | G55: =IFERROR(G54/G52,0) -> 0 | H55: =IFERROR(H54/H52,0) -> 0 | I55: =IFERROR(I54/I52,0) -> 0 | J55: =IFERROR(J54/J52,0) -> 0 | ... M55: =IFERROR(M54/M52,0) -> 0 | N55: =N54/N52 -> 0.022435897
A56: Admitted Pts (HCA Dashboard) | B56: 100 | C56: 88 | D56: 74 | N56: =SUM(B56:M56) -> 262
A57: Admitted Pts % | B57: =B56/B52 -> 0.11587486 | C57: =IFERROR(C56/C52,0) -> 0.10640871 | D57: =IFERROR(D56/D52,0) -> 0.091811414 | E57: =IFERROR(E56/E52,0) -> 0 | F57: =IFERROR(F56/F52,0) -> 0 | G57: =IFERROR(G56/G52,0) -> 0 | H57: =IFERROR(H56/H52,0) -> 0 | I57: =IFERROR(I56/I52,0) -> 0 | J57: =IFERROR(J56/J52,0) -> 0 | ... M57: =IFERROR(M56/M52,0) -> 0 | N57: =N56/N52 -> 0.10496795
A58: Admitted Pts ALOS | B58: 269 | C58: 270 | D58: 279 | N58: =SUM(B58:M58) -> 818
A59: Departed Pts % | B59: =B60/B52 -> 0.88412514 | C59: =IFERROR(C60/C52,0) -> 0.89359129 | D59: =IFERROR(D60/D52,0) -> 0.90818859 | E59: =IFERROR(E60/E52,0) -> 0 | F59: =IFERROR(F60/F52,0) -> 0 | G59: =IFERROR(G60/G52,0) -> 0 | H59: =IFERROR(H60/H52,0) -> 0 | I59: =IFERROR(I60/I52,0) -> 0 | J59: =IFERROR(J60/J52,0) -> 0 | ... M59: =IFERROR(M60/M52,0) -> 0 | N59: =N60/N52 -> 0.89503205
A60: Departed Pts | B60: =B52-B56 -> 763 | C60: =C52-C56 -> 739 | D60: =D52-D56 -> 732 | N60: =SUM(B60:M60) -> 2234
A61: Departed pts ALOS | B61: 92 | C61: 98 | D61: 99 | N61: =SUMPRODUCT(B61:M61,B60:M60)/SUM(B60:M60) -> 96.278424
A62: LPMSE + LPT | B62: =3+1 -> 4 | C62: 0 | D62: 4 | N62: =SUM(B62:K62) -> 8
A63: LPMSE + LPT % | B63: =B62/B52 -> 0.0046349942 | C63: =IFERROR(C62/C52,0) -> 0 | D63: =IFERROR(D62/D52,0) -> 0.0049627792 | E63: =IFERROR(E62/E52,0) -> 0 | F63: =IFERROR(F62/F52,0) -> 0 | G63: =IFERROR(G62/G52,0) -> 0 | H63: =IFERROR(H62/H52,0) -> 0 | I63: =IFERROR(I62/I52,0) -> 0 | J63: =IFERROR(J62/J52,0) -> 0 | ... M63: =IFERROR(M62/M52,0) -> 0 | N63: =N62/N52 -> 0.0032051282
A64: AMA | B64: 9 | C64: 9 | D64: 11 | N64: =SUM(B64:K64) -> 29
A65: AMA % | B65: =B64/B52 -> 0.010428737 | C65: =IFERROR(C64/C52,0) -> 0.010882709 | D65: =IFERROR(D64/D52,0) -> 0.013647643 | E65: =IFERROR(E64/E52,0) -> 0 | F65: =IFERROR(F64/F52,0) -> 0 | G65: =IFERROR(G64/G52,0) -> 0 | H65: =IFERROR(H64/H52,0) -> 0 | I65: =IFERROR(I64/I52,0) -> 0 | J65: =IFERROR(J64/J52,0) -> 0 | ... M65: =IFERROR(M64/M52,0) -> 0 | N65: =N64/N52 -> 0.01161859
A66: JFK PBG
A68: Total Pts | B68: 469 | C68: 502 | D68: 571 | N68: =SUM(B68:M68) -> 1542
A69: Arrival to Provider Greet (Min) | B69: 6 | C69: 7 | D69: 7 | N69: =SUMPRODUCT(B69:M69,B68:M68)/SUM(B68:M68) -> 6.6958495
A70: Duplicate MSE | B70: 8 | C70: 2 | D70: 4 | N70: =SUM(B70:M70) -> 14
A71: Duplicate MSE % | B71: =B70/B68 -> 0.017057569 | C71: =IFERROR(C70/C68,0) -> 0.0039840637 | D71: =IFERROR(D70/D68,0) -> 0.0070052539 | E71: =IFERROR(E70/E68,0) -> 0 | F71: =IFERROR(F70/F68,0) -> 0 | G71: =IFERROR(G70/G68,0) -> 0 | H71: =IFERROR(H70/H68,0) -> 0 | I71: =IFERROR(I70/I68,0) -> 0 | J71: =IFERROR(J70/J68,0) -> 0 | ... M71: =IFERROR(M70/M68,0) -> 0 | N71: =N70/N68 -> 0.009079118
A72: Admitted Pts | B72: 13 | C72: 1 | D72: 8 | N72: =SUM(B72:M72) -> 22
A73: Admitted Pts % | B73: =B72/B68 -> 0.02771855 | C73: =IFERROR(C72/C68,0) -> 0.0019920319 | D73: =IFERROR(D72/D68,0) -> 0.014010508 | E73: =IFERROR(E72/E68,0) -> 0 | F73: =IFERROR(F72/F68,0) -> 0 | G73: =IFERROR(G72/G68,0) -> 0 | H73: =IFERROR(H72/H68,0) -> 0 | I73: =IFERROR(I72/I68,0) -> 0 | J73: =IFERROR(J72/J68,0) -> 0 | ... M73: =IFERROR(M72/M68,0) -> 0 | N73: =N72/N68 -> 0.014267185
A74: Admitted Pts ALOS | B74: 261 | C74: 204 | D74: 275 | N74: =SUM(B74:M74) -> 740
A75: Departed Pts % | B75: =B76/B68 -> 0.97228145 | C75: =IFERROR(C76/C68,0) -> 0.99800797 | D75: =IFERROR(D76/D68,0) -> 0.98598949 | E75: =IFERROR(E76/E68,0) -> 0 | F75: =IFERROR(F76/F68,0) -> 0 | G75: =IFERROR(G76/G68,0) -> 0 | H75: =IFERROR(H76/H68,0) -> 0 | I75: =IFERROR(I76/I68,0) -> 0 | J75: =IFERROR(J76/J68,0) -> 0 | ... M75: =IFERROR(M76/M68,0) -> 0 | N75: =N76/N68 -> 0.98573281
A76: Departed Pts | B76: =B68-B72 -> 456 | C76: =C68-C72 -> 501 | D76: =D68-D72 -> 563 | N76: =SUM(B76:M76) -> 1520
A77: Departed pts ALOS | B77: 77 | C77: 88 | D77: 93 | N77: =SUMPRODUCT(B77:M77,B76:M76)/SUM(B76:M76) -> 86.551974
A78: LPMSE + LPT | B78: =0+1 -> 1 | C78: 0 | D78: 1 | N78: =SUM(B78:M78) -> 2
A79: LPMSE + LPT % | B79: =B78/B68 -> 0.0021321962 | C79: =IFERROR(C78/C68,0) -> 0 | D79: =IFERROR(D78/D68,0) -> 0.0017513135 | E79: =IFERROR(E78/E68,0) -> 0 | F79: =IFERROR(F78/F68,0) -> 0 | G79: =IFERROR(G78/G68,0) -> 0 | H79: =IFERROR(H78/H68,0) -> 0 | I79: =IFERROR(I78/I68,0) -> 0 | J79: =IFERROR(J78/J68,0) -> 0 | ... M79: =IFERROR(M78/M68,0) -> 0 | N79: =N78/N68 -> 0.0012970169
A80: AMA | B80: 5 | C80: 7 | D80: 6 | N80: =SUM(B80:M80) -> 18
A81: AMA % | B81: =B80/B68 -> 0.010660981 | C81: =IFERROR(C80/C68,0) -> 0.013944223 | D81: =IFERROR(D80/D68,0) -> 0.010507881 | E81: =IFERROR(E80/E68,0) -> 0 | F81: =IFERROR(F80/F68,0) -> 0 | G81: =IFERROR(G80/G68,0) -> 0 | H81: =IFERROR(H80/H68,0) -> 0 | I81: =IFERROR(I80/I68,0) -> 0 | J81: =IFERROR(J80/J68,0) -> 0 | ... M81: =IFERROR(M80/M68,0) -> 0 | N81: =N80/N68 -> 0.011673152

Sheet EDP PREMIUM LABOR (COST & HRS)
B17: PREMIUM HOURS
B18: Month | C18: DIVISION TOTAL | F18: BAPTIST | I18: JFK | L18: JFK BB | O18: JFK PBG | R18: JUPITER | U18: KENDALL | X18: MOBERLY | AA18: MONROE | AD18: OCALA | AG18: SAN RAMON | AJ18: ST MARY'S | AM18: W MARION QC | AP18: W MARION | AS18: WESTCHESTER | AV18: PROVIDENCE | AY18: ST JOHN | BB18: OSCEOLA
C19: Transition Team | D19: Shift Incentive | E19: Locum | F19: Transition Team | G19: Shift Incentive | H19: Locum | I19: Transition Team | J19: Shift Incentive | K19: Locum | L19: Transition Team | M19: Shift Incentive | N19: Locum | O19: Transition Team | P19: Shift Incentive | Q19: Locum | R19: Transition Team | S19: Shift Incentive | T19: Locum | U19: Transition Team | V19: Shift Incentive | W19: Locum | X19: Transition Team | Y19: Shift Incentive | Z19: Locum | AA19: Transition Team | AB19: Shift Incentive | AC19: Locum | AD19: Transition Team | AE19: Shift Incentive | AF19: Locum | AG19: Transition Team | AH19: Shift Incentive | AI19: Locum | AJ19: Transition Team | AK19: Shift Incentive | AL19: Locum | AM19: Transition Team | AN19: Shift Incentive | AO19: Locum | AP19: Transition Team | AQ19: Shift Incentive | AR19: Locum | AS19: Transition Team | AT19: Shift Incentive | AU19: Locum | AV19: Transition Team | AW19: Shift Incentive | AX19: Locum | AY19: Transition Team | AZ19: Shift Incentive | BA19: Locum | BB19: Transition Team | BC19: Shift Incentive | BD19: Locum
B20: 42370 | C20: =COMPOSITE!B$199 -> 2542 | D20: =COMPOSITE!C$199 -> 69 | E20: =COMPOSITE!D$199 -> 482 | F20: =COMPOSITE!$B$176 -> 0 | G20: =COMPOSITE!$C$176 -> 0 | I20: =COMPOSITE!$B$177 -> 0 | J20: =COMPOSITE!$C$177 -> 0 | K20: =COMPOSITE!$D$177 -> 0 | L20: =COMPOSITE!$B$178 -> 60 | M20: =COMPOSITE!C$178 -> 24 | O20: =COMPOSITE!B$179 -> 0 | P20: =COMPOSITE!C$179 -> 24 | Q20: =COMPOSITE!D$179 -> 0 | R20: =COMPOSITE!B$180 -> 1.5 | S20: =COMPOSITE!C$180 -> 0 | T20: =COMPOSITE!D$180 -> 0 | U20: =COMPOSITE!B$181 -> 452 | V20: =COMPOSITE!C$181 -> 0 | W20: =COMPOSITE!D$181 -> 0 | X20: =COMPOSITE!B$182 -> 165 | Y20: =COMPOSITE!C$182 -> 0 | Z20: =COMPOSITE!D$182 -> 0 | AA20: =COMPOSITE!B183 -> 0 | AB20: =COMPOSITE!C183 -> 0 | AC20: =COMPOSITE!D183 -> 132 | AD20: =COMPOSITE!B$184 -> 608.5 | AE20: =COMPOSITE!C$184 -> 0 | AF20: =COMPOSITE!D$184 -> 0 | AG20: =COMPOSITE!B185 -> 0 | AH20: =COMPOSITE!C185 -> 0 | AI20: =COMPOSITE!D185 -> 0 | AJ20: =COMPOSITE!B$186 -> 0 | AK20: =COMPOSITE!C$186 -> 21 | AL20: =COMPOSITE!D$186 -> 0 | AM20: =COMPOSITE!B$188 -> 24 | AN20: =COMPOSITE!C$188 -> 0 | AO20: =COMPOSITE!D$188 -> 0 | AP20: =COMPOSITE!B$187 -> 297 | AQ20: =COMPOSITE!C$187 -> 0 | AR20: =COMPOSITE!D$187 -> 0 | AS20: =COMPOSITE!B$189 -> 324 | AT20: =COMPOSITE!C$189 -> 0 | AU20: =COMPOSITE!D$189 -> 0 | AV20: =COMPOSITE!B190 -> 174 | AW20: =COMPOSITE!C190 -> 0 | AX20: =COMPOSITE!D190 -> 0 | AY20: =COMPOSITE!B191 -> 0 | AZ20: =COMPOSITE!C191 -> 0 | BA20: =COMPOSITE!D191 -> 26 | BB20: =COMPOSITE!B192 -> 436 | BC20: =COMPOSITE!C192 -> 0 | BD20: =COMPOSITE!D192 -> 300
B21: 42401 | C21: =COMPOSITE!E$199 -> 2253 | D21: =COMPOSITE!F$199 -> 111 | E21: =COMPOSITE!G$199 -> 594 | F21: =COMPOSITE!$E$176 -> 0 | G21: =COMPOSITE!$F$176 -> 0 | I21: =COMPOSITE!$E$177 -> 0 | J21: =COMPOSITE!$F$177 -> 0 | K21: =COMPOSITE!$G$177 -> 0 | L21: =COMPOSITE!$E$178 -> 24 | M21: =COMPOSITE!F$178 -> 48 | O21: =COMPOSITE!E$179 -> 0 | P21: =COMPOSITE!F$179 -> 24 | Q21: =COMPOSITE!G$179 -> 0 | R21: =COMPOSITE!E$180 -> 0 | S21: =COMPOSITE!F$180 -> 0 | T21: =COMPOSITE!G$180 -> 0 | U21: =COMPOSITE!E$181 -> 173 | V21: =COMPOSITE!F$181 -> 10 | W21: =COMPOSITE!G$181 -> 91 | X21: =COMPOSITE!E$182 -> 180 | Y21: =COMPOSITE!F$182 -> 0 | Z21: =COMPOSITE!G$182 -> 0 | AA21: =COMPOSITE!E183 -> 187 | AB21: =COMPOSITE!F183 -> 0 | AC21: =COMPOSITE!G183 -> 359 | AD21: =COMPOSITE!E$184 -> 698 | AE21: =COMPOSITE!F$184 -> 0 | AF21: =COMPOSITE!G$184 -> 13 | AG21: =COMPOSITE!E185 -> 0 | AH21: =COMPOSITE!F185 -> 0 | AI21: =COMPOSITE!G185 -> 0 | AJ21: =COMPOSITE!E$186 -> 0 | AK21: =COMPOSITE!F$186 -> 17 | AL21: =COMPOSITE!G$186 -> 0 | AM21: =COMPOSITE!E$188 -> 67 | AN21: =COMPOSITE!F$188 -> 12 | AO21: =COMPOSITE!G$188 -> 0 | AP21: =COMPOSITE!E$187 -> 236 | AQ21: =COMPOSITE!F$187 -> 0 | AR21: =COMPOSITE!G$187 -> 13 | AS21: =COMPOSITE!E$189 -> 36 | AT21: =COMPOSITE!F$189 -> 0 | AU21: =COMPOSITE!G$189 -> 0 | AV21: =COMPOSITE!E190 -> 186 | AW21: =COMPOSITE!F190 -> 0 | AX21: =COMPOSITE!G190 -> 0 | AY21: =COMPOSITE!E191 -> 72 | AZ21: =COMPOSITE!F191 -> 0 | BA21: =COMPOSITE!G191 -> 24 | BB21: =COMPOSITE!E192 -> 370 | BC21: =COMPOSITE!F192 -> 0 | BD21: =COMPOSITE!G192 -> 94
B22: 42430 | C22: =COMPOSITE!H$199 -> 2443 | D22: =COMPOSITE!I$199 -> 34 | E22: =COMPOSITE!J$199 -> 438 | F22: =COMPOSITE!$H$176 -> 0 | G22: =COMPOSITE!$I$176 -> 0 | I22: =COMPOSITE!$H$177 -> 0 | J22: =COMPOSITE!$I$177 -> 0 | K22: =COMPOSITE!$J$177 -> 0 | L22: =COMPOSITE!$H$178 -> 48 | M22: =COMPOSITE!I$178 -> 24 | O22: =COMPOSITE!H$179 -> 12 | P22: =COMPOSITE!I$179 -> 0 | Q22: =COMPOSITE!J$179 -> 0 | R22: =COMPOSITE!H$180 -> 130 | S22: =COMPOSITE!I$180 -> 0 | T22: =COMPOSITE!J$180 -> 0 | U22: =COMPOSITE!H$181 -> 197 | V22: =COMPOSITE!I$181 -> 10 | W22: =COMPOSITE!J$181 -> 101 | X22: =COMPOSITE!H$182 -> 240 | Y22: =COMPOSITE!I$182 -> 0 | Z22: =COMPOSITE!J$182 -> 0 | AA22: =COMPOSITE!H183 -> 217.5 | AB22: =COMPOSITE!I183 -> 0 | AC22: =COMPOSITE!J183 -> 195 | AD22: =COMPOSITE!H$184 -> 752.5 | AE22: =COMPOSITE!I$184 -> 0 | AF22: =COMPOSITE!J$184 -> 0 | AG22: =COMPOSITE!H185 -> 0 | AH22: =COMPOSITE!I185 -> 0 | AI22: =COMPOSITE!J185 -> 0 | AJ22: =COMPOSITE!H$186 -> 0 | AK22: =COMPOSITE!I$186 -> 0 | AL22: =COMPOSITE!J$186 -> 0 | AM22: =COMPOSITE!H$188 -> 54 | AN22: =COMPOSITE!I$188 -> 0 | AO22: =COMPOSITE!J$188 -> 0 | AP22: =COMPOSITE!H$187 -> 250 | AQ22: =COMPOSITE!I$187 -> 0 | AR22: =COMPOSITE!J$187 -> 0 | AS22: =COMPOSITE!H$189 -> 36 | AT22: =COMPOSITE!I$189 -> 0 | AU22: =COMPOSITE!J$189 -> 0 | AV22: =COMPOSITE!H191 -> 48 | AW22: =COMPOSITE!I190 -> 0 | AX22: =COMPOSITE!J190 -> 0 | AY22: =COMPOSITE!H191 -> 48 | AZ22: =COMPOSITE!I191 -> 0 | BA22: =COMPOSITE!J191 -> 0 | BB22: =COMPOSITE!H192 -> 257 | BC22: =COMPOSITE!I192 -> 0 | BD22: =COMPOSITE!J192 -> 142
B23: 42461 | C23: =COMPOSITE!K$199 -> 2728 | D23: =COMPOSITE!L$199 -> 240 | E23: =COMPOSITE!J$199 -> 438
B24: 42491
B25: 42522
B26: 42552
B27: 42583
B28: 42614
B29: 42644
B30: 42675
B31: 42705
B32: YTD Total | C32: =SUM(C20:C31) -> 9966 | D32: =SUM(D20:D31) -> 454 | E32: =SUM(E20:E31) -> 1952 | F32: =SUM(F20:F31) -> 0 | G32: =SUM(G20:G31) -> 0 | H32: =SUM(H20:H31) -> 0 | I32: =SUM(I20:I31) -> 0 | J32: =SUM(J20:J31) -> 0 | ... BD32: =SUM(BD20:BD31) -> 536
B34: PREMIUM COSTS
B35: Month | C35: DIVISION TOTAL | F35: BAPTIST | I35: JFK | L35: JFK BB | O35: JFK PBG | R35: JUPITER | U35: KENDALL | X35: MOBERLY | AA35: MONROE | AD35: OCALA | AG35: SAN RAMON | AJ35: ST MARY'S | AM35: W Marion QC | AP35: W MARION | AS35: WESTCHESTER | AV35: PROVIDENCE | AY35: ST JOHN | BB35: OSCEOLA
C36: Transition Team | D36: Shift Incentive | E36: Locum | F36: Transition Team | G36: Shift Incentive | H36: Locum | I36: Transition Team | J36: Shift Incentive | K36: Locum | L36: Transition Team | M36: Shift Incentive | N36: Locum | O36: Transition Team | P36: Shift Incentive | Q36: Locum | R36: Transition Team | S36: Shift Incentive | T36: Locum | U36: Transition Team | V36: Shift Incentive | W36: Locum | X36: Transition Team | Y36: Shift Incentive | Z36: Locum | AA36: Transition Team | AB36: Shift Incentive | AC36: Locum | AD36: Transition Team | AE36: Shift Incentive | AF36: Locum | AG36: Transition Team | AH36: Shift Incentive | AI36: Locum | AJ36: Transition Team | AK36: Shift Incentive | AL36: Locum | AM36: Transition Team | AN36: Shift Incentive | AO36: Locum | AP36: Transition Team | AQ36: Shift Incentive | AR36: Locum | AS36: Transition Team | AT36: Shift Incentive | AU36: Locum | AV36: Transition Team | AW36: Shift Incentive | AX36: Locum | AY36: Transition Team | AZ36: Shift Incentive | BA36: Locum | BB36: Transition Team | BC36: Shift Incentive | BD36: Locum
B37: 42370 | C37: =COMPOSITE!B$226 -> 479749.4 | D37: =COMPOSITE!C$226 -> 42081 | E37: =COMPOSITE!D$226 -> 0 | F37: =COMPOSITE!$B$204 -> 0 | G37: =COMPOSITE!$C$204 -> 240 | H37: =COMPOSITE!$D$204 -> 0 | I37: =COMPOSITE!$B$205 -> 0 | J37: =COMPOSITE!$C$205 -> 0 | K37: =COMPOSITE!$D$205 -> 0 | L37: =COMPOSITE!B$206 -> 10500 | M37: =COMPOSITE!C$206 -> 8600 | N37: =COMPOSITE!$D$206 -> 0 | O37: =COMPOSITE!B$207 -> 0 | P37: =COMPOSITE!C$207 -> 4011 | Q37: =COMPOSITE!$D$207 -> 0 | R37: =COMPOSITE!B$208 -> 300 | S37: =COMPOSITE!C$208 -> 0 | T37: =COMPOSITE!$D$208 -> 0 | U37: =COMPOSITE!B$209 -> 38000 | V37: =COMPOSITE!C$209 -> 1130 | W37: =COMPOSITE!$D$209 -> 0 | X37: =COMPOSITE!B$210 -> 30420 | Y37: =COMPOSITE!C$210 -> 0 | Z37: =COMPOSITE!$D$209 -> 0 | AA37: =COMPOSITE!B211 -> 42000 | AB37: =COMPOSITE!C211 -> 7000 | AC37: =COMPOSITE!D211 -> 0 | AD37: =COMPOSITE!B$212 -> 126658 | AE37: =COMPOSITE!C$212 -> 4112 | AF37: =COMPOSITE!D212 -> 0 | AG37: =COMPOSITE!B213 -> 0 | AH37: =COMPOSITE!C213 -> 0 | AI37: =COMPOSITE!D213 -> 0 | AJ37: =COMPOSITE!B$214 -> 0 | AK37: =COMPOSITE!C$214 -> 1300 | AL37: =COMPOSITE!D214 -> 0 | AM37: =COMPOSITE!B$216 -> 6000 | AN37: =COMPOSITE!C$216 -> 3988 | AO37: =COMPOSITE!D216 -> 0 | AP37: =COMPOSITE!B$215 -> 57915 | AQ37: =COMPOSITE!C$215 -> 0 | AR37: =COMPOSITE!D215 -> 0 | AS37: =COMPOSITE!B$217 -> 32400 | AT37: =COMPOSITE!C$217 -> 1700 | AU37: =COMPOSITE!D217 | AV37: =COMPOSITE!B218 -> 37410 | AW37: =COMPOSITE!C218 -> 8500 | AX37: =COMPOSITE!D218 -> 0 | AY37: =COMPOSITE!B219 -> 0 | AZ37: =COMPOSITE!C219 -> 500 | BA37: =COMPOSITE!D219 -> 0 | BB37: =COMPOSITE!B220 -> 98146.4 | BC37: =COMPOSITE!C220 -> 1000 | BD37: =COMPOSITE!D220 -> 0
B38: 42401 | C38: =COMPOSITE!E$226 -> 108007.2 | D38: =COMPOSITE!F$226 -> 40083 | E38: =COMPOSITE!G$226 -> 0 | F38: =COMPOSITE!$E$204 -> 0 | G38: =COMPOSITE!$F$204 -> 0 | H38: =COMPOSITE!$G$204 -> 0 | I38: =COMPOSITE!$E$205 -> 0 | J38: =COMPOSITE!$F$205 -> 1500 | K38: =COMPOSITE!$G$205 -> 0 | L38: =COMPOSITE!E$206 -> 1800 | M38: =COMPOSITE!F$206 -> 8000 | N38: =COMPOSITE!$G$206 -> 0 | O38: =COMPOSITE!E$207 -> 0 | P38: =COMPOSITE!F$207 -> 0 | Q38: =COMPOSITE!$G$207 -> 0 | R38: =COMPOSITE!E$208 -> 0 | S38: =COMPOSITE!F$208 -> 1680 | T38: =COMPOSITE!$G$208 -> 0 | U38: =COMPOSITE!E$209 -> 4325 | V38: =COMPOSITE!F$209 -> 2500 | W38: =COMPOSITE!$G$209 -> 0 | X38: =COMPOSITE!E$210 -> 9900 | Y38: =COMPOSITE!F$210 -> 2000 | Z38: =COMPOSITE!$G$209 -> 0 | AA38: =COMPOSITE!E211 -> 14025 | AB38: =COMPOSITE!F211 -> 2000 | AC38: =COMPOSITE!G211 -> 0 | AD38: =COMPOSITE!E$212 -> 29316 | AE38: =COMPOSITE!F$212 -> 3500 | AF38: =COMPOSITE!G212 -> 0 | AG38: =COMPOSITE!E213 -> 5400 | AH38: =COMPOSITE!F213 -> 0 | AI38: =COMPOSITE!G213 -> 0 | AJ38: =COMPOSITE!E$214 -> 0 | AK38: =COMPOSITE!F$214 -> 700 | AL38: =COMPOSITE!G214 -> 0 | AM38: =COMPOSITE!E$216 -> 6030 | AN38: =COMPOSITE!F$216 -> 5443 | AO38: =COMPOSITE!J216 -> 0 | AP38: =COMPOSITE!E$215 -> 12980 | AQ38: =COMPOSITE!F$215 -> 0 | AR38: =COMPOSITE!G215 -> 0 | AS38: =COMPOSITE!E$217 -> 3600 | AT38: =COMPOSITE!F$217 -> 1260 | AU38: =COMPOSITE!G217 | AV38: =COMPOSITE!E218 -> 6510 | AW38: =COMPOSITE!F218 -> 9000 | AX38: =COMPOSITE!G218 -> 0 | AY38: =COMPOSITE!E219 -> 0 | AZ38: =COMPOSITE!F219 -> 0 | BA38: =COMPOSITE!G219 -> 0 | BB38: =COMPOSITE!E220 -> 12950 | BC38: =COMPOSITE!F220 -> 2500 | BD38: =COMPOSITE!G220 -> 0
B39: 42430 | C39: =COMPOSITE!H$226 -> 119379.3 | D39: =COMPOSITE!I$226 -> 39240 | E39: =COMPOSITE!J$226 -> 0 | F39: =COMPOSITE!$H$204 -> 0 | G39: =COMPOSITE!$I$204 -> 0 | H39: =COMPOSITE!$J$204 -> 0 | I39: =COMPOSITE!$H$205 -> 0 | J39: =COMPOSITE!$I$205 -> 6000 | K39: =COMPOSITE!$J$205 -> 0 | L39: =COMPOSITE!H$206 -> 3600 | M39: =COMPOSITE!I$206 -> 4000 | N39: =COMPOSITE!$J$206 -> 0 | O39: =COMPOSITE!H$207 -> 900 | P39: =COMPOSITE!I$207 -> 0 | Q39: =COMPOSITE!$J$207 -> 0 | R39: =COMPOSITE!H$208 -> 6500 | S39: =COMPOSITE!I$208 -> 0 | T39: =COMPOSITE!$J$208 -> 0 | U39: =COMPOSITE!H$209 -> 4925 | V39: =COMPOSITE!I$209 -> 500 | W39: =COMPOSITE!$J$209 -> 0 | X39: =COMPOSITE!E$210 -> 9900 | Y39: =COMPOSITE!FI210 -> 0 | Z39: =COMPOSITE!$J$208 -> 0 | AA39: =COMPOSITE!H211 -> 16312.5 | AB39: =COMPOSITE!I211 -> 3000 | AC39: =COMPOSITE!J213 -> 0 | AD39: =COMPOSITE!H$212 -> 31605 | AE39: =COMPOSITE!I$212 -> 8000 | AF39: =COMPOSITE!J212 -> 0 | AG39: =COMPOSITE!H213 -> 0 | AH39: =COMPOSITE!I213 -> 0 | AI39: =COMPOSITE!J213 -> 0 | AJ39: =COMPOSITE!H$214 -> 0 | AK39: =COMPOSITE!I$214 -> 0 | AL39: =COMPOSITE!J214 -> 0 | AM39: =COMPOSITE!H$216 -> 4860 | AN39: =COMPOSITE!I$216 -> 0 | AO39: =COMPOSITE!J216 -> 0 | AP39: =COMPOSITE!H$215 -> 13750 | AQ39: =COMPOSITE!I$215 -> 1000 | AR39: =COMPOSITE!J215 -> 0 | AS39: =COMPOSITE!H$217 -> 3600 | AT39: =COMPOSITE!I$217 -> 240 | AU39: =COMPOSITE!J217 -> 0 | AV39: =COMPOSITE!H218 -> 5775 | AW39: =COMPOSITE!I218 -> 7000 | AX39: =COMPOSITE!J218 -> 0 | AY39: =COMPOSITE!H219 -> 3600 | AZ39: =COMPOSITE!I219 -> 500 | BA39: =COMPOSITE!J219 -> 0 | BB39: =COMPOSITE!H220 -> 8995 | BC39: =COMPOSITE!I220 -> 0 | BD39: =COMPOSITE!J220 -> 0
B40: 42461
B41: 42491
B42: 42522
B43: 42552
B44: 42583
B45: 42614
B46: 42644
B47: 42675
B48: 42705
B49: YTD Total | C49: =SUM(C37:C48) -> 707135.9 | D49: =SUM(D37:D48) -> 121404 | F49: =SUM(F37:F48) -> 0 | G49: =SUM(G37:G48) -> 240 | I49: =SUM(I37:I48) -> 0 | J49: =SUM(J37:J48) -> 7500 | L49: =SUM(L37:L48) -> 15900 | M49: =SUM(M37:M48) -> 20600 | O49: =SUM(O37:O48) -> 900 | P49: =SUM(P37:P48) -> 4011 | R49: =SUM(R37:R48) -> 6800 | S49: =SUM(S37:S48) -> 1680 | U49: =SUM(U37:U48) -> 47250 | V49: =SUM(V37:V48) -> 4130 | X49: =SUM(X37:X48) -> 50220 | Y49: =SUM(Y37:Y48) -> 2000 | Z49: =SUM(Z37:Z48) -> 0 | AA49: =SUM(AA37:AA48) -> 72337.5 | AB49: =SUM(AB37:AB48) -> 12000 | AD49: =SUM(AD37:AD48) -> 187579 | AE49: =SUM(AE37:AE48) -> 15612 | AG49: =SUM(AG37:AG48) -> 5400 | AH49: =SUM(AH37:AH48) -> 0 | AJ49: =SUM(AJ37:AJ48) -> 0 | AK49: =SUM(AK37:AK48) -> 2000 | AM49: =SUM(AM37:AM48) -> 16890 | AN49: =SUM(AN37:AN48) -> 9431 | AP49: =SUM(AP37:AP48) -> 84645 | AQ49: =SUM(AQ37:AQ48) -> 1000 | AS49: =SUM(AS37:AS48) -> 39600 | AT49: =SUM(AT37:AT48) -> 3200 | AV49: =SUM(AV37:AV48) -> 49695 | AW49: =SUM(AW37:AW48) -> 24500 | AY49: =SUM(AY37:AY48) -> 3600 | AZ49: =SUM(AZ37:AZ48) -> 1000 | BB49: =SUM(BB37:BB48) -> 120091.4 | BC49: =SUM(BC37:BC48) -> 3500

Sheet BUDGET HOURS
B19: ED PHYSICIANS HOURS
B20: Month | C20: DIVISION TOTAL | G20: BAPTIST | I20: JFK | K20: JFK BB | M20: JFK PBG | O20: JUPITER | Q20: KENDALL | S20: MOBERLY | U20: MONROE | W20: OCALA | Y20: SAN RAMON | AA20: ST. MARY'S | AC20: W MARION QC | AE20: W MARION | AG20: WESTCHESTER | AI20: PROVIDENCE | AK20: ST. JOHN | AM20: OSCEOLA | AO20: HUNTERS CREEK | AQ20: CHANDLER | AS20: MERCY GILBERT
C21: EDP Budget | D21: EDP Actual | E21: QC PCP Budget | F21: QC PCP Actual | G21: EDP Budget | H21: EDP Actual | I21: EDP Budget | J21: EDP Actual | K21: EDP Budget | L21: EDP Actual | M21: EDP Budget | N21: EDP Actual | O21: EDP Budget | P21: EDP Actual | Q21: EDP Budget | R21: EDP Actual | S21: EDP Budget | T21: EDP Actual | U21: EDP Budget | V21: EDP Actual | W21: EDP Budget | X21: EDP Actual | Y21: EDP Budget | Z21: EDP Actual | AA21: EDP Budget | AB21: EDP Actual | AC21: PCP Budget | AD21: PCP Actual | AE21: EDP Budget | AF21: EDP Actual | AG21: EDP Budget | AH21: EDP Actual | AI21: EDP Budget | AJ21: EDP Actual | AK21: EDP Budget | AL21: EDP Actual | AM21: EDP Budget | AN21: EDP Actual | AO21: EDP Budget | AP21: EDP Actual | AQ21: EDP Budget | AR21: EDP Actual | AS21: EDP Budget | AT21: EDP Actual
B22: 42370 | C22: =COMPOSITE!B$297-COMPOSITE!B$287 -> 946.85671 | D22: =(COMPOSITE!D$297-COMPOSITE!D$287)/31 -> 950.54839 | E22: =COMPOSITE!B$287 -> 24 | F22: =COMPOSITE!D$287/31 -> 24 | G22: =COMPOSITE!B$273 -> 120 | H22: =COMPOSITE!D$273/31 -> 120 | I22: =COMPOSITE!B$274 -> 85.814208 | J22: =COMPOSITE!D$274/31 -> 86.193548 | K22: =COMPOSITE!B$275 -> 24 | L22: =COMPOSITE!D$275/31 -> 24 | M22: =COMPOSITE!B$276 -> 24 | N22: =COMPOSITE!D$276/31 -> 24.032258 | O22: =COMPOSITE!B$277 -> 37 | P22: =COMPOSITE!D$277/31 -> 37.032258 | Q22: =COMPOSITE!B$279 -> 82.57 | R22: =COMPOSITE!D$279/31 -> 80.419355 | S22: =COMPOSITE!B$281 -> 24 | T22: =COMPOSITE!D$281/31 -> 24.258065 | U22: =COMPOSITE!B282 -> 24 | V22: =COMPOSITE!D282/31 -> 24 | W22: =COMPOSITE!B$283 -> 42 | X22: =COMPOSITE!D$283/31 -> 42.806452 | Y22: =COMPOSITE!B284 -> 32 | Z22: =COMPOSITE!D284/31 -> 31.983871 | AA22: =COMPOSITE!B$285 -> 24 | AB22: =COMPOSITE!D$285/31 -> 24 | AC22: =COMPOSITE!B$287 -> 24 | AD22: =COMPOSITE!D$287/31 -> 24 | AE22: =COMPOSITE!B$286 -> 24 | AF22: =COMPOSITE!D$286/31 -> 26.096774 | AG22: =COMPOSITE!B$288 -> 24 | AH22: =COMPOSITE!D$288/31 -> 24 | AI22: =COMPOSITE!B289 -> 36 | AJ22: =COMPOSITE!D289/31 -> 36 | AK22: =COMPOSITE!B290 -> 24 | AL22: =COMPOSITE!D290/31 -> 24 | AM22: =COMPOSITE!B291 -> 63.8125 | AN22: =COMPOSITE!D291/31 -> 63.032258 | AO22: =COMPOSITE!B293 -> 24 | AP22: =COMPOSITE!D293/31 -> 24 | AQ22: =COMPOSITE!B294 -> 110 | AR22: =COMPOSITE!D294/31 -> 110 | AS22: =COMPOSITE!B295 -> 68 | AT22: =COMPOSITE!D295/31 -> 68
B23: 42401 | C23: =COMPOSITE!E$297-COMPOSITE!E$287 -> 947.62671 | D23: =(COMPOSITE!G$297-COMPOSITE!G$287)/29 -> 956.72414 | E23: =COMPOSITE!E$287 -> 22 | F23: =COMPOSITE!G$287/29 -> 22.905172 | G23: =COMPOSITE!E$273 -> 120 | H23: =COMPOSITE!G$273/29 -> 120 | I23: =COMPOSITE!E$274 -> 85.814208 | J23: =COMPOSITE!G$274/29 -> 86.482759 | K23: =COMPOSITE!E$275 -> 24 | L23: =COMPOSITE!G$275/29 -> 24 | M23: =COMPOSITE!E$276 -> 24 | N23: =COMPOSITE!G$276/29 -> 24 | O23: =COMPOSITE!E$277 -> 37 | P23: =COMPOSITE!G$277/29 -> 37 | Q23: =COMPOSITE!E$279 -> 83 | R23: =COMPOSITE!G$279/29 -> 81.551724 | S23: =COMPOSITE!E$281 -> 24 | T23: =COMPOSITE!G$281/29 -> 24.241379 | U23: =COMPOSITE!E282 -> 24 | V23: =COMPOSITE!G282/29 -> 24 | W23: =COMPOSITE!E$283 -> 42 | X23: =COMPOSITE!G$283/29 -> 46.275862 | Y23: =COMPOSITE!E284 -> 32 | Z23: =COMPOSITE!G284/29 -> 32.206897 | AA23: =COMPOSITE!E$285 -> 24 | AB23: =COMPOSITE!G$285/29 -> 24 | AC23: =COMPOSITE!E$287 -> 22 | AD23: =COMPOSITE!G$287/29 -> 22.905172 | AE23: =COMPOSITE!E$286 -> 24 | AF23: =COMPOSITE!G$286/29 -> 25.655172 | AG23: =COMPOSITE!E$288 -> 24 | AH23: =COMPOSITE!G$288/29 -> 24 | AI23: =COMPOSITE!E289 -> 36 | AJ23: =COMPOSITE!G289/29 -> 36 | AK23: =COMPOSITE!E290 -> 24 | AL23: =COMPOSITE!G290/29 -> 24 | AM23: =COMPOSITE!E291 -> 63.8125 | AN23: =COMPOSITE!G291/29 -> 64.724138 | AO23: =COMPOSITE!E293 -> 24 | AP23: =COMPOSITE!G293/29 -> 24.086207 | AQ23: =COMPOSITE!E294 -> 110 | AR23: =COMPOSITE!G294/29 -> 110 | AS23: =COMPOSITE!E295 -> 68 | AT23: =COMPOSITE!G295/29 -> 68
B24: 42430 | C24: =COMPOSITE!H$297-COMPOSITE!H$287 -> 953.62671 | D24: =(COMPOSITE!J$297-COMPOSITE!J$287)/31 -> 958.55387 | E24: =COMPOSITE!H$287 -> 22 | F24: =COMPOSITE!J$287/31 -> 22.258065 | G24: =COMPOSITE!H$273 -> 120 | H24: =COMPOSITE!J$273/31 -> 118.03226 | I24: =COMPOSITE!H$274 -> 85.814208 | J24: =COMPOSITE!J$274/31 -> 86.451613 | K24: =COMPOSITE!H$275 -> 24 | L24: =COMPOSITE!J$275/31 -> 24 | M24: =COMPOSITE!H$276 -> 24 | N24: =COMPOSITE!J$276/31 -> 23.967742 | O24: =COMPOSITE!H$277 -> 37 | P24: =COMPOSITE!J$277/31 -> 38.967742 | Q24: =COMPOSITE!H$279 -> 83 | R24: =COMPOSITE!J$279/31 -> 82.596774 | S24: =COMPOSITE!H$281 -> 24 | T24: =COMPOSITE!J$281/31 -> 24.5 | U24: =COMPOSITE!H282 -> 24 | V24: =COMPOSITE!J282/31 -> 24 | W24: =COMPOSITE!H$283 -> 48 | X24: =COMPOSITE!J$283/31 -> 48.247419 | Y24: =COMPOSITE!H284 -> 32 | Z24: =COMPOSITE!J284/31 -> 32.096774 | AA24: =COMPOSITE!H$285 -> 24 | AB24: =COMPOSITE!J$285/31 -> 24 | AC24: =COMPOSITE!H$287 -> 22 | AD24: =COMPOSITE!J$287/31 -> 22.258065 | AE24: =COMPOSITE!H$286 -> 24 | AF24: =COMPOSITE!J$286/31 -> 25 | AG24: =COMPOSITE!H$288 -> 24 | AH24: =COMPOSITE!J$288/31 -> 24.064516 | AI24: =COMPOSITE!H289 -> 36 | AJ24: =COMPOSITE!J289/31 -> 36.290323 | AK24: =COMPOSITE!H290 -> 24 | AL24: =COMPOSITE!J290/31 -> 24 | AM24: =COMPOSITE!H291 -> 63.8125 | AN24: =COMPOSITE!J291/31 -> 64.096774 | AO24: =COMPOSITE!H293 -> 24 | AP24: =COMPOSITE!J293/31 -> 24 | AQ24: =COMPOSITE!H294 -> 110 | AR24: =COMPOSITE!J294/31 -> 111.43548 | AS24: =COMPOSITE!H295 -> 68 | AT24: =COMPOSITE!J295/31 -> 67.935484
B25: 42461 | C25: =COMPOSITE!K$297-COMPOSITE!K$287 -> 953.62671 | D25: =(COMPOSITE!M$297-COMPOSITE!M$287)/30 -> 949.37767 | E25: =COMPOSITE!K$287 -> 22 | F25: =COMPOSITE!M$287/30 -> 22 | G25: =COMPOSITE!K$273 -> 120 | H25: =COMPOSITE!M$273/30 -> 117.26667 | I25: =COMPOSITE!H$274 -> 85.814208 | J25: =COMPOSITE!M$274/31 -> 81.881613 | K25: =COMPOSITE!H$275 -> 24 | L25: =COMPOSITE!M$275/30 -> 23.883333 | M25: =COMPOSITE!H$276 -> 24 | N25: =COMPOSITE!M$276/30 -> 23.891667 | O25: =COMPOSITE!H$277 -> 37 | P25: =COMPOSITE!M$277/30 -> 37.6 | Q25: =COMPOSITE!H$279 -> 83 | R25: =COMPOSITE!M$279/30 -> 81.733333 | S25: =COMPOSITE!H$281 -> 24 | T25: =COMPOSITE!M$281/30 -> 23.75 | U25: =COMPOSITE!H283 -> 48 | V25: =COMPOSITE!M282/30 -> 24 | W25: =COMPOSITE!H$283 -> 48 | X25: =COMPOSITE!M$283/30 -> 48 | Y25: =COMPOSITE!H285 -> 24 | Z25: =COMPOSITE!J284/30 -> 33.166667 | AA25: =COMPOSITE!H$285 -> 24 | AB25: =COMPOSITE!M$285/30 -> 24 | AC25: =COMPOSITE!H$287 -> 22 | AD25: =COMPOSITE!M$287/30 -> 22 | AE25: =COMPOSITE!H$286 -> 24 | AF25: =COMPOSITE!M$286/30 -> 24 | AG25: =COMPOSITE!H$288 -> 24 | AH25: =COMPOSITE!M$288/30 -> 24 | AI25: =COMPOSITE!H290 -> 24 | AJ25: =COMPOSITE!M289/30 -> 36 | AK25: =COMPOSITE!H291 -> 63.8125 | AL25: =COMPOSITE!M290/30 -> 24 | AM25: =COMPOSITE!H292 -> 21 | AN25: =COMPOSITE!M291/30 -> 63.8 | AO25: =COMPOSITE!H294 -> 110 | AP25: =COMPOSITE!M293/30 -> 24 | AQ25: =COMPOSITE!H295 -> 68 | AR25: =COMPOSITE!M294/30 -> 110.425 | AS25: =COMPOSITE!H296 -> 0 | AT25: =COMPOSITE!M295/30 -> 68.1
B26: 42491
B27: 42522
B28: 42552
B29: 42583
B30: 42614
B31: 42644
B32: 42675
B33: 42705
B34: YTD Total | C34: =SUM(C22:C33) -> 3801.7368 | D34: =SUM(D22:D33) -> 3815.2041 | E34: =SUM(E22:E33) -> 90 | F34: =SUM(F22:F33) -> 91.163237 | G34: =SUM(G22:G33) -> 480 | H34: =SUM(H22:H33) -> 475.29892 | I34: =SUM(I22:I33) -> 343.25683 | J34: =SUM(J22:J33) -> 341.00953 | ... AT34: =SUM(AT22:AT33) -> 272.03548
B36: APP / MLP HOURS
B37: Month | C37: DIVISION TOTAL | E37: JFK | G37: JUPITER | I37: KENDALL | K37: KENDALL PEDS | M37: OCALA | O37: ST MARY'S | Q37: W MARION | S37: W MARION QC | U37: PROVIDENCE | W37: OSCEOLA | Y37: HUNTERS CREEK | AA37: CHANDLER | AC37: M GILBERT
C38: Budget | D38: Actual | E38: Budget | F38: Actual | G38: Budget | H38: Actual | I38: Budget | J38: Actual | K38: Budget | L38: Actual | M38: Budget | N38: Actual | O38: Budget | P38: Actual | Q38: Budget | R38: Actual | S38: Budget | T38: Actual | U38: Budget | V38: Actual | W38: Budget | X38: Actual | Y38: Budget | Z38: Actual | AA38: Budget | AB38: Actual | AC38: Budget | AD38: Actual
B39: 42370 | C39: =COMPOSITE!B$321 -> 438.92481 | D39: =COMPOSITE!D$321/31 -> 430.72581 | E39: =COMPOSITE!B$302 -> 58.819672 | F39: =COMPOSITE!D$302/31 -> 53.741935 | G39: =COMPOSITE!B$303 -> 24 | H39: =COMPOSITE!D$303/31 -> 24 | I39: =COMPOSITE!B$305 -> 35.803279 | J39: =COMPOSITE!D$305/31 -> 40.814516 | K39: =COMPOSITE!B306 -> 14.28 | L39: =COMPOSITE!D306/31 -> 8.0241935 | M39: =COMPOSITE!B$309 -> 36 | N39: =COMPOSITE!D$309/31 -> 36 | O39: =COMPOSITE!B308 -> 20 | P39: =COMPOSITE!D308/31 -> 19.145161 | Q39: =COMPOSITE!B$310 -> 20 | R39: =COMPOSITE!D310/31 -> 20.129032 | S39: =COMPOSITE!B$311 -> 10 | T39: =COMPOSITE!D$311/31 -> 6.7741935 | U39: =COMPOSITE!B313 -> 20 | V39: =COMPOSITE!D313/31 -> 20 | W39: =COMPOSITE!B315 -> 50 | X39: =COMPOSITE!D315/31 -> 52.096774 | Y39: =COMPOSITE!B317 -> 12.010929 | Z39: =COMPOSITE!D317/31 -> 12 | AA39: =COMPOSITE!B318 -> 76 | AB39: =COMPOSITE!D318/31 -> 76 | AC39: =COMPOSITE!B319 -> 50 | AD39: =COMPOSITE!D319/31 -> 50
B40: 42401 | C40: =COMPOSITE!E$321 -> 438.64481 | D40: =COMPOSITE!G$321/29 -> 449.32989 | E40: =COMPOSITE!E$302 -> 58.819672 | F40: =COMPOSITE!G$302/29 -> 56.456897 | G40: =COMPOSITE!E$303 -> 24 | H40: =COMPOSITE!G$303/29 -> 25.172414 | I40: =COMPOSITE!E$305 -> 35.803279 | J40: =COMPOSITE!G$305/29 -> 39.939655 | K40: =COMPOSITE!E306 -> 14 | L40: =COMPOSITE!G306/29 -> 18.913793 | M40: =COMPOSITE!E$309 -> 36 | N40: =COMPOSITE!G$309/29 -> 35.094828 | O40: =COMPOSITE!E308 -> 20 | P40: =COMPOSITE!G308/29 -> 18.784483 | Q40: =COMPOSITE!E$310 -> 20 | R40: =COMPOSITE!G310/29 -> 20.25 | S40: =COMPOSITE!E$311 -> 10 | T40: =COMPOSITE!G$311/29 -> 7.2413793 | U40: =COMPOSITE!E313 -> 20 | V40: =COMPOSITE!G313/29 -> 20.137931 | W40: =COMPOSITE!E315 -> 50 | X40: =COMPOSITE!G315/29 -> 56.482759 | Y40: =COMPOSITE!E317 -> 12.010929 | Z40: =COMPOSITE!G317/29 -> 12.844828 | AA40: =COMPOSITE!E318 -> 76 | AB40: =COMPOSITE!G318/29 -> 76 | AC40: =COMPOSITE!E319 -> 50 | AD40: =COMPOSITE!G319/29 -> 50
B41: 42430 | C41: =COMPOSITE!H$321 -> 431.90295 | D41: =COMPOSITE!J$321/31 -> 429.64516 | E41: =COMPOSITE!H$302 -> 58.819672 | F41: =COMPOSITE!J$302/31 -> 58.806452 | G41: =COMPOSITE!H$303 -> 24 | H41: =COMPOSITE!J$303/29 -> 26.068966 | I41: =COMPOSITE!H$305 -> 35.803279 | J41: =COMPOSITE!J$305/31 -> 36.193548 | K41: =COMPOSITE!H306 -> 14.28 | L41: =COMPOSITE!J307/31 -> 0 | M41: =COMPOSITE!H$309 -> 36 | N41: =COMPOSITE!J$309/31 -> 36 | O41: =COMPOSITE!H308 -> 20 | P41: =COMPOSITE!J309/31 -> 36 | Q41: =COMPOSITE!H$310 -> 20 | R41: =COMPOSITE!J310/31 -> 20 | S41: =COMPOSITE!H$311 -> 10 | T41: =COMPOSITE!J$311/31 -> 7.4193548 | U41: =COMPOSITE!H313 -> 20 | V41: =COMPOSITE!J313/31 -> 20 | W41: =COMPOSITE!H315 -> 50 | X41: =COMPOSITE!J315/31 -> 50 | Y41: =COMPOSITE!H317 -> 17 | Z41: =COMPOSITE!J317/31 -> 13.935484 | AA41: =COMPOSITE!H318 -> 76 | AB41: =COMPOSITE!J318/31 -> 74.451613 | AC41: =COMPOSITE!H319 -> 50 | AD41: =COMPOSITE!J319/31 -> 50
B42: 42461 | C42: =COMPOSITE!K$321 -> 431.81967 | D42: =COMPOSITE!M$321/31 -> 420.45968 | E42: =COMPOSITE!K$302 -> 58.819672 | F42: =COMPOSITE!M$302/30 -> 58.8 | G42: =COMPOSITE!K$303 -> 24 | H42: =COMPOSITE!M$303/30 -> 24.458333 | I42: =COMPOSITE!K$305 -> 36 | J42: =COMPOSITE!M$305/30 -> 37.666667 | K42: =COMPOSITE!K306 -> 14 | L42: =COMPOSITE!M308/30 -> 20 | M42: =COMPOSITE!K$309 -> 36 | N42: =COMPOSITE!M$309/30 -> 36.491667 | O42: =COMPOSITE!K308 -> 20 | P42: =COMPOSITE!M310/30 -> 21.208333 | Q42: =COMPOSITE!K$310 -> 20 | R42: =COMPOSITE!M310/30 -> 21.208333 | S42: =COMPOSITE!K$311 -> 10 | T42: =COMPOSITE!M$311/30 -> 7 | U42: =COMPOSITE!K313 -> 20 | V42: =COMPOSITE!M313/30 -> 20.666667 | W42: =COMPOSITE!K315 -> 50 | X42: =COMPOSITE!M317/30 -> 17.466667 | Y42: =COMPOSITE!K317 -> 17 | Z42: =COMPOSITE!M317/31 -> 16.903226 | AA42: =COMPOSITE!K318 -> 76 | AB42: =COMPOSITE!M318/31 -> 73.290323 | AC42: =COMPOSITE!K319 -> 50 | AD42: =COMPOSITE!M319/31 -> 48.209677
B43: 42491
B44: 42522
B45: 42552
B46: 42583
B47: 42614
B48: 42644
B49: 42675
B50: 42705
B51: YTD Total | C51: =SUM(C39:C50) -> 1741.2922 | D51: =SUM(D39:D50) -> 1730.1605 | E51: =SUM(E39:E50) -> 235.27869 | F51: =SUM(F39:F50) -> 227.80528 | G51: =SUM(G39:G50) -> 96 | H51: =SUM(H39:H50) -> 99.699713 | I51: =SUM(I39:I50) -> 143.40984 | J51: =SUM(J39:J50) -> 154.61439 | ... AD51: =SUM(AD39:AD50) -> 198.20968
B53: SCRIBE HOURS
B54: Month | C54: DIVISION TOTAL | E54: BAPTIST | G54: JUPITER | I54: KENDALL | K54: MOBERLY | M54: ST MARY'S | O54: OSCEOLA | Q54: OSCEOLA PEDS | S54: HUNTERS CREEK | U54: OCALA | W54: W MARION
C55: Budget | D55: Actual | E55: Budget | F55: Actual | G55: Budget | H55: Actual | I55: Budget | J55: Actual | K55: Budget | L55: Actual | M55: Budget | N55: Actual | O55: Budget | P55: Actual | Q55: Budget | R55: Actual | S55: Budget | T55: Actual | U55: Budget | V55: Actual | W55: Budget | X55: Actual
B56: 42370 | C56: =COMPOSITE!B$340 -> 452 | D56: =COMPOSITE!C$340 -> 476.58032 | E56: =COMPOSITE!B$325 -> 100 | F56: =COMPOSITE!C$325 -> 101.49194 | G56: =COMPOSITE!B326 -> 10 | H56: =COMPOSITE!C326 -> 12.26 | I56: =COMPOSITE!B$327 -> 73 | J56: =COMPOSITE!C$327 -> 90.668387 | K56: =COMPOSITE!B$328 -> 8 | L56: =COMPOSITE!C$328 -> 8.38 | M56: =COMPOSITE!B$329 -> 24 | N56: =COMPOSITE!C$329 -> 24.36 | O56: =COMPOSITE!B332 -> 65 | P56: =COMPOSITE!C332 -> 69 | Q56: =COMPOSITE!B333 -> 18 | R56: =COMPOSITE!C333 -> 13.34 | S56: =COMPOSITE!B334 -> 12 | T56: =COMPOSITE!C334 -> 11.58 | U56: =COMPOSITE!B337 -> 24 | V56: =COMPOSITE!C337 -> 25.69 | W56: =COMPOSITE!B338 -> 16 | X56: =COMPOSITE!C338 -> 17.81
B57: 42401 | C57: =COMPOSITE!D$340 -> 451.90452 | D57: =COMPOSITE!E$340 -> 461.53276 | E57: =COMPOSITE!D$325 -> 100 | F57: =COMPOSITE!E$325 -> 102 | G57: =COMPOSITE!D326 -> 10 | H57: =COMPOSITE!E326 -> 12 | I57: =COMPOSITE!D$327 -> 73 | J57: =COMPOSITE!E$327 -> 73 | K57: =COMPOSITE!D$328 -> 8 | L57: =COMPOSITE!E$328 -> 8.5 | M57: =COMPOSITE!D$329 -> 24 | N57: =COMPOSITE!E$329 -> 24.18 | O57: =COMPOSITE!D332 -> 65 | P57: =COMPOSITE!E332 -> 67 | Q57: =COMPOSITE!D333 -> 18 | R57: =COMPOSITE!E333 -> 19 | S57: =COMPOSITE!D334 -> 11.904516 | T57: =COMPOSITE!E334 -> 10.852759 | U57: =COMPOSITE!D337 -> 24 | V57: =COMPOSITE!E337 -> 26 | W57: =COMPOSITE!D338 -> 16 | X57: =COMPOSITE!E338 -> 17
B58: 42430 | C58: =COMPOSITE!F$340 -> 452 | D58: =COMPOSITE!G$340 -> 492.43194 | E58: =COMPOSITE!F$325 -> 100 | F58: =COMPOSITE!G$325 -> 102 | G58: =COMPOSITE!F326 -> 10 | H58: =COMPOSITE!G326 -> 12.290323 | I58: =COMPOSITE!F$327 -> 73 | J58: =COMPOSITE!G$327 -> 93.563226 | K58: =COMPOSITE!F$328 -> 8 | L58: =COMPOSITE!G$328 -> 8.5 | M58: =COMPOSITE!F$329 -> 24 | N58: =COMPOSITE!G$329 -> 25.567419 | O58: =COMPOSITE!F332 -> 65 | P58: =COMPOSITE!G332 -> 68.994839 | Q58: =COMPOSITE!F333 -> 18 | R58: =COMPOSITE!G333 -> 18.600968 | S58: =COMPOSITE!F334 -> 12 | T58: =COMPOSITE!E334 -> 10.852759 | U58: =COMPOSITE!F337 -> 24 | V58: =COMPOSITE!G337 -> 31.870323 | W58: =COMPOSITE!F338 -> 16 | X58: =COMPOSITE!G338 -> 17.140323
B59: 42461 | C59: =COMPOSITE!H$340 -> 452 | D59: =COMPOSITE!I$340 -> 451.81967 | E59: =COMPOSITE!H$325 -> 100 | F59: =COMPOSITE!I$325 -> 99 | G59: =COMPOSITE!H326 -> 10 | H59: =COMPOSITE!I326 -> 8.3833333 | I59: =COMPOSITE!H$327 -> 73 | J59: =COMPOSITE!I$327 -> 96.328667 | K59: =COMPOSITE!H$328 -> 8 | L59: =COMPOSITE!I$328 -> 8.7 | M59: =COMPOSITE!H$329 -> 24 | N59: =COMPOSITE!I$329 -> 27.551333 | O59: =COMPOSITE!H332 -> 65 | P59: =COMPOSITE!I332 -> 53 | Q59: =COMPOSITE!H333 -> 18 | R59: =COMPOSITE!I333 -> 12.485333 | S59: =COMPOSITE!H334 -> 12 | T59: =COMPOSITE!E334 -> 10.852759 | U59: =COMPOSITE!H337 -> 24 | V59: =COMPOSITE!I337 -> 24.995333 | W59: =COMPOSITE!H338 -> 16 | X59: =COMPOSITE!I338 -> 11.652333
B60: 42491
B61: 42522
B62: 42552
B63: 42583
B64: 42614
B65: 42644
B66: 42675
B67: 42705
B68: YTD Total | C68: =SUM(C56:C67) -> 1807.9045 | D68: =SUM(D56:D67) -> 1882.3647 | E68: =SUM(E56:E67) -> 400 | F68: =SUM(F56:F67) -> 404.49194 | G68: =SUM(G56:G67) -> 40 | H68: =SUM(H56:H67) -> 44.933656 | I68: =SUM(I56:I67) -> 292 | J68: =SUM(J56:J67) -> 353.56028 | ... P68: =SUM(P56:P67) -> 257.99484 | Q68: =SUM(S56:S67) -> 47.904516 | R68: =SUM(T56:T67) -> 44.138276 | S68: =SUM(U56:U67) -> 96 | T68: =SUM(V56:V67) -> 108.55566 | U68: =SUM(W56:W67) -> 64 | V68: =SUM(X56:X67) -> 63.602656 | W68: =SUM(W56:W67) -> 64 | X68: =SUM(X56:X67) -> 63.602656

Sheet MLP PREMIUM LABOR
A1: PREMIUM HOURS
A2: Month | B2: DIVISION TOTAL | F2: JFK | J2: JUPITER | N2: KENDALL | R2: KENDALL PEDS | V2: OCALA | Z2: ST MARY'S | AD2: W MARION QC | AH2: W MARION | AL2: PROVICENCE | AP2: ST JOHN | AT2: OSCEOLA | AX2: OSCEOLA PEDS | BB2: HUNTERS CREEK
B3: Transition Team | C3: Shift Incentive | D3: Total OT | E3: Locums | F3: Transition Team | G3: Shift Incentive | H3: Total OT | I3: Locums | J3: Transition Team | K3: Shift Incentive | L3: Total OT | M3: Locums | N3: Transition Team | O3: Shift Incentive | P3: Total OT | Q3: Locums | R3: Transition Team | S3: Shift Incentive | T3: Total OT | U3: Locums | V3: Transition Team | W3: Shift Incentive | X3: Total OT | Y3: Locums | Z3: Transition Team | AA3: Shift Incentive | AB3: Total OT | AC3: Locums | AD3: Transition Team | AE3: Shift Incentive | AF3: Total OT | AG3: Locums | AH3: Transition Team | AI3: Shift Incentive | AJ3: Total OT | AK3: Locums | AL3: Transition Team | AM3: Shift Incentive | AN3: Total OT | AO3: Locums | AP3: Transition Team | AQ3: Shift Incentive | AR3: Total OT | AS3: Locums | AT3: Transition Team | AU3: Shift Incentive | AV3: Total OT | AW3: Locums | AX3: Transition Team | AY3: Shift Incentive | AZ3: Total OT | BA3: Locums | BB3: Transition Team | BC3: Shift Incentive | BD3: Total OT | BE3: Locums
A4: 42370 | B4: =COMPOSITE!B$247 -> 0 | C4: =COMPOSITE!C$247 -> 93.75 | D4: =COMPOSITE!D$247 -> 725.25 | E4: =COMPOSITE!E$247 -> 92 | F4: =COMPOSITE!B$230 -> 0 | G4: =COMPOSITE!C$230 -> 0 | H4: =COMPOSITE!D$230 -> 280.75 | I4: =COMPOSITE!E$230 -> 0 | J4: =COMPOSITE!B$231 -> 0 | K4: =COMPOSITE!C$231 -> 0 | L4: =COMPOSITE!D$231 -> 0 | M4: =COMPOSITE!E$231 -> 0 | N4: =COMPOSITE!B$232 -> 0 | O4: =COMPOSITE!C$232 -> 12 | P4: =COMPOSITE!D$232 -> 64.5 | Q4: =COMPOSITE!E$232 -> 0 | R4: =COMPOSITE!B233 -> 0 | S4: =COMPOSITE!C233 -> 0 | T4: =COMPOSITE!D233 -> 38.75 | U4: =COMPOSITE!E233 -> 0 | V4: =COMPOSITE!B$234 -> 0 | W4: =COMPOSITE!C$234 -> 14.25 | X4: =COMPOSITE!D$234 -> 80.75 | Y4: =COMPOSITE!E$234 -> 92 | Z4: =COMPOSITE!B$236 -> 0 | AA4: =COMPOSITE!C$236 -> 67.5 | AB4: =COMPOSITE!D$236 -> 9 | AC4: =COMPOSITE!E$236 -> 0 | AD4: =COMPOSITE!B238 -> 0 | AE4: =COMPOSITE!C238 -> 0 | AF4: =COMPOSITE!D238 -> 0 | AG4: =COMPOSITE!E238 -> 0 | AH4: =COMPOSITE!B$237 -> 0 | AI4: =COMPOSITE!C$237 -> 0 | AJ4: =COMPOSITE!D$237 -> 37.25 | AK4: =COMPOSITE!E$237 -> 0 | AL4: =COMPOSITE!B239 -> 0 | AM4: =COMPOSITE!C239 -> 0 | AN4: =COMPOSITE!D239 -> 70.25 | AO4: =COMPOSITE!E239 -> 0 | AT4: =COMPOSITE!B241 -> 0 | AU4: =COMPOSITE!C241 -> 0 | AV4: =COMPOSITE!D241 -> 116 | AW4: =COMPOSITE!E241 -> 0 | BB4: =COMPOSITE!B243 -> 0 | BC4: =COMPOSITE!C243 -> 0 | BD4: =COMPOSITE!D243 -> 28 | BE4: =COMPOSITE!E243 -> 0
A5: 42401 | B5: =COMPOSITE!F$247 -> 0 | C5: =COMPOSITE!G$247 -> 43 | D5: =COMPOSITE!H$247 -> 793.75 | E5: =COMPOSITE!I$247 -> 256 | F5: =COMPOSITE!F$230 -> 0 | G5: =COMPOSITE!G$230 -> 0 | H5: =COMPOSITE!H$230 -> 255 | I5: =COMPOSITE!I$230 -> 0 | J5: =COMPOSITE!F$231 -> 0 | K5: =COMPOSITE!G$231 -> 0 | L5: =COMPOSITE!H$231 -> 6 | M5: =COMPOSITE!I$231 -> 0 | N5: =COMPOSITE!F$232 -> 0 | O5: =COMPOSITE!G$232 -> 12 | P5: =COMPOSITE!H$232 -> 84.5 | Q5: =COMPOSITE!I$232 -> 0 | R5: =COMPOSITE!F233 -> 0 | S5: =COMPOSITE!G233 -> 0 | T5: =COMPOSITE!H233 -> 47.75 | U5: =COMPOSITE!I233 -> 0 | V5: =COMPOSITE!F$234 -> 0 | W5: =COMPOSITE!G$234 -> 0 | X5: =COMPOSITE!H$234 -> 81.5 | Y5: =COMPOSITE!I$234 -> 256 | Z5: =COMPOSITE!F$236 -> 0 | AA5: =COMPOSITE!G$236 -> 31 | AB5: =COMPOSITE!H$236 -> 15 | AC5: =COMPOSITE!I$236 -> 0 | AD5: =COMPOSITE!F238 -> 0 | AE5: =COMPOSITE!G238 -> 0 | AF5: =COMPOSITE!H238 -> 0 | AG5: =COMPOSITE!I238 -> 0 | AH5: =COMPOSITE!F$237 -> 0 | AI5: =COMPOSITE!G$237 -> 0 | AJ5: =COMPOSITE!H$237 -> 80 | AK5: =COMPOSITE!I$237 -> 0 | AL5: =COMPOSITE!F239 -> 0 | AM5: =COMPOSITE!G239 -> 0 | AN5: =COMPOSITE!H239 -> 20 | AO5: =COMPOSITE!I239 -> 0 | AT5: =COMPOSITE!F241 -> 0 | AU5: =COMPOSITE!G241 -> 0 | AV5: =COMPOSITE!H241 -> 138 | AW5: =COMPOSITE!I241 -> 0 | BB5: =COMPOSITE!F243 -> 0 | BC5: =COMPOSITE!G243 -> 0 | BD5: =COMPOSITE!H243 -> 58 | BE5: =COMPOSITE!I243 -> 0
A6: 42430 | B6: =COMPOSITE!J$247 -> 0 | C6: =COMPOSITE!K$247 -> 1022 | D6: =COMPOSITE!L$247 -> 614 | E6: =COMPOSITE!M$247 -> 233 | F6: =COMPOSITE!J$230 -> 0 | G6: =COMPOSITE!K$230 -> 0 | H6: =COMPOSITE!L$230 -> 167 | I6: =COMPOSITE!M$230 -> 0 | J6: =COMPOSITE!J$231 -> 0 | K6: =COMPOSITE!K$231 -> 0 | L6: =COMPOSITE!L$231 -> 20 | M6: =COMPOSITE!M$231 -> 0 | N6: =COMPOSITE!J$232 -> 0 | O6: =COMPOSITE!K$232 -> 22 | P6: =COMPOSITE!L$232 -> 77.75 | Q6: =COMPOSITE!M$232 -> 0 | R6: =COMPOSITE!J233 -> 0 | S6: =COMPOSITE!K233 -> 0 | T6: =COMPOSITE!L233 -> 67 | U6: =COMPOSITE!M233 -> 0 | V6: =COMPOSITE!J$234 -> 0 | W6: =COMPOSITE!K$234 -> 0 | X6: =COMPOSITE!L$234 -> 137.5 | Y6: =COMPOSITE!M$234 -> 233 | Z6: =COMPOSITE!J$236 -> 0 | AA6: =COMPOSITE!K$236 -> 0 | AB6: =COMPOSITE!L$236 -> 7.5 | AC6: =COMPOSITE!M$236 -> 0 | AD6: =COMPOSITE!J238 -> 0 | AE6: =COMPOSITE!K238 -> 0 | AF6: =COMPOSITE!L238 -> 0 | AG6: =COMPOSITE!M238 -> 0 | AH6: =COMPOSITE!J$237 -> 0 | AI6: =COMPOSITE!K$237 -> 0 | AJ6: =COMPOSITE!L$237 -> 40.25 | AK6: =COMPOSITE!M$237 -> 0 | AL6: =COMPOSITE!J239 -> 0 | AM6: =COMPOSITE!K239 -> 0 | AN6: =COMPOSITE!L239 -> 11 | AO6: =COMPOSITE!M239 -> 0 | AT6: =COMPOSITE!J241 -> 0 | AU6: =COMPOSITE!K241 -> 600 | AV6: =COMPOSITE!L241 -> 61 | AW6: =COMPOSITE!M241 -> 0 | BB6: =COMPOSITE!J243 -> 0 | BC6: =COMPOSITE!K243 -> 400 | BD6: =COMPOSITE!L243 -> 2.75 | BE6: =COMPOSITE!M243 -> 0
A7: 42461
A8: 42491
A9: 42522
A10: 42552
A11: 42583
A12: 42614
A13: 42644
A14: 42675
A15: 42705
A16: YTD Total | B16: =SUM(B4:B15) -> 0 | C16: =SUM(C4:C15) -> 1158.75 | D16: =SUM(D4:D15) -> 2133 | E16: =SUM(E4:E15) -> 581 | F16: =SUM(F4:F15) -> 0 | G16: =SUM(G4:G15) -> 0 | H16: =SUM(H4:H15) -> 702.75 | I16: =SUM(I4:I15) -> 0 | ... BE16: =SUM(BE4:BE15) -> 0
A18: PREMIUM COSTS
A19: Month | B19: DIVISION TOTAL | F19: JFK | J19: JUPITER | N19: KENDALL | R19: KENDALL PEDS | V19: OCALA | Z19: ST MARY'S | AD19: W MARION QC | AH19: W MARION | AL19: PROVIDENCE | AP19: ST JOHN | AT19: OSCEOLA | AX19: OSCEOLA PEDS | BB19: HUNTERS CREEK
B20: Transition Team | C20: Shift Incentive | D20: Total OT | E20: Incremental OT | F20: Transition Team | G20: Shift Incentive | H20: Total OT | I20: Incremental OT | J20: Transition Team | K20: Shift Incentive | L20: Total OT | M20: Incremental OT | N20: Transition Team | O20: Shift Incentive | P20: Total OT | Q20: Incremental OT | R20: Transition Team | S20: Shift Incentive | T20: Total OT | U20: Incremental OT | V20: Transition Team | W20: Shift Incentive | X20: Total OT | Y20: Incremental OT | Z20: Transition Team | AA20: Shift Incentive | AB20: Total OT | AC20: Incremental OT | AD20: Transition Team | AE20: Shift Incentive | AF20: Total OT | AG20: Incremental OT | AH20: Transition Team | AI20: Shift Incentive | AJ20: Total OT | AK20: Incremental OT | AL20: Transition Team | AM20: Shift Incentive | AN20: Total OT | AO20: Incremental OT | AP20: Transition Team | AQ20: Shift Incentive | AR20: Total OT | AS20: Incremental OT | AT20: Transition Team | AU20: Shift Incentive | AV20: Total OT | AW20: Incremental OT | AX20: Transition Team | AY20: Shift Incentive | AZ20: Total OT | BA20: Incremental OT | BB20: Transition Team | BC20: Shift Incentive | BD20: Total OT | BE20: Incremental OT
A21: 42370 | B21: =COMPOSITE!B$269 -> 0 | C21: =COMPOSITE!C$269 -> 3940 | D21: =COMPOSITE!D$269 -> 57119.52 | E21: =COMPOSITE!E$269 -> 30707.49 | F21: =COMPOSITE!B$252 -> 0 | G21: =COMPOSITE!C$252 -> 0 | H21: =COMPOSITE!D$252 -> 20820.42 | I21: =COMPOSITE!E$252 -> 10410.21 | J21: =COMPOSITE!B$253 -> 0 | K21: =COMPOSITE!C$253 -> 0 | L21: =COMPOSITE!D$253 -> 75 | M21: =COMPOSITE!E$253 -> 75 | N21: =COMPOSITE!B$254 -> 0 | O21: =COMPOSITE!C$254 -> 500 | P21: =COMPOSITE!D$254 -> 5603.2 | Q21: =COMPOSITE!E$254 -> 3085.52 | R21: =COMPOSITE!B255 -> 0 | S21: =COMPOSITE!C255 -> 0 | T21: =COMPOSITE!D255 -> 2939.71 | U21: =COMPOSITE!E255 -> 1781.16 | V21: =COMPOSITE!B$256 -> 0 | W21: =COMPOSITE!C$256 -> 500 | X21: =COMPOSITE!D$256 -> 8149.88 | Y21: =COMPOSITE!E$256 -> 4074.94 | Z21: =COMPOSITE!B$257 -> 0 | AA21: =COMPOSITE!C$257 -> 2440 | AB21: =COMPOSITE!D$257 -> 585 | AC21: =COMPOSITE!E$257 -> 427.5 | AD21: =COMPOSITE!B$259 -> 0 | AE21: =COMPOSITE!C$259 -> 0 | AF21: =COMPOSITE!D$259 -> 0 | AG21: =COMPOSITE!E$259 -> 0 | AH21: =COMPOSITE!B$258 -> 0 | AI21: =COMPOSITE!C$258 -> 0 | AJ21: =COMPOSITE!D$258 -> 2877.56 | AK21: =COMPOSITE!E$258 -> 1438.78 | AL21: =COMPOSITE!B260 -> 0 | AM21: =COMPOSITE!C260 -> 0 | AN21: =COMPOSITE!D260 -> 5268.75 | AO21: =COMPOSITE!E260 -> 2634.38 | AT21: =COMPOSITE!B262 -> 0 | AU21: =COMPOSITE!C262 -> 500 | AV21: =COMPOSITE!D262 -> 8700 | AW21: =COMPOSITE!E262 -> 5220 | BB21: =COMPOSITE!B264 -> 0 | BC21: =COMPOSITE!C264 -> 0 | BD21: =COMPOSITE!D264 -> 2100 | BE21: =COMPOSITE!E264 -> 1560
A22: 42401 | B22: =COMPOSITE!F$269 -> 0 | C22: =COMPOSITE!G$269 -> 3012.5 | D22: =COMPOSITE!H$269 -> 96061.27 | E22: =COMPOSITE!I$269 -> 34013.3 | F22: =COMPOSITE!F$252 -> 0 | G22: =COMPOSITE!G$252 -> 0 | H22: =COMPOSITE!H$252 -> 28366.2 | I22: =COMPOSITE!I$252 -> 9455.4 | J22: =COMPOSITE!F$253 -> 0 | K22: =COMPOSITE!G$253 -> 0 | L22: =COMPOSITE!H$253 -> 675 | M22: =COMPOSITE!I$253 -> 225 | N22: =COMPOSITE!F$254 -> 0 | O22: =COMPOSITE!G$254 -> 0 | P22: =COMPOSITE!H$254 -> 10853.79 | Q22: =COMPOSITE!I$254 -> 3867.3 | R22: =COMPOSITE!F255 -> 0 | S22: =COMPOSITE!G255 -> 0 | T22: =COMPOSITE!H255 -> 5262.47 | U22: =COMPOSITE!I255 -> 1817.79 | V22: =COMPOSITE!F$256 -> 0 | W22: =COMPOSITE!G$256 -> 250 | X22: =COMPOSITE!H$256 -> 11461.22 | Y22: =COMPOSITE!I$256 -> 3832.78 | Z22: =COMPOSITE!F$257 -> 0 | AA22: =COMPOSITE!G$257 -> 1762.5 | AB22: =COMPOSITE!H$257 -> 1687.5 | AC22: =COMPOSITE!I$257 -> 712.5 | AD22: =COMPOSITE!F$259 -> 0 | AE22: =COMPOSITE!G$259 -> 0 | AF22: =COMPOSITE!H$259 -> 0 | AG22: =COMPOSITE!I$259 -> 0 | AH22: =COMPOSITE!F$258 -> 0 | AI22: =COMPOSITE!G$258 -> 0 | AJ22: =COMPOSITE!H$258 -> 10110.09 | AK22: =COMPOSITE!I$258 -> 3370.03 | AL22: =COMPOSITE!F260 -> 0 | AM22: =COMPOSITE!G260 -> 500 | AN22: =COMPOSITE!H260 -> 2250 | AO22: =COMPOSITE!I260 -> 750 | AT22: =COMPOSITE!F262 -> 0 | AU22: =COMPOSITE!G262 -> 500 | AV22: =COMPOSITE!H262 -> 16560 | AW22: =COMPOSITE!I262 -> 6210 | BB22: =COMPOSITE!F264 -> 0 | BC22: =COMPOSITE!G264 -> 0 | BD22: =COMPOSITE!H264 -> 7470 | BE22: =COMPOSITE!I264 -> 3120
A23: 42430 | B23: =COMPOSITE!J$269 -> 0 | C23: =COMPOSITE!K$269 -> 2000 | D23: =COMPOSITE!L$269 -> 70274.89 | E23: =COMPOSITE!M$269 -> 23814.76 | F23: =COMPOSITE!J$252 -> 0 | G23: =COMPOSITE!K$252 -> 0 | H23: =COMPOSITE!L$252 -> 18577.08 | I23: =COMPOSITE!M$252 -> 6192.36 | J23: =COMPOSITE!J$253 -> 0 | K23: =COMPOSITE!K$253 -> 0 | L23: =COMPOSITE!L$253 -> 2250 | M23: =COMPOSITE!M$253 -> 750 | N23: =COMPOSITE!J$254 -> 0 | O23: =COMPOSITE!K$254 -> 1250 | P23: =COMPOSITE!L$254 -> 8821.61 | Q23: =COMPOSITE!M$254 -> 3130.86 | R23: =COMPOSITE!J255 -> 0 | S23: =COMPOSITE!K255 -> 0 | T23: =COMPOSITE!L255 -> 7305.37 | U23: =COMPOSITE!M255 -> 2473.33 | V23: =COMPOSITE!J$256 -> 0 | W23: =COMPOSITE!K$256 -> 0 | X23: =COMPOSITE!L$256 -> 16338.38 | Y23: =COMPOSITE!M$256 -> 5446.13 | Z23: =COMPOSITE!J$257 -> 0 | AA23: =COMPOSITE!K$257 -> 0 | AB23: =COMPOSITE!L$257 -> 843.75 | AC23: =COMPOSITE!M$257 -> 356.25 | AD23: =COMPOSITE!J$259 -> 0 | AE23: =COMPOSITE!K$259 -> 0 | AF23: =COMPOSITE!L$259 -> 0 | AG23: =COMPOSITE!M$259 -> 0 | AH23: =COMPOSITE!J$258 -> 0 | AI23: =COMPOSITE!K$258 -> 0 | AJ23: =COMPOSITE!L$258 -> 5040.56 | AK23: =COMPOSITE!M$258 -> 1680.19 | AL23: =COMPOSITE!J260 -> 0 | AM23: =COMPOSITE!K260 -> 250 | AN23: =COMPOSITE!L260 -> 1237.5 | AO23: =COMPOSITE!M260 -> 412.5 | AT23: =COMPOSITE!J262 -> 0 | AU23: =COMPOSITE!K262 -> 500 | AV23: =COMPOSITE!L262 -> 5971.88 | AW23: =COMPOSITE!M262 -> 2034.38 | BB23: =COMPOSITE!J264 -> 0 | BC23: =COMPOSITE!K264 -> 0 | BD23: =COMPOSITE!L264 -> 309.38 | BE23: =COMPOSITE!M264 -> 103.13
A24: 42461
A25: 42491
A26: 42522
A27: 42552
A28: 42583
A29: 42614
A30: 42644
A31: 42675
A32: 42705
A33: YTD Total | B33: =SUM(B21:B32) -> 0 | C33: =SUM(C21:C32) -> 8952.5 | D33: =SUM(D21:D32) -> 223455.68 | E33: =SUM(E21:E32) -> 88535.55 | F33: =SUM(F21:F32) -> 0 | G33: =SUM(G21:G32) -> 0 | H33: =SUM(H21:H32) -> 67763.7 | I33: =SUM(I21:I32) -> 26057.97 | ... BE33: =SUM(BE21:BE32) -> 4783.13

Sheet LABOR COST VARIANCE
L2: Sparkline
K3: Baptist
K4: JFK
K5: JFK BB
K6: JFK PBG
K7: Jupiter
K8: Kendall
K9: Moberly
K10: Monroe
K11: Ocala
K12: San Ramon
K13: St. Mary's
K14: W. Marion QC
... K18: EM DIVISION
B21: Month | C21: DIVISION | D21: BAPTIST | E21: JFK | F21: JFK BB | G21: JFK PBG | H21: JUPITER | I21: JUPITER PEDS | J21: KENDALL | K21: MOBERLY | L21: MONROE | M21: OCALA | N21: SAN RAMON | O21: ST MARY'S | P21: W MARION QC | Q21: W MARION | R21: WESTCHESTER | S21: PROVIDENCE | T21: ST JOHN | U21: OSCEOLA | V21: OSCEOLA PEDS | W21: HUNTERS CREEK | X21: CHANDLER | Y21: MERCY GILBERT
B22: 42370 | C22: =COMPOSITE!$D$367 -> 57.641668 | D22: =COMPOSITE!$D$344 -> -4.48 | E22: =COMPOSITE!$D$345 -> 39.3 | F22: =COMPOSITE!$D$346 -> 66.81 | G22: =COMPOSITE!$D$347 -> 9.03 | H22: =COMPOSITE!$D$348 -> 37.48 | I22: =COMPOSITE!D349 -> -197.87 | J22: =COMPOSITE!$D$350 -> 16.85 | K22: =COMPOSITE!$D$351 -> 52.265385 | L22: =COMPOSITE!$D$352 -> 71.13 | M22: =COMPOSITE!$D$353 -> 63.418811 | N22: =COMPOSITE!$D$354 -> 22.36 | O22: =COMPOSITE!$D$355 -> 71.97 | P22: =COMPOSITE!$D$356 -> 22.792128 | Q22: =COMPOSITE!$D$357 -> 75.73 | R22: =COMPOSITE!$D$358 -> 31.8 | S22: =COMPOSITE!$D$359 -> 35.72 | T22: =COMPOSITE!$D$360 -> -68.76 | U22: =COMPOSITE!$D$361 -> -2.4731919 | V22: =COMPOSITE!$D$362 -> -6.5595241 | W22: =COMPOSITE!$D$363 -> -105.15169 | X22: =COMPOSITE!$D$364 -> 26.133367 | Y22: =COMPOSITE!$D$365 -> 143.33402
B23: 42401 | C23: =COMPOSITE!$G$367 -> -12.187075 | D23: =COMPOSITE!$G$344 -> 0.7 | E23: =COMPOSITE!$G$345 -> 2.82 | F23: =COMPOSITE!$G$346 -> -22.44 | G23: =COMPOSITE!$G$347 -> -77.93 | H23: =COMPOSITE!$G$348 -> 34.06 | I23: =COMPOSITE!G349 -> -79.46 | J23: =COMPOSITE!$G$350 -> -21.81 | K23: =COMPOSITE!$G$351 -> 0.50704015 | L23: =COMPOSITE!$G$352 -> -13.73 | M23: =COMPOSITE!$G$353 -> 32.700574 | N23: =COMPOSITE!$G$354 -> -3.17 | O23: =COMPOSITE!$G$355 -> -2.7 | P23: =COMPOSITE!$G$356 -> 5.1368702 | Q23: =COMPOSITE!$G$357 -> -58.78 | R23: =COMPOSITE!$G$358 -> -25.62 | S23: =COMPOSITE!$G$359 -> 3.01 | T23: =COMPOSITE!$G$360 -> 34.44 | U23: =COMPOSITE!$G$361 -> -65.31875 | V23: =COMPOSITE!$G$362 -> -41.940541 | W23: =COMPOSITE!$G$363 -> -95.949273 | X23: =COMPOSITE!$G$364 -> 39.58 | Y23: =COMPOSITE!$G$365 -> -49.733089
B24: 42430 | C24: =COMPOSITE!$J$367 -> -11.832043 | D24: =COMPOSITE!$J$344 -> -3.96 | E24: =COMPOSITE!$J$345 -> 6.97 | F24: =COMPOSITE!$J$346 -> -43.54 | G24: =COMPOSITE!$J$347 -> -88.36 | H24: =COMPOSITE!$J$348 -> 24.83 | I24: =COMPOSITE!J350 -> 31.91 | J24: =COMPOSITE!$J$350 -> 31.91 | K24: =COMPOSITE!$J$351 -> 206.84854 | L24: =COMPOSITE!$J$352 -> 2.1131437 | M24: =COMPOSITE!$J$353 -> -22.18 | N24: =COMPOSITE!$J$354 -> 28.59 | O24: =COMPOSITE!$J$355 -> -9.6 | P24: =COMPOSITE!$J$356 -> 0.30925753 | Q24: =COMPOSITE!$J$357 -> 12.47 | R24: =COMPOSITE!$J$358 -> 10.5 | S24: =COMPOSITE!$J$359 -> -1.87 | T24: =COMPOSITE!$J$360 -> -66.37 | U24: =COMPOSITE!$J$361 -> -92.927389 | V24: =COMPOSITE!$J$362 -> -38.974961 | W24: =COMPOSITE!$J$363 -> -93.086564 | X24: =COMPOSITE!$J$364 -> -20.42 | Y24: =COMPOSITE!$J$365 -> 35.618751
B25: 42461
B26: 42491
B27: 42522
B28: 42552
B29: 42583
B30: 42614
B31: 42644
B32: 42675
B33: 42705
B34: YTD Total | C34: =SUM(C22:C33) -> 33.622551 | D34: =SUM(D22:D33) -> -7.74 | E34: =SUM(E22:E33) -> 49.09 | F34: =SUM(F22:F33) -> 0.83 | G34: =SUM(G22:G33) -> -157.26 | H34: =SUM(H22:H33) -> 96.37 | I34: =SUM(I22:I33) -> -245.42 | J34: =SUM(J22:J33) -> 26.95 | ... Y34: =SUM(Y22:Y33) -> 129.21969

Sheet LABOR COST PER CASE

Sheet PQRS GRAPH

Sheet GRAPH DATA
A7: Composite Graph | B7: 41548 | C7: 42186 | D7: 42217 | E7: 42248 | F7: 42278 | G7: 42309 | H7: 42339 | I7: 42370 | J7: 42401 | K7: 42430 | L7: 42461 | M7: 42491 | N7: 42522 | O7: 42552 | P7: 42583 | Q7: 42614 | R7: 42644 | S7: 42675 | T7: 42705
A8: 72hr Returns (Admits) | B8: 113 | C8: 122 | D8: 117 | E8: 93 | F8: 86 | G8: 56 | H8: 64 | I8: =COMPOSITE!C470 -> 535 | J8: =COMPOSITE!E470 -> 497 | K8: =COMPOSITE!G470 -> 508 | L8: =COMPOSITE!I470 -> 472 | M8: =COMPOSITE!K470 -> 556 | N8: =COMPOSITE!M470 -> 536 | O8: =COMPOSITE!O470 -> 579 | P8: =COMPOSITE!Q470 -> 540 | Q8: =COMPOSITE!S470 -> 554 | R8: =COMPOSITE!U470 -> 533 | S8: =COMPOSITE!W470 -> 480 | T8: =COMPOSITE!Y470 -> 445
A9: Category III Mortalities | B9: 0 | C9: 0 | D9: 0 | E9: 0 | F9: 0 | G9: 1 | H9: 1 | I9: =COMPOSITE!B10 -> 0 | J9: =COMPOSITE!C10 -> 0 | K9: =COMPOSITE!D10 -> 1 | L9: =COMPOSITE!E10 -> 1 | M9: =COMPOSITE!F10 -> 1 | N9: =COMPOSITE!G10 -> 0 | O9: =COMPOSITE!H10 -> 0 | P9: =COMPOSITE!I10 -> 0 | ... T9: =COMPOSITE!M10 -> 0
A10: Case Volume | B10: 43027 | C10: 39120 | D10: 39554 | E10: 39807 | F10: 40247 | G10: 39355 | H10: 42349 | I10: =COMPOSITE!B69 -> 70019 | J10: =COMPOSITE!C69 -> 70334 | K10: =COMPOSITE!D69 -> 76071 | L10: =COMPOSITE!E69 -> 69769 | M10: =COMPOSITE!F69 -> 62391 | N10: =COMPOSITE!G69 -> 58565 | O10: =COMPOSITE!H69 -> 60599 | P10: =COMPOSITE!I69 -> 60242 | ... T10: =COMPOSITE!M69 -> 62363
A11: POC (Mortalities & Unscheduled Returns) | B11: 0.99868687 | C11: 0.9984407 | D11: 0.99852101 | E11: 0.99883186 | F11: 0.9989316 | G11: 0.97656125 | H11: 0.9765171 | I11: =COMPOSITE!B14 -> 0.99617961 | J11: =COMPOSITE!C14 -> 0.99646686 | K11: =COMPOSITE!D14 -> 0.98930807 | L11: =COMPOSITE!E14 -> 0.98828408 | M11: =COMPOSITE!F14 -> 0.98661566 | N11: =COMPOSITE!G14 -> 0.99542389 | O11: =COMPOSITE!H14 -> 0.99522269 | P11: =COMPOSITE!I14 -> 0.99551808 | ... T11: =COMPOSITE!M14 -> 0.99643218
A12: PQRS (Avg) | B12: 0.98229167 | C12: 0.99369937 | D12: 0.99277326 | E12: 0.99235182 | F12: 0.98700093 | G12: 0.98322148 | H12: 0.98899587 | I12: =COMPOSITE!B29 -> 0.97670535 | J12: =COMPOSITE!C29 -> 0.9778355 | K12: =COMPOSITE!D29 -> 0.99145245 | L12: =COMPOSITE!E29 -> 0.99851412 | M12: =COMPOSITE!F29 -> 0.99486295 | N12: =COMPOSITE!G29 -> 0.99328464 | O12: =COMPOSITE!H29 -> 0.94986284 | P12: =COMPOSITE!I29 -> 0.99224485 | ... S12: =COMPOSITE!L29 -> 0.99297015
A13: COMPOSITE POC 50% PQRS 50% | B13: 0.99048927 | C13: 0.99607003 | D13: 0.99564714 | E13: 0.99559184 | F13: 0.99296626 | G13: 0.97989137 | H13: 0.98275649 | I13: =(I11+I12)/2 -> 0.98644248 | J13: =(J11+J12)/2 -> 0.98715118 | K13: =(K11+K12)/2 -> 0.99038026 | L13: =(L11+L12)/2 -> 0.9933991 | M13: =(M11+M12)/2 -> 0.9907393 | N13: =(N11+N12)/2 -> 0.99435427 | O13: =(O11+O12)/2 -> 0.97254277 | P13: =(P11+P12)/2 -> 0.99388146 | ... S13: =(S11+S12)/2 -> 0.99445207
A14: TARGET | B14: 0.95 | C14: 0.95 | D14: 0.95 | E14: 0.95 | F14: 0.95 | G14: 0.95 | H14: 0.95 | I14: 0.95 | J14: 0.95 | K14: 0.95 | L14: 0.95 | M14: 0.95 | N14: 0.95 | O14: 0.95 | P14: 0.95 | Q14: 0.95 | R14: 0.95 | S14: 0.95 | T14: 0.95
A17: Arrival to Provider | B17: 41548 | C17: 42186 | D17: 42217 | E17: 42248 | F17: 42278 | G17: 42309 | H17: 42339 | I17: 42370 | J17: 42401 | K17: 42430 | L17: 42461 | M17: 42491 | N17: 42522 | O17: 42552 | P17: 42583 | Q17: 42614 | R17: 42644 | S17: 42675 | T17: 42705
A18: All Sites | B18: 28.317172 | C18: 36 | D18: 29 | E18: 28 | F18: 27 | G18: 28 | H18: 39 | I18: =EFFICIENCY!C19 -> 27.030028 | J18: =EFFICIENCY!C20 -> 28.897045 | K18: =EFFICIENCY!C21 -> 34.247115 | L18: =EFFICIENCY!C22 -> 29.52317 | M18: =EFFICIENCY!C23 -> 27.620735 | N18: =EFFICIENCY!C24 -> 30.77507 | O18: =EFFICIENCY!C25 -> 21.541802 | P18: =EFFICIENCY!C26 -> 24.887208 | Q18: =EFFICIENCY!C27 -> 27.796773 | R18: =EFFICIENCY!C28 -> 26.360567 | S18: =EFFICIENCY!C29 -> 11.946667 | T18: =EFFICIENCY!C30 -> 11.854
A19: Excluding Baptist Hospital Miami | B19: 23 | C19: 19 | D19: 18 | E19: 20 | F19: 21 | G19: 21 | H19: 31 | I19: =EFFICIENCY!D19 -> 12.595024 | J19: =EFFICIENCY!D20 -> 14.813263 | K19: =EFFICIENCY!D21 -> 14.031227 | L19: =EFFICIENCY!D22 -> 12.678473 | M19: =EFFICIENCY!D23 -> 10.911563 | N19: =EFFICIENCY!D24 -> 10.355744 | O19: =EFFICIENCY!D25 -> 10.836217 | P19: =EFFICIENCY!D26 -> 9.4540261 | Q19: =EFFICIENCY!D27 -> 9.8441333 | R19: =EFFICIENCY!D28 -> 9.2787827 | S19: =EFFICIENCY!D29 -> 11.946667 | T19: =EFFICIENCY!D30 -> 11.854
A20: TARGET (< 30 mins) | B20: 30 | C20: 30 | D20: 30 | E20: 30 | F20: 30 | G20: 30 | H20: 30 | I20: 30 | J20: 30 | K20: 30 | L20: 30 | M20: 30 | N20: 30 | O20: 30 | P20: 30 | Q20: 30 | R20: 30 | S20: 30 | T20: 30
A23: PPH - Physician | B23: 41548 | C23: 42186 | D23: 42217 | E23: 42248 | F23: 42278 | G23: 42309 | H23: 42339 | I23: 42370 | J23: 42401 | K23: 42430 | L23: 42461 | M23: 42491 | N23: 42522 | O23: 42552 | P23: 42583 | Q23: 42614 | R23: 42644 | S23: 42675 | T23: 42705
A24: ≥ 20k Visits (Physician Only) | B24: 2.1837791 | C24: 2.2565938 | D24: 2.3093246 | E24: 2.3698763 | F24: 2.2844538 | G24: 2.2774725 | H24: 2.3532215 | I24: =COMPOSITE!B37 -> 2.4535281 | J24: =COMPOSITE!C37 -> 2.6307196 | K24: =COMPOSITE!D37 -> 2.6669153 | L24: =COMPOSITE!E37 -> 2.5634975 | M24: =COMPOSITE!F37 -> 2.5087352 | N24: =COMPOSITE!G37 -> 2.4730433 | O24: =COMPOSITE!H37 -> 2.4498894 | P24: =COMPOSITE!I37 -> 2.3565026 | ... T24: =COMPOSITE!M37 -> 2.4360325
A25: < 20k Visits (Physician Only) | B25: 0.93649518 | C25: 1.1502743 | D25: 1.159909 | E25: 1.1776762 | F25: 1.1822555 | G25: 1.230515 | H25: 1.3229727 | I25: =COMPOSITE!B38 -> 1.2082868 | J25: =COMPOSITE!C38 -> 1.3393924 | K25: =COMPOSITE!D38 -> 1.2804476 | L25: =COMPOSITE!E38 -> 1.2513025 | M25: =COMPOSITE!F38 -> 1.1786646 | N25: =COMPOSITE!G38 -> 1.1495636 | O25: =COMPOSITE!H38 -> 1.0822638 | P25: =COMPOSITE!I38 -> 1.1258345 | ... T25: =COMPOSITE!M38 -> 1.1795075
A26: Overall Pts. per Adjusted Hr (≥ 20k Visits) Formula: Volume / (EDP Hrs + (0.5*MLP Hrs)) Excludes W Marion Quick Care | B26: 1.8562411 | C26: 1.8657119 | D26: 1.8934819 | E26: 1.95257 | F26: 1.8893731 | G26: 1.9024682 | H26: 2.0066179 | I26: =COMPOSITE!B39 -> 1.8954812 | J26: =COMPOSITE!C39 -> 2.0055749 | K26: =COMPOSITE!D39 -> 2.0406858 | L26: =COMPOSITE!E39 -> 1.9389658 | M26: =COMPOSITE!F39 -> 1.913324 | N26: =COMPOSITE!G39 -> 1.8662755 | O26: =COMPOSITE!H39 -> 1.8446512 | P26: =COMPOSITE!I39 -> 1.7907578 | ... T26: =COMPOSITE!M39 -> 1.8826757
A27: Target for ≥ 20k Visits (Physician Only) | B27: 2 | C27: 2 | D27: 2 | E27: 2 | F27: 2 | G27: 2 | H27: 2 | I27: 2 | J27: 2 | K27: 2 | L27: 2 | M27: 2 | N27: 2 | O27: 2 | P27: 2 | Q27: 2 | R27: 2 | S27: 2 | T27: 2
A30: Labor Cost/Case | C30: 42186 | D30: 42217 | E30: 42248 | F30: 42278 | G30: 42309 | H30: 42339 | I30: 42370 | J30: 42401 | K30: 42430 | L30: 42461 | M30: 42491 | N30: 42522 | O30: 42552 | P30: 42583 | Q30: 42614 | R30: 42644 | S30: 42675 | T30: 42705
A31: Budget | C31: 112.49804 | D31: 109.96205 | E31: 109.88028 | F31: 118.66903 | G31: 120.05017 | H31: 117.59322 | I31: =COMPOSITE!C367 -> 109.20528 | J31: =COMPOSITE!F367 -> 130.10862 | K31: =COMPOSITE!I367 -> 130.30324
A32: Actual | C32: 119.74022 | D32: 123.89096 | E32: 123.80101 | F32: 126.99421 | G32: 127.59606 | H32: 169.74761 | I32: =COMPOSITE!B367 -> 166.84695 | J32: =COMPOSITE!E367 -> 117.92155 | K32: =COMPOSITE!H367 -> 118.4712
A33: Variance | C33: 7.242178 | D33: 13.928913 | E33: 13.920723 | F33: 8.3251788 | G33: 7.5458949 | H33: 52.15439 | I33: =COMPOSITE!D367 -> 57.641668 | J33: =COMPOSITE!G367 -> -12.187075 | K33: =COMPOSITE!H367 -> 118.4712
A34: Premium Costs: travelers, shift incentives, MLP OT | C34: 6.3776274 | D34: 7.3517497 | E34: 7.0612353 | F34: 9.3229209 | G34: 9.7513202 | H34: 10.875495 | I34: =SUM(I35:I38)/I39 -> 14.247883 | J34: =SUM(J35:J38)/J39 -> 4.6730074 | K34: =SUM(K35:K38)/K39 -> 4.595054
A35: Traveler's Expenses | C35: 30000 | D35: 58545 | E35: 71352 | F35: 58623 | G35: 56565 | H35: 69899 | I35: ='TOTAL LABOR COST'!M16 -> 96876.57 | J35: ='TOTAL LABOR COST'!M44 -> 79438.78 | K35: ='TOTAL LABOR COST'!M72 -> 107352.47
A36: Traveler's Costs | C36: 77010 | D36: 77757.5 | E36: 80585 | F36: 87797.5 | G36: 76140 | H36: 80735 | I36: =SUM(COMPOSITE!B226,COMPOSITE!B269) -> 479749.4 | J36: =SUM(COMPOSITE!E226,COMPOSITE!F269) -> 108007.2 | K36: =SUM(COMPOSITE!H226,COMPOSITE!J269) -> 119379.3
A37: Shift Incentives | C37: 57020 | D37: 98810 | E37: 69120 | F37: 65920 | G37: 106880 | H37: 131171 | I37: =SUM(COMPOSITE!C226,COMPOSITE!C269) -> 46021 | J37: =SUM(COMPOSITE!F226,COMPOSITE!G269) -> 43095.5 | K37: =SUM(COMPOSITE!I226,COMPOSITE!K269) -> 41240
A38: MLP OT | C38: 86674.534 | D38: 62501.03 | E38: 62501.025 | F38: 87344.794 | G38: 68400.698 | H38: 58913.374 | I38: =COMPOSITE!D269 -> 57119.52 | J38: =COMPOSITE!H269 -> 96061.27 | K38: =COMPOSITE!L269 -> 70274.89
A39: CASES | C39: 39310 | D39: 40482 | E39: 40157 | F39: 32145 | G39: 31584 | H39: 31329 | I39: ='TOTAL LABOR COST'!F16 -> 47710 | J39: ='TOTAL LABOR COST'!F44 -> 69891.34 | K39: ='TOTAL LABOR COST'!F72 -> 73611.03

Sheet TOTAL LABOR COST
A1: Categories: | B1: Physician_Payroll
B2: Allied_Payroll
B3: Locums_and_Independent_Contractors_Expense (i.e Locums, Locumtenes, Independent Contractor)
B4: CONSULTING FEES
M5: TRAVEL EXPENSE
B6: 42370 | C6: COSTS | F6: CASES | I6: COST/CASE
C7: Actual | D7: Budget | F7: Actual | G7: Budget | I7: Actual | J7: Budget | K7: Variance | M7: Actual | N7: Budget
A8: Total | B8: Physician Payroll | C8: 4104486.5 | D8: 3753692.3 | E8: Total | F8: 34215 | G8: 41393.658 | I8: =C26/F16 -> 166.84695 | J8: =D26/G16 -> 109.20528 | K8: =I8-J8 -> 57.641668 | L8: Total | M8: 47308.16 | N8: 60531.617
B9: Allied Payroll | C9: 508968.11 | D9: 566282.9 | E9: Kendall | F9: 4500 | G9: 6248 | L9: Kendall | M9: 13223.44 | N9: 14208.333
B10: Consulting Fees | C10: 133855.36 | D10: 126905.9 | E10: JFK Main | F10: 5314 | G10: 7827 | L10: JFK Main | M10: 2418.65 | N10: 5416.6667
B11: Locumtenes Physician | C11: 89691.86 | D11: 379469.23 | E11: JFK PBG | F11: 421 | G11: 474 | L11: JFK PBG | M11: 0 | N11: 162.5
B12: Independend Contractor - Physician | C12: 288725 | D12: 345462.81 | E12: JFK BB | F12: 671 | G12: 943 | L12: JFK BB | M12: 51.32 | N12: 2041.6667
B13: Kendall | C13: 525687.58 | D13: 619448.88 | E13: Osceola | F13: 1286 | G13: =COMPOSITE!B166 -> 4990 | L13: Osceola | M13: 28324 | N13: 0
C14: 103256.8 | D14: 96979.091 | E14: Osceola Peds | F14: 509 | G14: =COMPOSITE!B167 -> 1622 | L14: Osceola Peds | M14: 4213 | N14: 0
C15: 66339.79 | D15: 65700 | E15: Hunters Creek | F15: 794 | G15: =COMPOSITE!B168 -> 1990 | L15: Hunters Creek | M15: 1338 | N15: 0
C16: 0 | D16: 78000 | F16: =SUM(F8:F15) -> 47710 | G16: =SUM(G8:G15) -> 65487.658 | M16: =SUM(M8:M15) -> 96876.57 | N16: =SUM(N8:N15) -> 82360.783
B17: JFK Main | C17: 635034.84 | D17: 703586.91
C18: 150207.7 | D18: 112192.31
C19: 0 | D19: 750
C20: 0 | D20: 32500
B21: JFK PBG | C21: 131880 | D21: 144201.26
B22: JFK BB | C22: 156498.61 | D22: 126426.67
B23: Osceola | C23: 950328 | D23: 0
B24: Osceola Peds | C24: 69789 | D24: 0
B25: Hunters Creek | C25: 45519 | D25: 0
C26: =SUM(C8:C25) -> 7960268.1 | D26: =SUM(D8:D25) -> 7151598.3
A29: Categories: | B29: Physician_Payroll
B30: Allied_Payroll
B31: Locums_and_Independent_Contractors_Expense (i.e Locums, Locumtenes, Independent Contractor)
B32: CONSULTING FEES
M33: TRAVEL EXPENSE
B34: 42401 | C34: COSTS | F34: CASES | I34: COST/CASE
C35: Actual | D35: Budget | F35: Actual | G35: Budget | I35: Actual | J35: Budget | K35: Variance | M35: Actual | N35: Budget
A36: Total | B36: Physician Payroll | C36: 3934152.9 | D36: 3490111.5 | E36: Total | F36: 39413.34 | G36: 36899.6 | I36: =C55/F44 -> 117.92155 | J36: =D55/G44 -> 130.10862 | K36: =I36-J36 -> -12.187075 | L36: Total | M36: 38103.67 | N36: 57128.93
B37: Allied Payroll | C37: 469550.42 | D37: 520807.18 | E37: Kendall | F37: 6436 | G37: 5676 | L37: Kendall | M37: 9701.31 | N37: 14208.32
B38: Consulting Fees | C38: 81085.54 | D38: 116792.46 | E38: JFK Main | F38: 7050 | G38: 7230 | L38: JFK Main | M38: 105.8 | N38: 5416.66
B39: Locumtenes Physician | C39: 72214.51 | D39: 351587.72 | E39: JFK PBG | F39: 547 | G39: 449 | L39: JFK PBG | M39: 0 | N39: 162.5
B40: Independend Contractor - Physician | C40: 313389.6 | D40: 323174.88 | E40: JFK BB | F40: 885 | G40: 891 | L40: JFK BB | M40: 0 | N40: 2041.66
B41: Kendall | C41: 588210.75 | D41: 556659.91 | E41: Osceola | F41: 9974 | G41: 4622 | L41: Osceola | M41: 22951 | N41: 34183
C42: 103915.15 | D42: 91233.11 | E42: Osceola Peds | F42: 1721 | G42: =COMPOSITE!C167 -> 1517 | L42: Osceola Peds | M42: 5210
C43: 65083.7 | D43: 65700 | E43: Hunters Creek | F43: 3865 | G43: 1682 | L43: Hunters Creek | M43: 3367 | N43: 6691
C44: 0 | D44: 78000 | F44: =SUM(F36:F43) -> 69891.34 | G44: =SUM(G36:G43) -> 58966.6 | M44: =SUM(M36:M43) -> 79438.78 | N44: =SUM(N36:N43) -> 119832.07
B45: JFK Main | C45: 652679.41 | D45: 661885.55
C46: 148837.15 | D46: 106462.68
C47: 0 | D47: 750
C48: 0 | D48: 32500
B49: JFK PBG | C49: 121818 | D49: 134982.88
B50: JFK BB | C50: 131795.01 | D50: 118773.31
C51: 157.95 | D51: 34071.03
B52: Osceola | C52: 1196286 | D52: 736110
B53: Osceola Peds | C53: 175579
B54: Hunters Creek | C54: 186940 | D54: 252461
C55: =SUM(C36:C54) -> 8241695.1 | D55: =SUM(D36:D54) -> 7672063.2
A57: Categories: | B57: Physician_Payroll
B58: Allied_Payroll
B59: Locums_and_Independent_Contractors_Expense (i.e Locums, Locumtenes, Independent Contractor)
B60: CONSULTING FEES
M61: TRAVEL EXPENSE
B62: 42430 | C62: COSTS | F62: CASES | I62: COST/CASE
C63: Actual | D63: Budget | F63: Actual | G63: Budget | I63: Actual | J63: Budget | K63: Variance | M63: Actual | N63: Budget
A64: Total | B64: Physician Payroll | C64: 4234969.3 | D64: 3604446.4 | E64: Total | F64: 43272.03 | G64: 40700.27 | I64: =C83/F72 -> 118.4712 | J64: =D83/G72 -> 130.30324 | K64: =I64-J64 -> -11.832043 | L64: Total | M64: 79319.58 | N64: 53483.28
B65: Allied Payroll | C65: 564180.4 | D65: 554770.9 | E65: Kendall | F65: 4917 | G65: 6617 | L65: Kendall | M65: 50.27 | N65: 14208.32
B66: Consulting Fees | C66: 125121.06 | D66: 121569.83 | E66: JFK Main | F66: 7697 | G66: 7900 | L66: JFK Main | M66: 0 | N66: 5416.66
B67: Locumtenes Physician | C67: 121079.17 | D67: 362229.22 | E67: JFK PBG | F67: 625 | G67: 478 | L67: JFK PBG | M67: 0 | N67: 162.5
B68: Independend Contractor - Physician | C68: 288000.9 | D68: 345462.8 | E68: JFK BB | F68: 926 | G68: 821 | L68: JFK BB | M68: 322.62 | N68: 2041.66
B69: Kendall | C69: 576156.26 | D69: 595037.2 | E69: Osceola | F69: 9598 | G69: 4940 | L69: Osceola | M69: 20278 | N69: 34183
C70: 102382.9 | D70: 96979.07 | E70: Osceola Peds | F70: 2263 | G70: 1622 | L70: Osceola Peds | M70: 4720 | N70: 9385
C71: 61067.2 | D71: 65700 | E71: Hunters Creek | F71: 4313 | G71: 1990 | L71: Hunters Creek | M71: 2662 | N71: 6691
C72: 38306 | D72: 78000 | F72: =SUM(F64:F71) -> 73611.03 | G72: =SUM(G64:G71) -> 65068.27 | M72: =SUM(M64:M71) -> 107352.47 | N72: =SUM(N64:N71) -> 125571.42
B73: JFK Main | C73: 722170.73 | D73: 714936.42
C74: 171795.93 | D74: 123950.91
C75: 9431.25 | D75: 750
C76: 0 | D76: 32500
B77: JFK PBG | C77: 133327.4 | D77: 144201.25
B78: JFK BB | C78: 143355.38 | D78: 126426.66
C79: 0 | D79: 36420.76
B80: Osceola | C80: 889326 | D80: 916789
B81: Osceola Peds | C81: 237980 | D81: 233789
B82: Hunters Creek | C82: 302137 | D82: 324647
C83: =SUM(C64:C82) -> 8720786.9 | D83: =SUM(D64:D82) -> 8478606.5

Sheet  CASE  VOLUME - BUDGET VARIANCE
P1: Case Variance
P2: Baptist
P3: JFK
P4: JFK BB
P5: JFK PBG
P6: Jupiter
P7: Kendall
P8: Moberly
P9: Monroe
P10: Ocala
P11: San Ramon
P12: St. Mary's
... P16: EM DIVISION
A18: Month | B18: DIVISION TOTAL | D18: BAPTIST | F18: JFK MAIN | H18: JFK BB | J18: JFK PBG | L18: JUPITER | N18: JUPITER PEDS | P18: KENDALL | R18: KENDALL PEDS | T18: MOBERLY | V18: MONROE | X18: OCALA | Z18: SAN RAMON | AB18: ST. MARY'S | AD18: W. MARION QC | AF18: W. MARION | AH18: WESTCHESTER | AJ18: PROVIDENCE | AL18: ST. JOHN | AN18: OSCEOLA | AP18: OSCEOLA PEDS | AR18: HUNTERS CREEK | AT18: CHANDLER | AV18: MERCY GILBERT
B19: Budget Vs. DPD Volume Variance | C19: % Variance | D19: Budget Vs. DPD Volume Variance | E19: % Variance | F19: Budget Vs. DPD Volume Variance | G19: % Variance | H19: Budget Vs. DPD Volume Variance | I19: % Variance | J19: Budget Vs. DPD Volume Variance | K19: % Variance | L19: Budget Vs. DPD Volume Variance | M19: % Variance | N19: Budget Vs. DPD Volume Variance | O19: % Variance | P19: Budget Vs. DPD Volume Variance | Q19: % Variance | R19: Budget Vs. DPD Volume Variance | S19: % Variance | T19: Budget Vs. DPD Volume Variance | U19: % Variance | V19: Budget Vs. DPD Volume Variance | W19: % Variance | X19: Budget Vs. DPD Volume Variance | Y19: % Variance | Z19: Budget Vs. DPD Volume Variance | AA19: % Variance | AB19: Budget Vs. DPD Volume Variance | AC19: % Variance | AD19: Budget Vs. DPD Volume Variance | AE19: % Variance | AF19: Budget Vs. DPD Volume Variance | AG19: % Variance | AH19: Budget Vs. DPD Volume Variance | AI19: % Variance | AJ19: Budget Vs. DPD Volume Variance | AK19: % Variance | AL19: Budget Vs. DPD Volume Variance | AM19: % Variance | AN19: Budget Vs. DPD Volume Variance | AO19: % Variance | AP19: Budget Vs. DPD Volume Variance | AQ19: % Variance | AR19: Budget Vs. DPD Volume Variance | AS19: % Variance | AT19: Budget Vs. DPD Volume Variance | AU19: % Variance | AV19: Budget Vs. DPD Volume Variance | AW19: % Variance
A20: 42370 | B20: =C36-B36 -> 2659 | C20: =B20/B36 -> 0.039474466 | D20: =E36-D36 -> 210 | E20: =D20/D36 -> 0.029292788 | F20: =G36-F36 -> -455 | G20: =F20/F36 -> -0.058132107 | H20: =I36-H36 -> -90 | I20: =H20/H36 -> -0.095440085 | J20: =K36-J36 -> -7 | K20: =IFERROR(J20/J36,0) -> -0.014767932 | L20: =M36-L36 -> 59 | M20: =L20/L36 -> 0.019581812 | N20: =O36-N36 -> 72 | O20: =N20/N36 -> 0.8372093 | P20: =Q36-P36 -> -896 | Q20: =IFERROR(P20/P36,0) -> -0.14340589 | R20: =S36-R36 -> -252 | S20: =IFERROR(R20/R36,0) -> -0.12637914 | T20: =U36-T36 -> 6044 | U20: =T20/T36 -> 5.7561905 | V20: =W36-V36 -> -29 | W20: =IFERROR(V20/V36,0) -> -0.03183315 | X20: =Y36-X36 -> 145 | Y20: =X20/X36 -> 0.039306045 | Z20: =AA36-Z36 -> 85 | AA20: =Z20/Z36 -> 0.058864266 | AB20: =AC36-AB36 -> -67 | AC20: =AB20/AB36 -> -0.031889576 | AD20: =AE36-AD36 -> -8 | AE20: =AD20/AD36 -> -0.0037105751 | AF20: =AG36-AF36 -> 144 | AG20: =AF20/AF36 -> 0.077544426 | AH20: =AI36-AH36 -> -10 | AI20: =AH20/AH36 -> -0.0095877277 | AJ20: =AK36-AJ36 -> -18 | AK20: =IFERROR(AJ20/AJ36,0) -> -0.0059760956 | AL20: =AM36-AL36 -> -95 | AM20: =IFERROR(AL20/AL36,0) -> -0.10662177 | AN20: =AO36-AN36 -> 93 | AO20: =IFERROR(AN20/AN36,0) -> 0.018637275 | AP20: =AQ36-AP36 -> -591 | AQ20: =IFERROR(AP20/AP36,0) -> -0.36436498 | AR20: =AS36-AR36 -> 87 | AS20: =IFERROR(AR20/AR36,0) -> 0.043718593 | AT20: =AU36-AT36 -> -1019 | AU20: =IFERROR(AT20/AT36,0) -> -0.1279026 | AV20: =AW36-AV36 -> -743 | AW20: =IFERROR(AV20/AV36,0) -> -0.15216056
A21: 42401 | B21: =C37-B37 -> 9322 | C21: =B21/B37 -> 0.15278962 | D21: =E37-D37 -> 335 | E21: =D21/D37 -> 0.05013469 | F21: =G37-F37 -> 29 | G21: =F21/F37 -> 0.004011065 | H21: =I37-H37 -> -67 | I21: =H21/H37 -> -0.075196409 | J21: =K37-J37 -> 51 | K21: =IFERROR(J21/J37,0) -> 0.11358575 | L21: =M37-L37 -> 29 | M21: =L21/L37 -> 0.010272759 | N21: =O37-N37 -> 85 | O21: =N21/N37 -> 0.57823129 | P21: =Q37-P37 -> -442 | Q21: =IFERROR(P21/P37,0) -> -0.077871741 | R21: =S37-R37 -> 110 | S21: =IFERROR(R21/R37,0) -> 0.058981233 | T21: =U37-T37 -> 6727 | U21: =T21/T37 -> 13.956432 | V21: =W37-V37 -> 2 | W21: =IFERROR(V21/V37,0) -> 0.0023529412 | X21: =Y37-X37 -> 158 | Y21: =X21/X37 -> 0.04478458 | Z21: =AA37-Z37 -> 132 | AA21: =Z21/Z37 -> 0.097705403 | AB21: =AC37-AB37 -> 114 | AC21: =AB21/AB37 -> 0.057721519 | AD21: =AE37-AD37 -> 35 | AE21: =AD21/AD37 -> 0.017148457 | AF21: =AG37-AF37 -> 319 | AG21: =AF21/AF37 -> 0.18439306 | AH21: =AI37-AH37 -> -37 | AI21: =AH21/AH37 -> -0.036561265 | AJ21: =AK37-AJ37 -> -27 | AK21: =IFERROR(AJ21/AJ37,0) -> -0.0095812633 | AL21: =AM37-AL37 -> 11 | AM21: =IFERROR(AL21/AL37,0) -> 0.013189448 | AN21: =AO37-AN37 -> 498 | AO21: =IFERROR(AN21/AN37,0) -> 0.10774556 | AP21: =AQ37-AP37 -> -369 | AQ21: =IFERROR(AP21/AP37,0) -> -0.24324324 | AR21: =AS37-AR37 -> 542 | AS21: =IFERROR(AR21/AR37,0) -> 0.29108485 | AT21: =AU37-AT37 -> 698 | AU21: =IFERROR(AT21/AT37,0) -> 0.10593413 | AV21: =AW37-AV37 -> 389 | AW21: =IFERROR(AV21/AV37,0) -> 0.096334819
A22: 42430 | B22: =C38-B38 -> 8017 | C22: =B22/B38 -> 0.11780351 | D22: =E38-D38 -> 159 | E22: =D22/D38 -> 0.021231139 | F22: =G38-F38 -> -113 | G22: =F22/F38 -> -0.014303797 | H22: =I38-H38 -> -21 | I22: =H22/H38 -> -0.025578563 | J22: =K38-J38 -> 91 | K22: =IFERROR(J22/J38,0) -> 0.19037657 | L22: =M38-L38 -> 218 | M22: =L22/L38 -> 0.072763685 | N22: =O38-N38 -> 55 | O22: =N22/N38 -> 0.25700935 | P22: =Q38-P38 -> -619 | Q22: =IFERROR(P22/P38,0) -> -0.093546925 | R22: =S38-R38 -> 310 | S22: =IFERROR(R22/R38,0) -> 0.16693592 | T22: =U38-T38 -> 7036 | U22: =T22/T38 -> 6.2320638 | V22: =W38-V38 -> 69 | W22: =IFERROR(V22/V38,0) -> 0.075824176 | X22: =Y38-X38 -> 252 | Y22: =X22/X38 -> 0.06483149 | Z22: =AA38-Z38 -> 100 | AA22: =Z22/Z38 -> 0.069252078 | AB22: =AC38-AB38 -> 16 | AC22: =AB22/AB38 -> 0.007079646 | AD22: =AE38-AD38 -> 8 | AE22: =AD22/AD38 -> 0.0034632035 | AF22: =AG38-AF38 -> 229 | AG22: =AF22/AF38 -> 0.10909957 | AH22: =AI38-AH38 -> -163 | AI22: =AH22/AH38 -> -0.13931624 | AJ22: =AK38-AJ38 -> 30 | AK22: =IFERROR(AJ22/AJ38,0) -> 0.0099601594 | AL22: =AM38-AL38 -> 4 | AM22: =IFERROR(AL22/AL38,0) -> 0.0044893378 | AN22: =AO38-AN38 -> 390 | AO22: =IFERROR(AN22/AN38,0) -> 0.078947368 | AP22: =AQ38-AP38 -> -575 | AQ22: =IFERROR(AP22/AP38,0) -> -0.35450062 | AR22: =AS38-AR38 -> 632 | AS22: =IFERROR(AR22/AR38,0) -> 0.31758794 | AT22: =AU38-AT38 -> -111 | AU22: =IFERROR(AT22/AT38,0) -> -0.014897329 | AV22: =AW38-AV38 -> 20 | AW22: =IFERROR(AV22/AV38,0) -> 0.0043792424
A23: 42461 | B23: =C39-B39 -> 6922 | C23: =B23/B39 -> 0.1101405 | D23: =E39-D39 -> 120 | E23: =D23/D39 -> 0.017241379 | F23: =G39-F39 -> -177 | G23: =F23/F39 -> -0.023822342 | H23: =I39-H39 -> 3 | I23: =H23/H39 -> 0.0041322314 | J23: =K39-J39 -> 16 | K23: =IFERROR(J23/J39,0) -> 0.038554217 | L23: =M39-L39 -> 77 | M23: =L23/L39 -> 0.029034691 | N23: =O39-N39 -> 33 | O23: =N23/N39 -> 0.17368421 | P23: =Q39-P39 -> -709 | Q23: =IFERROR(P23/P39,0) -> -0.11483641 | R23: =S39-R39 -> 1843 | S23: =IFERROR(R23/R39,0) -> 0 | T23: =U39-T39 -> 6198 | U23: =T23/T39 -> 5.5837838 | V23: =W39-V39 -> 112 | W23: =IFERROR(V23/V39,0) -> 0.12712826 | X23: =Y39-X39 -> 192 | Y23: =X23/X39 -> 0.052747253 | Z23: =AA39-Z39 -> -16 | AA23: =Z23/Z39 -> -0.011453114 | AB23: =AC39-AB39 -> 74 | AC23: =AB23/AB39 -> 0.035355948 | AD23: =AE39-AD39 -> -112 | AE23: =AD23/AD39 -> -0.049955397 | AF23: =AG39-AF39 -> 148 | AG23: =AF23/AF39 -> 0.074111167 | AH23: =AI39-AH39 -> -161 | AI23: =AH23/AH39 -> -0.14210062 | AJ23: =AK39-AJ39 -> 167 | AK23: =IFERROR(AJ23/AJ39,0) -> 0.05728988 | AL23: =AM39-AL39 -> -38 | AM23: =IFERROR(AL23/AL39,0) -> -0.044083527 | AN23: =AO39-AN39 -> 96 | AO23: =IFERROR(AN23/AN39,0) -> 0.020079481 | AP23: =AQ39-AP39 -> -524 | AQ23: =IFERROR(AP23/AP39,0) -> -0.33397068 | AR23: =AS39-AR39 -> 286 | AS23: =IFERROR(AR23/AR39,0) -> 0.14849429 | AT23: =AU39-AT39 -> -564 | AU23: =IFERROR(AT23/AT39,0) -> -0.077398106 | AV23: =AW39-AV39 -> -142 | AW23: =IFERROR(AV23/AV39,0) -> -0.031788672
A24: 42491
A25: 42522
A26: 42552
A27: 42583
A28: 42614
A29: 42644
A30: 42675
A31: 42705
A32: YTD Total | B32: =SUM(B20:B31) -> 26920 | C32: =B32/B48 -> 0.10382878 | D32: =SUM(D20:D31) -> 824 | E32: =D32/D48 -> 0.029116608 | F32: =SUM(F20:F31) -> -716 | G32: =IFERROR(F32/F48,0) -> -0.023562708 | H32: =SUM(H20:H31) -> -175 | I32: =IFERROR(H32/H48,0) -> -0.051759834 | J32: =SUM(J20:J31) -> 151 | K32: =IFERROR(J32/J48,0) -> 0.08314978 | L32: =SUM(L20:L31) -> 383 | M32: =L32/L48 -> 0.033350749 | N32: =SUM(N20:N31) -> 245 | O32: =N32/N48 -> 0.38461538 | P32: =SUM(P20:P31) -> -2666 | Q32: =IFERROR(P32/P48,0) -> -0.10786971 | R32: =SUM(R20:R31) -> 2011 | S32: =IFERROR(R32/R48,0) -> 0.35181945 | T32: =SUM(T20:T31) -> 26005 | U32: =T32/T48 -> 6.8960488 | V32: =SUM(V20:V31) -> 154 | W32: =V32/V48 -> 0.043355856 | X32: =SUM(X20:X31) -> 747 | Y32: =X32/X48 -> 0.050664677 | Z32: =SUM(Z20:Z31) -> 301 | AA32: =IFERROR(Z32/Z48,0) -> 0.053406671 | AB32: =SUM(AB20:AB31) -> 137 | AC32: =AB32/AB48 -> 0.016253411 | AD32: =SUM(AD20:AD31) -> -77 | AE32: =AD32/AD48 -> -0.0088010058 | AF32: =SUM(AF20:AF31) -> 840 | AG32: =AF32/AF48 -> 0.10933229 | AH32: =SUM(AH20:AH31) -> -371 | AI32: =AH32/AH48 -> -0.085130794 | AJ32: =SUM(AJ20:AJ31) -> 152 | AK32: =IFERROR(AJ32/AJ48,0) -> 0.012928468 | AN32: =SUM(AN20:AN31) -> 1077 | AO32: =AN32/AN48 -> 0.055707857 | AP32: =SUM(AP20:AP31) -> -2059 | AQ32: =AP32/AP48 -> -0.32527646 | AR32: =SUM(AR20:AR31) -> 1547 | AS32: =AR32/AR48 -> 0.19915036 | AT32: =SUM(AT20:AT31) -> -996 | AU32: =AT32/AT48 -> -0.034000137 | AV32: =SUM(AV20:AV31) -> -476 | AW32: =AV32/AV48 -> -0.026510721
A34: Month | B34: DIVISION TOTAL | D34: BAPTIST | F34: JFK | H34: JFK BB | J34: JFK PBG | L34: JUPITER | N34: JUPITER PEDS | P34: KENDALL | R34: KENDALL PEDS | T34: MOBERLY | V34: MONROE | X34: OCALA | Z34: SAN RAMON | AB34: ST. MARY'S | AD34: W. MARION QC | AF34: W. MARION | AH34: WESTCHESTER | AJ34: PROVIDENCE | AL34: ST. JOHN | AN34: OSCEOLA | AP34: OSCEOLA PEDS | AR34: HUNTERS CREEK | AT34: CHANDLER | AV34: MERCY GILBERT
B35: Budget Case Volume | C35: DPD Case Volume | D35: Budget Case Volume | E35: DPD Case Volume | F35: Budget Case Volume | G35: DPD Case Volume | H35: Budget Case Volume | I35: DPD Case Volume | J35: Budget Case Volume | K35: DPD Case Volume | L35: Budget Case Volume | M35: DPD Case Volume | N35: Budget Case Volume | O35: DPD Case Volume | P35: Budget Case Volume | Q35: DPD Case Volume | R35: Budget Case Volume | S35: DPD Case Volume | T35: Budget Case Volume | U35: DPD Case Volume | V35: Budget Case Volume | W35: DPD Case Volume | X35: Budget Case Volume | Y35: DPD Case Volume | Z35: Budget Case Volume | AA35: DPD Case Volume | AB35: Budget Case Volume | AC35: DPD Case Volume | AD35: Budget Case Volume | AE35: DPD Case Volume | AF35: Budget Case Volume | AG35: DPD Case Volume | AH35: Budget Case Volume | AI35: DPD Case Volume | AJ35: Budget Case Volume | AK35: DPD Case Volume | AL35: Budget Case Volume | AM35: DPD Case Volume | AN35: Budget Case Volume | AO35: DPD Case Volume | AP35: Budget Case Volume | AQ35: DPD Case Volume | AR35: Budget Case Volume | AS35: DPD Case Volume | AT35: Budget Case Volume | AU35: DPD Case Volume | AV35: Budget Case Volume | AW35: DPD Case Volume
A36: 42370 | B36: =COMPOSITE!B$172 -> 67360 | C36: =COMPOSITE!B$69 -> 70019 | D36: =COMPOSITE!B$148 -> 7169 | E36: =COMPOSITE!B$45 -> 7379 | F36: =COMPOSITE!B$149 -> 7827 | G36: =COMPOSITE!B$46 -> 7372 | H36: =COMPOSITE!B$150 -> 943 | I36: =COMPOSITE!B$47 -> 853 | J36: =COMPOSITE!B$151 -> 474 | K36: =COMPOSITE!B$48 -> 467 | L36: =COMPOSITE!B$152 -> 3013 | M36: =COMPOSITE!B$49 -> 3072 | N36: =COMPOSITE!B$153 -> 86 | O36: =COMPOSITE!B$50 -> 158 | P36: =COMPOSITE!B$154 -> 6248 | Q36: =COMPOSITE!B$51 -> 5352 | R36: =COMPOSITE!B$155 -> 1994 | S36: =COMPOSITE!B$52 -> 1742 | T36: =COMPOSITE!B$156 -> 1050 | U36: =COMPOSITE!B$53 -> 7094 | V36: =COMPOSITE!B$157 -> 911 | W36: =COMPOSITE!B$54 -> 882 | X36: =COMPOSITE!B$158 -> 3689 | Y36: =COMPOSITE!B$55 -> 3834 | Z36: =COMPOSITE!B$159 -> 1444 | AA36: =COMPOSITE!B$56 -> 1529 | AB36: =COMPOSITE!B$160 -> 2101 | AC36: =COMPOSITE!B$57 -> 2034 | AD36: =COMPOSITE!B$161 -> 2156 | AE36: =COMPOSITE!B$58 -> 2148 | AF36: =COMPOSITE!B$162 -> 1857 | AG36: =COMPOSITE!B$59 -> 2001 | AH36: =COMPOSITE!B$163 -> 1043 | AI36: =COMPOSITE!B$60 -> 1033 | AJ36: =COMPOSITE!B$164 -> 3012 | AK36: =COMPOSITE!B$61 -> 2994 | AL36: =COMPOSITE!B$165 -> 891 | AM36: =COMPOSITE!B$62 -> 796 | AN36: =COMPOSITE!B$166 -> 4990 | AO36: =COMPOSITE!B$63 -> 5083 | AP36: =COMPOSITE!B$167 -> 1622 | AQ36: =COMPOSITE!B$64 -> 1031 | AR36: =COMPOSITE!B$168 -> 1990 | AS36: =COMPOSITE!B$65 -> 2077 | AT36: =COMPOSITE!B$169 -> 7967 | AU36: =COMPOSITE!B$66 -> 6948 | AV36: =COMPOSITE!B$170 -> 4883 | AW36: =COMPOSITE!B$67 -> 4140
A37: 42401 | B37: =COMPOSITE!C$172 -> 61012 | C37: =COMPOSITE!C$69 -> 70334 | D37: =COMPOSITE!C$148 -> 6682 | E37: =COMPOSITE!C$45 -> 7017 | F37: =COMPOSITE!C$149 -> 7230 | G37: =COMPOSITE!C$46 -> 7259 | H37: =COMPOSITE!C$150 -> 891 | I37: =COMPOSITE!C$47 -> 824 | J37: =COMPOSITE!C$151 -> 449 | K37: =COMPOSITE!C$48 -> 500 | L37: =COMPOSITE!C$152 -> 2823 | M37: =COMPOSITE!C$49 -> 2852 | N37: =COMPOSITE!C$153 -> 147 | O37: =COMPOSITE!C$50 -> 232 | P37: =COMPOSITE!C$154 -> 5676 | Q37: =COMPOSITE!C$51 -> 5234 | R37: =COMPOSITE!C$155 -> 1865 | S37: =COMPOSITE!C$52 -> 1975 | T37: =COMPOSITE!C$156 -> 482 | U37: =COMPOSITE!C$53 -> 7209 | V37: =COMPOSITE!C$157 -> 850 | W37: =COMPOSITE!C$54 -> 852 | X37: =COMPOSITE!C$158 -> 3528 | Y37: =COMPOSITE!C$55 -> 3686 | Z37: =COMPOSITE!C$159 -> 1351 | AA37: =COMPOSITE!C$56 -> 1483 | AB37: =COMPOSITE!C$160 -> 1975 | AC37: =COMPOSITE!C$57 -> 2089 | AD37: =COMPOSITE!C$161 -> 2041 | AE37: =COMPOSITE!C$58 -> 2076 | AF37: =COMPOSITE!C$162 -> 1730 | AG37: =COMPOSITE!C$59 -> 2049 | AH37: =COMPOSITE!C$163 -> 1012 | AI37: =COMPOSITE!C$60 -> 975 | AJ37: =COMPOSITE!C$164 -> 2818 | AK37: =COMPOSITE!C$61 -> 2791 | AL37: =COMPOSITE!C$165 -> 834 | AM37: =COMPOSITE!C$62 -> 845 | AN37: =COMPOSITE!C$166 -> 4622 | AO37: =COMPOSITE!C$63 -> 5120 | AP37: =COMPOSITE!C$167 -> 1517 | AQ37: =COMPOSITE!C$64 -> 1148 | AR37: =COMPOSITE!C$168 -> 1862 | AS37: =COMPOSITE!C$65 -> 2404 | AT37: =COMPOSITE!C$169 -> 6589 | AU37: =COMPOSITE!C$66 -> 7287 | AV37: =COMPOSITE!C$170 -> 4038 | AW37: =COMPOSITE!C$67 -> 4427
A38: 42430 | B38: =COMPOSITE!D$172 -> 68054 | C38: =COMPOSITE!D$69 -> 76071 | D38: =COMPOSITE!D$148 -> 7489 | E38: =COMPOSITE!D$45 -> 7648 | F38: =COMPOSITE!D$149 -> 7900 | G38: =COMPOSITE!D$46 -> 7787 | H38: =COMPOSITE!D$150 -> 821 | I38: =COMPOSITE!D$47 -> 800 | J38: =COMPOSITE!D$151 -> 478 | K38: =COMPOSITE!D$48 -> 569 | L38: =COMPOSITE!D$152 -> 2996 | M38: =COMPOSITE!D$49 -> 3214 | N38: =COMPOSITE!D$153 -> 214 | O38: =COMPOSITE!D$50 -> 269 | P38: =COMPOSITE!D$154 -> 6617 | Q38: =COMPOSITE!D$51 -> 5998 | R38: =COMPOSITE!D$155 -> 1857 | S38: =COMPOSITE!D$52 -> 2167 | T38: =COMPOSITE!D$156 -> 1129 | U38: =COMPOSITE!D$53 -> 8165 | V38: =COMPOSITE!D$157 -> 910 | W38: =COMPOSITE!D$54 -> 979 | X38: =COMPOSITE!D$158 -> 3887 | Y38: =COMPOSITE!D$55 -> 4139 | Z38: =COMPOSITE!D$159 -> 1444 | AA38: =COMPOSITE!D$56 -> 1544 | AB38: =COMPOSITE!D$160 -> 2260 | AC38: =COMPOSITE!D$57 -> 2276 | AD38: =COMPOSITE!D$161 -> 2310 | AE38: =COMPOSITE!D$58 -> 2318 | AF38: =COMPOSITE!D$162 -> 2099 | AG38: =COMPOSITE!D$59 -> 2328 | AH38: =COMPOSITE!D$163 -> 1170 | AI38: =COMPOSITE!D$60 -> 1007 | AJ38: =COMPOSITE!D$164 -> 3012 | AK38: =COMPOSITE!D$61 -> 3042 | AL38: =COMPOSITE!D$165 -> 891 | AM38: =COMPOSITE!D$62 -> 895 | AN38: =COMPOSITE!D$166 -> 4940 | AO38: =COMPOSITE!D$63 -> 5330 | AP38: =COMPOSITE!D$167 -> 1622 | AQ38: =COMPOSITE!D$64 -> 1047 | AR38: =COMPOSITE!D$168 -> 1990 | AS38: =COMPOSITE!D$65 -> 2622 | AT38: =COMPOSITE!D$169 -> 7451 | AU38: =COMPOSITE!D$66 -> 7340 | AV38: =COMPOSITE!D$170 -> 4567 | AW38: =COMPOSITE!D$67 -> 4587
A39: 42461 | B39: =COMPOSITE!E$172 -> 62847 | C39: =COMPOSITE!E$69 -> 69769 | D39: =COMPOSITE!E$148 -> 6960 | E39: =COMPOSITE!E$45 -> 7080 | F39: =COMPOSITE!E$149 -> 7430 | G39: =COMPOSITE!E$46 -> 7253 | H39: =COMPOSITE!E$150 -> 726 | I39: =COMPOSITE!E$47 -> 729 | J39: =COMPOSITE!E$151 -> 415 | K39: =COMPOSITE!E$48 -> 431 | L39: =COMPOSITE!E$152 -> 2652 | M39: =COMPOSITE!E$49 -> 2729 | N39: =COMPOSITE!E$153 -> 190 | O39: =COMPOSITE!E$50 -> 223 | P39: =COMPOSITE!E$154 -> 6174 | Q39: =COMPOSITE!E$51 -> 5465 | R39: =COMPOSITE!E$155 -> 0 | S39: =COMPOSITE!E$52 -> 1843 | T39: =COMPOSITE!E$156 -> 1110 | U39: =COMPOSITE!E$53 -> 7308 | V39: =COMPOSITE!E$157 -> 881 | W39: =COMPOSITE!E$54 -> 993 | X39: =COMPOSITE!E$158 -> 3640 | Y39: =COMPOSITE!E$55 -> 3832 | Z39: =COMPOSITE!E$159 -> 1397 | AA39: =COMPOSITE!E$56 -> 1381 | AB39: =COMPOSITE!E$160 -> 2093 | AC39: =COMPOSITE!E$57 -> 2167 | AD39: =COMPOSITE!E$161 -> 2242 | AE39: =COMPOSITE!E$58 -> 2130 | AF39: =COMPOSITE!E$162 -> 1997 | AG39: =COMPOSITE!E$59 -> 2145 | AH39: =COMPOSITE!E$163 -> 1133 | AI39: =COMPOSITE!E$60 -> 972 | AJ39: =COMPOSITE!E$164 -> 2915 | AK39: =COMPOSITE!E$61 -> 3082 | AL39: =COMPOSITE!E$165 -> 862 | AM39: =COMPOSITE!E$62 -> 824 | AN39: =COMPOSITE!E$166 -> 4781 | AO39: =COMPOSITE!E$63 -> 4877 | AP39: =COMPOSITE!E$167 -> 1569 | AQ39: =COMPOSITE!E$64 -> 1045 | AR39: =COMPOSITE!E$168 -> 1926 | AS39: =COMPOSITE!E$65 -> 2212 | AT39: =COMPOSITE!E$169 -> 7287 | AU39: =COMPOSITE!E$66 -> 6723 | AV39: =COMPOSITE!E$170 -> 4467 | AW39: =COMPOSITE!E$67 -> 4325
A40: 42491
A41: 42522
A42: 42552
A43: 42583
A44: 42614
A45: 42644
A46: 42675
A47: 42705
A48: YTD Total | B48: =SUM(B36:B47) -> 259273 | C48: =SUM(C36:C47) -> 286193 | D48: =SUM(D36:D47) -> 28300 | E48: =SUM(E36:E47) -> 29124 | F48: =SUM(F36:F47) -> 30387 | G48: =SUM(G36:G47) -> 29671 | H48: =SUM(H36:H47) -> 3381 | I48: =SUM(I36:I47) -> 3206 | ... AW48: =SUM(AW36:AW47) -> 17479

Sheet COMPOSITE
A1: Emergency Medicine - 2016 Clinical Performance Data
B3: Jan | C3: Feb | D3: Mar | E3: Apr | F3: May | G3: Jun | H3: Jul | I3: Aug | J3: Sep | K3: Oct | L3: Nov | M3: Dec
A5: 72hr Returns (Total) | B5: =B470 -> 1835 | C5: =D470 -> 1705 | D5: =F470 -> 1986 | E5: =H470 -> 1747 | F5: =J470 -> 1821 | G5: =L470 -> 1822 | H5: =N470 -> 1785 | I5: =P470 -> 1737 | J5: =R470 -> 1801 | K5: =T470 -> 1678 | L5: =V470 -> 1593 | M5: =X470 -> 1378
A6: 72hr Returns (Admits) | B6: =C470 -> 535 | C6: =E470 -> 497 | D6: =G470 -> 508 | E6: =I470 -> 472 | F6: =K470 -> 556 | G6: =M470 -> 536 | H6: =O470 -> 579 | I6: =Q470 -> 540 | J6: =S470 -> 554 | K6: =U470 -> 533 | L6: =W470 -> 480 | M6: =Y470 -> 445
A7: % Returns Admitted 2nd Visit | B7: =B6/B41 -> 0.0076407832 | C7: =C6/C41 -> 0.0070662837 | D7: =D6/D41 -> 0.0066779719 | E7: =E6/E41 -> 0.0067651822 | F7: =F6/F41 -> 0.0089115417 | G7: =G6/G41 -> 0.009152224 | H7: =H6/H41 -> 0.0095546131 | I7: =I6/I41 -> 0.0089638458 | ... M7: =M6/M41 -> 0.0071356413
A8: Quarterly | B8: =SUM(B6:D6)/SUM(B69:D69) -> 0.0071156618 | E8: =SUM(E6:G6)/SUM(E69:G69) -> 0.0082002884
A9: Mortalities | B9: =B493 -> 78 | C9: =D493 -> 75 | D9: =F493 -> 68 | E9: =H493 -> 60 | F9: =J493 -> 56 | G9: =L493 -> 63 | H9: =N493 -> 60 | I9: =P493 -> 51 | J9: =R493 -> 51 | K9: =T493 -> 76 | L9: =V493 -> 74 | M9: =X493 -> 69
A10: Category III | B10: =C493 -> 0 | C10: =E493 -> 0 | D10: =G493 -> 1 | E10: =I493 -> 1 | F10: =K493 -> 1 | G10: =M493 -> 0 | H10: =O493 -> 0 | I10: =Q493 -> 0 | J10: =S493 -> 0 | K10: =U493 -> 0 | L10: =W493 -> 0 | M10: =Y493 -> 0
A11: % Mortalities w/ Opportunity | B11: =B10/B9 -> 0 | C11: =C10/C9 -> 0 | D11: =D10/D9 -> 0.014705882 | E11: =E10/E9 -> 0.016666667 | F11: =F10/F9 -> 0.017857143 | G11: =G10/G9 -> 0 | H11: =H10/H9 -> 0 | I11: =I10/I9 -> 0 | ... M11: =M10/M9 -> 0
A12: % Mortalities w/ Opportunity Quarterly | B12: =SUM(B10:D10)/SUM(B9:D9) -> 0.0045248869 | E12: =SUM(E10:G10)/SUM(E9:G9) -> 0.011173184 | H12: =SUM(H10:J10)/SUM(H9:J9) -> 0
A13: % Mortalities No Opportunity Quarterly | B13: =1-B12 -> 0.99547511 | E13: =1-E12 -> 0.98882682 | H13: =1-H12 -> 1
A14: POC (> 95%) | B14: =(1-B7)/2+(1-B11)/2 -> 0.99617961 | C14: =(1-C7)/2+(1-C11)/2 -> 0.99646686 | D14: =(1-D7)/2+(1-D11)/2 -> 0.98930807 | E14: =(1-E7)/2+(1-E11)/2 -> 0.98828408 | F14: =(1-F7)/2+(1-F11)/2 -> 0.98661566 | G14: =(1-G7)/2+(1-G11)/2 -> 0.99542389 | H14: =(1-H7)/2+(1-H11)/2 -> 0.99522269 | I14: =(1-I7)/2+(1-I11)/2 -> 0.99551808 | ... M14: =(1-M7)/2+(1-M11)/2 -> 0.99643218
A15: AMI (ASA On Arrival) | B15: =B443/C443 -> 0.94416244 | C15: =L443/M443 -> 0.93636364 | D15: =V443/W443 -> 0.97714286
A16: Quarterly | B16: =AVERAGE(B15:D15) -> 0.95255631
A17: PNA (VS Reviewed) | B17: =D443/E443 -> 0.99328859 | C17: =N443/O443 -> 1 | D17: =X443/Y443 -> 1
A18: Quarterly | B18: =AVERAGE(B17:D17) -> 0.99776286
A19: Syncope (12 Lead >50) | B19: =F443/G443 -> 0.99266504 | C19: =P443/Q443 -> 0.99714286 | D19: =Z443/AA443 -> 0.99721448
A20: Quarterly | B20: =AVERAGE(B19:D19) -> 0.99567413
A21: ECG Non Trauma Chest Pain (Apr->) | E21: =AL443/AM443 -> 1 | F21: =AX443/AY443 -> 0.99629172 | G21: =BJ443/BK443 -> 0.99593023 | H21: =BV443/BW443 -> 0.91150442 | I21: =CH443/CI443 -> 0.99467022 | J21: =CT443/CU443 -> 0.99242902 | K21: =DF443/DG443 -> 0.99011407 | L21: =DR443/DS443 -> 0.99569707
A22: Quarterly | E22: =AVERAGE(E21:G21) -> 0.99740732
A23: High Blood Pressure Screening (Apr->) | E23: =AN443/AO443 -> 0.99702823 | F23: =AZ443/BA443 -> 0.99343418 | G23: =BL443/BM443 -> 0.99063906 | H23: =BX443/BY443 -> 0.98822125 | I23: =CJ443/CK443 -> 0.98981947 | J23: =CV443/CW443 -> 0.98879841 | K23: =DH443/DI443 -> 0.99379966 | L23: =DT443/DU443 -> 0.99024323
A24: Quarterly | E24: =AVERAGE(E23:G23) -> 0.99370049
A25: Ultrasound for Pregnantcy w/ Abdo Pain (Apr->) | E25: no data | F25: no data | G25: no data | H25: no data | I25: no data | J25: no data | K25: no data | L25: no data | M25: no data
A26: Quarterly
A27: (Rhogam) for RH(-) Pregnant w/ Expo. Risk (Apr->) | E27: no data | F27: no data | G27: no data | H27: no data | I27: no data | J27: no data | K27: no data | L27: no data | M27: no data
A28: Quarterly
A29: PQRS Composite (>95%) | B29: =AVERAGE(B15,B17,B19) -> 0.97670535 | C29: =AVERAGE(C15,C17,C19) -> 0.9778355 | D29: =AVERAGE(D15,D17,D19) -> 0.99145245 | E29: =AVERAGE(E21,E23) -> 0.99851412 | F29: =AVERAGE(F21,F23) -> 0.99486295 | G29: =AVERAGE(G21,G23) -> 0.99328464 | H29: =AVERAGE(H21,H23) -> 0.94986284 | I29: =AVERAGE(I21,I23) -> 0.99224485 | J29: =AVERAGE(J21,J23) -> 0.99061372 | K29: =AVERAGE(K21,K23) -> 0.99195686 | L29: =AVERAGE(L21,L23) -> 0.99297015
A30: PQRS Quarterly Composite | B30: =AVERAGE(B29:D29) -> 0.98199777 | E30: =AVERAGE(E29:G29) -> 0.9955539 | H30: =AVERAGE(H29:J29) -> 0.9775738
A31: LBBS | B31: =LBBS!D3 -> 1058 | C31: =LBBS!D4 -> 1235 | D31: =LBBS!D5 -> 1307 | E31: =LBBS!D6 -> 1043 | F31: =LBBS!D7 -> 901 | G31: =LBBS!D8 -> 795 | H31: =LBBS!D9 -> 769 | I31: =LBBS!D10 -> 762 | J31: =LBBS!D11 -> 854 | K31: =LBBS!D12 -> 811 | L31: =LBBS!D13 -> 693 | M31: =LBBS!D14 -> 717
A32: Facility Reported Volume | B32: =LBBS!C3 -> 65146 | C32: =LBBS!C4 -> 65709 | D32: =LBBS!C5 -> 70200 | E32: =LBBS!C6 -> 64605 | F32: =LBBS!C7 -> 64223 | G32: =LBBS!C8 -> 60206 | H32: =LBBS!C9 -> 60369 | I32: =LBBS!C10 -> 61047 | J32: =LBBS!C11 -> 61027 | K32: =LBBS!C12 -> 60301 | L32: =LBBS!C13 -> 52421 | M32: =LBBS!C14 -> 51145
A33: Quarterly | B33: =SUM(B31:D31)/SUM(B32:D32) -> 0.017905548 | E33: =SUM(E31:G31)/SUM(E32:G32) -> 0.014489457 | H33: =SUM(H31:J31)/SUM(H32:J32) -> 0.013072576
A34: Arrival to Provider | B34: =EFFICIENCY!C19 -> 27.030028 | C34: =EFFICIENCY!C20 -> 28.897045 | D34: =EFFICIENCY!C21 -> 34.247115 | E34: =EFFICIENCY!C22 -> 29.52317 | F34: =EFFICIENCY!C23 -> 27.620735 | G34: =EFFICIENCY!C24 -> 30.77507 | H34: =EFFICIENCY!C25 -> 21.541802 | I34: =EFFICIENCY!C26 -> 24.887208 | J34: =EFFICIENCY!C27 -> 27.796773 | K34: =EFFICIENCY!C28 -> 26.360567 | L34: =EFFICIENCY!C30 -> 11.854 | M34: =EFFICIENCY!D29 -> 11.946667
A35: Quarterly | B35: =((B34*B32)+(C34*C32)+(D34*D32))/SUM(B32:D32) -> 30.160114 | E35: =((E34*E32)+(F34*F32)+(G34*G32))/SUM(E32:G32) -> 29.275552 | H35: =((H34*H32)+(I34*I32)+(J34*J32))/SUM(H32:J32) -> 24.753485 | K35: =AVERAGE(K34:M34) -> 16.720411
A36: PPH
A37: EDP - PHY ≥ 20k Visits | B37: ='PROVIDER PRODUCTIVITY'!D25 -> 2.4535281 | C37: ='PROVIDER PRODUCTIVITY'!D26 -> 2.6307196 | D37: ='PROVIDER PRODUCTIVITY'!D27 -> 2.6669153 | E37: ='PROVIDER PRODUCTIVITY'!D28 -> 2.5634975 | F37: ='PROVIDER PRODUCTIVITY'!D29 -> 2.5087352 | G37: ='PROVIDER PRODUCTIVITY'!D30 -> 2.4730433 | H37: ='PROVIDER PRODUCTIVITY'!D31 -> 2.4498894 | I37: ='PROVIDER PRODUCTIVITY'!D32 -> 2.3565026 | J37: ='PROVIDER PRODUCTIVITY'!D33 -> 2.4554369 | K37: ='PROVIDER PRODUCTIVITY'!D34 -> 2.3262814 | L37: ='PROVIDER PRODUCTIVITY'!D35 -> 2.2899899 | M37: ='PROVIDER PRODUCTIVITY'!D36 -> 2.4360325
A38: EDP - PHY < 20k Visits | B38: ='PROVIDER PRODUCTIVITY'!C25 -> 1.2082868 | C38: ='PROVIDER PRODUCTIVITY'!C26 -> 1.3393924 | D38: ='PROVIDER PRODUCTIVITY'!C27 -> 1.2804476 | E38: ='PROVIDER PRODUCTIVITY'!C28 -> 1.2513025 | F38: ='PROVIDER PRODUCTIVITY'!C29 -> 1.1786646 | G38: ='PROVIDER PRODUCTIVITY'!C30 -> 1.1495636 | H38: ='PROVIDER PRODUCTIVITY'!C31 -> 1.0822638 | I38: ='PROVIDER PRODUCTIVITY'!C32 -> 1.1258345 | J38: ='PROVIDER PRODUCTIVITY'!C33 -> 1.1256469 | K38: ='PROVIDER PRODUCTIVITY'!C34 -> 1.1130986 | L38: ='PROVIDER PRODUCTIVITY'!C35 -> 1.1920219 | M38: ='PROVIDER PRODUCTIVITY'!C36 -> 1.1795075
A39: Pts. per adjusted hr (≥ 20k Visits) | B39: ='PROVIDER PRODUCTIVITY'!B25 -> 1.8954812 | C39: ='PROVIDER PRODUCTIVITY'!B26 -> 2.0055749 | D39: ='PROVIDER PRODUCTIVITY'!B27 -> 2.0406858 | E39: ='PROVIDER PRODUCTIVITY'!B28 -> 1.9389658 | F39: ='PROVIDER PRODUCTIVITY'!B29 -> 1.913324 | G39: ='PROVIDER PRODUCTIVITY'!B30 -> 1.8662755 | H39: ='PROVIDER PRODUCTIVITY'!B31 -> 1.8446512 | I39: ='PROVIDER PRODUCTIVITY'!B32 -> 1.7907578 | J39: ='PROVIDER PRODUCTIVITY'!B33 -> 1.8521746 | K39: ='PROVIDER PRODUCTIVITY'!B34 -> 1.7906337 | L39: ='PROVIDER PRODUCTIVITY'!B35 -> 1.7638412 | M39: ='PROVIDER PRODUCTIVITY'!B36 -> 1.8826757
A40: Quarterly
A41: Sheridan Case Volume *DPD | B41: =B69 -> 70019 | C41: =C69 -> 70334 | D41: =D69 -> 76071 | E41: =E69 -> 69769 | F41: =F69 -> 62391 | G41: =G69 -> 58565 | H41: =H69 -> 60599 | I41: =I69 -> 60242 | ... M41: =M69 -> 62363
A43: Case Volume | B43: Jan | C43: Feb | D43: Mar | E43: Apr | F43: May | G43: Jun | H43: Jul | I43: Aug | J43: Sep | K43: Oct | L43: Nov | M43: Dec | N43: TOTAL
A44: *DPD as of 2/3/17
A45: Baptist (From Smart GEN 520) | B45: 7379 | C45: 7017 | D45: 7648 | E45: 7080 | F45: 7253 | G45: 6975 | H45: 7147 | I45: 6830 | J45: 6893 | K45: 6989 | L45: 6422 | M45: 6757 | N45: =SUM(B45:M45) -> 84390
A46: JFK - MAIN | B46: 7372 | C46: 7259 | D46: 7787 | E46: 7253 | F46: 7142 | G46: 6935 | H46: 7043 | I46: 6956 | J46: 7107 | K46: 7023 | L46: 6860 | M46: 7248 | N46: =SUM(B46:M46) -> 85985
A47: JFK BB (<20k Visits) | B47: 853 | C47: 824 | D47: 800 | E47: 729 | F47: 608 | G47: 591 | H47: 872 | I47: 580 | J47: 551 | K47: 618 | L47: 631 | M47: 828 | N47: =SUM(B47:M47) -> 8485
A48: JFK PBG (<20k Visits) | B48: 467 | C48: 500 | D48: 569 | E48: 431 | F48: 333 | G48: 305 | H48: 304 | I48: 276 | J48: 275 | K48: 342 | L48: 377 | M48: 492 | N48: =SUM(B48:M48) -> 4671
A49: Jupiter | B49: 3072 | C49: 2852 | D49: 3214 | E49: 2729 | F49: 2691 | G49: 2599 | H49: 2587 | I49: 2611 | J49: 2456 | K49: 2686 | L49: 2821 | M49: 3181 | N49: =SUM(B49:M49) -> 33499
A50: Jupiter Peds (<20k Visits) | B50: 158 | C50: 232 | D50: 269 | E50: 223 | F50: 243 | G50: 180 | H50: 188 | I50: 191 | J50: 202 | K50: 231 | L50: 213 | M50: 251 | N50: =SUM(B50:M50) -> 2581
A51: Kendall | B51: 5352 | C51: 5234 | D51: 5998 | E51: 5465 | F51: 5762 | G51: 5455 | H51: 5610 | I51: 5470 | J51: 5599 | K51: 5447 | L51: 5451 | M51: 5591 | N51: =SUM(B51:M51) -> 66434
A52: Kendall Peds | B52: 1742 | C52: 1975 | D52: 2167 | E52: 1843 | F52: 1865 | G52: 1330 | H52: 1383 | I52: 1274 | J52: 1733 | K52: 1543 | L52: 1738 | M52: 1927 | N52: =SUM(B52:M52) -> 20520
A53: Moberly (<20k Visits) | B53: =B51+B52 -> 7094 | C53: =C51+C52 -> 7209 | D53: =D51+D52 -> 8165 | E53: =E51+E52 -> 7308
A54: Monroe (<20k Visits) | B54: 882 | C54: 852 | D54: 979 | E54: 993 | F54: 919 | G54: 939 | H54: 942 | I54: 1005 | J54: 1027 | K54: 928 | L54: 888 | M54: 893 | N54: =SUM(B54:M54) -> 11247
A55: Ocala | B55: 3834 | C55: 3686 | D55: 4139 | E55: 3832 | F55: 3803 | G55: 3641 | H55: 3859 | I55: 3824 | J55: 3875 | K55: 3922 | L55: 3749 | M55: 4050 | N55: =SUM(B55:M55) -> 46214
A56: San Ramon (<20k Visits) | B56: 1529 | C56: 1483 | D56: 1544 | E56: 1381 | F56: 1593 | G56: 1574 | H56: 1607 | I56: 1577 | J56: 1521 | K56: 1481 | L56: 1421 | M56: 1655 | N56: =SUM(B56:M56) -> 18366
A57: St. Mary's | B57: 2034 | C57: 2089 | D57: 2276 | E57: 2167 | F57: 2162 | G57: 2179 | H57: 2182 | I57: 2357 | J57: 2244 | K57: 2245 | L57: 2195 | M57: 2289 | N57: =SUM(B57:M57) -> 26419
A58: W. Marion QC | B58: 2148 | C58: 2076 | D58: 2318 | E58: 2130 | F58: 1953 | G58: 1744 | H58: 1885 | I58: 1967 | J58: 1970 | K58: 1868 | L58: 1995 | M58: 1990 | N58: =SUM(B58:M58) -> 24044
A59: W. Marion | B59: 2001 | C59: 2049 | D59: 2328 | E59: 2145 | F59: 2092 | G59: 1987 | H59: 2026 | I59: 2095 | J59: 2094 | K59: 2099 | L59: 2180 | M59: 2321 | N59: =SUM(B59:M59) -> 25417
A60: Westchester (From Smart GEN 520) (<20k Visits) | B60: 1033 | C60: 975 | D60: 1007 | E60: 972 | F60: 924 | G60: 839 | H60: 1010 | I60: 852 | J60: 818 | K60: 806 | L60: 760 | M60: 889 | N60: =SUM(B60:M60) -> 10885
A61: Providence | B61: 2994 | C61: 2791 | D61: 3042 | E61: 3082 | F61: 2987 | G61: 2951 | H61: 3103 | I61: 3090 | J61: 3024 | K61: 3071 | L61: 2982 | M61: 2958 | N61: =SUM(B61:M61) -> 36075
A62: St. John (<20k Visits) | B62: 796 | C62: 845 | D62: 895 | E62: 824 | F62: 888 | G62: 910 | H62: 919 | I62: 951 | J62: 964 | K62: 1044 | L62: 935 | M62: 927 | N62: =SUM(B62:M62) -> 10898
A63: Osceola | B63: 5083 | C63: 5120 | D63: 5330 | E63: 4877 | F63: 4812 | G63: 4484 | H63: 4535 | I63: 4547 | J63: 4295 | K63: 4235 | L63: 4179 | M63: 4476 | N63: =SUM(B63:M63) -> 55973
A64: Osceola (PEDS) (<20K Visits) | B64: 1031 | C64: 1148 | D64: 1047 | E64: 1045 | F64: 1001 | G64: 793 | H64: 998 | I64: 906 | J64: 907 | K64: 909 | L64: 986 | M64: 928 | N64: =SUM(B64:M64) -> 11699
A65: Hunters Creek | B65: 2077 | C65: 2404 | D65: 2622 | E65: 2212 | F65: 2228 | G65: 1973 | H65: 1979 | I65: 2006 | J65: 2035 | K65: 1906 | L65: 1903 | M65: 1973 | N65: =SUM(B65:M65) -> 25318
... A67: Mercy Gilbert | B67: 4140 | C67: 4427 | D67: 4587 | E67: 4325 | F67: 4274 | G67: 3782 | H67: 3924 | I67: 4083 | J67: 4001 | K67: 3986 | L67: 3872 | M67: 4023 | N67: =SUM(B67:M67) -> 49424
A68: INSERT ROW HERE
A69: MONTHLY TOTAL | B69: =SUM(B45:B68) -> 70019 | C69: =SUM(C45:C68) -> 70334 | D69: =SUM(D45:D68) -> 76071 | E69: =SUM(E45:E68) -> 69769 | F69: =SUM(F45:F68) -> 62391 | G69: =SUM(G45:G68) -> 58565 | H69: =SUM(H45:H68) -> 60599 | I69: =SUM(I45:I68) -> 60242 | ... M69: =SUM(M45:M68) -> 62363 | N69: =SUM(B69:M69) -> 769346
A71: Case Volume - Physicians | B71: Jan | C71: Feb | D71: Mar | E71: Apr | F71: May | G71: Jun | H71: Jul | I71: Aug | J71: Sep | K71: Oct | L71: Nov | M71: Dec
A72: *Billed Case Volumes as of 2/1/17
A73: Baptist | B73: 7330 | C73: 6982 | D73: 7633 | E73: 7031 | F73: 7201 | G73: 6943 | H73: 7139 | I73: 7048 | J73: 7024 | K73: 7019 | L73: 6969
A74: JFK MAIN | B74: 7362 | C74: 7249 | D74: 7767 | E74: 7246 | F74: 7128 | G74: 6930 | H74: 7015 | I74: 6959 | J74: 7064 | K74: 7033 | L74: 6852 | M74: 7105
A75: JFK BB (<20k Visits) | B75: 854 | C75: 820 | D75: 798 | E75: 725 | F75: 606 | G75: 590 | H75: 570 | I75: 578 | J75: 552 | K75: 616 | L75: 633 | M75: 822
A76: JFK PBG (<20k Visits) | B76: 465 | C76: 499 | D76: 568 | E76: 429 | F76: 333 | G76: 304 | H76: 301 | I76: 277 | J76: 275 | K76: 342 | L76: 375 | M76: 478
A77: Jupiter - Loc 24 | B77: 3067 | C77: 2844 | D77: 3213 | E77: 2710 | F77: 2698 | G77: 2582 | H77: 2576 | I77: 2604 | J77: 2502 | K77: 2671 | L77: 2854 | M77: 2862
A78: Jupiter (PEDS) - Loc 8 (<20k Visits) | B78: 155 | C78: 232 | D78: 269 | E78: 223 | F78: 223 | G78: 180 | H78: 185 | I78: 190 | J78: 202 | K78: 230 | L78: 210 | M78: 225
A79: Kendall - Loc 1 | B79: 5347 | C79: 5229 | D79: 5989 | E79: 5482 | F79: 5759 | G79: 5434 | H79: 5604 | I79: 5463 | J79: 5592 | K79: 5450 | L79: 5221 | M79: 5404
A80: Kendall (PEDS) - Loc 5 | B80: 1743 | C80: 1974 | D80: 2166 | E80: 1823 | F80: 1857 | G80: 1328 | H80: 1373 | I80: 1274 | J80: 1729 | K80: 1541 | L80: 1738 | M80: 1907
A81: Moberly (<20k Visits) | B81: 982 | C81: 992 | D81: 1094 | E81: 1098 | F81: 1077 | G81: 1006 | H81: 993
A82: Monroe (<20k Visits) | B82: 881 | C82: 852 | D82: 940 | E82: 931 | F82: 866 | G82: 904 | H82: 907 | I82: 1006 | J82: 1027 | K82: 917 | L82: 880 | M82: 863
A83: Ocala | B83: 3827 | C83: 3684 | D83: 4136 | E83: 3823 | F83: 3797 | G83: 3636 | H83: 3854 | I83: 3818 | J83: 3855 | K83: 3892 | L83: 3718 | M83: 3898
A84: San Ramon (<20k Visits) | B84: 1528 | C84: 1481 | D84: 1543 | E84: 1381 | F84: 1593 | G84: 1573 | H84: 1604 | I84: 1575 | J84: 1520 | K84: 1478 | L84: 1422 | M84: 1589
A85: St. Mary's | B85: 2031 | C85: 2091 | D85: 2271 | E85: 2166 | F85: 2161 | G85: 2177 | H85: 2178 | I85: 2353 | J85: 2242 | K85: 2238 | L85: 2187 | M85: 2179
A86: W. Marion - Loc 16 | B86: 1996 | C86: 2043 | D86: 2312 | E86: 2144 | F86: 2087 | G86: 1986 | H86: 2026 | I86: 2093 | J86: 2093 | K86: 1839 | L86: 2147 | M86: 2249
A87: W. Marion QC - Loc 27 | B87: 2147 | C87: 2081 | D87: 2329 | E87: 2123 | F87: 1952 | G87: 1744 | H87: 1885 | I87: 1966 | J87: 1969 | K87: 1867 | L87: 2025 | M87: 1965
A88: Westchester (<20k Visits) | B88: 1002 | C88: 1044 | D88: 1003 | E88: 968 | F88: 922 | G88: 834 | H88: 776 | I88: 838 | J88: 802 | K88: 779 | L88: 756 | M88: 858
A89: Providence | B89: 2990 | C89: 2786 | D89: 3028 | E89: 3078 | F89: 2972 | G89: 2955 | H89: 3099 | I89: 3081 | J89: 3024 | K89: 3064
A90: St. John (<20k Visits) | B90: 791 | C90: 845 | D90: 891 | E90: 823 | F90: 887 | G90: 910 | H90: 919 | I90: 950 | J90: 963 | K90: 1042
A91: Osceola - Loc 2 | B91: 5077 | C91: 5106 | D91: 5321 | E91: 4865 | F91: 4810 | G91: 4472 | H91: 4527 | I91: 4542 | J91: 4289 | K91: 4172 | L91: 4143 | M91: 4337
A92: Osceola (PEDS) - Loc 3 (<20k Visits) | B92: 1018 | C92: 1148 | D92: 1048 | E92: 1042 | F92: 995 | G92: 796 | H92: 696 | I92: 905 | J92: 905 | K92: 909 | L92: 965 | M92: 921
A93: Hunters Creek | B93: 2085 | C93: 2403 | D93: 2617 | E93: 2210 | F93: 2226 | G93: 1969 | H93: 1981 | I93: 2002 | J93: 2033 | K93: 1905 | L93: 1851 | M93: 1826
A94: Chandler | B94: 6842 | C94: 7137 | D94: 7156 | E94: 6618 | F94: 6796 | G94: 6320 | H94: 6412 | I94: 6697 | J94: 6419 | K94: 6380 | L94: 6334 | M94: 6514
A95: Mercy Gilbert | B95: 4084 | C95: 4333 | D95: 4499 | E95: 4234 | F95: 4210 | G95: 3734 | H95: 3854 | I95: 4012 | J95: 3936 | K95: 3896 | L95: 3789 | M95: 3875
A96: INSERT ROW HERE
A97: MONTHLY TOTAL | B97: =SUM(B73:B96) -> 63604 | C97: =SUM(C73:C96) -> 63855 | D97: =SUM(D73:D96) -> 68591 | E97: =SUM(E73:E96) -> 63173 | F97: =SUM(F73:F96) -> 63156 | G97: =SUM(G73:G96) -> 59307 | H97: =SUM(H73:H96) -> 60474 | I97: =SUM(I73:I96) -> 60231 | ... M97: =SUM(M73:M96) -> 49877
A99: Case Volume - APP / MLP | B99: Jan | C99: Feb | D99: Mar | E99: Apr | F99: May | G99: Jun | H99: Jul | I99: Aug | J99: Sep | K99: Oct | L99: Nov | M99: Dec
A100: *Billed Case Volumes as of 10/31/16
A101: Baptist No App's/MLP's
A102: JFK | B102: 1514 | C102: 1904 | D102: 4146 | E102: 4994 | F102: 3595 | G102: 3681 | H102: 3658 | I102: 3798 | J102: 3758 | K102: 3591 | L102: 3557 | M102: 2510
A103: Jupiter | B103: 903 | C103: 887 | D103: 928 | E103: 749 | F103: 830 | G103: 817 | H103: 819 | I103: 827 | J103: 862 | K103: 819 | L103: 825 | M103: 797
A104: Kendall - Loc 1 | B104: 1552 | C104: 1766 | D104: 2684 | E104: 2282 | F104: 2179 | G104: 2375 | H104: 2307 | I104: 2067 | J104: 2341 | K104: 2342 | L104: 2291 | M104: 2257
A105: Kendall PEDS - Loc 5 | B105: 647 | C105: 872 | D105: 1001 | E105: 824 | F105: 817 | G105: 806 | H105: 832 | I105: 814 | J105: 806 | K105: 822 | L105: 816 | M105: 827
A106: Ocala | B106: 1388 | C106: 1326 | D106: 1482 | E106: 1318 | F106: 1388 | G106: 1321 | H106: 1360 | I106: 1383 | J106: 1354 | K106: 1457 | L106: 1363 | M106: 1399
...

Sheet FACILITIES
B1: 42370 | C1: 42401 | D1: 42430 | E1: 42461 | F1: 42491 | G1: 42522 | H1: 42552 | I1: 42583 | J1: 42614 | K1: 42644 | L1: 42675 | M1: 42705
A3: Kendall - HCA East
A5: Total Patient Volume | B5: 7558 | C5: 7752 | D5: 8404 | E5: 7545 | F5: 7782 | G5: 6870 | H5: 7066 | I5: 6820 | J5: 7417 | K5: 7061 | L5: 7058 | M5: 7664
A6: Door / Arrival to Provider Greet (Min Wait) | B6: 16 | C6: 16 | D6: 11 | E6: 9 | F6: 8 | G6: 6 | H6: 6 | I6: 5 | J6: 6 | K6: 6 | L6: 7 | M6: 9
A7: Duplicate MSE | B7: 143 | C7: 171 | D7: 142 | E7: 177 | F7: 133 | G7: 80 | H7: 58 | I7: 62 | J7: 94 | K7: 74 | L7: 54 | M7: 90
A8: Duplicate MSE % | B8: =B7/B5 -> 0.018920349 | C8: =IFERROR(C7/C5,0) -> 0.022058824 | D8: =IFERROR(D7/D5,0) -> 0.016896716 | E8: =IFERROR(E7/E5,0) -> 0.023459245 | F8: =IFERROR(F7/F5,0) -> 0.017090722 | G8: =IFERROR(G7/G5,0) -> 0.011644833 | H8: =IFERROR(H7/H5,0) -> 0.0082083215 | I8: =IFERROR(I7/I5,0) -> 0.0090909091 | J8: =IFERROR(J7/J5,0) -> 0.012673588 | ... M8: =IFERROR(M7/M5,0) -> 0.011743215
A9: Admitted Patients Qty. | B9: 1599 | C9: 1326 | D9: 1773 | E9: 1631 | F9: 1846 | G9: 1725 | H9: 1811 | I9: 1777 | J9: 1564 | K9: 1789 | L9: 1841 | M9: 1763
A10: % Admitted Patients % | B10: =B9/B5 -> 0.21156391 | C10: =IFERROR(C9/C5,0) -> 0.17105263 | D10: =IFERROR(D9/D5,0) -> 0.21097097 | E10: =IFERROR(E9/E5,0) -> 0.21616965 | F10: =IFERROR(F9/F5,0) -> 0.23721408 | G10: =IFERROR(G9/G5,0) -> 0.2510917 | H10: =IFERROR(H9/H5,0) -> 0.25629776 | I10: =IFERROR(I9/I5,0) -> 0.26055718 | J10: =IFERROR(J9/J5,0) -> 0.21086693 | ... M10: =IFERROR(M9/M5,0) -> 0.23003653
A11: Admitted Patients - ALOS Min. | B11: 459 | C11: 448 | D11: 362 | E11: 381 | F11: 296 | G11: 274 | H11: 261 | I11: 284 | J11: 323 | K11: 297 | L11: 293 | M11: 314
A12: Departed Patients % | B12: =B13/B5 -> 0.78843609 | C12: =IFERROR(C13/C5,0) -> 0.82894737 | D12: =IFERROR(D13/D5,0) -> 0.78902903 | E12: =IFERROR(E13/E5,0) -> 0.78383035 | F12: =IFERROR(F13/F5,0) -> 0.76278592 | G12: =IFERROR(G13/G5,0) -> 0.7489083 | H12: =IFERROR(H13/H5,0) -> 0.70987829 | I12: =IFERROR(I13/I5,0) -> 0.69618768 | J12: =IFERROR(J13/J5,0) -> 0.70891196 | ... M12: =IFERROR(M13/M5,0) -> 0.72325157
A13: Departed Patients Qty. | B13: =B5-B9 -> 5959 | C13: =C5-C9 -> 6426 | D13: =D5-D9 -> 6631 | E13: =E5-E9 -> 5914 | F13: =F5-F9 -> 5936 | G13: =G5-G9 -> 5145 | H13: 5016 | I13: 4748 | J13: 5258 | K13: 4955 | L13: 4955 | M13: 5543
A14: ED Arrival to Departure ALOS Min. / Discharged Patients | B14: 186 | C14: 194 | D14: 173 | E14: 170 | F14: 152 | G14: 142 | H14: 130 | I14: 132 | J14: 143 | K14: 143 | L14: 136 | M14: 152
A15: LPMSE + LPT | B15: =3+284 -> 287 | C15: 305 | D15: 146 | E15: 173 | F15: 95 | G15: 32 | H15: 48 | I15: 47 | J15: 37 | K15: 28 | L15: 33 | M15: 89
A16: LPMSE + LPT % | B16: =B15/B5 -> 0.037973009 | C16: =IFERROR(C15/C5,0) -> 0.039344685 | D16: =IFERROR(D15/D5,0) -> 0.01737268 | E16: =IFERROR(E15/E5,0) -> 0.022929092 | F16: =IFERROR(F15/F5,0) -> 0.012207659 | G16: =IFERROR(G15/G5,0) -> 0.004657933 | H16: =IFERROR(H15/H5,0) -> 0.0067930937 | I16: =IFERROR(I15/I5,0) -> 0.0068914956 | J16: =IFERROR(J15/J5,0) -> 0.0049885398 | ... M16: =IFERROR(M15/M5,0) -> 0.011612735
A17: AMA | B17: 54 | C17: 47 | D17: 55 | E17: 57 | F17: 53 | G17: 44 | H17: 39 | I17: 49 | J17: 59 | K17: 55 | L17: 40 | M17: 60
A18: AMA % | B18: =B17/B5 -> 0.0071447473 | C18: =IFERROR(C17/C5,0) -> 0.0060629515 | D18: =IFERROR(D17/D5,0) -> 0.0065445026 | E18: =IFERROR(E17/E5,0) -> 0.007554672 | F18: =IFERROR(F17/F5,0) -> 0.0068105885 | G18: =IFERROR(G17/G5,0) -> 0.0064046579 | H18: =IFERROR(H17/H5,0) -> 0.0055193886 | I18: =IFERROR(I17/I5,0) -> 0.0071847507 | J18: =IFERROR(J17/J5,0) -> 0.0079546987 | ... M18: =IFERROR(M17/M5,0) -> 0.00782881
A19: Patient Satisfaction (Top Box) | B19: 0.758 | C19: 0.613 | D19: 0.652 | E19: 0.733 | F19: 0.68 | G19: 0.715 | H19: 0.789 | I19: 0.802 | J19: 0.749 | K19: 0.707 | L19: 0.765
A20: AMI - PCI w/in 90 mins of Arrival
A21: Stroke - Interpretation of Head CT
A22: Pain Mgmt - Long Bone Fracture | B22: 0.5 | C22: 0.64
A23: Kendall Peds (incl w/Kendall Main)
A25: Total Patients
A26: Door / Arrival to Provider Greet (Min Wait)
A27: Duplicate MSE
A28: Duplicate MSE %
A29: Admitted Patients Qty.
A30: % Admitted Patients %
A31: Admitted Patients - ALOS Min.
A32: Departed Patients %
A33: Departed Patients
A34: ED Arrival to Departure ALOS Min. / Discharged Patients
A35: LPMSE + LPT
... A43: JFK Main - HCA East
A45: Total Patients | B45: 7515 | C45: 7460 | D45: 8153 | E45: 7404 | F45: 7247 | G45: 7064 | H45: 7151 | I45: 7062 | J45: 7175 | K45: 7101 | L45: 6893 | M45: 7295
A46: Door / Arrival to Provider Greet (Min Wait) | B46: 10 | C46: 9 | D46: 10 | E46: 7 | F46: 9 | G46: 8 | H46: 6 | I46: 7 | J46: 8 | K46: 8 | L46: 7 | M46: 8
A47: Duplicate MSE | B47: 303 | C47: 308 | D47: 143 | E47: 153 | F47: 223 | G47: 180 | H47: 179 | I47: 243 | J47: 236 | K47: 135 | L47: 208 | M47: 174
A48: Duplicate MSE % | B48: =B47/B45 -> 0.040319361 | C48: =IFERROR(C47/C45,0) -> 0.041286863 | D48: =IFERROR(D47/D45,0) -> 0.017539556 | E48: =IFERROR(E47/E45,0) -> 0.020664506 | F48: =IFERROR(F47/F45,0) -> 0.030771354 | G48: =IFERROR(G47/G45,0) -> 0.025481314 | H48: =IFERROR(H47/H45,0) -> 0.025031464 | I48: =IFERROR(I47/I45,0) -> 0.034409516 | J48: =IFERROR(J47/J45,0) -> 0.032891986 | ... M48: =IFERROR(M47/M45,0) -> 0.023851953
A49: Admitted Patients Qty. | B49: 3008 | C49: 2853 | D49: 3055 | E49: 2776 | F49: 2795 | G49: 2694 | H49: 2677 | I49: 2708 | J49: 2721 | K49: 2640 | L49: 2660 | M49: 2859
A50: % Admitted Patients | B50: =B49/B45 -> 0.40026613 | C50: =IFERROR(C49/C45,0) -> 0.38243968 | D50: =IFERROR(D49/D45,0) -> 0.3747087 | E50: =IFERROR(E49/E45,0) -> 0.37493247 | F50: =IFERROR(F49/F45,0) -> 0.38567683 | G50: =IFERROR(G49/G45,0) -> 0.38137033 | H50: =IFERROR(H49/H45,0) -> 0.37435324 | I50: =IFERROR(I49/I45,0) -> 0.38346078 | J50: =IFERROR(J49/J45,0) -> 0.37923345 | ... M50: =IFERROR(M49/M45,0) -> 0.39191227
A51: Admitted Patients - ALOS Min. | B51: 352 | C51: 392 | D51: 367 | E51: 290 | F51: 267 | G51: 296 | H51: 276 | I51: 293 | J51: 307 | K51: 347 | L51: 320 | M51: 327
A52: Departed Patients % | B52: =B53/B45 -> 0.59973387 | C52: =IFERROR(C53/C45,0) -> 0.61756032 | D52: =IFERROR(D53/D45,0) -> 0.6252913 | E52: =IFERROR(E53/E45,0) -> 0.62506753 | F52: =IFERROR(F53/F45,0) -> 0.61432317 | G52: =IFERROR(G53/G45,0) -> 0.61862967 | H52: =IFERROR(H53/H45,0) -> 0.62047266 | I52: =IFERROR(I53/I45,0) -> 0.60903427 | J52: =IFERROR(J53/J45,0) -> 0.61226481 | ... M52: =IFERROR(M53/M45,0) -> 0.58725154
A53: Departed Patients | B53: =B45-B49 -> 4507 | C53: =C45-C49 -> 4607 | D53: =D45-D49 -> 5098 | E53: =E45-E49 -> 4628 | F53: =F45-F49 -> 4452 | G53: =G45-G49 -> 4370 | H53: 4437 | I53: 4301 | J53: 4393 | K53: 4307 | L53: 4114 | M53: 4284
A54: ED Arrival to Departure ALOS Min. / Discharged Patients | B54: 165 | C54: 175 | D54: 177 | E54: 159 | F54: 161 | G54: 164 | H54: 157 | I54: 152 | J54: 155 | K54: 157 | L54: 152 | M54: 155
A55: LPMSE + LPT | B55: =3+88 -> 91 | C55: 180 | D55: 304 | E55: 102 | F55: 49 | G55: 112 | H55: 78 | I55: 58 | J55: 43 | K55: 18 | L55: 9 | M55: 11
A56: LPMSE + LPT % | B56: =B55/B45 -> 0.012109115 | C56: =IFERROR(C55/C45,0) -> 0.024128686 | D56: =IFERROR(D55/D45,0) -> 0.037286888 | E56: =IFERROR(E55/E45,0) -> 0.013776337 | F56: =IFERROR(F55/F45,0) -> 0.0067614185 | G56: =IFERROR(G55/G45,0) -> 0.01585504 | H56: =IFERROR(H55/H45,0) -> 0.010907565 | I56: =IFERROR(I55/I45,0) -> 0.0082129708 | J56: =IFERROR(J55/J45,0) -> 0.0059930314 | ... M56: =IFERROR(M55/M45,0) -> 0.0015078821
A57: AMA | B57: 129 | C57: 177 | D57: 155 | E57: 125 | F57: 125 | G57: 122 | H57: 111 | I57: 122 | J57: 144 | K57: 159 | L57: 159 | M57: 153
A58: AMA % | B58: =B57/B45 -> 0.017165669 | C58: =IFERROR(C57/C45,0) -> 0.023726542 | D58: =IFERROR(D57/D45,0) -> 0.019011407 | E58: =IFERROR(E57/E45,0) -> 0.016882766 | F58: =IFERROR(F57/F45,0) -> 0.017248517 | G58: =IFERROR(G57/G45,0) -> 0.017270668 | H58: =IFERROR(H57/H45,0) -> 0.015522305 | I58: =IFERROR(I57/I45,0) -> 0.017275559 | J58: =IFERROR(J57/J45,0) -> 0.020069686 | ... M58: =IFERROR(M57/M45,0) -> 0.020973269
A59: Patient Satisfaction (Top Box) | B59: 0.577 | C59: 0.562 | D59: 0.507 | E59: 0.699 | F59: 0.588 | G59: 0.599 | H59: 0.598 | I59: 0.585 | J59: 0.596 | K59: 0.608 | L59: 0.56
A60: AMI - PCI w/in 90 mins of Arrival
A61: Stroke - Interpretation of Head CT
A62: Pain Mgmt - Long Bone Fracture | B62: 0.45 | C62: 0.445
A63: JFK BB - HCA East
A65: Total Patients | B65: 863 | C65: 827 | D65: 806 | E65: 732 | F65: 611 | G65: 594 | H65: 571 | I65: 584 | J65: 554 | K65: 623 | L65: 790 | M65: 831
A66: Door / Arrival to Provider Greet (Min Wait) | B66: 9 | C66: 9 | D66: 8 | E66: 5 | F66: 6 | G66: 6 | H66: 5 | I66: 5 | J66: 4 | K66: 5 | L66: 5 | M66: 6
A67: Duplicate MSE | B67: 26 | C67: 20 | D67: 10 | E67: 12 | F67: 8 | G67: 6 | H67: 2 | I67: 11 | J67: 2 | K67: 10 | L67: 37 | M67: 39
A68: Duplicate MSE % | B68: =B67/B65 -> 0.030127462 | C68: =IFERROR(C67/C65,0) -> 0.024183797 | D68: =IFERROR(D67/D65,0) -> 0.012406948 | E68: =IFERROR(E67/E65,0) -> 0.016393443 | F68: =IFERROR(F67/F65,0) -> 0.01309329 | G68: =IFERROR(G67/G65,0) -> 0.01010101 | H68: =IFERROR(H67/H65,0) -> 0.003502627 | I68: =IFERROR(I67/I65,0) -> 0.018835616 | J68: =IFERROR(J67/J65,0) -> 0.0036101083 | ... M68: =IFERROR(M67/M65,0) -> 0.046931408
A69: Admitted Patients Qty. | B69: 100 | C69: 88 | D69: 74 | E69: 77 | F69: 53 | G69: 51 | H69: 67 | I69: 76 | J69: 67 | K69: 62 | L69: 65 | M69: 72
A70: % Admitted Patients | B70: =B69/B65 -> 0.11587486 | C70: =IFERROR(C69/C65,0) -> 0.10640871 | D70: =IFERROR(D69/D65,0) -> 0.091811414 | E70: =IFERROR(E69/E65,0) -> 0.10519126 | F70: =IFERROR(F69/F65,0) -> 0.086743044 | G70: =IFERROR(G69/G65,0) -> 0.085858586 | H70: =IFERROR(H69/H65,0) -> 0.117338 | I70: =IFERROR(I69/I65,0) -> 0.13013699 | J70: =IFERROR(J69/J65,0) -> 0.12093863 | ... M70: =IFERROR(M69/M65,0) -> 0.086642599
A71: Admitted Patients - ALOS Min. | B71: 269 | C71: 270 | D71: 279 | E71: 247 | F71: 248 | G71: 252 | H71: 258 | I71: 260 | J71: 252 | K71: 294 | L71: 319 | M71: 319
A72: Departed Patients % | B72: =B73/B65 -> 0.88412514 | C72: =IFERROR(C73/C65,0) -> 0.89359129 | D72: =IFERROR(D73/D65,0) -> 0.90818859 | E72: =IFERROR(E73/E65,0) -> 0.89480874 | F72: =IFERROR(F73/F65,0) -> 0.91325696 | G72: =IFERROR(G73/G65,0) -> 0.91414141 | H72: =IFERROR(H73/H65,0) -> 0.88091068 | I72: =IFERROR(I73/I65,0) -> 0.86472603 | J72: =IFERROR(J73/J65,0) -> 0.8700361 | ... M72: =IFERROR(M73/M65,0) -> 0.90252708
A73: Departed Patients | B73: =B65-B69 -> 763 | C73: =C65-C69 -> 739 | D73: =D65-D69 -> 732 | E73: =E65-E69 -> 655 | F73: =F65-F69 -> 558 | G73: =G65-G69 -> 543 | H73: 503 | I73: 505 | J73: 482 | K73: 553 | L73: 717 | M73: 750
A74: ED Arrival to Departure ALOS Min. / Discharged Patients | B74: 92 | C74: 98 | D74: 99 | E74: 95 | F74: 84 | G74: 87 | H74: 86 | I74: 91 | J74: 94 | K74: 96 | L74: 98 | M74: 98
A75: LPMSE + LPT | B75: =3+1 -> 4 | C75: 0 | D75: 4 | E75: 0 | F75: 1 | G75: 1 | H75: 1 | I75: 1 | J75: 1 | K75: 0 | L75: 0 | M75: 1
A76: LPMSE + LPT % | B76: =B75/B65 -> 0.0046349942 | C76: =IFERROR(C75/C65,0) -> 0 | D76: =IFERROR(D75/D65,0) -> 0.0049627792 | E76: =IFERROR(E75/E65,0) -> 0 | F76: =IFERROR(F75/F65,0) -> 0.0016366612 | G76: =IFERROR(G75/G65,0) -> 0.0016835017 | H76: =IFERROR(H75/H65,0) -> 0.0017513135 | I76: =IFERROR(I75/I65,0) -> 0.0017123288 | J76: =IFERROR(J75/J65,0) -> 0.0018050542 | ... M76: =IFERROR(M75/M65,0) -> 0.0012033694
A77: AMA | B77: 9 | C77: 9 | D77: 11 | E77: 9 | F77: 9 | G77: 11 | H77: 7 | I77: 11 | J77: 7 | K77: 16 | L77: 14 | M77: 15
A78: AMA % | B78: =B77/B65 -> 0.010428737 | C78: =IFERROR(C77/C65,0) -> 0.010882709 | D78: =IFERROR(D77/D65,0) -> 0.013647643 | E78: =IFERROR(E77/E65,0) -> 0.012295082 | F78: =IFERROR(F77/F65,0) -> 0.014729951 | G78: =IFERROR(G77/G65,0) -> 0.018518519 | H78: =IFERROR(H77/H65,0) -> 0.012259194 | I78: =IFERROR(I77/I65,0) -> 0.018835616 | J78: =IFERROR(J77/J65,0) -> 0.012635379 | ... M78: =IFERROR(M77/M65,0) -> 0.018050542
A79: Patient Satisfaction (Top Box) | B79: 0.87 | C79: 0.832 | D79: 0.814 | E79: 0.783 | F79: 0.922 | G79: 0.837 | H79: 0.788 | I79: 0.882 | J79: 0.829 | K79: 0.669 | L79: 0.849
A80: AMI - PCI w/in 90 mins of Arrival
A81: Stroke - Interpretation of Head CT
A82: Pain Mgmt - Long Bone Fracture
A83: JFK PBG
A85: Total Patients | B85: 469 | C85: 502 | D85: 571 | E85: 432 | F85: 336 | G85: 308 | H85: 306 | I85: 277 | J85: 276 | K85: 344 | L85: 472 | M85: 493
A86: Door / Arrival to Provider Greet (Min Wait) | B86: 6 | C86: 7 | D86: 7 | E86: 6 | F86: 6 | G86: 6 | H86: 5 | I86: 6 | J86: 5 | K86: 5 | L86: 5 | M86: 5
A87: Duplicate MSE | B87: 8 | C87: 2 | D87: 4 | E87: 0 | F87: 0 | G87: 2 | H87: 0 | I87: 4 | J87: 0 | K87: 8 | L87: 4 | M87: 4
A88: Duplicate MSE % | B88: =B87/B85 -> 0.017057569 | C88: =IFERROR(C87/C85,0) -> 0.0039840637 | D88: =IFERROR(D87/D85,0) -> 0.0070052539 | E88: =IFERROR(E87/E85,0) -> 0 | F88: =IFERROR(F87/F85,0) -> 0 | G88: =IFERROR(G87/G85,0) -> 0.0064935065 | H88: =IFERROR(H87/H85,0) -> 0 | I88: =IFERROR(I87/I85,0) -> 0.014440433 | J88: =IFERROR(J87/J85,0) -> 0 | ... M88: =IFERROR(M87/M85,0) -> 0.0081135903
A89: Admitted Patients Qty. | B89: 13 | C89: 1 | D89: 8 | E89: 5 | F89: 9 | G89: 8 | H89: 5 | I89: 10 | J89: 4 | K89: 1 | L89: 9 | M89: 9
A90: Admitted Patients % | B90: =B89/B85 -> 0.02771855 | C90: =IFERROR(C89/C85,0) -> 0.0019920319 | D90: =IFERROR(D89/D85,0) -> 0.014010508 | E90: =IFERROR(E89/E85,0) -> 0.011574074 | F90: =IFERROR(F89/F85,0) -> 0.026785714 | G90: =IFERROR(G89/G85,0) -> 0.025974026 | H90: =IFERROR(H89/H85,0) -> 0.016339869 | I90: =IFERROR(I89/I85,0) -> 0.036101083 | J90: =IFERROR(J89/J85,0) -> 0.014492754 | ... M90: =IFERROR(M89/M85,0) -> 0.018255578
A91: Admitted Patients - ALOS Min. | B91: 261 | C91: 204 | D91: 275 | E91: 195 | F91: 245 | G91: 306 | H91: 213 | I91: 186 | J91: 154 | K91: 99 | L91: 216 | M91: 216
A92: Departed Patients % | B92: =B93/B85 -> 0.97228145 | C92: =IFERROR(C93/C85,0) -> 0.99800797 | D92: =IFERROR(D93/D85,0) -> 0.98598949 | E92: =IFERROR(E93/E85,0) -> 0.98842593 | F92: =IFERROR(F93/F85,0) -> 0.97321429 | G92: =IFERROR(G93/G85,0) -> 0.97402597 | H92: =IFERROR(H93/H85,0) -> 0.98039216 | I92: =IFERROR(I93/I85,0) -> 0.96389892 | J92: =IFERROR(J93/J85,0) -> 0.98550725 | ... M92: =IFERROR(M93/M85,0) -> 0.97971602
A93: Departed Patients | B93: =B85-B89 -> 456 | C93: =C85-C89 -> 501 | D93: =D85-D89 -> 563 | E93: =E85-E89 -> 427 | F93: =F85-F89 -> 327 | G93: =G85-G89 -> 300 | H93: 300 | I93: =I85-I89 -> 267 | J93: =J85-J89 -> 272 | K93: 342 | L93: =L85-L89 -> 463 | M93: 483
A94: ED Arrival to Departure ALOS Min. / Discharged Patients | B94: 77 | C94: 88 | D94: 93 | E94: 78 | F94: 80 | G94: 85 | H94: 84 | I94: 87 | J94: 85 | K94: 88 | L94: 91 | M94: 90
A95: LPMSE + LPT | B95: =0+1 -> 1 | C95: 0 | D95: 1 | E95: 0 | F95: 0 | G95: 1 | H95: 1 | I95: 1 | J95: 0 | K95: 0 | L95: 0 | M95: 0
A96: LPMSE + LPT % | B96: =B95/B85 -> 0.0021321962 | C96: =IFERROR(C95/C85,0) -> 0 | D96: =IFERROR(D95/D85,0) -> 0.0017513135 | E96: =IFERROR(E95/E85,0) -> 0 | F96: =IFERROR(F95/F85,0) -> 0 | G96: =IFERROR(G95/G85,0) -> 0.0032467532 | H96: =IFERROR(H95/H85,0) -> 0.0032679739 | I96: =IFERROR(I95/I85,0) -> 0.0036101083 | J96: =IFERROR(J95/J85,0) -> 0 | ... M96: =IFERROR(M95/M85,0) -> 0
A97: AMA | B97: 5 | C97: 7 | D97: 6 | E97: 4 | F97: 6 | G97: 2 | H97: 3 | I97: 3 | J97: 6 | K97: 3 | L97: 4 | M97: 4
A98: AMA % | B98: =B97/B85 -> 0.010660981 | C98: =IFERROR(C97/C85,0) -> 0.013944223 | D98: =IFERROR(D97/D85,0) -> 0.010507881 | E98: =IFERROR(E97/E85,0) -> 0.0092592593 | F98: =IFERROR(F97/F85,0) -> 0.017857143 | G98: =IFERROR(G97/G85,0) -> 0.0064935065 | H98: =IFERROR(H97/H85,0) -> 0.0098039216 | I98: =IFERROR(I97/I85,0) -> 0.010830325 | J98: =IFERROR(J97/J85,0) -> 0.02173913 | ... M98: =IFERROR(M97/M85,0) -> 0.0081135903
A99: Patient Satisfaction (Top Box) | B99: 0.845 | C99: 0.863 | D99: 0.86 | E99: 0.865 | F99: 0.875 | G99: 0.866 | H99: 0.984 | I99: 0.859 | J99: 0.838 | K99: 0.855 | L99: 0.902
A100: AMI - PCI w/in 90 mins of Arrival
A101: Stroke - Interpretation of Head CT
A102: Pain Mgmt - Long Bone Fracture
A103: Ocala
A105: Total Patients | B105: 3927 | C105: 3763 | D105: 4248 | E105: 3890 | F105: 3850 | G105: 3659 | H105: 3912 | I105: 3875 | J105: 3939 | K105: 3972 | L105: 4019 | M105: 4154
A106: Door / Arrival to Provider Greet (Min Wait) | B106: 6 | C106: 6 | D106: 7 | E106: 6 | F106: 5 | G106: 5 | H106: 4 | I106: 5 | J106: 5 | K106: 5 | L106: 6 | M106: 6
A107: Duplicate MSE | B107: 85 | C107: 64 | D107: 74 | E107: 84 | F107: 87 | G107: 56 | H107: 102 | I107: 77 | J107: 71 | K107: 79 | L107: 60 | M107: 60
A108: Duplicate MSE % | B108: =B107/B105 -> 0.021645022 | C108: =IFERROR(C107/C105,0) -> 0.017007707 | D108: =IFERROR(D107/D105,0) -> 0.017419962 | E108: =IFERROR(E107/E105,0) -> 0.02159383 | F108: =IFERROR(F107/F105,0) -> 0.022597403 | G108: =IFERROR(G107/G105,0) -> 0.015304728 | H108: =IFERROR(H107/H105,0) -> 0.02607362 | I108: =IFERROR(I107/I105,0) -> 0.019870968 | J108: =IFERROR(J107/J105,0) -> 0.018024879 | ... M108: =IFERROR(M107/M105,0) -> 0.014443909
A109: Admitted Patients Qty. | B109: 1022 | C109: 1030 | D109: 1107 | E109: 1019 | F109: 1014 | G109: 1012 | H109: 987 | I109: 993 | J109: 1027 | K109: 1084 | L109: 1091 | M109: 1132
A110: Admitted Patients % | B110: =B109/B105 -> 0.26024955 | C110: =IFERROR(C109/C105,0) -> 0.27371778 | D110: =IFERROR(D109/D105,0) -> 0.26059322 | E110: =IFERROR(E109/E105,0) -> 0.26195373 | F110: =IFERROR(F109/F105,0) -> 0.26337662 | G110: =IFERROR(G109/G105,0) -> 0.2765783 | H110: =IFERROR(H109/H105,0) -> 0.25230061 | I110: =IFERROR(I109/I105,0) -> 0.25625806 | J110: =IFERROR(J109/J105,0) -> 0.26072607 | ... M110: =IFERROR(M109/M105,0) -> 0.27250843
A111: Admitted Patients - ALOS Min. | B111: 438 | C111: 398 | D111: 483 | E111: 331 | F111: 307 | G111: 325 | H111: 266 | I111: 247 | J111: 222 | K111: 243 | L111: 304 | M111: 303
A112: Departed Patients % | B112: =B113/B105 -> 0.73975045 | C112: =IFERROR(C113/C105,0) -> 0.72628222 | D112: =IFERROR(D113/D105,0) -> 0.73940678 | E112: =IFERROR(E113/E105,0) -> 0.73804627 | F112: =IFERROR(F113/F105,0) -> 0.73662338 | G112: =IFERROR(G113/G105,0) -> 0.7234217 | H112: =IFERROR(H113/H105,0) -> 0.73159509 | I112: =IFERROR(I113/I105,0) -> 0.72490323 | J112: =IFERROR(J113/J105,0) -> 0.73292714 | ... M112: =IFERROR(M113/M105,0) -> 0.72026962
A113: Departed Patients | B113: =B105-B109 -> 2905 | C113: =C105-C109 -> 2733 | D113: =D105-D109 -> 3141 | E113: =E105-E109 -> 2871 | F113: =F105-F109 -> 2836 | G113: =G105-G109 -> 2647 | H113: 2862 | I113: 2809 | J113: 2887 | K113: 2860 | L113: 2900 | M113: 2992
A114: ED Arrival to Departure ALOS Min. / Discharged Patients | B114: 169 | C114: 167 | D114: 168 | E114: 152 | F114: 142 | G114: 143 | H114: 134 | I114: 139 | J114: 137 | K114: 137 | L114: 148 | M114: 147
...

Sheet TABLE OF CONTENTS
C3: SERVICE | E3: PEOPLE | G3: BOARD REPORTS | I3: MIDWAY GRAPHS | K3: OPERATIONS | M3: FINANCE | O3: QUALITY
C5: PATIENT SATISFACTION | E5: PROVIDER RETENTION | G5: EXECUTIVE SUMMARY | I5: QUALITY COMPOSITE | K5: EFFICIENCY METRICS | M5: LEFT BEFORE BEING SEEN (LBBS/LPT) | O5: 72 HOUR RETURNS
E6: Providers Terminating | G6: Action Plan | I6: Timeliness | K6: Arrival to Qualified Provider | M6: Facility Reported Case Volume | O6: No. 72hr Returns
I7: Patients per Hour | K7: LOS - Discharged and Admitted | M7: Total and % LBBS (Includes LBT) | O7: % 72hr Ret. Admissions on 2nd Visit
K9: PROVIDER PRODUCTIVITY | M9: ADMISSIONS | O9: MORTALITIES
K10: Overall Patients / Adjusted Hour | M10: Admissions & Observation (%) | O10: % Mortalities
K11: Patients per Hour: EDP, PCP, MLP | M11: Critical Care % (E&M 99291) | O11: % Category III (Opportunity)
M13: CASE VOLUME - BUDGET VARIANCE | O13: FPPE/OPPE
M14: Sheridan Budget, Captured, Variance | O14: FPPE & OPPE Completed YTD
O16: PQRS
O17: Acute MI: Aspirin Given Upon Arrival
O18: PNA: Vital Signs Documented
O19: Syncope: 12 Lead EKG Performed
O21: NATIONAL QUALITY MEASURES
O22: Acute MI: PCI w/in 90 mins of Arrival
O23: Stroke: Interpretation of Head CT
O24: Pain Mgmt: Long Bone Fracture

Sheet 2016 EM EXECUTIVE COMMITTEE
B1: EM Division - Clinical Performance Summary
B2: Dimension of Quality | C2: Measure Description | D2: Threshold | E2: Oct & Nov 2016 | F2: Volume Sample Size | G2: Unit | H2: Comments | I2: December 2016 | J2: Volume Sample Size | K2: 4Q 2015 | L2: Volume Sample Size | M2: 1Q 2016 | N2: Volume Sample Size | O2: 2Q 2016 | P2: Volume Sample Size | Q2: 3Q 2016 | R2: Volume Sample Size
B4: Patient Safety
B5: Legal Cases (per 100k visits) | C5: Cases requiring legal intervention | D5: 4.3 | E5: =0/182279 -> 0 | F5: =SUM(COMPOSITE!H32,COMPOSITE!I32,COMPOSITE!J32) -> 182443 | G5: per 100k cases | H5: claims submitted; benchmark from Sullivan Group | I5: =0/121067 -> 0 | J5: pending | K5: =2/125557 -> 1.592902e-05 | L5: 2 / 125,557 | M5: 0 | N5: 0 / 200,884 | O5: 0 | P5: 0 / 189,034 | Q5: 0 | R5: 182369
B6: Occurrence Reporting Rates (Risk Management) | C6: Cases referred to RM for review | D6: TBD | E6: N/A | G6: Cases | I6: NA | J6: NA | K6: N/A | M6: N/A | O6: N/A | Q6: N/A
B7: Clinical Standards
B8: *Myocardial Infarction (AMI) - Only Up to March 2016 | C8: ASA Received | D8: ≥ 95% | E8: N/A | G8: CPT | H8: Abstracted and validated for RVU sites only | K8: =624/654 -> 0.95412844 | L8: 624/654 | M8: =563/592 -> 0.95101351 | N8: 563 / 592
B9: *Pneumonia (PNA) - Only Up to March 2016 | C9: Vital Signs Documented | D9: ≥ 95% | E9: N/A | G9: CPT | H9: Abstracted and validated for RVU sites only | K9: =1440/1444 -> 0.99722992 | L9: 1440/1444 | M9: =1691/1695 -> 0.99764012 | N9: 1691 / 1695
B10: *Syncope - Only Up to March 2016 | C10: EKG Documented | D10: ≥ 95% | E10: N/A | G10: CPT | H10: Abstracted and validated for RVU sites only | K10: =1167/1176 -> 0.99234694 | L10: 1167/1176 | M10: =1113/1113 -> 1 | N10: 1113 / 1113
B11: *PQRS Composite - Only Up to March 2016 | C11: MI, PNA,& Syncope | D11: ≥ 95% | E11: N/A | G11: CPT | H11: Abstracted and validated for RVU sites only | K11: =3231/3274 -> 0.98686622 | L11: 3231/3274 | M11: =3367/3400 -> 0.99029412 | N11: 3367 / 3400
B12: ECG (Electrocardiogram) - As of April 2016 | C12: ECG Performed for Non Trauma Chest Pain | D12: ≥ 95% | E12: =2459/2477 -> 0.99273314 | F12: 2459 / 2477 | G12: CPT | H12: Abstracted and validated for RVU sites only | I12: Pending | O12: =3742/3752 -> 0.99733475 | P12: 3742 / 3752 | Q12: 0.97542243 | R12: 1905 / 1953
B13: High Blood Pressure Screening - As of April 2016 | C13: Screening for High Blood Pressure and Follow-Up Documented | D13: ≥ 95% | E13: =43053/43399 -> 0.99202747 | F13: 43,053 / 43,399 | G13: CPT | H13: Abstracted and validated for RVU sites only | I13: Pending | O13: =57871/58245 -> 0.99357885 | P13: 57,871 / 58,245 | Q13: 0.98900632 | R13: 48,849 / 49,392
B14: Ultrasound for Pregnancy w/ Abdo Pain - As of April 2016 | C14: For Pregnancy w/ Abdominal Pain | D14: ≥ 95% | E14: N/A | G14: CPT | I14: N/A | O14: N/A | Q14: N/A
B15: (Rhogam) for RH(-) Pregnant w/ Expo. Risk - As of April 2016 | C15: For Rh-Negative Pregnant Women at Risk of Fetal Blood Exposure | D15: ≥ 95% | E15: N/A | G15: CPT | I15: N/A | O15: N/A | Q15: N/A
B16: *PQRS Composite - As of April 2016 | C16: ECG & BP Screening | D16: ≥ 95% | E16: =45512/45817 -> 0.99334308 | F16: 45,512 / 45,817 | G16: CPT | H16: Abstracted and validated for RVU sites only | I16: Pending | O16: =61613/61997 -> 0.99380615 | P16: 61,613 / 61,997 | Q16: 0.98848963 | R16: 50,754 / 51,345
B17: Patient Outcomes
B18: *Mortalities (With Cat III Opportunities for Improvement) | C18: Patients expiring in the ED | D18: 0 | E18: =0/130 -> 0 | F18: 0 / 130 | G18: Cases | H18: 9 of 16 sites reporting as of 7/1/2016 (Westchester 3/8/2016) *Currently reviewing metric definition to better reflect the delivery of quality. | I18: Pending | K18: =(1/144) -> 0.0069444444 | L18: 1 / 144 | M18: =1/201 -> 0.0049751244 | N18: 1 / 201 | O18: =2/143 -> 0.013986014 | P18: 2 / 143 | Q18: 0 | R18: 0 / 124
B19: *72hr Return Unanticipated Admissions | C19: Patients admitted 2nd visit in < 72hrs | D19: ≤ 1% | E19: =922/102409 -> 0.009003115 | F19: 922 / 102,409 | G19: Cases | H19: 14 of 23 sites reporting as of 7/1/2016 (Reporting sites listed in hidden comment) | I19: Pending | K19: =499/125557 -> 0.0039742906 | L19: 499 / 125,557 | M19: =1479/121723 -> 0.012150539 | N19: 1479 / 121,723 | O19: =1506/176349 -> 0.008539884 | P19: 1506 / 176,349 | Q19: 0.0087228918 | R19: 1590 / 182,279
B20: Efficiency & Productivity
B21: Overall Patients per Adjusted Hour | C21: Patients seen by EDP and MLP per hour | D21: 2.0-2.5 | E21: =SUM('PROVIDER PRODUCTIVITY'!B34,'PROVIDER PRODUCTIVITY'!B35)/2 -> 1.7772375 | F21: =SUM(COMPOSITE!K41,COMPOSITE!L41) -> 118908 | G21: Cases | H21: Facilities w/ ≥ 20k; MLP = 75% EDP Hour | I21: Pending | K21: 1.81 | L21: 115152 | M21: 1.7544592 | N21: 193855 | O21: =SUM('PROVIDER PRODUCTIVITY'!#REF!,'PROVIDER PRODUCTIVITY'!#REF!,'PROVIDER PRODUCTIVITY'!#REF!)/3 -> #REF! | P21: 186502 | Q21: 1.6363178 | R21: 201995
B22: Left Before Being Seen (LBBS) | C22: Patients left before being seen | D22: ≤ 2% | E22: =1408/112552 -> 0.012509773 | F22: 1408 / 112552 | G22: Cases | H22: Excludes Chandler, Mercy Gilbert, Moberly (Feb.-March) & St. John | I22: Pending | K22: =(1064/125557) -> 0.0084742388 | L22: 1064 / 125,557 | M22: 0.020577583 | N22: 3443 / 167,318 | O22: =1799/149023 -> 0.012071962 | P22: 1799 / 149,023 | Q22: 0.015053413 | R22: 2218 / 147,342
B23: Arrival to Qualified Provider | C23: time of arrival to provider | D23: ≤ 30 mins | E23: =SUM(COMPOSITE!K34+COMPOSITE!L34)/2 -> 19.107284 | F23: 87408 | G23: Cases | H23: Excludes Chandler, Mercy Gilbert, Jupiter, San Ramon, | I23: Pending | K23: =([1]Efficiency!L30+[1]Efficiency!L31+[1]Efficiency!L32)/3 -> 27.666667 | L23: 125557 | M23: 29.663619 | N23: 199682 | O23: =SUM(COMPOSITE!C34+COMPOSITE!D34+COMPOSITE!E34)/3 -> 30.88911 | P23: 142031 | Q23: 24.741928 | R23: 142031
B24: Customer Service
B25: † Patient Satisfaction | C25: Patients survey of care provided | D25: tbd | E25: N/A | G25: Responses | I25: N/A | K25: N/A | M25: N/A | O25: N/A | Q25: N/A
B26: Staff Satisfaction | C26: Staff survey of EDP/MLP | D26: tbd | E26: N/A | G26: Responses | I26: N/A | K26: N/A | M26: N/A | O26: N/A | Q26: N/A
B27: Patient Complaints (NON HCA): Quality | C27: Patient complaint related to care | D27: ≤1% | E27: NA | G27: Indicator | I27: N/A | K27: =(7/125557) -> 5.5751571e-05 | L27: 1 / 125,557 | M27: NA | O27: NA | Q27: NA
B28: Professionalism Complaints (NON HCA) | C28: Complaint about professionalism | D28: ≤1% | E28: NA | G28: Indicator | I28: N/A | K28: =(8/125557) -> 6.3716081e-05 | L28: 7 / 125,557 | M28: NA | O28: NA | Q28: NA
B29: Provider Outcomes
B30: Cases Referred to IQ With Opportunity for Education | C30: % cases referred to IQ for education | D30: tbd | E30: N/A | G30: Indicator | I30: N/A | K30: N/A | M30: N/A | O30: N/A | Q30: N/A
B31: FPPE-Targeted | C31: % providers referred for FPPE | D31: ≤1% | E31: 0 | G31: Providers | I31: Pending | K31: 0 | M31: 0 | O31: 0 | Q31: 0
B32: FPPE- Initial within 90 days | C32: FPPE completed in current month | D32: 1 | E32: =9/22 -> 0.40909091 | F32: 9 / 22 | G32: Providers | I32: Pending | K32: =15/20 -> 0.75 | L32: 15 / 20 | M32: =1/1 -> 1 | N32: 1 / 1 | O32: =10/22 -> 0.45454545 | P32: 10 / 22 | Q32: 0.40909091 | R32: 9 / 22
B33: OPPE provider report distribution | C33: % OPPE sent to chief for review | D33: 1 | E33: =1/1 -> 1 | G33: Facilities | H33: As needed by site; ongoing analytics project for automation | I33: Pending | K33: 1 | M33: 1 | O33: =1/1 -> 1 | Q33: 1
B34: Reappointment | C34: % providers approved for reaccreditation | D34: 1 | E34: Pending | G34: Reaccreditation | H34: Awaiting report from new credentialing system | I34: Pending | K34: Pending | M34: Pending | O34: Pending | Q34: Pending
C35: Goal Met
C36: Within 10% of Goal
C37: > 10% Below Goal
C38: Insufficient Data
B39: *Elements used for composite score
B40: † Includes HCA JV data
B41: Tony Andrulonis, M. D., Chairman, EM Quality Committee Prepared by: Abby Adeife, Clinical Quality Specialist Reviewed by EM QC

Sheet EM ACTION PLAN
A2: EM Division - Clinical Performance Summary Variance Report Actions & Recommendations
A3: Domain | C3: Clinical Standards | E3: Threshold | F3: Variance/ Issue | G3: Corrective Action Plan and Recommendations
A5: Dimension | C5: PQRS Composite | D5: Measures changed as of 4/1 | E5: 0.95 | F5: N/A | G5: Continued issues with abstraction of new PQRS measures; not all of the data elements are being collected.
G6: Resources are needed to abstract and validate the data for all sites.
A8: Dimension | C8: Patient Satisfaction | D8: Patient survey of care provided | E8: TBD | F8: N/A | G8: A "Patient Satisfaction Champion" is being identified out each facility, then initiating meetings with champions.
G9: Initiating "Press Ganey" for a patient satisfaction training at JFK and Kendall. Training to start 8/5/16 with leadership
G10: Survey vitals pilot is to be implemented by Q3 in two test facilities (Jupiter and San Ramon).
A12: Dimension | C12: Staff Satisfaction | D12: Staff survey of EDP/MLP | E12: TBD | F12: N/A | G12: TBD - HR to roll out a "Talent Keeper" survey.
B14: Goal Met
B15: Within 10% of Goal
B16: > 10% Below Goal
B17: Insufficient Data
A19: Tony Andrulonis, M. D., Chairman, EM Quality Committee Prepared by: Abby Adeife, Clinical Quality Specialist Reviewed by EM QC

Sheet JV All Sites Exec Committee
B3: HCA JV Clinical Performance Summary
B5: Dimension of Quality | C5: Measure Description | D5: Threshold | E5: 4Q 2015 | F5: Volume Sample Size | G5: unit | H5: Comments | J5: Q1 2014 | K5: Q1 Volume Sample Size | L5: Q2 2014 | M5: Q2 Volume Sample Size | N5: Q3 2014 | O5: Q2 Volume Sample Size | P5: Nov 2014 - Jan 2015 | Q5: Volume Sample Size | R5: 1Q 2015 | S5: Volume Sample Size | T5: 2Q 2015 | U5: Volume Sample Size | V5: 3Q 2015 | W5: Volume Sample Size
B6: Anesthesia
B15: Radiology
B16: HCA JV: Target VR rates with goal of 100% self editing | C16: Voice Recognition (VR) rate per provider. | D16: 1 | E16: N/A | F16: N/A | G16: N/A | H16: effective 5/1/2014 | J16: N/A | K16: N/A | L16: N/A | M16: N/A | N16: N/A | O16: N/A | P16: N/A | Q16: N/A | R16: N/A | S16: N/A | T16: N/A | U16: N/A | V16: N/A | W16: N/A
B17: HCA JV: Achieve HCA baseline of TAT | C17: Completed to Signed (inpatient only) | D17: Avg TAT 2.30 | E17: N/A | F17: N/A | G17: N/A | H17: effective 5/1/2014 | J17: N/A | K17: N/A | L17: N/A | M17: N/A | N17: N/A | O17: N/A | P17: N/A | Q17: N/A | R17: N/A | S17: N/A | T17: N/A | U17: N/A | V17: N/A | W17: N/A
B18: HCA JV: Timeliness of critical result communication | C18: Critical Findings | D18: Avg TAT ≤ 30 mins | E18: N/A | F18: N/A | G18: N/A | H18: effective 5/1/2014 | J18: N/A | K18: N/A | L18: N/A | M18: N/A | N18: N/A | O18: N/A | P18: N/A | Q18: N/A | R18: N/A | S18: N/A | T18: N/A | U18: N/A | V18: N/A | W18: N/A
B19: HCA JV: Track 100% compliance of critical results and documentation | C19: Communication details | D19: 1 | E19: N/A | F19: N/A | G19: N/A | H19: effective 5/1/2014 | J19: N/A | K19: N/A | L19: N/A | M19: N/A | N19: N/A | O19: N/A | P19: N/A | Q19: N/A | R19: N/A | S19: N/A | T19: N/A | U19: N/A | V19: N/A | W19: N/A
B20: HCA JV: Referring physician satisfaction as it relates to JV physician services | C20: Survey Monkey | D20: 5% improvement | E20: N/A | F20: N/A | G20: N/A | H20: effective 5/1/2014; Determine baseline by 5/1/14 and improve 5% in 4th quarter | J20: N/A | K20: N/A | L20: N/A | M20: N/A | N20: N/A | O20: N/A | P20: N/A | Q20: N/A | R20: N/A | S20: N/A | T20: N/A | U20: N/A | V20: N/A | W20: N/A
B21: HCA JV: 24/7 outpatient tracking, goal under 8 hours | C21: Outpatient routine studies completed to signed. | D21: Avg TAT 1.45 | E21: N/A | F21: N/A | G21: N/A | H21: effective 5/1/2014 | J21: N/A | K21: N/A | L21: N/A | M21: N/A | N21: N/A | O21: N/A | P21: N/A | Q21: N/A | R21: N/A | S21: N/A | T21: N/A | U21: N/A | V21: N/A | W21: N/A
B22: HCA JV: Left Before Being Seen | C22: pts left before being seen | D22: ≤ 1% | E22: =(617/46223) -> 0.013348333 | F22: 617/46223 | G22: cases | J22: 0.0062230357 | K22: 238/38245 | L22: 0.0056778946 | M22: 222/39099 | N22: 0.0046760353 | O22: 188/40205 | P22: 0.011052004 | Q22: 482/43612 | R22: 0.013645749 | S22: 608/44556 | T22: 0.0080169169 | U22: 345/43034 | V22: 0.0077928971 | W22: 323/41448
B23: HCA JV: Arrival to Qualified Provider | C23: time of arrival to provider | D23: ≤ 20 mins | E23: ='JV QUARTER'!N6 -> 0 | F23: ='JV QUARTER'!M6 -> 0 | G23: cases | J23: 11.818898 | K23: 38245 | L23: 13.302832 | M23: 39099 | N23: 14.061217 | O23: 40205 | P23: 17 | Q23: 43612 | R23: 18 | S23: 44556 | T23: 8.5927226 | U23: 43034 | V23: 7.5258415 | W23: ='JV QUARTER'!M13 -> 50880
B24: HCA JV: Duplicate MSE | D24: ≤ 4% | E24: =(1121/46223) -> 0.024251996 | F24: 1121/46223 | G24: cases | J24: 0.075853053 | K24: 38245 | L24: 0.014731835 | M24: 576/39099 | N24: 0.011317 | O24: 455/40205 | P24: 0.013 | Q24: 581/43612 | R24: 0.012635784 | S24: 563/44556 | T24: 0.020565135 | U24: 885/43034 | V24: 0.020797143 | W24: 862/41448
B25: HCA JV: Length of Stay (Admit) | C25: pt arrival to EDP disposition | D25: ≤ 170 mins | E25: 272 | F25: 13942/46223 | G25: cases | J25: N/A | K25: N/A | L25: N/A | M25: 39099 | N25: 209.49993 | O25: 13700/40205 | P25: 128 | Q25: 13067/43612 | S25: 44556 | W25: ='JV QUARTER'!M13 -> 50880
B26: HCA JV: Length of Stay (Discharged) | C26: pt arrival to time pt discharge | D26: ≤ 150 mins | E26: 156 | F26: ='JV QUARTER'!M6 -> 0 | G26: cases | J26: N/A | K26: N/A | L26: 148 | M26: 39099 | N26: 146.62124 | O26: 26505/40205 | P26: 160 | Q26: 30545/43612 | R26: 162 | S26: 44556 | T26: 156.51562 | U26: 43034 | V26: 150.68817 | W26: ='JV QUARTER'!M13 -> 50880
B27: HCA JV: Against Medical Advice | C27: pts left before provider d/c | D27: ≤ 2.0% | E27: =(518/46223) -> 0.011206542 | F27: 518/46223 | G27: cases | J27: 0.014537848 | K27: 38245 | L27: 0.014962019 | M27: 585/39099 | N27: 0.013157567 | O27: 529/40205 | P27: 0.011 | Q27: 606/43612 | R27: 0.015261693 | S27: 680/44556 | T27: 0.014105126 | U27: 607/43034 | V27: 0.012738854 | W27: 528/41448
B28: HCA JV: Patient Satisfaction | C28: pt survey of care provided | D28: 70 | E28: Pending | G28: responses | H28: Scores based on Top Box Score | J28: N/A | K28: N/A | L28: 0.6 | P28: 0.623 | Q28: 1304 | R28: Awaiting Data | T28: 67.7 | U28: 789 | V28: Pending
C30: Goal Met
C31: Within 10% of Goal
C32: > 10% Below Goal
C33: Insufficient Data

Sheet QUALITY COMPOSITE
B27: Domain | C27: 42370 | D27: 42401 | E27: 42430 | F27: 42461 | G27: 42491 | H27: 42522 | I27: 42552 | J27: 42583 | K27: 42614 | L27: 42644 | M27: 42675 | N27: 42705
A28: 72hr Returns (Admits) | B28: Pt. Outcome | C28: ='GRAPH DATA'!I8 -> 535 | D28: ='GRAPH DATA'!J8 -> 497 | E28: ='GRAPH DATA'!K8 -> 508 | F28: ='GRAPH DATA'!L8 -> 472 | G28: ='GRAPH DATA'!M8 -> 556 | H28: ='GRAPH DATA'!N8 -> 536 | I28: ='GRAPH DATA'!O8 -> 579 | J28: ='GRAPH DATA'!P8 -> 540 | ... N28: ='GRAPH DATA'!T8 -> 445
A29: Category III Mortalities | B29: Pt. Outcome | C29: ='GRAPH DATA'!I9 -> 0 | D29: ='GRAPH DATA'!J9 -> 0 | E29: ='GRAPH DATA'!K9 -> 1 | F29: ='GRAPH DATA'!L9 -> 1 | G29: ='GRAPH DATA'!M9 -> 1 | H29: ='GRAPH DATA'!N9 -> 0 | I29: ='GRAPH DATA'!O9 -> 0 | J29: ='GRAPH DATA'!P9 -> 0 | ... N29: ='GRAPH DATA'!T9 -> 0
A30: PQRS (Avg) | B30: Clinical Standard | C30: ='GRAPH DATA'!I12 -> 0.97670535 | D30: ='GRAPH DATA'!J12 -> 0.9778355 | E30: ='GRAPH DATA'!K12 -> 0.99145245 | F30: ='GRAPH DATA'!L12 -> 0.99851412 | G30: ='GRAPH DATA'!M12 -> 0.99486295 | H30: ='GRAPH DATA'!N12 -> 0.99328464 | I30: ='GRAPH DATA'!O12 -> 0.94986284 | J30: ='GRAPH DATA'!P12 -> 0.99224485 | ... M30: ='GRAPH DATA'!S12 -> 0.99297015
A31: Case Volume | C31: ='GRAPH DATA'!I10 -> 70019 | D31: ='GRAPH DATA'!J10 -> 70334 | E31: ='GRAPH DATA'!K10 -> 76071 | F31: ='GRAPH DATA'!L10 -> 69769 | G31: ='GRAPH DATA'!M10 -> 62391 | H31: ='GRAPH DATA'!N10 -> 58565 | I31: ='GRAPH DATA'!O10 -> 60599 | J31: ='GRAPH DATA'!P10 -> 60242 | ... N31: ='GRAPH DATA'!T10 -> 62363
A32: * POC Formula = [ (1- (Admitted 72hr Returns / Case Volume))/2] + [ (1- (Category III Mortalities / Case Volume))/2)]
A33: * PQRS Inclusive of 6 RVU facilities

Sheet ARR TO PROVIDER

Sheet PPH

Sheet EDP PREMIUM LABOR (HOURS)
A20: PREMIUM HOURS
A21: Month | B21: DIVISION TOTAL | D21: BAPTIST | F21: JFK | H21: JFK BB | J21: JFK PBG | L21: JUPITER | N21: KENDALL | P21: MOBERLY | R21: MONROE | T21: OCALA | V21: SAN RAMON | X21: ST. MARY'S | Z21: W MARION QC | AB21: W MARION | AD21: WESTCHESTER | AF21: PROVIDENCE | AH21: ST. JOHN | AJ21: OSCEOLA | AL21: OSCEOLA PEDS
B22: Transition Team | C22: Locums | D22: Transition Team | E22: Locums | F22: Transition Team | G22: Locums | H22: Transition Team | I22: Locums | J22: Transition Team | K22: Locums | L22: Transition Team | M22: Locums | N22: Transition Team | O22: Locums | P22: Transition Team | Q22: Locums | R22: Transition Team | S22: Locums | T22: Transition Team | U22: Locums | V22: Transition Team | W22: Locums | X22: Transition Team | Y22: Locums | Z22: Transition Team | AA22: Locums | AB22: Transition Team | AC22: Locums | AD22: Transition Team | AE22: Locums | AF22: Transition Team | AG22: Locums | AH22: Transition Team | AI22: Locums | AJ22: Transition Team | AK22: Locums | AL22: Transition Team | AM22: Locums
A23: 42370 | B23: =COMPOSITE!B$199 -> 2542 | C23: =COMPOSITE!D$199 -> 482 | D23: =COMPOSITE!$B$176 -> 0 | E23: =COMPOSITE!$D$176 -> 0 | F23: =COMPOSITE!$B$177 -> 0 | G23: =COMPOSITE!$D$177 -> 0 | H23: =COMPOSITE!$B$178 -> 60 | I23: =COMPOSITE!D$178 -> 0 | J23: =COMPOSITE!$B$179 -> 0 | K23: =COMPOSITE!D$179 -> 0 | L23: =COMPOSITE!B$180 -> 1.5 | M23: =COMPOSITE!D$180 -> 0 | N23: =COMPOSITE!B$181 -> 452 | O23: =COMPOSITE!D$181 -> 0 | P23: =COMPOSITE!B$182 -> 165 | Q23: =COMPOSITE!D$182 -> 0 | R23: =COMPOSITE!B$183 -> 0 | S23: =COMPOSITE!D$183 -> 132 | T23: =COMPOSITE!B$184 -> 608.5 | U23: =COMPOSITE!D$184 -> 0 | V23: =COMPOSITE!B$185 -> 0 | W23: =COMPOSITE!D$185 -> 0 | X23: =COMPOSITE!B$186 -> 0 | Y23: =COMPOSITE!D$185 -> 0 | Z23: =COMPOSITE!B$188 -> 24 | AA23: =COMPOSITE!D$188 -> 0 | AB23: =COMPOSITE!B$187 -> 297 | AC23: =COMPOSITE!D$187 -> 0 | AD23: =COMPOSITE!B$189 -> 324 | AE23: =COMPOSITE!D$189 -> 0 | AF23: =COMPOSITE!B$190 -> 174 | AG23: =COMPOSITE!D$190 -> 0 | AH23: =COMPOSITE!B$191 -> 0 | AI23: =COMPOSITE!D$191 -> 26 | AJ23: =COMPOSITE!B$192 -> 436 | AK23: =COMPOSITE!D$192 -> 300 | AL23: =COMPOSITE!B$193 -> 0 | AM23: =COMPOSITE!D$193 -> 0
A24: 42401 | B24: =COMPOSITE!E$199 -> 2253 | C24: =COMPOSITE!G$199 -> 594 | D24: =COMPOSITE!$E$176 -> 0 | E24: =COMPOSITE!$G$176 -> 0 | F24: =COMPOSITE!$E$177 -> 0 | G24: =COMPOSITE!$G$177 -> 0 | H24: =COMPOSITE!$E$178 -> 24 | I24: =COMPOSITE!G$178 -> 0 | J24: =COMPOSITE!$E$179 -> 0 | K24: =COMPOSITE!G$179 -> 0 | L24: =COMPOSITE!E$180 -> 0 | M24: =COMPOSITE!G$180 -> 0 | N24: =COMPOSITE!E$181 -> 173 | O24: =COMPOSITE!G$181 -> 91 | P24: =COMPOSITE!E$182 -> 180 | Q24: =COMPOSITE!G$182 -> 0 | R24: =COMPOSITE!E$183 -> 187 | S24: =COMPOSITE!G$183 -> 359 | T24: =COMPOSITE!E$184 -> 698 | U24: =COMPOSITE!G$184 -> 13 | V24: =COMPOSITE!E$185 -> 0 | W24: =COMPOSITE!G$185 -> 0 | X24: =COMPOSITE!E$186 -> 0 | Y24: =COMPOSITE!G$185 -> 0 | Z24: =COMPOSITE!E$188 -> 67 | AA24: =COMPOSITE!G$188 -> 0 | AB24: =COMPOSITE!E$187 -> 236 | AC24: =COMPOSITE!G$187 -> 13 | AD24: =COMPOSITE!E$189 -> 36 | AE24: =COMPOSITE!G$189 -> 0 | AF24: =COMPOSITE!E$190 -> 186 | AG24: =COMPOSITE!G$190 -> 0 | AH24: =COMPOSITE!E$191 -> 72 | AI24: =COMPOSITE!G$191 -> 24 | AJ24: =COMPOSITE!E$192 -> 370 | AK24: =COMPOSITE!G$192 -> 94 | AL24: =COMPOSITE!E$193 -> 0 | AM24: =COMPOSITE!G$193 -> 0
A25: 42430 | B25: =COMPOSITE!H$199 -> 2443 | C25: =COMPOSITE!J$199 -> 438 | D25: =COMPOSITE!$H$176 -> 0 | E25: =COMPOSITE!$J$176 -> 0 | F25: =COMPOSITE!$H$177 -> 0 | G25: =COMPOSITE!$J$177 -> 0 | H25: =COMPOSITE!$H$178 -> 48 | I25: =COMPOSITE!J$178 -> 0 | J25: =COMPOSITE!$H$179 -> 12 | K25: =COMPOSITE!J$179 -> 0 | L25: =COMPOSITE!H$180 -> 130 | M25: =COMPOSITE!J$180 -> 0 | N25: =COMPOSITE!H$181 -> 197 | O25: =COMPOSITE!J$181 -> 101 | P25: =COMPOSITE!H$182 -> 240 | Q25: =COMPOSITE!J$182 -> 0 | R25: =COMPOSITE!H$183 -> 217.5 | S25: =COMPOSITE!J$183 -> 195 | T25: =COMPOSITE!H$184 -> 752.5 | U25: =COMPOSITE!J$184 -> 0 | V25: =COMPOSITE!H$185 -> 0 | W25: =COMPOSITE!J$185 -> 0 | X25: =COMPOSITE!H$186 -> 0 | Y25: =COMPOSITE!J$185 -> 0 | Z25: =COMPOSITE!H$188 -> 54 | AA25: =COMPOSITE!G$188 -> 0 | AB25: =COMPOSITE!H$187 -> 250 | AC25: =COMPOSITE!J$187 -> 0 | AD25: =COMPOSITE!H$189 -> 36 | AE25: =COMPOSITE!J$189 -> 0 | AF25: =COMPOSITE!H$190 -> 165 | AG25: =COMPOSITE!J$190 -> 0 | AH25: =COMPOSITE!H$191 -> 48 | AI25: =COMPOSITE!J$191 -> 0 | AJ25: =COMPOSITE!H$192 -> 257 | AK25: =COMPOSITE!J$192 -> 142 | AL25: =COMPOSITE!H$193 -> 0 | AM25: =COMPOSITE!J$193 -> 0
A26: 42461 | B26: =COMPOSITE!K$199 -> 2728 | C26: =COMPOSITE!M$199 -> 488 | D26: =COMPOSITE!$K$176 -> 0 | E26: =COMPOSITE!$M$176 -> 0 | F26: =COMPOSITE!$K$177 -> 0 | G26: =COMPOSITE!$M$177 -> 0 | H26: =COMPOSITE!$K$178 -> 96 | I26: =COMPOSITE!M$178 -> 0 | J26: =COMPOSITE!$K$179 -> 36 | K26: =COMPOSITE!M$179 -> 0 | L26: =COMPOSITE!K$180 -> 145 | M26: =COMPOSITE!M$180 -> 0 | N26: =COMPOSITE!K$181 -> 410 | O26: =COMPOSITE!M$181 -> 0 | P26: =COMPOSITE!K$182 -> 192 | Q26: =COMPOSITE!M$182 -> 0 | R26: =COMPOSITE!K$183 -> 280 | S26: =COMPOSITE!M$183 -> 130 | T26: =COMPOSITE!K$184 -> 648 | U26: =COMPOSITE!M$184 -> 65 | V26: =COMPOSITE!K$185 -> 0 | W26: =COMPOSITE!M$185 -> 0 | X26: =COMPOSITE!K$186 -> 0 | Y26: =COMPOSITE!M$185 -> 0 | Z26: =COMPOSITE!K$188 -> 34 | AA26: =COMPOSITE!M$188 -> 0 | AB26: =COMPOSITE!K$187 -> 226 | AC26: =COMPOSITE!M$187 -> 0 | AD26: =COMPOSITE!K$189 -> 342 | AE26: =COMPOSITE!M$189 -> 0 | AF26: =COMPOSITE!K$190 -> 153 | AG26: =COMPOSITE!M$190 -> 50 | AH26: =COMPOSITE!K$191 -> 0 | AI26: =COMPOSITE!M$191 -> 13 | AJ26: =COMPOSITE!K$192 -> 166 | AK26: =COMPOSITE!M$192 -> 178 | AL26: =COMPOSITE!K$193 -> 0 | AM26: =COMPOSITE!M$193 -> 0
A27: 42491 | B27: =COMPOSITE!N$199 -> 2691 | C27: =COMPOSITE!P$199 -> 440 | D27: =COMPOSITE!$N$176 -> 0 | E27: =COMPOSITE!$P$176 -> 0 | F27: =COMPOSITE!$N$177 -> 0 | G27: =COMPOSITE!$P$177 -> 0 | H27: =COMPOSITE!$N$178 -> 144 | I27: =COMPOSITE!P$178 -> 0 | J27: =COMPOSITE!$N$179 -> 0 | K27: =COMPOSITE!P$179 -> 0 | L27: =COMPOSITE!N$180 -> 0 | M27: =COMPOSITE!P$180 -> 0 | N27: =COMPOSITE!N$181 -> 402 | O27: =COMPOSITE!P$181 -> 0 | P27: =COMPOSITE!N$182 -> 264 | Q27: =COMPOSITE!P$182 -> 0 | R27: =COMPOSITE!N$183 -> 314.5 | S27: =COMPOSITE!P$183 -> 91 | T27: =COMPOSITE!N$184 -> 743.5 | U27: =COMPOSITE!P$184 -> 0 | V27: =COMPOSITE!N$185 -> 0 | W27: =COMPOSITE!P$185 -> 0 | X27: =COMPOSITE!N$186 -> 0 | Y27: =COMPOSITE!P$185 -> 0 | Z27: =COMPOSITE!N$188 -> 44 | AA27: =COMPOSITE!P$188 -> 0 | AB27: =COMPOSITE!N$187 -> 152 | AC27: =COMPOSITE!P$187 -> 39 | AD27: =COMPOSITE!N$189 -> 324 | AE27: =COMPOSITE!P$189 -> 0 | AF27: =COMPOSITE!N$190 -> 225 | AG27: =COMPOSITE!P$190 -> 30 | AH27: =COMPOSITE!N$191 -> 0 | AI27: =COMPOSITE!P$191 -> 26 | AJ27: =COMPOSITE!N$192 -> 78 | AK27: =COMPOSITE!P$192 -> 254 | AL27: =COMPOSITE!N$193 -> 0 | AM27: =COMPOSITE!P$193 -> 0
A28: 42522 | B28: =COMPOSITE!Q$199 -> 2468 | C28: =COMPOSITE!S$199 -> 479 | D28: =COMPOSITE!$Q$176 -> 0 | E28: =COMPOSITE!$S$176 -> 0 | F28: =COMPOSITE!$Q$177 -> 0 | G28: =COMPOSITE!$S$177 -> 0 | H28: =COMPOSITE!$Q$178 -> 36 | I28: =COMPOSITE!S$178 -> 0 | J28: =COMPOSITE!$Q$179 -> 0 | K28: =COMPOSITE!S$179 -> 0 | L28: =COMPOSITE!Q$180 -> 0 | M28: =COMPOSITE!S$180 -> 0 | N28: =COMPOSITE!Q$181 -> 359 | O28: =COMPOSITE!S$181 -> 0 | P28: =COMPOSITE!Q$182 -> 276 | Q28: =COMPOSITE!S$182 -> 0 | R28: =COMPOSITE!Q$183 -> 252 | S28: =COMPOSITE!S$183 -> 78 | T28: =COMPOSITE!Q$184 -> 672 | U28: =COMPOSITE!S$184 -> 13 | V28: =COMPOSITE!Q$185 -> 0 | W28: =COMPOSITE!S$185 -> 0 | X28: =COMPOSITE!Q$186 -> 0 | Y28: =COMPOSITE!S$185 -> 0 | Z28: =COMPOSITE!Q$188 -> 10 | AA28: =COMPOSITE!S$188 -> 0 | AB28: =COMPOSITE!Q$187 -> 204 | AC28: =COMPOSITE!S$187 -> 0 | AD28: =COMPOSITE!Q$189 -> 336 | AE28: =COMPOSITE!S$189 -> 0 | AF28: =COMPOSITE!Q$190 -> 165 | AG28: =COMPOSITE!S$190 -> 95 | AH28: =COMPOSITE!Q$191 -> 0 | AI28: =COMPOSITE!S$191 -> 39 | AJ28: =COMPOSITE!Q$192 -> 158 | AK28: =COMPOSITE!S$192 -> 254 | AL28: =COMPOSITE!Q$193 -> 0 | AM28: =COMPOSITE!S$193 -> 0
A29: 42552 | B29: =COMPOSITE!T$199 -> 2138.25 | C29: =COMPOSITE!V$199 -> 578 | D29: =COMPOSITE!$T$176 -> 0 | E29: =COMPOSITE!$V$176 -> 0 | F29: =COMPOSITE!$T$177 -> 0 | G29: =COMPOSITE!$V$177 -> 0 | H29: =COMPOSITE!$T$178 -> 156 | I29: =COMPOSITE!V$178 -> 0 | J29: =COMPOSITE!$T$179 -> 12 | K29: =COMPOSITE!V$179 -> 0 | L29: =COMPOSITE!T$180 -> 0 | M29: =COMPOSITE!V$180 -> 0 | N29: =COMPOSITE!T$181 -> 327 | O29: =COMPOSITE!V$181 -> 0 | P29: =COMPOSITE!T$182 -> 156 | Q29: =COMPOSITE!V$182 -> 0 | R29: =COMPOSITE!T$183 -> 264 | S29: =COMPOSITE!V$183 -> 52 | T29: =COMPOSITE!T$184 -> 467.25 | U29: =COMPOSITE!V$184 -> 207 | V29: =COMPOSITE!T$185 -> 0 | W29: =COMPOSITE!V$185 -> 0 | X29: =COMPOSITE!T$186 -> 0 | Y29: =COMPOSITE!V$185 -> 0 | Z29: =COMPOSITE!T$188 -> 24 | AA29: =COMPOSITE!V$188 -> 0 | AB29: =COMPOSITE!T$187 -> 241 | AC29: =COMPOSITE!V$187 -> 0 | AD29: =COMPOSITE!T$189 -> 300 | AE29: =COMPOSITE!V$189 -> 0 | AF29: =COMPOSITE!T$190 -> 153 | AG29: =COMPOSITE!V$190 -> 73 | AH29: =COMPOSITE!T$191 -> 9 | AI29: =COMPOSITE!V$191 -> 26 | AJ29: =COMPOSITE!T$192 -> 29 | AK29: =COMPOSITE!V$192 -> 207 | AL29: =COMPOSITE!T$193 -> 0 | AM29: =COMPOSITE!V$193 -> 0
A30: 42583 | B30: =COMPOSITE!W$199 -> 2290 | C30: =COMPOSITE!Y$199 -> 236 | D30: =COMPOSITE!$W$176 -> 0 | E30: =COMPOSITE!$Y$176 -> 0 | F30: =COMPOSITE!$W$177 -> 0 | G30: =COMPOSITE!$Y$177 -> 0 | H30: =COMPOSITE!$W$178 -> 48 | I30: =COMPOSITE!Y$178 -> 0 | J30: =COMPOSITE!$W$179 -> 12 | K30: =COMPOSITE!Y$179 -> 0 | L30: =COMPOSITE!W$180 -> 0 | M30: =COMPOSITE!Y$180 -> 0 | N30: =COMPOSITE!W$181 -> 340 | O30: =COMPOSITE!Y$181 -> 0 | R30: =COMPOSITE!W$183 -> 360 | S30: =COMPOSITE!Y$183 -> 0 | T30: =COMPOSITE!W$184 -> 511 | U30: =COMPOSITE!Y$184 -> 111 | V30: =COMPOSITE!W$185 -> 0 | W30: =COMPOSITE!Y$185 -> 0 | X30: =COMPOSITE!W$186 -> 0 | Y30: =COMPOSITE!Y$185 -> 0 | Z30: =COMPOSITE!W$188 -> 68 | AA30: =COMPOSITE!Y$188 -> 0 | AB30: =COMPOSITE!W$187 -> 212 | AC30: =COMPOSITE!Y$187 -> 0 | AD30: =COMPOSITE!W$189 -> 384 | AE30: =COMPOSITE!Y$189 -> 0 | AF30: =COMPOSITE!W$190 -> 111 | AG30: =COMPOSITE!Y$190 -> 63 | AH30: =COMPOSITE!W$191 -> 12 | AI30: =COMPOSITE!Y$191 -> 26 | AJ30: =COMPOSITE!W$192 -> 136 | AK30: =COMPOSITE!Y$192 -> 36 | AL30: =COMPOSITE!W$193 -> 0 | AM30: =COMPOSITE!Y$193 -> 0
A31: 42614 | B31: =COMPOSITE!Z$199 -> 2131 | C31: =COMPOSITE!AB$199 -> 248 | D31: =COMPOSITE!$Z$176 -> 0 | E31: =COMPOSITE!$AB$176 -> 0 | F31: =COMPOSITE!$Z$177 -> 0 | G31: =COMPOSITE!$AB$177 -> 0 | H31: =COMPOSITE!$Z$178 -> 24 | I31: =COMPOSITE!AB$178 -> 0 | J31: =COMPOSITE!$Z$179 -> 0 | K31: =COMPOSITE!AB$179 -> 0 | L31: =COMPOSITE!Z$180 -> 0 | M31: =COMPOSITE!AB$180 -> 0 | N31: =COMPOSITE!Z$181 -> 332 | O31: =COMPOSITE!AB$181 -> 0 | R31: =COMPOSITE!Z$183 -> 372 | S31: =COMPOSITE!AB$183 -> 39 | T31: =COMPOSITE!Z$184 -> 614 | U31: =COMPOSITE!AB$184 -> 39 | V31: =COMPOSITE!Z$185 -> 0 | W31: =COMPOSITE!AB$185 -> 0 | X31: =COMPOSITE!Z$186 -> 0 | Y31: =COMPOSITE!AB$185 -> 0 | Z31: =COMPOSITE!Z$188 -> 106 | AA31: =COMPOSITE!AB$188 -> 0 | AB31: =COMPOSITE!Z$187 -> 121 | AC31: =COMPOSITE!AB$187 -> 39 | AD31: =COMPOSITE!Z$189 -> 360 | AE31: =COMPOSITE!AB$189 -> 0 | AF31: =COMPOSITE!Z$190 -> 0 | AG31: =COMPOSITE!AB$190 -> 40 | AH31: =COMPOSITE!Z$191 -> 0 | AI31: =COMPOSITE!AB$191 -> 91 | AJ31: =COMPOSITE!Z$192 -> 154 | AK31: =COMPOSITE!AB$192 -> 0 | AL31: =COMPOSITE!Z$193 -> 0 | AM31: =COMPOSITE!AB$193 -> 0
A32: 42644 | B32: =COMPOSITE!AC$199 -> 2177.33 | C32: =COMPOSITE!AE$199 -> 565 | D32: =COMPOSITE!$AC$176 -> 0 | E32: =COMPOSITE!$AE$176 -> 0 | F32: =COMPOSITE!$AC$177 -> 0 | G32: =COMPOSITE!$AE$177 -> 0 | H32: =COMPOSITE!$AC$178 -> 84 | I32: =COMPOSITE!AE$178 -> 0 | J32: =COMPOSITE!$AC$179 -> 0 | K32: =COMPOSITE!AE$179 -> 0 | L32: =COMPOSITE!AC$180 -> 1.33 | M32: =COMPOSITE!AE$180 -> 0 | N32: =COMPOSITE!AC$181 -> 343 | O32: =COMPOSITE!AE$181 -> 0 | R32: =COMPOSITE!AC$183 -> 300 | S32: =COMPOSITE!AE$183 -> 78 | T32: =COMPOSITE!AC$184 -> 754 | U32: =COMPOSITE!AE$184 -> 169 | V32: =COMPOSITE!AC$185 -> 0 | W32: =COMPOSITE!AE$185 -> 0 | X32: =COMPOSITE!AC$186 -> 0 | Y32: =COMPOSITE!AE$185 -> 0 | Z32: =COMPOSITE!AC$188 -> 114 | AA32: =COMPOSITE!AE$188 -> 0 | AB32: =COMPOSITE!AC$187 -> 192 | AC32: =COMPOSITE!AE$187 -> 39 | AD32: =COMPOSITE!AC$189 -> 276 | AE32: =COMPOSITE!AE$189 -> 130 | AF32: =COMPOSITE!AC$190 -> 0 | AG32: =COMPOSITE!AE$190 -> 20 | AH32: =COMPOSITE!AC$191 -> 0 | AI32: =COMPOSITE!AE$191 -> 104 | AJ32: =COMPOSITE!AC$192 -> 77 | AK32: =COMPOSITE!AE$192 -> 12 | AL32: =COMPOSITE!AC$193 -> 0 | AM32: =COMPOSITE!AE$193 -> 0
A33: 42675 | B33: =COMPOSITE!AF$199 -> 2387.25 | C33: =COMPOSITE!AH$199 -> 411 | D33: =COMPOSITE!$AF$176 -> 0 | E33: =COMPOSITE!$AH$176 -> 0 | F33: =COMPOSITE!$AF$177 -> 0 | G33: =COMPOSITE!$AH$177 -> 0 | H33: =COMPOSITE!$AF$178 -> 36 | I33: =COMPOSITE!AH$178 -> 0 | J33: =COMPOSITE!$AF$179 -> 0 | K33: =COMPOSITE!AH$179 -> 0 | L33: =COMPOSITE!AF$180 -> 0 | M33: =COMPOSITE!AH$180 -> 0 | N33: =COMPOSITE!AF$181 -> 326 | O33: =COMPOSITE!AH$181 -> 0 | R33: =COMPOSITE!AF$183 -> 385 | S33: =COMPOSITE!AH$183 -> 39 | T33: =COMPOSITE!AF$184 -> 876.5 | U33: =COMPOSITE!AH$184 -> 117 | V33: =COMPOSITE!AF$185 -> 0 | W33: =COMPOSITE!AH$185 -> 0 | X33: =COMPOSITE!AF$186 -> 0 | Y33: =COMPOSITE!AH$185 -> 0 | Z33: =COMPOSITE!AF$188 -> 142.75 | AA33: =COMPOSITE!AH$188 -> 0 | AB33: =COMPOSITE!AF$187 -> 192 | AC33: =COMPOSITE!AH$187 -> 52 | AD33: =COMPOSITE!AF$189 -> 245 | AE33: =COMPOSITE!AH$189 -> 91 | AF33: =COMPOSITE!AF$190 -> 0 | AG33: =COMPOSITE!AH$190 -> 60 | AH33: =COMPOSITE!AF$191 -> 0 | AI33: =COMPOSITE!AH$191 -> 52 | AJ33: =COMPOSITE!AF$192 -> 70 | AK33: =COMPOSITE!AH$192 -> 0 | AL33: =COMPOSITE!AF$193 -> 0 | AM33: =COMPOSITE!AH$193 -> 0
A34: 42705 | B34: =COMPOSITE!AI$199 -> 3040.25 | C34: =COMPOSITE!AK$199 -> 622 | D34: =COMPOSITE!$AI$176 -> 0 | E34: =COMPOSITE!$AK$176 -> 0 | F34: =COMPOSITE!$AI$177 -> 0 | G34: =COMPOSITE!$AK$177 -> 0 | H34: =COMPOSITE!$AI$178 -> 0 | I34: =COMPOSITE!AK$178 -> 0 | J34: =COMPOSITE!$AI$179 -> 0 | K34: =COMPOSITE!AK$179 -> 0 | L34: =COMPOSITE!AI$180 -> 115.5 | M34: =COMPOSITE!AK$180 -> 0 | N34: =COMPOSITE!AI$181 -> 389 | O34: =COMPOSITE!AK$181 -> 0 | R34: =COMPOSITE!AI$183 -> 432 | S34: =COMPOSITE!AK$183 -> 78 | T34: =COMPOSITE!AI$184 -> 648 | U34: =COMPOSITE!AK$184 -> 60 | V34: =COMPOSITE!AI$185 -> 0 | W34: =COMPOSITE!AK$185 -> 0 | X34: =COMPOSITE!AI$186 -> 0 | Y34: =COMPOSITE!AK$185 -> 0 | Z34: =COMPOSITE!AI$188 -> 180.75 | AA34: =COMPOSITE!AK$188 -> 24 | AB34: =COMPOSITE!AI$187 -> 205.5 | AC34: =COMPOSITE!AK$187 -> 13 | AD34: =COMPOSITE!AI$189 -> 312 | AE34: =COMPOSITE!AK$189 -> 195 | AF34: =COMPOSITE!AI$190 -> 0 | AG34: =COMPOSITE!AK$190 -> 70 | AH34: =COMPOSITE!AI$191 -> 0 | AI34: =COMPOSITE!AK$191 -> 39 | AJ34: =COMPOSITE!AI$192 -> 77 | AK34: =COMPOSITE!AK$192 -> 0 | AL34: =COMPOSITE!AI$193 -> 0 | AM34: =COMPOSITE!AK$193 -> 0
A35: YTD Total | B35: =SUM(B23:B34) -> 29289.08 | C35: =SUM(C23:C34) -> 5581 | D35: =SUM(D23:D34) -> 0 | E35: =SUM(E23:E34) -> 0 | F35: =SUM(F23:F34) -> 0 | G35: =SUM(G23:G34) -> 0 | H35: =SUM(H23:H34) -> 756 | I35: =SUM(I23:I34) -> 0 | ... AM35: =SUM(AM23:AM34) -> 0

Sheet EDP PREMIUM LABOR (HOURS) (2)
A20: PREMIUM HOURS
A21: Month | B21: DIVISION TOTAL | K21: BAPTIST | N21: JFK | Q21: JFK BB | T21: JFK PBG | W21: JUPITER | Z21: KENDALL | AC21: MOBERLY | AF21: MONROE | AI21: OCALA w/APP | AL21: SAN RAMON | AO21: ST. MARY'S | AR21: W MARION QC | AU21: W MARION | AX21: SUMMERFIELD | BA21: WESTCHESTER | BD21: PROVIDENCE | BG21: ST. JOHN | BJ21: OSCEOLA | BM21: OSCEOLA PEDS | BP21: HUNTERS CREEK
B22: Budgeted Hrs JV Sites | C22: Actual Hrs JV Sites | D22: JV Sites % | E22: Budgeted Hrs Organic | F22: Actual Hrs Organic | G22: Organic % | H22: Budgeted Hrs Same Contract | I22: Actual Hrs Same Contract | J22: Same Contracts % | K22: Budget | L22: Actual | M22: % | N22: Budget | O22: Actual | P22: % | Q22: Budget | R22: Actual | S22: % | T22: Budget | U22: Actual | V22: % | W22: Budget | X22: Actual | Y22: % | Z22: Budget | AA22: Actual | AB22: % | AC22: Budget | AD22: Actual | AE22: % | AF22: Budget | AG22: Actual | AH22: % | AI22: Budget | AJ22: Actual | AK22: % | AL22: Budget | AM22: Actual | AN22: % | AO22: Budget | AP22: Actual | AQ22: % | AR22: Budget | AS22: Actual | AT22: % | AU22: Budget | AV22: Actual | AW22: % | AX22: Budget | AY22: Actual | AZ22: % | BA22: Budget | BB22: Actual | BC22: % | BD22: Budget | BE22: Actual | BF22: % | BG22: Budget | BH22: Actual | BI22: % | BJ22: Budget | BK22: Actual | BL22: % | BM22: Budget | BN22: Actual | BO22: % | BP22: Budget | BQ22: Actual | BR22: %
A23: 42370 | B23: =371*31 -> 11501 | C23: =SUM(O23,R23,U23,AA23,BK23,BN23,BQ23) -> 1272 | D23: =C23/B23 -> 0.11059908 | E23: =313*31 -> 9703 | F23: =SUM(AG23,AM23,AY23,BE23,BH23,AD23) -> 497 | G23: =F23/E23 -> 0.051221272 | H23: =303*31 -> 9393 | I23: =SUM(L23,X23,AP23,AS23,AV23,AJ23,BB23) -> 1407 | J23: =I23/H23 -> 0.1497924 | K23: =120*31 -> 3720 | L23: =COMPOSITE!$D$176+COMPOSITE!$B$176 -> 0 | M23: =L23/K23 -> 0 | N23: =95*31 -> 2945 | O23: =COMPOSITE!$D$177+COMPOSITE!$B$177 -> 0 | P23: =O23/N23 -> 0 | Q23: =24*31 -> 744 | R23: =COMPOSITE!D$178+COMPOSITE!$B$178 -> 60 | S23: =R23/Q23 -> 0.080645161 | T23: =24*31 -> 744 | U23: =COMPOSITE!D$179+COMPOSITE!$B$179 -> 0 | V23: =U23/T23 -> 0 | W23: =47*31 -> 1457 | X23: =COMPOSITE!D$180+COMPOSITE!$B$180 -> 1.5 | Y23: =X23/W23 -> 0.0010295127 | Z23: =117*31 -> 3627 | AA23: =COMPOSITE!D$181+COMPOSITE!$B$181 -> 452 | AB23: =AA23/Z23 -> 0.1246209 | AC23: =4*31 -> 124 | AD23: =COMPOSITE!B$182 -> 165 | AF23: =24*31 -> 744 | AG23: =COMPOSITE!D$183+COMPOSITE!$B$183 -> 132 | AH23: =AG23/AF23 -> 0.17741935 | AI23: =42*31 -> 1302 | AJ23: =152+COMPOSITE!$B$184 -> 760.5 | AK23: =AJ23/AI23 -> 0.58410138 | AL23: =32*31 -> 992 | AM23: =COMPOSITE!D$185+COMPOSITE!$B$185 -> 0 | AN23: =AM23/AL23 -> 0 | AO23: =24*31 -> 744 | AP23: =COMPOSITE!D$186+COMPOSITE!$B$186 -> 0 | AQ23: =AP23/AO23 -> 0 | AR23: =22*31 -> 682 | AS23: =COMPOSITE!D$188+COMPOSITE!$B$188 -> 24 | AT23: =AS23/AR23 -> 0.035190616 | AU23: =24*31 -> 744 | AV23: =COMPOSITE!D$187+COMPOSITE!$B$187 -> 297 | AW23: =AV23/AU23 -> 0.39919355 | AX23: =12*31 -> 372 | AY23: 0 | AZ23: =AY23/AX23 -> 0 | BA23: =24*31 -> 744 | BB23: =COMPOSITE!D$189+COMPOSITE!$B$189 -> 324 | BC23: =BB23/BA23 -> 0.43548387 | BD23: =36*31 -> 1116 | BE23: =COMPOSITE!D$190+COMPOSITE!$B$190 -> 174 | BF23: =BE23/BD23 -> 0.15591398 | BG23: =24*31 -> 744 | BH23: =COMPOSITE!D$191+COMPOSITE!$B$191 -> 26 | BI23: =BH23/BG23 -> 0.034946237 | BJ23: =65*31 -> 2015 | BK23: =COMPOSITE!D$192+COMPOSITE!$B$192 -> 736 | BL23: =BK23/BJ23 -> 0.36526055 | BM23: =21*31 -> 651 | BN23: =COMPOSITE!D$193+COMPOSITE!$B$193 -> 0 | BO23: =BN23/BM23 -> 0 | BP23: =24*31 -> 744 | BQ23: =COMPOSITE!D$194+COMPOSITE!$B$194 -> 24 | BR23: =BQ23/BP23 -> 0.032258065
A24: 42401 | B24: =371*29 -> 10759 | C24: =SUM(O24,R24,U24,AA24,BK24,BN24,BQ24) -> 776 | D24: =C24/B24 -> 0.072125662 | E24: =313*29 -> 9077 | F24: =SUM(AG24,AM24,AY24,BE24,BH24,AD24) -> 1008 | G24: =F24/E24 -> 0.11104991 | H24: =303*29 -> 8787 | I24: =SUM(L24,X24,AP24,AS24,AV24,AJ24,BB24) -> 1319 | J24: =I24/H24 -> 0.15010811 | K24: =120*29 -> 3480 | L24: =COMPOSITE!$G$176+COMPOSITE!$E$176 -> 0 | M24: =L24/K24 -> 0 | N24: =95*29 -> 2755 | O24: =COMPOSITE!$G$177++COMPOSITE!$E$177 -> 0 | P24: =O24/N24 -> 0 | Q24: =24*29 -> 696 | R24: =COMPOSITE!G$178+COMPOSITE!$E$178 -> 24 | S24: =R24/Q24 -> 0.034482759 | T24: =24*29 -> 696 | U24: =COMPOSITE!G$179+COMPOSITE!$E$179 -> 0 | V24: =U24/T24 -> 0 | W24: =47*29 -> 1363 | X24: =COMPOSITE!G$180+COMPOSITE!$E$180 -> 0 | Y24: =X24/W24 -> 0 | Z24: =117*29 -> 3393 | AA24: =COMPOSITE!G$181+COMPOSITE!$E$181 -> 264 | AB24: =AA24/Z24 -> 0.07780725 | AC24: =4*29 -> 116 | AD24: =COMPOSITE!E$182 -> 180 | AF24: =24*29 -> 696 | AG24: =COMPOSITE!G$183+COMPOSITE!$E$183 -> 546 | AH24: =AG24/AF24 -> 0.78448276 | AI24: =42*29 -> 1218 | AJ24: =269+COMPOSITE!$E$184 -> 967 | AK24: =AJ24/AI24 -> 0.79392447 | AL24: =32*29 -> 928 | AM24: =COMPOSITE!G$185+COMPOSITE!$E$185 -> 0 | AN24: =AM24/AL24 -> 0 | AO24: =24*29 -> 696 | AP24: =COMPOSITE!G$186+COMPOSITE!$E$186 -> 0 | AQ24: =AP24/AO24 -> 0 | AR24: =22*29 -> 638 | AS24: =COMPOSITE!G$188+COMPOSITE!$E$188 -> 67 | AT24: =AS24/AR24 -> 0.10501567 | AU24: =24*29 -> 696 | AV24: =COMPOSITE!G$187+COMPOSITE!$E$187 -> 249 | AW24: =AV24/AU24 -> 0.35775862 | AX24: =12*29 -> 348 | AY24: 0 | AZ24: =AY24/AX24 -> 0 | BA24: =24*29 -> 696 | BB24: =COMPOSITE!G$189+COMPOSITE!$E$189 -> 36 | BC24: =BB24/BA24 -> 0.051724138 | BD24: =36*29 -> 1044 | BE24: =COMPOSITE!G$190+COMPOSITE!$E$190 -> 186 | BF24: =BE24/BD24 -> 0.17816092 | BG24: =24*29 -> 696 | BH24: =COMPOSITE!G$191+COMPOSITE!$E$191 -> 96 | BI24: =BH24/BG24 -> 0.13793103 | BJ24: =65*29 -> 1885 | BK24: =COMPOSITE!G$192+COMPOSITE!$E$192 -> 464 | BL24: =BK24/BJ24 -> 0.24615385 | BM24: =21*29 -> 609 | BN24: =COMPOSITE!G$193+COMPOSITE!$E$193 -> 0 | BO24: =BN24/BM24 -> 0 | BP24: =24*29 -> 696 | BQ24: =COMPOSITE!G$194+COMPOSITE!$E$194 -> 24 | BR24: =BQ24/BP24 -> 0.034482759
A25: 42430 | B25: =371*31 -> 11501 | C25: =SUM(O25,R25,U25,AA25,BK25,BN25,BQ25) -> 793 | D25: =C25/B25 -> 0.068950526 | E25: =313*31 -> 9703 | F25: =SUM(AG25,AM25,AY25,BE25,BH25,AD25) -> 865.5 | G25: =F25/E25 -> 0.089199217 | H25: =303*31 -> 9393 | I25: =SUM(L25,X25,AP25,AS25,AV25,AJ25,BB25) -> 1455.5 | J25: =I25/H25 -> 0.15495582 | K25: =120*31 -> 3720 | L25: =COMPOSITE!$J$176+COMPOSITE!$H$176 -> 0 | M25: =L25/K25 -> 0 | N25: =95*31 -> 2945 | O25: =COMPOSITE!$J$177++COMPOSITE!$H$177 -> 0 | P25: =O25/N25 -> 0 | Q25: =24*31 -> 744 | R25: =COMPOSITE!J$178++COMPOSITE!$H$178 -> 48 | S25: =R25/Q25 -> 0.064516129 | T25: =24*31 -> 744 | U25: =COMPOSITE!J$179+COMPOSITE!$H$179 -> 12 | V25: =U25/T25 -> 0.016129032 | W25: =47*31 -> 1457 | X25: =COMPOSITE!J$180+COMPOSITE!$H$180 -> 130 | Y25: =X25/W25 -> 0.089224434 | Z25: =117*31 -> 3627 | AA25: =COMPOSITE!J$181+COMPOSITE!$H$181 -> 298 | AB25: =AA25/Z25 -> 0.082161566 | AC25: =4*31 -> 124 | AD25: =COMPOSITE!H$182 -> 240 | AF25: =24*31 -> 744 | AG25: =COMPOSITE!J$183+COMPOSITE!$H$183 -> 412.5 | AH25: =AG25/AF25 -> 0.55443548 | AI25: =42*31 -> 1302 | AJ25: =233+COMPOSITE!$H$184 -> 985.5 | AK25: =AJ25/AI25 -> 0.75691244 | AL25: =32*31 -> 992 | AM25: =COMPOSITE!J$185+COMPOSITE!$H$185 -> 0 | AN25: =AM25/AL25 -> 0 | AO25: =24*31 -> 744 | AP25: =COMPOSITE!J$186+COMPOSITE!$H$186 -> 0 | AQ25: =AP25/AO25 -> 0 | AR25: =22*31 -> 682 | AS25: =COMPOSITE!J$188+COMPOSITE!$H$188 -> 54 | AT25: =AS25/AR25 -> 0.079178886 | AU25: =24*31 -> 744 | AV25: =COMPOSITE!J$187+COMPOSITE!$H$187 -> 250 | AW25: =AV25/AU25 -> 0.33602151 | AX25: =12*31 -> 372 | AY25: 0 | AZ25: =AY25/AX25 -> 0 | BA25: =24*31 -> 744 | BB25: =COMPOSITE!J$189+COMPOSITE!$H$189 -> 36 | BC25: =BB25/BA25 -> 0.048387097 | BD25: =36*31 -> 1116 | BE25: =COMPOSITE!J$190+COMPOSITE!$H$190 -> 165 | BF25: =BE25/BD25 -> 0.14784946 | BG25: =24*31 -> 744 | BH25: =COMPOSITE!J$191+COMPOSITE!$H$191 -> 48 | BI25: =BH25/BG25 -> 0.064516129 | BJ25: =65*31 -> 2015 | BK25: =COMPOSITE!J$192+COMPOSITE!$H$192 -> 399 | BL25: =BK25/BJ25 -> 0.19801489 | BM25: =21*31 -> 651 | BN25: =COMPOSITE!J$193+COMPOSITE!$H$193 -> 0 | BO25: =BN25/BM25 -> 0 | BP25: =24*31 -> 744 | BQ25: =COMPOSITE!J$194+COMPOSITE!$H$194 -> 36 | BR25: =BQ25/BP25 -> 0.048387097
A26: 42461 | B26: =371*30 -> 11130 | C26: =SUM(O26,R26,U26,AA26,BK26,BN26,BQ26) -> 938 | D26: =C26/B26 -> 0.08427673 | E26: =313*30 -> 9390 | F26: =SUM(AG26,AM26,AY26,BE26,BH26,AD26) -> 818 | G26: =F26/E26 -> 0.087113951 | H26: =303*30 -> 9090 | I26: =SUM(L26,X26,AP26,AS26,AV26,AJ26,BB26) -> 1759 | J26: =I26/H26 -> 0.19350935 | K26: =120*30 -> 3600 | L26: =COMPOSITE!$M$176+COMPOSITE!$K$176 -> 0 | M26: =L26/K26 -> 0 | N26: =95*31 -> 2945 | O26: =COMPOSITE!$M$177+COMPOSITE!$K$177 -> 0 | P26: =O26/N26 -> 0 | Q26: =24*30 -> 720 | R26: =COMPOSITE!M$178++COMPOSITE!$K$178 -> 96 | S26: =R26/Q26 -> 0.13333333 | T26: =24*30 -> 720 | U26: =COMPOSITE!M$179+COMPOSITE!$K$179 -> 36 | V26: =U26/T26 -> 0.05 | W26: =47*30 -> 1410 | X26: =COMPOSITE!M$180+COMPOSITE!$K$180 -> 145 | Y26: =X26/W26 -> 0.10283688 | Z26: =117*30 -> 3510 | AA26: =COMPOSITE!M$181+COMPOSITE!$K$181 -> 410 | AB26: =AA26/Z26 -> 0.11680912 | AC26: =4*30 -> 120 | AD26: =COMPOSITE!K$182 -> 192 | AF26: =24*30 -> 720 | AG26: =COMPOSITE!M$183+COMPOSITE!$K$183 -> 410 | AH26: =AG26/AF26 -> 0.56944444 | AI26: =42*30 -> 1260 | AJ26: =364+COMPOSITE!$K$184 -> 1012 | AK26: =AJ26/AI26 -> 0.8031746 | AL26: =32*30 -> 960 | AM26: =COMPOSITE!M$185+COMPOSITE!$K$185 -> 0 | AN26: =AM26/AL26 -> 0 | AO26: =24*30 -> 720 | AP26: =COMPOSITE!M$186+COMPOSITE!$K$186 -> 0 | AQ26: =AP26/AO26 -> 0 | AR26: =22*30 -> 660 | AS26: =COMPOSITE!M$188+COMPOSITE!$K$188 -> 34 | AT26: =AS26/AR26 -> 0.051515152 | AU26: =24*30 -> 720 | AV26: =COMPOSITE!M$187+COMPOSITE!$K$187 -> 226 | AW26: =AV26/AU26 -> 0.31388889 | AX26: =12*30 -> 360 | AY26: 0 | AZ26: =AY26/AX26 -> 0 | BA26: =24*30 -> 720 | BB26: =COMPOSITE!M$189+COMPOSITE!$K$189 -> 342 | BC26: =BB26/BA26 -> 0.475 | BD26: =36*30 -> 1080 | BE26: =COMPOSITE!M$190+COMPOSITE!$K$190 -> 203 | BF26: =BE26/BD26 -> 0.18796296 | BG26: =24*30 -> 720 | BH26: =COMPOSITE!M$191+COMPOSITE!$K$191 -> 13 | BI26: =BH26/BG26 -> 0.018055556 | BJ26: =65*30 -> 1950 | BK26: =COMPOSITE!M$192+COMPOSITE!$K$192 -> 344 | BL26: =BK26/BJ26 -> 0.17641026 | BM26: =21*30 -> 630 | BN26: =COMPOSITE!M$193+COMPOSITE!$K$193 -> 0 | BO26: =BN26/BM26 -> 0 | BP26: =24*30 -> 720 | BQ26: =COMPOSITE!M$194+COMPOSITE!$K$194 -> 52 | BR26: =BQ26/BP26 -> 0.072222222
A27: 42491 | B27: =371*31 -> 11501 | C27: =SUM(O27,R27,U27,AA27,BK27,BN27,BQ27) -> 878 | D27: =C27/B27 -> 0.076341188 | E27: =313*31 -> 9703 | F27: =SUM(AG27,AM27,AY27,BE27,BH27,AD27) -> 950.5 | G27: =F27/E27 -> 0.097959394 | H27: =303*31 -> 9393 | I27: =SUM(L27,X27,AP27,AS27,AV27,AJ27,BB27) -> 1666.5 | J27: =I27/H27 -> 0.17741935 | K27: =120*31 -> 3720 | L27: =COMPOSITE!$P$176+COMPOSITE!$N$176 -> 0 | M27: =L27/K27 -> 0 | N27: =95*31 -> 2945 | O27: =COMPOSITE!$P$177++COMPOSITE!$N$177 -> 0 | P27: =O27/N27 -> 0 | Q27: =24*31 -> 744 | R27: =COMPOSITE!P$178+COMPOSITE!$N$178 -> 144 | S27: =R27/Q27 -> 0.19354839 | T27: =24*31 -> 744 | U27: =COMPOSITE!P$179+COMPOSITE!$N$179 -> 0 | V27: =U27/T27 -> 0 | W27: =47*31 -> 1457 | X27: =COMPOSITE!P$180+COMPOSITE!$N$180 -> 0 | Y27: =X27/W27 -> 0 | Z27: =117*31 -> 3627 | AA27: =COMPOSITE!P$181+COMPOSITE!$N$181 -> 402 | AB27: =AA27/Z27 -> 0.1108354 | AC27: =4*31 -> 124 | AD27: =COMPOSITE!N$182 -> 264 | AF27: =24*31 -> 744 | AG27: =COMPOSITE!P$183+COMPOSITE!$N$183 -> 405.5 | AH27: =AG27/AF27 -> 0.54502688 | AI27: =42*31 -> 1302 | AJ27: =364+COMPOSITE!$N$184 -> 1107.5 | AK27: =AJ27/AI27 -> 0.85061444 | AL27: =32*31 -> 992 | AM27: =COMPOSITE!P$185+COMPOSITE!$N$185 -> 0 | AN27: =AM27/AL27 -> 0 | AO27: =24*31 -> 744 | AP27: =COMPOSITE!P$186+COMPOSITE!$N$186 -> 0 | AQ27: =AP27/AO27 -> 0 | AR27: =22*31 -> 682 | AS27: =COMPOSITE!P$188+COMPOSITE!$N$188 -> 44 | AT27: =AS27/AR27 -> 0.064516129 | AU27: =24*31 -> 744 | AV27: =COMPOSITE!P$187+COMPOSITE!$N$187 -> 191 | AW27: =AV27/AU27 -> 0.25672043 | AX27: =12*31 -> 372 | AY27: 0 | AZ27: =AY27/AX27 -> 0 | BA27: =24*31 -> 744 | BB27: =COMPOSITE!P$189+COMPOSITE!$N$189 -> 324 | BC27: =BB27/BA27 -> 0.43548387 | BD27: =36*31 -> 1116 | BE27: =COMPOSITE!P$190+COMPOSITE!$N$190 -> 255 | BF27: =BE27/BD27 -> 0.22849462 | BG27: =24*31 -> 744 | BH27: =COMPOSITE!P$191+COMPOSITE!$N$191 -> 26 | BI27: =BH27/BG27 -> 0.034946237 | BJ27: =65*31 -> 2015 | BK27: =COMPOSITE!P$192+COMPOSITE!$N$192 -> 332 | BL27: =BK27/BJ27 -> 0.16476427 | BM27: =21*31 -> 651 | BN27: =COMPOSITE!P$193+COMPOSITE!$N$193 -> 0 | BO27: =BN27/BM27 -> 0 | BP27: =24*31 -> 744 | BQ27: =COMPOSITE!P$194+COMPOSITE!$N$194 -> 0 | BR27: =BQ27/BP27 -> 0
A28: 42522 | B28: =371*30 -> 11130 | C28: =SUM(O28,R28,U28,AA28,BK28,BN28,BQ28) -> 807 | D28: =C28/B28 -> 0.072506739 | E28: =313*30 -> 9390 | F28: =SUM(AG28,AM28,AY28,BE28,BH28,AD28) -> 905 | G28: =F28/E28 -> 0.096379127 | H28: =303*30 -> 9090 | I28: =SUM(L28,X28,AP28,AS28,AV28,AJ28,BB28) -> 1612 | J28: =I28/H28 -> 0.17733773 | K28: =120*30 -> 3600 | L28: =COMPOSITE!$S$176+COMPOSITE!$Q$176 -> 0 | M28: =L28/K28 -> 0 | N28: =95*31 -> 2945 | O28: =COMPOSITE!$S$177++COMPOSITE!$Q$177 -> 0 | P28: =O28/N28 -> 0 | Q28: =24*30 -> 720 | R28: =COMPOSITE!S$178+COMPOSITE!$Q$178 -> 36 | S28: =R28/Q28 -> 0.05 | T28: =24*30 -> 720 | U28: =COMPOSITE!S$179+COMPOSITE!$Q$179 -> 0 | V28: =U28/T28 -> 0 | W28: =47*30 -> 1410 | X28: =COMPOSITE!S$180+COMPOSITE!$Q$180 -> 0 | Y28: =X28/W28 -> 0 | Z28: =117*30 -> 3510 | AA28: =COMPOSITE!S$181+COMPOSITE!$Q$181 -> 359 | AB28: =AA28/Z28 -> 0.1022792 | AC28: =4*30 -> 120 | AD28: =COMPOSITE!Q$182 -> 276 | AF28: =24*30 -> 720 | AG28: =COMPOSITE!S$183+COMPOSITE!$Q$183 -> 330 | AH28: =AG28/AF28 -> 0.45833333 | AI28: =42*30 -> 1260 | AJ28: =390+COMPOSITE!$Q$184 -> 1062 | AK28: =AJ28/AI28 -> 0.84285714 | AL28: =32*30 -> 960 | AM28: =COMPOSITE!S$185+COMPOSITE!$Q$185 -> 0 | AN28: =AM28/AL28 -> 0 | AO28: =24*30 -> 720 | AP28: =COMPOSITE!S$186+COMPOSITE!$Q$186 -> 0 | AQ28: =AP28/AO28 -> 0 | AR28: =22*30 -> 660 | AS28: =COMPOSITE!S$188+COMPOSITE!$Q$188 -> 10 | AT28: =AS28/AR28 -> 0.015151515 | AU28: =24*30 -> 720 | AV28: =COMPOSITE!S$187+COMPOSITE!$Q$187 -> 204 | AW28: =AV28/AU28 -> 0.28333333 | AX28: =12*30 -> 360 | AY28: 0 | AZ28: =AY28/AX28 -> 0 | BA28: =24*30 -> 720 | BB28: =COMPOSITE!S$189+COMPOSITE!$Q$189 -> 336 | BC28: =BB28/BA28 -> 0.46666667 | BD28: =36*30 -> 1080 | BE28: =COMPOSITE!S$190+COMPOSITE!$Q$190 -> 260 | BF28: =BE28/BD28 -> 0.24074074 | BG28: =24*30 -> 720 | BH28: =COMPOSITE!S$191+COMPOSITE!$Q$191 -> 39 | BI28: =BH28/BG28 -> 0.054166667 | BJ28: =65*30 -> 1950 | BK28: =COMPOSITE!S$192+COMPOSITE!$Q$192 -> 412 | BL28: =BK28/BJ28 -> 0.21128205 | BM28: =21*30 -> 630 | BN28: =COMPOSITE!S$193+COMPOSITE!$Q$193 -> 0 | BO28: =BN28/BM28 -> 0 | BP28: =24*30 -> 720 | BQ28: =COMPOSITE!S$194+COMPOSITE!$Q$194 -> 0 | BR28: =BQ28/BP28 -> 0
A29: 42552 | B29: =371*31 -> 11501 | C29: =SUM(O29,R29,U29,AA29,BK29,BN29,BQ29) -> 744 | D29: =C29/B29 -> 0.064690027 | E29: =313*31 -> 9703 | F29: =SUM(AG29,AM29,AY29,BE29,BH29,AD29) -> 733 | G29: =F29/E29 -> 0.075543646 | H29: =303*31 -> 9393 | I29: =SUM(L29,X29,AP29,AS29,AV29,AJ29,BB29) -> 1624.25 | J29: =I29/H29 -> 0.17292132 | K29: =120*31 -> 3720 | L29: =COMPOSITE!$V$176+COMPOSITE!$T$176 -> 0 | M29: =L29/K29 -> 0 | N29: =95*31 -> 2945 | O29: =COMPOSITE!$V$177++COMPOSITE!$T$177 -> 0 | P29: =O29/N29 -> 0 | Q29: =24*31 -> 744 | R29: =COMPOSITE!V$178+COMPOSITE!$T$178 -> 156 | S29: =R29/Q29 -> 0.20967742 | T29: =24*31 -> 744 | U29: =COMPOSITE!V$179+COMPOSITE!$T$179 -> 12 | V29: =U29/T29 -> 0.016129032 | W29: =47*31 -> 1457 | X29: =COMPOSITE!V$180+COMPOSITE!$T$180 -> 0 | Y29: =X29/W29 -> 0 | Z29: =117*31 -> 3627 | AA29: =COMPOSITE!V$181+COMPOSITE!$T$181 -> 327 | AB29: =AA29/Z29 -> 0.090157155 | AC29: =4*31 -> 124 | AD29: =COMPOSITE!T$182 -> 156 | AF29: =24*31 -> 744 | AG29: =COMPOSITE!V$183+COMPOSITE!$T$183 -> 316 | AH29: =AG29/AF29 -> 0.42473118 | AI29: =42*31 -> 1302 | AJ29: =592+COMPOSITE!$T$184 -> 1059.25 | AK29: =AJ29/AI29 -> 0.81355607 | AL29: =32*31 -> 992 | AM29: =COMPOSITE!V$185+COMPOSITE!$T$185 -> 0 | AN29: =AM29/AL29 -> 0 | AO29: =24*31 -> 744 | AP29: =COMPOSITE!V$186+COMPOSITE!$T$186 -> 0 | AQ29: =AP29/AO29 -> 0 | AR29: =22*31 -> 682 | AS29: =COMPOSITE!V$188+COMPOSITE!$T$188 -> 24 | AT29: =AS29/AR29 -> 0.035190616 | AU29: =24*31 -> 744 | AV29: =COMPOSITE!V$187+COMPOSITE!$T$187 -> 241 | AW29: =AV29/AU29 -> 0.32392473 | AX29: =12*31 -> 372 | AY29: 0 | AZ29: =AY29/AX29 -> 0 | BA29: =24*31 -> 744 | BB29: =COMPOSITE!V$189+COMPOSITE!$T$189 -> 300 | BC29: =BB29/BA29 -> 0.40322581 | BD29: =36*31 -> 1116 | BE29: =COMPOSITE!V$190+COMPOSITE!$T$190 -> 226 | BF29: =BE29/BD29 -> 0.20250896 | BG29: =24*31 -> 744 | BH29: =COMPOSITE!V$191+COMPOSITE!$T$191 -> 35 | BI29: =BH29/BG29 -> 0.047043011 | BJ29: =65*31 -> 2015 | BK29: =COMPOSITE!V$192+COMPOSITE!$T$192 -> 236 | BL29: =BK29/BJ29 -> 0.11712159 | BM29: =21*31 -> 651 | BN29: =COMPOSITE!V$193+COMPOSITE!$T$193 -> 0 | BO29: =BN29/BM29 -> 0 | BP29: =24*31 -> 744 | BQ29: =COMPOSITE!V$194+COMPOSITE!$T$194 -> 13 | BR29: =BQ29/BP29 -> 0.017473118
