Workbook
Name Category: survey_data!$F$2:$F$1699
Name n_apr: Satisfaction!$K$9:$K$40,Satisfaction!$K$48:$K$79,Satisfaction!$K$87:$K$118,Satisfaction!$K$126:$K$157,Satisfaction!$K$165:$K$196,Satisfaction!$K$204:$K$235
Name Period: survey_data!$B$2:$B$1699
Name Provider: survey_data!$E$2:$E$1699
Name Responses: survey_data!$H$2:$H$1699
Name Score: survey_data!$G$2:$G$1699

Sheet Sheet1
A3: Month | B3: Person | C3: Task | D3: y | E3: x | J3: patients | K3: y_satisf | M3: patients | N3: y_satisf
A4: Jan | B4: Smith | C4: Fishing | D4: 34 | E4: 4 | J4: 7 | K4: 85.7 | M4: 7 | N4: 85.7
A5: Jan | B5: Jim | C5: Fishing | D5: 56 | E5: 5 | J5: 7 | K5: 82.1 | M5: 7 | N5: 82.1
A6: Jan | B6: John | C6: Fishing | D6: 85 | E6: 4 | J6: 7 | K6: 92.9 | M6: 7 | N6: 92.9
A7: Jan | B7: Fred | C7: Fishing | D7: 35 | E7: 6 | J7: 4 | K7: 68.8 | M7: 4 | N7: 68.8
A8: Jan | B8: Smith | C8: Running | D8: 45 | E8: 2 | J8: 7 | K8: 85.7 | M8: 7 | N8: 85.7
A9: Jan | B9: Jim | C9: Running | D9: 34 | E9: 8 | J9: 4 | K9: 50 | M9: 4 | N9: 50
A10: Jan | B10: John | C10: Running | D10: 45 | E10: 7 | J10: 4 | K10: 93.8 | M10: 4 | N10: 93.8
A11: Jan | B11: Fred | C11: Running | D11: 56 | E11: 9 | J11: 5 | K11: 90 | M11: 5 | N11: 90
A12: Feb | B12: Smith | C12: Fishing | D12: .. | E12: .. | J12: 8 | K12: 78.1 | M12: 8 | N12: 78.1
A13: Feb | B13: Jim | C13: Fishing | D13: .. | E13: .. | J13: 8 | K13: 93.8 | M13: 8 | N13: 93.8
A14: Feb | B14: John | C14: Fishing | D14: .. | E14: .. | J14: 4 | K14: 93.8 | M14: 4 | N14: 93.8
A15: Feb | B15: Fred | C15: Fishing | D15: .. | E15: .. | J15: 11 | K15: 88.6 | M15: 11 | N15: 88.6
A16: Feb | B16: Smith | C16: Running | D16: .. | E16: .. | J16: 9 | K16: 80.6 | M16: 9 | N16: 80.6
A17: Feb | B17: Jim | C17: Running | D17: .. | E17: .. | J17: 1 | K17: 75 | M17: 1 | N17: 75
A18: Feb | B18: John | C18: Running | D18: .. | E18: .. | J18: 7 | K18: 71.4 | M18: 7 | N18: 71.4
A19: Feb | B19: Fred | C19: Running | D19: .. | E19: .. | J19: 11 | K19: 86.4 | M19: 11 | N19: 86.4
A20: Mar | B20: Smith | C20: Fishing | D20: .. | E20: .. | J20: 1 | K20: 100 | M20: 1 | N20: 100
A21: Mar | B21: Jim | C21: Fishing | D21: .. | E21: .. | J21: 11 | K21: 61.4 | M21: 11 | N21: 61.4
A22: Mar | B22: John | C22: Fishing | D22: .. | E22: .. | J22: 6 | K22: 83.3 | M22: 6 | N22: 83.3
A23: Mar | B23: Fred | C23: Fishing | D23: .. | E23: .. | J23: 8 | K23: 59.4 | M23: 8 | N23: 59.4
... A28: .. | B28: .. | C28: .. | D28: .. | E28: .. | J28: 1 | K28: 75 | M28: 1 | N28: 75
J29: 3 | K29: 58.3 | M29: 3 | N29: 58.3
A30: 12 Mths | B30: 4 People | C30: 2 tasks each | D30: Y variable | E30: X variable | J30: 6 | K30: 100 | M30: 6 | N30: 100
J31: 6 | K31: 87.5 | M31: 6 | N31: 87.5
J32: 9 | K32: 16.7 | M32: 7 | N32: 82.1
J33: 7 | K33: 82.1 | M33: 5 | N33: 90
J34: 5 | K34: 90 | M34: 13 | N34: 71.2
J35: 13 | K35: 71.2

Sheet Reg1
A1: Doctor informative re treatment | H1: β1 | I1: β0 | R1: Doctor took time to listen | Y1: β1 | Z1: β0 | AI1: Doctors concern for comfort | AP1: β1 | AQ1: β0 | AZ1: Doctors courtesy | BG1: β1 | BH1: β0 | BQ1: Std Doctors | BX1: β1 | BY1: β0
H2: -0.8596 | I2: 78.797 | Y2: -0.643 | Z2: 79.571 | AP2: -1.3854 | AQ2: 83.09 | BG2: -0.8974 | BH2: 85.371 | BX2: -0.9511 | BY2: 81.857
B4: patients | C4: y_satisf | D4: ŷ | E4: ε | S4: patients | T4: y_satisf | U4: ŷ | V4: ε | AJ4: patients | AK4: y_satisf | AL4: ŷ | AM4: ε | BA4: patients | BB4: y_satisf | BC4: ŷ | BD4: ε | BR4: patients | BS4: y_satisf | BT4: ŷ | BU4: ε
A5: 1 | B5: =Satisfaction!K9 -> 7 | C5: =Satisfaction!I9 -> 85.7 | D5: =($H$2*B5)+$I$2 -> 72.7798 | E5: =C5-D5 -> 12.9202 | R5: 1 | S5: 7 | T5: 89.3 | U5: =($Y$2*S5)+$Z$2 -> 75.07 | V5: =T5-U5 -> 14.23 | AI5: 1 | AJ5: 7 | AK5: 89.3 | AL5: =($AP$2*AJ5)+$AQ$2 -> 73.3922 | AM5: =AK5-AL5 -> 15.9078 | AZ5: 1 | BA5: 7 | BB5: 85.7 | BC5: =($BG$2*BA5)+$BH$2 -> 79.0892 | BD5: =BB5-BC5 -> 6.6108 | BQ5: 1 | BR5: 7 | BS5: 87.5 | BT5: =($BX$2*BR5)+$BY$2 -> 75.1993 | BU5: =BS5-BT5 -> 12.3007
A6: 2 | B6: =Satisfaction!K10 -> 7 | C6: =Satisfaction!I10 -> 71.4 | D6: =($H$2*B6)+$I$2 -> 72.7798 | E6: =C6-D6 -> -1.3798 | R6: 2 | S6: 7 | T6: 82.1 | U6: =($Y$2*S6)+$Z$2 -> 75.07 | V6: =T6-U6 -> 7.03 | AI6: 2 | AJ6: 7 | AK6: 78.6 | AL6: =($AP$2*AJ6)+$AQ$2 -> 73.3922 | AM6: =AK6-AL6 -> 5.2078 | AZ6: 2 | BA6: 7 | BB6: 82.1 | BC6: =($BG$2*BA6)+$BH$2 -> 79.0892 | BD6: =BB6-BC6 -> 3.0108 | BQ6: 2 | BR6: 7 | BS6: 78.6 | BT6: =($BX$2*BR6)+$BY$2 -> 75.1993 | BU6: =BS6-BT6 -> 3.4007
A7: 3 | B7: =Satisfaction!K11 -> 7 | C7: =Satisfaction!I11 -> 92.9 | D7: =($H$2*B7)+$I$2 -> 72.7798 | E7: =C7-D7 -> 20.1202 | R7: 3 | S7: 7 | T7: 92.9 | U7: =($Y$2*S7)+$Z$2 -> 75.07 | V7: =T7-U7 -> 17.83 | AI7: 3 | AJ7: 7 | AK7: 96.4 | AL7: =($AP$2*AJ7)+$AQ$2 -> 73.3922 | AM7: =AK7-AL7 -> 23.0078 | AZ7: 3 | BA7: 7 | BB7: 92.9 | BC7: =($BG$2*BA7)+$BH$2 -> 79.0892 | BD7: =BB7-BC7 -> 13.8108 | BQ7: 3 | BR7: 7 | BS7: 93.8 | BT7: =($BX$2*BR7)+$BY$2 -> 75.1993 | BU7: =BS7-BT7 -> 18.6007
A8: 4 | B8: =Satisfaction!K12 -> 4 | C8: =Satisfaction!I12 -> 62.5 | D8: =($H$2*B8)+$I$2 -> 75.3586 | E8: =C8-D8 -> -12.8586 | R8: 4 | S8: 4 | T8: 68.8 | U8: =($Y$2*S8)+$Z$2 -> 76.999 | V8: =T8-U8 -> -8.199 | AI8: 4 | AJ8: 4 | AK8: 62.5 | AL8: =($AP$2*AJ8)+$AQ$2 -> 77.5484 | AM8: =AK8-AL8 -> -15.0484 | AZ8: 4 | BA8: 4 | BB8: 68.8 | BC8: =($BG$2*BA8)+$BH$2 -> 81.7814 | BD8: =BB8-BC8 -> -12.9814 | BQ8: 4 | BR8: 4 | BS8: 65.6 | BT8: =($BX$2*BR8)+$BY$2 -> 78.0526 | BU8: =BS8-BT8 -> -12.4526
A9: 5 | B9: =Satisfaction!K13 -> 7 | C9: =Satisfaction!I13 -> 78.6 | D9: =($H$2*B9)+$I$2 -> 72.7798 | E9: =C9-D9 -> 5.8202 | R9: 5 | S9: 7 | T9: 85.7 | U9: =($Y$2*S9)+$Z$2 -> 75.07 | V9: =T9-U9 -> 10.63 | AI9: 5 | AJ9: 7 | AK9: 78.6 | AL9: =($AP$2*AJ9)+$AQ$2 -> 73.3922 | AM9: =AK9-AL9 -> 5.2078 | AZ9: 5 | BA9: 7 | BB9: 85.7 | BC9: =($BG$2*BA9)+$BH$2 -> 79.0892 | BD9: =BB9-BC9 -> 6.6108 | BQ9: 5 | BR9: 7 | BS9: 82.1 | BT9: =($BX$2*BR9)+$BY$2 -> 75.1993 | BU9: =BS9-BT9 -> 6.9007
A10: 6 | B10: =Satisfaction!K14 -> 4 | C10: =Satisfaction!I14 -> 50 | D10: =($H$2*B10)+$I$2 -> 75.3586 | E10: =C10-D10 -> -25.3586 | R10: 6 | S10: 4 | T10: 56.3 | U10: =($Y$2*S10)+$Z$2 -> 76.999 | V10: =T10-U10 -> -20.699 | AI10: 6 | AJ10: 4 | AK10: 50 | AL10: =($AP$2*AJ10)+$AQ$2 -> 77.5484 | AM10: =AK10-AL10 -> -27.5484 | AZ10: 6 | BA10: 4 | BB10: 50 | BC10: =($BG$2*BA10)+$BH$2 -> 81.7814 | BD10: =BB10-BC10 -> -31.7814 | BQ10: 6 | BR10: 4 | BS10: 51.6 | BT10: =($BX$2*BR10)+$BY$2 -> 78.0526 | BU10: =BS10-BT10 -> -26.4526
A11: 7 | B11: =Satisfaction!K15 -> 4 | C11: =Satisfaction!I15 -> 81.3 | D11: =($H$2*B11)+$I$2 -> 75.3586 | E11: =C11-D11 -> 5.9414 | R11: 7 | S11: 4 | T11: 87.5 | U11: =($Y$2*S11)+$Z$2 -> 76.999 | V11: =T11-U11 -> 10.501 | AI11: 7 | AJ11: 4 | AK11: 87.5 | AL11: =($AP$2*AJ11)+$AQ$2 -> 77.5484 | AM11: =AK11-AL11 -> 9.9516 | AZ11: 7 | BA11: 4 | BB11: 93.8 | BC11: =($BG$2*BA11)+$BH$2 -> 81.7814 | BD11: =BB11-BC11 -> 12.0186 | BQ11: 7 | BR11: 4 | BS11: 87.5 | BT11: =($BX$2*BR11)+$BY$2 -> 78.0526 | BU11: =BS11-BT11 -> 9.4474
A12: 8 | B12: =Satisfaction!K16 -> 5 | C12: =Satisfaction!I16 -> 85 | D12: =($H$2*B12)+$I$2 -> 74.499 | E12: =C12-D12 -> 10.501 | R12: 8 | S12: 5 | T12: 95 | U12: =($Y$2*S12)+$Z$2 -> 76.356 | V12: =T12-U12 -> 18.644 | AI12: 8 | AJ12: 5 | AK12: 80 | AL12: =($AP$2*AJ12)+$AQ$2 -> 76.163 | AM12: =AK12-AL12 -> 3.837 | AZ12: 8 | BA12: 5 | BB12: 90 | BC12: =($BG$2*BA12)+$BH$2 -> 80.884 | BD12: =BB12-BC12 -> 9.116 | BQ12: 8 | BR12: 5 | BS12: 87.5 | BT12: =($BX$2*BR12)+$BY$2 -> 77.1015 | BU12: =BS12-BT12 -> 10.3985
A13: 9 | B13: =Satisfaction!K17 -> 8 | C13: =Satisfaction!I17 -> 75 | D13: =($H$2*B13)+$I$2 -> 71.9202 | E13: =C13-D13 -> 3.0798 | R13: 9 | S13: 8 | T13: 75 | U13: =($Y$2*S13)+$Z$2 -> 74.427 | V13: =T13-U13 -> 0.573 | AI13: 9 | AJ13: 8 | AK13: 71.9 | AL13: =($AP$2*AJ13)+$AQ$2 -> 72.0068 | AM13: =AK13-AL13 -> -0.1068 | AZ13: 9 | BA13: 8 | BB13: 78.1 | BC13: =($BG$2*BA13)+$BH$2 -> 78.1918 | BD13: =BB13-BC13 -> -0.0918 | BQ13: 9 | BR13: 8 | BS13: 75 | BT13: =($BX$2*BR13)+$BY$2 -> 74.2482 | BU13: =BS13-BT13 -> 0.7518
A14: 10 | B14: =Satisfaction!K18 -> 8 | C14: =Satisfaction!I18 -> 87.5 | D14: =($H$2*B14)+$I$2 -> 71.9202 | E14: =C14-D14 -> 15.5798 | R14: 10 | S14: 8 | T14: 90.6 | U14: =($Y$2*S14)+$Z$2 -> 74.427 | V14: =T14-U14 -> 16.173 | AI14: 10 | AJ14: 8 | AK14: 93.8 | AL14: =($AP$2*AJ14)+$AQ$2 -> 72.0068 | AM14: =AK14-AL14 -> 21.7932 | AZ14: 10 | BA14: 8 | BB14: 93.8 | BC14: =($BG$2*BA14)+$BH$2 -> 78.1918 | BD14: =BB14-BC14 -> 15.6082 | BQ14: 10 | BR14: 8 | BS14: 91.4 | BT14: =($BX$2*BR14)+$BY$2 -> 74.2482 | BU14: =BS14-BT14 -> 17.1518
A15: 11 | B15: =Satisfaction!K19 -> 4 | C15: =Satisfaction!I19 -> 81.3 | D15: =($H$2*B15)+$I$2 -> 75.3586 | E15: =C15-D15 -> 5.9414 | R15: 11 | S15: 4 | T15: 87.5 | U15: =($Y$2*S15)+$Z$2 -> 76.999 | V15: =T15-U15 -> 10.501 | AI15: 11 | AJ15: 4 | AK15: 93.8 | AL15: =($AP$2*AJ15)+$AQ$2 -> 77.5484 | AM15: =AK15-AL15 -> 16.2516 | AZ15: 11 | BA15: 4 | BB15: 93.8 | BC15: =($BG$2*BA15)+$BH$2 -> 81.7814 | BD15: =BB15-BC15 -> 12.0186 | BQ15: 11 | BR15: 4 | BS15: 89.1 | BT15: =($BX$2*BR15)+$BY$2 -> 78.0526 | BU15: =BS15-BT15 -> 11.0474
A16: 12 | B16: =Satisfaction!K20 -> 11 | C16: =Satisfaction!I20 -> 79.6 | D16: =($H$2*B16)+$I$2 -> 69.3414 | E16: =C16-D16 -> 10.2586 | R16: 12 | S16: 11 | T16: 81.8 | U16: =($Y$2*S16)+$Z$2 -> 72.498 | V16: =T16-U16 -> 9.302 | AI16: 12 | AJ16: 11 | AK16: 75 | AL16: =($AP$2*AJ16)+$AQ$2 -> 67.8506 | AM16: =AK16-AL16 -> 7.1494 | AZ16: 12 | BA16: 11 | BB16: 88.6 | BC16: =($BG$2*BA16)+$BH$2 -> 75.4996 | BD16: =BB16-BC16 -> 13.1004 | BQ16: 12 | BR16: 11 | BS16: 81.3 | BT16: =($BX$2*BR16)+$BY$2 -> 71.3949 | BU16: =BS16-BT16 -> 9.9051
... A23: 19 | B23: =Satisfaction!K27 -> 6 | C23: =Satisfaction!I27 -> 70.8 | D23: =($H$2*B23)+$I$2 -> 73.6394 | E23: =C23-D23 -> -2.8394 | R23: 19 | S23: 6 | T23: 75 | U23: =($Y$2*S23)+$Z$2 -> 75.713 | V23: =T23-U23 -> -0.713 | AI23: 19 | AJ23: 6 | AK23: 66.7 | AL23: =($AP$2*AJ23)+$AQ$2 -> 74.7776 | AM23: =AK23-AL23 -> -8.0776 | AZ23: 19 | BA23: 6 | BB23: 83.3 | BC23: =($BG$2*BA23)+$BH$2 -> 79.9866 | BD23: =BB23-BC23 -> 3.3134 | BQ23: 19 | BR23: 6 | BS23: 74 | BT23: =($BX$2*BR23)+$BY$2 -> 76.1504 | BU23: =BS23-BT23 -> -2.1504
A24: 20 | B24: =Satisfaction!K28 -> 8 | C24: =Satisfaction!I28 -> 53.1 | D24: =($H$2*B24)+$I$2 -> 71.9202 | E24: =C24-D24 -> -18.8202 | H24: Residuals: | R24: 20 | S24: 8 | T24: 50 | U24: =($Y$2*S24)+$Z$2 -> 74.427 | V24: =T24-U24 -> -24.427 | Y24: Residuals: | AI24: 20 | AJ24: 8 | AK24: 50 | AL24: =($AP$2*AJ24)+$AQ$2 -> 72.0068 | AM24: =AK24-AL24 -> -22.0068 | AP24: Residuals: | AZ24: 20 | BA24: 8 | BB24: 59.4 | BC24: =($BG$2*BA24)+$BH$2 -> 78.1918 | BD24: =BB24-BC24 -> -18.7918 | BG24: Residuals: | BQ24: 20 | BR24: 8 | BS24: 53.1 | BT24: =($BX$2*BR24)+$BY$2 -> 74.2482 | BU24: =BS24-BT24 -> -21.1482 | BX24: Residuals:
A25: 21 | B25: =Satisfaction!K29 -> 9 | C25: =Satisfaction!I29 -> 77.8 | D25: =($H$2*B25)+$I$2 -> 71.0606 | E25: =C25-D25 -> 6.7394 | R25: 21 | S25: 9 | T25: 77.8 | U25: =($Y$2*S25)+$Z$2 -> 73.784 | V25: =T25-U25 -> 4.016 | AI25: 21 | AJ25: 9 | AK25: 80.6 | AL25: =($AP$2*AJ25)+$AQ$2 -> 70.6214 | AM25: =AK25-AL25 -> 9.9786 | AZ25: 21 | BA25: 9 | BB25: 88.9 | BC25: =($BG$2*BA25)+$BH$2 -> 77.2944 | BD25: =BB25-BC25 -> 11.6056 | BQ25: 21 | BR25: 9 | BS25: 81.3 | BT25: =($BX$2*BR25)+$BY$2 -> 73.2971 | BU25: =BS25-BT25 -> 8.0029
A26: 22 | B26: =Satisfaction!K30 -> 4 | C26: =Satisfaction!I30 -> 81.3 | D26: =($H$2*B26)+$I$2 -> 75.3586 | E26: =C26-D26 -> 5.9414 | R26: 22 | S26: 4 | T26: 75 | U26: =($Y$2*S26)+$Z$2 -> 76.999 | V26: =T26-U26 -> -1.999 | AI26: 22 | AJ26: 3 | AK26: 75 | AL26: =($AP$2*AJ26)+$AQ$2 -> 78.9338 | AM26: =AK26-AL26 -> -3.9338 | AZ26: 22 | BA26: 4 | BB26: 81.3 | BC26: =($BG$2*BA26)+$BH$2 -> 81.7814 | BD26: =BB26-BC26 -> -0.4814 | BQ26: 22 | BR26: 4 | BS26: 79.7 | BT26: =($BX$2*BR26)+$BY$2 -> 78.0526 | BU26: =BS26-BT26 -> 1.6474
A27: 23 | B27: =Satisfaction!K31 -> 5 | C27: =Satisfaction!I31 -> 85 | D27: =($H$2*B27)+$I$2 -> 74.499 | E27: =C27-D27 -> 10.501 | R27: 23 | S27: 5 | T27: 85 | U27: =($Y$2*S27)+$Z$2 -> 76.356 | V27: =T27-U27 -> 8.644 | AI27: 23 | AJ27: 5 | AK27: 80 | AL27: =($AP$2*AJ27)+$AQ$2 -> 76.163 | AM27: =AK27-AL27 -> 3.837 | AZ27: 23 | BA27: 5 | BB27: 85 | BC27: =($BG$2*BA27)+$BH$2 -> 80.884 | BD27: =BB27-BC27 -> 4.116 | BQ27: 23 | BR27: 5 | BS27: 83.8 | BT27: =($BX$2*BR27)+$BY$2 -> 77.1015 | BU27: =BS27-BT27 -> 6.6985
A28: 24 | B28: =Satisfaction!K32 -> 4 | C28: =Satisfaction!I32 -> 75 | D28: =($H$2*B28)+$I$2 -> 75.3586 | E28: =C28-D28 -> -0.3586 | R28: 24 | S28: 4 | T28: 75 | U28: =($Y$2*S28)+$Z$2 -> 76.999 | V28: =T28-U28 -> -1.999 | AI28: 24 | AJ28: 4 | AK28: 81.3 | AL28: =($AP$2*AJ28)+$AQ$2 -> 77.5484 | AM28: =AK28-AL28 -> 3.7516 | AZ28: 24 | BA28: 4 | BB28: 93.8 | BC28: =($BG$2*BA28)+$BH$2 -> 81.7814 | BD28: =BB28-BC28 -> 12.0186 | BQ28: 24 | BR28: 4 | BS28: 81.3 | BT28: =($BX$2*BR28)+$BY$2 -> 78.0526 | BU28: =BS28-BT28 -> 3.2474
A29: 25 | B29: =Satisfaction!K33 -> 1 | C29: =Satisfaction!I33 -> 75 | D29: =($H$2*B29)+$I$2 -> 77.9374 | E29: =C29-D29 -> -2.9374 | R29: 25 | S29: 1 | T29: 75 | U29: =($Y$2*S29)+$Z$2 -> 78.928 | V29: =T29-U29 -> -3.928 | AI29: 25 | AJ29: 1 | AK29: 75 | AL29: =($AP$2*AJ29)+$AQ$2 -> 81.7046 | AM29: =AK29-AL29 -> -6.7046 | AZ29: 25 | BA29: 1 | BB29: 75 | BC29: =($BG$2*BA29)+$BH$2 -> 84.4736 | BD29: =BB29-BC29 -> -9.4736 | BQ29: 25 | BR29: 1 | BS29: 75 | BT29: =($BX$2*BR29)+$BY$2 -> 80.9059 | BU29: =BS29-BT29 -> -5.9059
A30: 26 | B30: =Satisfaction!K34 -> 3 | C30: =Satisfaction!I34 -> 58.3 | D30: =($H$2*B30)+$I$2 -> 76.2182 | E30: =C30-D30 -> -17.9182 | R30: 26 | S30: 3 | T30: 58.3 | U30: =($Y$2*S30)+$Z$2 -> 77.642 | V30: =T30-U30 -> -19.342 | AI30: 26 | AJ30: 3 | AK30: 58.3 | AL30: =($AP$2*AJ30)+$AQ$2 -> 78.9338 | AM30: =AK30-AL30 -> -20.6338 | AZ30: 26 | BA30: 3 | BB30: 58.3 | BC30: =($BG$2*BA30)+$BH$2 -> 82.6788 | BD30: =BB30-BC30 -> -24.3788 | BQ30: 26 | BR30: 3 | BS30: 58.3 | BT30: =($BX$2*BR30)+$BY$2 -> 79.0037 | BU30: =BS30-BT30 -> -20.7037
A31: 27 | B31: =Satisfaction!K35 -> 6 | C31: =Satisfaction!I35 -> 100 | D31: =($H$2*B31)+$I$2 -> 73.6394 | E31: =C31-D31 -> 26.3606 | R31: 27 | S31: 6 | T31: 91.7 | U31: =($Y$2*S31)+$Z$2 -> 75.713 | V31: =T31-U31 -> 15.987 | AI31: 27 | AJ31: 6 | AK31: 100 | AL31: =($AP$2*AJ31)+$AQ$2 -> 74.7776 | AM31: =AK31-AL31 -> 25.2224 | AZ31: 27 | BA31: 6 | BB31: 100 | BC31: =($BG$2*BA31)+$BH$2 -> 79.9866 | BD31: =BB31-BC31 -> 20.0134 | BQ31: 27 | BR31: 6 | BS31: 97.9 | BT31: =($BX$2*BR31)+$BY$2 -> 76.1504 | BU31: =BS31-BT31 -> 21.7496
A32: 28 | B32: =Satisfaction!K36 -> 6 | C32: =Satisfaction!I36 -> 79.2 | D32: =($H$2*B32)+$I$2 -> 73.6394 | E32: =C32-D32 -> 5.5606 | R32: 28 | S32: 6 | T32: 83.3 | U32: =($Y$2*S32)+$Z$2 -> 75.713 | V32: =T32-U32 -> 7.587 | AI32: 28 | AJ32: 6 | AK32: 79.2 | AL32: =($AP$2*AJ32)+$AQ$2 -> 74.7776 | AM32: =AK32-AL32 -> 4.4224 | AZ32: 28 | BA32: 6 | BB32: 87.5 | BC32: =($BG$2*BA32)+$BH$2 -> 79.9866 | BD32: =BB32-BC32 -> 7.5134 | BQ32: 28 | BR32: 6 | BS32: 82.3 | BT32: =($BX$2*BR32)+$BY$2 -> 76.1504 | BU32: =BS32-BT32 -> 6.1496
A33: 29 | B33: =Satisfaction!K37 -> 9 | C33: =Satisfaction!I37 -> 11.1 | D33: =($H$2*B33)+$I$2 -> 71.0606 | E33: =C33-D33 -> -59.9606 | R33: 29 | S33: 9 | T33: 11.1 | U33: =($Y$2*S33)+$Z$2 -> 73.784 | V33: =T33-U33 -> -62.684 | AI33: 29 | AJ33: 9 | AK33: 11.1 | AL33: =($AP$2*AJ33)+$AQ$2 -> 70.6214 | AM33: =AK33-AL33 -> -59.5214 | AZ33: 29 | BA33: 9 | BB33: 16.7 | BC33: =($BG$2*BA33)+$BH$2 -> 77.2944 | BD33: =BB33-BC33 -> -60.5944 | BQ33: 29 | BR33: 9 | BS33: 12.5 | BT33: =($BX$2*BR33)+$BY$2 -> 73.2971 | BU33: =BS33-BT33 -> -60.7971
A34: 30 | B34: =Satisfaction!K38 -> 6 | C34: =Satisfaction!I38 -> 83.3 | D34: =($H$2*B34)+$I$2 -> 73.6394 | E34: =C34-D34 -> 9.6606 | R34: 30 | S34: 7 | T34: 71.4 | U34: =($Y$2*S34)+$Z$2 -> 75.07 | V34: =T34-U34 -> -3.67 | AI34: 30 | AJ34: 7 | AK34: 75 | AL34: =($AP$2*AJ34)+$AQ$2 -> 73.3922 | AM34: =AK34-AL34 -> 1.6078 | AZ34: 30 | BA34: 7 | BB34: 82.1 | BC34: =($BG$2*BA34)+$BH$2 -> 79.0892 | BD34: =BB34-BC34 -> 3.0108 | BQ34: 30 | BR34: 7 | BS34: 78.6 | BT34: =($BX$2*BR34)+$BY$2 -> 75.1993 | BU34: =BS34-BT34 -> 3.4007
A35: 31 | B35: =Satisfaction!K39 -> 5 | C35: =Satisfaction!I39 -> 80 | D35: =($H$2*B35)+$I$2 -> 74.499 | E35: =C35-D35 -> 5.501 | R35: 31 | S35: 5 | T35: 85 | U35: =($Y$2*S35)+$Z$2 -> 76.356 | V35: =T35-U35 -> 8.644 | AI35: 31 | AJ35: 5 | AK35: 85 | AL35: =($AP$2*AJ35)+$AQ$2 -> 76.163 | AM35: =AK35-AL35 -> 8.837 | AZ35: 31 | BA35: 5 | BB35: 90 | BC35: =($BG$2*BA35)+$BH$2 -> 80.884 | BD35: =BB35-BC35 -> 9.116 | BQ35: 31 | BR35: 5 | BS35: 85 | BT35: =($BX$2*BR35)+$BY$2 -> 77.1015 | BU35: =BS35-BT35 -> 7.8985
A36: 32 | B36: =Satisfaction!K40 -> 13 | C36: =Satisfaction!I40 -> 67.3 | D36: =($H$2*B36)+$I$2 -> 67.6222 | E36: =C36-D36 -> -0.3222 | R36: 32 | S36: 13 | T36: 71.2 | U36: =($Y$2*S36)+$Z$2 -> 71.212 | V36: =T36-U36 -> -0.012 | AI36: 32 | AJ36: 13 | AK36: 67.3 | AL36: =($AP$2*AJ36)+$AQ$2 -> 65.0798 | AM36: =AK36-AL36 -> 2.2202 | AZ36: 32 | BA36: 13 | BB36: 71.2 | BC36: =($BG$2*BA36)+$BH$2 -> 73.7048 | BD36: =BB36-BC36 -> -2.5048 | BQ36: 32 | BR36: 13 | BS36: 69.2 | BT36: =($BX$2*BR36)+$BY$2 -> 69.4927 | BU36: =BS36-BT36 -> -0.2927
A37: 33 | B37: =Satisfaction!K41 -> 0 | C37: =Satisfaction!I41 -> 0 | D37: =($H$2*B37)+$I$2 -> 78.797 | E37: =C37-D37 -> -78.797 | R37: 33 | S37: =Satisfaction!AD41 -> 0 | T37: =Satisfaction!AB41 -> 0 | U37: =($Y$2*S37)+$Z$2 -> 79.571 | V37: =T37-U37 -> -79.571 | AI37: 33 | AJ37: 0 | AK37: 0 | AL37: =($AP$2*AJ37)+$AQ$2 -> 83.09 | AM37: =AK37-AL37 -> -83.09 | AZ37: 33 | BA37: =Satisfaction!BL41 -> 0 | BB37: =Satisfaction!BJ41 -> 0 | BC37: =($BG$2*BA37)+$BH$2 -> 85.371 | BD37: =BB37-BC37 -> -85.371 | BQ37: 33 | BR37: =Satisfaction!CC41 -> 0 | BS37: 0 | BT37: =($BX$2*BR37)+$BY$2 -> 81.857 | BU37: =BS37-BT37 -> -81.857
A38: 34 | B38: =Satisfaction!K42 -> 0 | C38: =Satisfaction!I42 -> 0 | D38: =($H$2*B38)+$I$2 -> 78.797 | E38: =C38-D38 -> -78.797 | R38: 34 | S38: =Satisfaction!AD42 -> 0 | T38: =Satisfaction!AB42 -> 0 | U38: =($Y$2*S38)+$Z$2 -> 79.571 | V38: =T38-U38 -> -79.571 | AI38: 34 | AJ38: =Satisfaction!AU42 -> 0 | AK38: =Satisfaction!AS42 -> 0 | AL38: =($AP$2*AJ38)+$AQ$2 -> 83.09 | AM38: =AK38-AL38 -> -83.09 | AZ38: 34 | BA38: =Satisfaction!BL42 -> 0 | BB38: =Satisfaction!BJ42 -> 0 | BC38: =($BG$2*BA38)+$BH$2 -> 85.371 | BD38: =BB38-BC38 -> -85.371 | BQ38: 34 | BR38: =Satisfaction!CC42 -> 0 | BS38: =Satisfaction!CA42 -> 0 | BT38: =($BX$2*BR38)+$BY$2 -> 81.857 | BU38: =BS38-BT38 -> -81.857
B42: =NA() -> #N/A | C42: =NA() -> #N/A | S42: =NA() -> #N/A | T42: =NA() -> #N/A | AJ42: =NA() -> #N/A | AK42: =NA() -> #N/A | BA42: =NA() -> #N/A | BB42: =NA() -> #N/A | BR42: =NA() -> #N/A | BS42: =NA() -> #N/A

Sheet Satisfaction
A1: Patient Satisfaction Survey
A2: Baptist ER, Oct YTD
C4: Jan | E4: Feb | G4: Mar | I4: Apr | Q4: May | Y4: Jun | AG4: Jul | AO4: Aug | AW4: Sep | BE4: Oct | BM4: Nov | BU4: Dec
M6: Category | O6: Overall | U6: Category | W6: Overall | AC6: Category | AE6: Overall | AK6: Category | AM6: Overall | AS6: Category | AU6: Overall | BA6: Category | BC6: Overall | BI6: Category | BK6: Overall | BQ6: Category | BS6: Overall | BY6: Category | CA6: Overall
I7: Score | K7: n | M7: Weight | O7: Weight | Q7: Score | S7: n | U7: Weight | W7: Weight | Y7: Score | AA7: n | AC7: Weight | AE7: Weight | AG7: Score | AI7: n | AK7: Weight | AM7: Weight | AO7: Score | AQ7: n | AS7: Weight | AU7: Weight | AW7: Score | AY7: n | BA7: Weight | BC7: Weight | BE7: Score | BG7: n | BI7: Weight | BK7: Weight | BM7: Score | BO7: n | BQ7: Weight | BS7: Weight | BU7: Score | BW7: n | BY7: Weight | CA7: Weight
A8: Doctor informative re treatment
B9: ALAN ITZKOWITZ | C9: 0 | E9: 0 | G9: 0 | I9: {=SUM(IF(Period=I$4,IF(Category=$A$8,IF(Provider=$B9,Score))))} -> 85.7 | K9: {=SUM(IF(Period=I$4,IF(Category=$A$8,IF(Provider=$B9,Responses))))} -> 7 | M9: =I9*(K9/SUM(K$9:K$42)) -> 2.9995 | O9: =I9*(K9/(SUM(K$9:K$42)+SUM(K$48:K$81)+SUM(K$87:K$120)+SUM(K$126:K$159)+SUM(K$165:K$198)+SUM(K$204:K$237))) -> 0.4961952 | Q9: {=SUM(IF(Period=Q$4,IF(Category=$A$8,IF(Provider=$B9,Score))))} -> 81.3 | S9: {=SUM(IF(Period=Q$4,IF(Category=$A$8,IF(Provider=$B9,Responses))))} -> 4 | U9: =Q9*(S9/SUM(S$9:S$42)) -> 1.7297872 | W9: =Q9*(S9/(SUM(S$9:S$42)+SUM(S$48:S$81)+SUM(S$87:S$120)+SUM(S$126:S$159)+SUM(S$165:S$198)+SUM(S$204:S$237))) -> 0.28983957 | Y9: {=SUM(IF(Period=Y$4,IF(Category=$A$8,IF(Provider=$B9,Score))))} -> 87.5 | AA9: {=SUM(IF(Period=Y$4,IF(Category=$A$8,IF(Provider=$B9,Responses))))} -> 14 | AC9: =Y9*(AA9/SUM(AA$9:AA$42)) -> 4.0296053 | AE9: =Y9*(AA9/(SUM(AA$9:AA$42)+SUM(AA$48:AA$81)+SUM(AA$87:AA$120)+SUM(AA$126:AA$159)+SUM(AA$165:AA$198)+SUM(AA$204:AA$237))) -> 0.67567568 | AG9: {=SUM(IF(Period=AG$4,IF(Category=$A$8,IF(Provider=$B9,Score))))} -> 100 | AI9: {=SUM(IF(Period=AG$4,IF(Category=$A$8,IF(Provider=$B9,Responses))))} -> 3 | AK9: =AG9*(AI9/SUM(AI$9:AI$42)) -> 1.171875 | AM9: =AG9*(AI9/(SUM(AI$9:AI$42)+SUM(AI$48:AI$81)+SUM(AI$87:AI$120)+SUM(AI$126:AI$159)+SUM(AI$165:AI$198)+SUM(AI$204:AI$237))) -> 0.19430052 | AO9: {=SUM(IF(Period=AO$4,IF(Category=$A$8,IF(Provider=$B9,Score))))} -> 87.5 | AQ9: {=SUM(IF(Period=AO$4,IF(Category=$A$8,IF(Provider=$B9,Responses))))} -> 2 | AS9: =AO9*(AQ9/SUM(AQ$9:AQ$42)) -> 1.0174419 | AU9: =AO9*(AQ9/(SUM(AQ$9:AQ$42)+SUM(AQ$48:AQ$81)+SUM(AQ$87:AQ$120)+SUM(AQ$126:AQ$159)+SUM(AQ$165:AQ$198)+SUM(AQ$204:AQ$237))) -> 0.1705653 | AW9: {=SUM(IF(Period=AW$4,IF(Category=$A$8,IF(Provider=$B9,Score))))} -> 90 | AY9: {=SUM(IF(Period=AW$4,IF(Category=$A$8,IF(Provider=$B9,Responses))))} -> 5 | BA9: =AW9*(AY9/SUM(AY$9:AY$42)) -> 2.0737327 | BC9: =AW9*(AY9/(SUM(AY$9:AY$42)+SUM(AY$48:AY$81)+SUM(AY$87:AY$120)+SUM(AY$126:AY$159)+SUM(AY$165:AY$198)+SUM(AY$204:AY$237))) -> 0.34562212 | BE9: {=SUM(IF(Period=BE$4,IF(Category=$A$8,IF(Provider=$B9,Score))))} -> 87.5 | BG9: {=SUM(IF(Period=BE$4,IF(Category=$A$8,IF(Provider=$B9,Responses))))} -> 8 | BI9: =BE9*(BG9/SUM(BG$9:BG$42)) -> 2.9787234 | BK9: =BE9*(BG9/(SUM(BG$9:BG$42)+SUM(BG$48:BG$81)+SUM(BG$87:BG$120)+SUM(BG$126:BG$159)+SUM(BG$165:BG$198)+SUM(BG$204:BG$237))) -> 0.49469965 | BM9: {=SUM(IF(Period=BM$4,IF(Category=$A$8,IF(Provider=$B9,Score))))} -> 100 | BO9: {=SUM(IF(Period=BM$4,IF(Category=$A$8,IF(Provider=$B9,Responses))))} -> 6 | BQ9: =BM9*(BO9/SUM(BO$9:BO$42)) -> 2.5862069 | BS9: =BM9*(BO9/(SUM(BO$9:BO$42)+SUM(BO$48:BO$81)+SUM(BO$87:BO$120)+SUM(BO$126:BO$159)+SUM(BO$165:BO$198)+SUM(BO$204:BO$237))) -> 0.43290043 | BU9: {=SUM(IF(Period=BU$4,IF(Category=$A$8,IF(Provider=$B9,Score))))} -> 90 | BW9: {=SUM(IF(Period=BU$4,IF(Category=$A$8,IF(Provider=$B9,Responses))))} -> 5 | BY9: =BU9*(BW9/SUM(BW$9:BW$42)) -> 1.8595041 | CA9: =BU9*(BW9/(SUM(BW$9:BW$42)+SUM(BW$48:BW$81)+SUM(BW$87:BW$120)+SUM(BW$126:BW$159)+SUM(BW$165:BW$198)+SUM(BW$204:BW$237))) -> 0.31098825
B10: ALEX PALMA | C10: 0 | E10: 0 | G10: 0 | I10: {=SUM(IF(Period=I$4,IF(Category=$A$8,IF(Provider=$B10,Score))))} -> 71.4 | K10: {=SUM(IF(Period=I$4,IF(Category=$A$8,IF(Provider=$B10,Responses))))} -> 7 | M10: =I10*(K10/SUM(K$9:K$42)) -> 2.499 | O10: =I10*(K10/(SUM(K$9:K$42)+SUM(K$48:K$81)+SUM(K$87:K$120)+SUM(K$126:K$159)+SUM(K$165:K$198)+SUM(K$204:K$237))) -> 0.4133995 | Q10: {=SUM(IF(Period=Q$4,IF(Category=$A$8,IF(Provider=$B10,Score))))} -> 95 | S10: {=SUM(IF(Period=Q$4,IF(Category=$A$8,IF(Provider=$B10,Responses))))} -> 10 | U10: =Q10*(S10/SUM(S$9:S$42)) -> 5.0531915 | W10: =Q10*(S10/(SUM(S$9:S$42)+SUM(S$48:S$81)+SUM(S$87:S$120)+SUM(S$126:S$159)+SUM(S$165:S$198)+SUM(S$204:S$237))) -> 0.84670232 | Y10: {=SUM(IF(Period=Y$4,IF(Category=$A$8,IF(Provider=$B10,Score))))} -> 83.3 | AA10: {=SUM(IF(Period=Y$4,IF(Category=$A$8,IF(Provider=$B10,Responses))))} -> 9 | AC10: =Y10*(AA10/SUM(AA$9:AA$42)) -> 2.4661184 | AE10: =Y10*(AA10/(SUM(AA$9:AA$42)+SUM(AA$48:AA$81)+SUM(AA$87:AA$120)+SUM(AA$126:AA$159)+SUM(AA$165:AA$198)+SUM(AA$204:AA$237))) -> 0.41351351 | AG10: {=SUM(IF(Period=AG$4,IF(Category=$A$8,IF(Provider=$B10,Score))))} -> 100 | AI10: {=SUM(IF(Period=AG$4,IF(Category=$A$8,IF(Provider=$B10,Responses))))} -> 6 | AK10: =AG10*(AI10/SUM(AI$9:AI$42)) -> 2.34375 | AM10: =AG10*(AI10/(SUM(AI$9:AI$42)+SUM(AI$48:AI$81)+SUM(AI$87:AI$120)+SUM(AI$126:AI$159)+SUM(AI$165:AI$198)+SUM(AI$204:AI$237))) -> 0.38860104 | AO10: {=SUM(IF(Period=AO$4,IF(Category=$A$8,IF(Provider=$B10,Score))))} -> 37.5 | AQ10: {=SUM(IF(Period=AO$4,IF(Category=$A$8,IF(Provider=$B10,Responses))))} -> 4 | AS10: =AO10*(AQ10/SUM(AQ$9:AQ$42)) -> 0.87209302 | AU10: =AO10*(AQ10/(SUM(AQ$9:AQ$42)+SUM(AQ$48:AQ$81)+SUM(AQ$87:AQ$120)+SUM(AQ$126:AQ$159)+SUM(AQ$165:AQ$198)+SUM(AQ$204:AQ$237))) -> 0.14619883 | AW10: {=SUM(IF(Period=AW$4,IF(Category=$A$8,IF(Provider=$B10,Score))))} -> 85.7 | AY10: {=SUM(IF(Period=AW$4,IF(Category=$A$8,IF(Provider=$B10,Responses))))} -> 7 | BA10: =AW10*(AY10/SUM(AY$9:AY$42)) -> 2.7645161 | BC10: =AW10*(AY10/(SUM(AY$9:AY$42)+SUM(AY$48:AY$81)+SUM(AY$87:AY$120)+SUM(AY$126:AY$159)+SUM(AY$165:AY$198)+SUM(AY$204:AY$237))) -> 0.46075269 | BE10: {=SUM(IF(Period=BE$4,IF(Category=$A$8,IF(Provider=$B10,Score))))} -> 100 | BG10: {=SUM(IF(Period=BE$4,IF(Category=$A$8,IF(Provider=$B10,Responses))))} -> 8 | BI10: =BE10*(BG10/SUM(BG$9:BG$42)) -> 3.4042553 | BK10: =BE10*(BG10/(SUM(BG$9:BG$42)+SUM(BG$48:BG$81)+SUM(BG$87:BG$120)+SUM(BG$126:BG$159)+SUM(BG$165:BG$198)+SUM(BG$204:BG$237))) -> 0.56537102 | BM10: {=SUM(IF(Period=BM$4,IF(Category=$A$8,IF(Provider=$B10,Score))))} -> 87.5 | BO10: {=SUM(IF(Period=BM$4,IF(Category=$A$8,IF(Provider=$B10,Responses))))} -> 6 | BQ10: =BM10*(BO10/SUM(BO$9:BO$42)) -> 2.262931 | BS10: =BM10*(BO10/(SUM(BO$9:BO$42)+SUM(BO$48:BO$81)+SUM(BO$87:BO$120)+SUM(BO$126:BO$159)+SUM(BO$165:BO$198)+SUM(BO$204:BO$237))) -> 0.37878788 | BU10: {=SUM(IF(Period=BU$4,IF(Category=$A$8,IF(Provider=$B10,Score))))} -> 77.3 | BW10: {=SUM(IF(Period=BU$4,IF(Category=$A$8,IF(Provider=$B10,Responses))))} -> 11 | BY10: =BU10*(BW10/SUM(BW$9:BW$42)) -> 3.5136364 | CA10: =BU10*(BW10/(SUM(BW$9:BW$42)+SUM(BW$48:BW$81)+SUM(BW$87:BW$120)+SUM(BW$126:BW$159)+SUM(BW$165:BW$198)+SUM(BW$204:BW$237))) -> 0.58762958
B11: ALEXANDER GARCIA | C11: 0 | E11: 0 | G11: 0 | I11: {=SUM(IF(Period=I$4,IF(Category=$A$8,IF(Provider=$B11,Score))))} -> 92.9 | K11: {=SUM(IF(Period=I$4,IF(Category=$A$8,IF(Provider=$B11,Responses))))} -> 7 | M11: =I11*(K11/SUM(K$9:K$42)) -> 3.2515 | O11: =I11*(K11/(SUM(K$9:K$42)+SUM(K$48:K$81)+SUM(K$87:K$120)+SUM(K$126:K$159)+SUM(K$165:K$198)+SUM(K$204:K$237))) -> 0.53788255 | Q11: {=SUM(IF(Period=Q$4,IF(Category=$A$8,IF(Provider=$B11,Score))))} -> 91.7 | S11: {=SUM(IF(Period=Q$4,IF(Category=$A$8,IF(Provider=$B11,Responses))))} -> 6 | U11: =Q11*(S11/SUM(S$9:S$42)) -> 2.9265957 | W11: =Q11*(S11/(SUM(S$9:S$42)+SUM(S$48:S$81)+SUM(S$87:S$120)+SUM(S$126:S$159)+SUM(S$165:S$198)+SUM(S$204:S$237))) -> 0.49037433 | Y11: {=SUM(IF(Period=Y$4,IF(Category=$A$8,IF(Provider=$B11,Score))))} -> 86.1 | AA11: {=SUM(IF(Period=Y$4,IF(Category=$A$8,IF(Provider=$B11,Responses))))} -> 9 | AC11: =Y11*(AA11/SUM(AA$9:AA$42)) -> 2.5490132 | AE11: =Y11*(AA11/(SUM(AA$9:AA$42)+SUM(AA$48:AA$81)+SUM(AA$87:AA$120)+SUM(AA$126:AA$159)+SUM(AA$165:AA$198)+SUM(AA$204:AA$237))) -> 0.42741313 | AG11: {=SUM(IF(Period=AG$4,IF(Category=$A$8,IF(Provider=$B11,Score))))} -> 96.4 | AI11: {=SUM(IF(Period=AG$4,IF(Category=$A$8,IF(Provider=$B11,Responses))))} -> 7 | AK11: =AG11*(AI11/SUM(AI$9:AI$42)) -> 2.6359375 | AM11: =AG11*(AI11/(SUM(AI$9:AI$42)+SUM(AI$48:AI$81)+SUM(AI$87:AI$120)+SUM(AI$126:AI$159)+SUM(AI$165:AI$198)+SUM(AI$204:AI$237))) -> 0.43704663 | AO11: {=SUM(IF(Period=AO$4,IF(Category=$A$8,IF(Provider=$B11,Score))))} -> 71.9 | AQ11: {=SUM(IF(Period=AO$4,IF(Category=$A$8,IF(Provider=$B11,Responses))))} -> 8 | AS11: =AO11*(AQ11/SUM(AQ$9:AQ$42)) -> 3.344186 | AU11: =AO11*(AQ11/(SUM(AQ$9:AQ$42)+SUM(AQ$48:AQ$81)+SUM(AQ$87:AQ$120)+SUM(AQ$126:AQ$159)+SUM(AQ$165:AQ$198)+SUM(AQ$204:AQ$237))) -> 0.56062378 | AW11: {=SUM(IF(Period=AW$4,IF(Category=$A$8,IF(Provider=$B11,Score))))} -> 100 | AY11: {=SUM(IF(Period=AW$4,IF(Category=$A$8,IF(Provider=$B11,Responses))))} -> 6 | BA11: =AW11*(AY11/SUM(AY$9:AY$42)) -> 2.764977 | BC11: =AW11*(AY11/(SUM(AY$9:AY$42)+SUM(AY$48:AY$81)+SUM(AY$87:AY$120)+SUM(AY$126:AY$159)+SUM(AY$165:AY$198)+SUM(AY$204:AY$237))) -> 0.46082949 | BE11: {=SUM(IF(Period=BE$4,IF(Category=$A$8,IF(Provider=$B11,Score))))} -> 87.5 | BG11: {=SUM(IF(Period=BE$4,IF(Category=$A$8,IF(Provider=$B11,Responses))))} -> 8 | BI11: =BE11*(BG11/SUM(BG$9:BG$42)) -> 2.9787234 | BK11: =BE11*(BG11/(SUM(BG$9:BG$42)+SUM(BG$48:BG$81)+SUM(BG$87:BG$120)+SUM(BG$126:BG$159)+SUM(BG$165:BG$198)+SUM(BG$204:BG$237))) -> 0.49469965 | BM11: {=SUM(IF(Period=BM$4,IF(Category=$A$8,IF(Provider=$B11,Score))))} -> 56.3 | BO11: {=SUM(IF(Period=BM$4,IF(Category=$A$8,IF(Provider=$B11,Responses))))} -> 8 | BQ11: =BM11*(BO11/SUM(BO$9:BO$42)) -> 1.9413793 | BS11: =BM11*(BO11/(SUM(BO$9:BO$42)+SUM(BO$48:BO$81)+SUM(BO$87:BO$120)+SUM(BO$126:BO$159)+SUM(BO$165:BO$198)+SUM(BO$204:BO$237))) -> 0.32496392 | BU11: {=SUM(IF(Period=BU$4,IF(Category=$A$8,IF(Provider=$B11,Score))))} -> 75 | BW11: {=SUM(IF(Period=BU$4,IF(Category=$A$8,IF(Provider=$B11,Responses))))} -> 6 | BY11: =BU11*(BW11/SUM(BW$9:BW$42)) -> 1.8595041 | CA11: =BU11*(BW11/(SUM(BW$9:BW$42)+SUM(BW$48:BW$81)+SUM(BW$87:BW$120)+SUM(BW$126:BW$159)+SUM(BW$165:BW$198)+SUM(BW$204:BW$237))) -> 0.31098825
B12: ANDREA J BETANCOURT | C12: 0 | E12: 0 | G12: 0 | I12: {=SUM(IF(Period=I$4,IF(Category=$A$8,IF(Provider=$B12,Score))))} -> 62.5 | K12: {=SUM(IF(Period=I$4,IF(Category=$A$8,IF(Provider=$B12,Responses))))} -> 4 | M12: =I12*(K12/SUM(K$9:K$42)) -> 1.25 | O12: =I12*(K12/(SUM(K$9:K$42)+SUM(K$48:K$81)+SUM(K$87:K$120)+SUM(K$126:K$159)+SUM(K$165:K$198)+SUM(K$204:K$237))) -> 0.20678246 | Q12: {=SUM(IF(Period=Q$4,IF(Category=$A$8,IF(Provider=$B12,Score))))} -> 85.7 | S12: {=SUM(IF(Period=Q$4,IF(Category=$A$8,IF(Provider=$B12,Responses))))} -> 7 | U12: =Q12*(S12/SUM(S$9:S$42)) -> 3.1909574 | W12: =Q12*(S12/(SUM(S$9:S$42)+SUM(S$48:S$81)+SUM(S$87:S$120)+SUM(S$126:S$159)+SUM(S$165:S$198)+SUM(S$204:S$237))) -> 0.53467023 | Y12: {=SUM(IF(Period=Y$4,IF(Category=$A$8,IF(Provider=$B12,Score))))} -> 77.3 | AA12: {=SUM(IF(Period=Y$4,IF(Category=$A$8,IF(Provider=$B12,Responses))))} -> 11 | AC12: =Y12*(AA12/SUM(AA$9:AA$42)) -> 2.7970395 | AE12: =Y12*(AA12/(SUM(AA$9:AA$42)+SUM(AA$48:AA$81)+SUM(AA$87:AA$120)+SUM(AA$126:AA$159)+SUM(AA$165:AA$198)+SUM(AA$204:AA$237))) -> 0.46900165 | AG12: {=SUM(IF(Period=AG$4,IF(Category=$A$8,IF(Provider=$B12,Score))))} -> 68.8 | AI12: {=SUM(IF(Period=AG$4,IF(Category=$A$8,IF(Provider=$B12,Responses))))} -> 4 | AK12: =AG12*(AI12/SUM(AI$9:AI$42)) -> 1.075 | AM12: =AG12*(AI12/(SUM(AI$9:AI$42)+SUM(AI$48:AI$81)+SUM(AI$87:AI$120)+SUM(AI$126:AI$159)+SUM(AI$165:AI$198)+SUM(AI$204:AI$237))) -> 0.17823834 | AO12: {=SUM(IF(Period=AO$4,IF(Category=$A$8,IF(Provider=$B12,Score))))} -> 77.8 | AQ12: {=SUM(IF(Period=AO$4,IF(Category=$A$8,IF(Provider=$B12,Responses))))} -> 9 | AS12: =AO12*(AQ12/SUM(AQ$9:AQ$42)) -> 4.0709302 | AU12: =AO12*(AQ12/(SUM(AQ$9:AQ$42)+SUM(AQ$48:AQ$81)+SUM(AQ$87:AQ$120)+SUM(AQ$126:AQ$159)+SUM(AQ$165:AQ$198)+SUM(AQ$204:AQ$237))) -> 0.68245614 | AW12: {=SUM(IF(Period=AW$4,IF(Category=$A$8,IF(Provider=$B12,Score))))} -> 62.5 | AY12: {=SUM(IF(Period=AW$4,IF(Category=$A$8,IF(Provider=$B12,Responses))))} -> 2 | BA12: =AW12*(AY12/SUM(AY$9:AY$42)) -> 0.57603687 | BC12: =AW12*(AY12/(SUM(AY$9:AY$42)+SUM(AY$48:AY$81)+SUM(AY$87:AY$120)+SUM(AY$126:AY$159)+SUM(AY$165:AY$198)+SUM(AY$204:AY$237))) -> 0.096006144 | BE12: {=SUM(IF(Period=BE$4,IF(Category=$A$8,IF(Provider=$B12,Score))))} -> 75 | BG12: {=SUM(IF(Period=BE$4,IF(Category=$A$8,IF(Provider=$B12,Responses))))} -> 2 | BI12: =BE12*(BG12/SUM(BG$9:BG$42)) -> 0.63829787 | BK12: =BE12*(BG12/(SUM(BG$9:BG$42)+SUM(BG$48:BG$81)+SUM(BG$87:BG$120)+SUM(BG$126:BG$159)+SUM(BG$165:BG$198)+SUM(BG$204:BG$237))) -> 0.10600707 | BM12: {=SUM(IF(Period=BM$4,IF(Category=$A$8,IF(Provider=$B12,Score))))} -> 87.5 | BO12: {=SUM(IF(Period=BM$4,IF(Category=$A$8,IF(Provider=$B12,Responses))))} -> 6 | BQ12: =BM12*(BO12/SUM(BO$9:BO$42)) -> 2.262931 | BS12: =BM12*(BO12/(SUM(BO$9:BO$42)+SUM(BO$48:BO$81)+SUM(BO$87:BO$120)+SUM(BO$126:BO$159)+SUM(BO$165:BO$198)+SUM(BO$204:BO$237))) -> 0.37878788 | BU12: {=SUM(IF(Period=BU$4,IF(Category=$A$8,IF(Provider=$B12,Score))))} -> 96.9 | BW12: {=SUM(IF(Period=BU$4,IF(Category=$A$8,IF(Provider=$B12,Responses))))} -> 8 | BY12: =BU12*(BW12/SUM(BW$9:BW$42)) -> 3.2033058 | CA12: =BU12*(BW12/(SUM(BW$9:BW$42)+SUM(BW$48:BW$81)+SUM(BW$87:BW$120)+SUM(BW$126:BW$159)+SUM(BW$165:BW$198)+SUM(BW$204:BW$237))) -> 0.53572909
B13: ANDREW MASON | C13: 0 | E13: 0 | G13: 0 | I13: {=SUM(IF(Period=I$4,IF(Category=$A$8,IF(Provider=$B13,Score))))} -> 78.6 | K13: {=SUM(IF(Period=I$4,IF(Category=$A$8,IF(Provider=$B13,Responses))))} -> 7 | M13: =I13*(K13/SUM(K$9:K$42)) -> 2.751 | O13: =I13*(K13/(SUM(K$9:K$42)+SUM(K$48:K$81)+SUM(K$87:K$120)+SUM(K$126:K$159)+SUM(K$165:K$198)+SUM(K$204:K$237))) -> 0.45508685 | Q13: {=SUM(IF(Period=Q$4,IF(Category=$A$8,IF(Provider=$B13,Score))))} -> 79.2 | S13: {=SUM(IF(Period=Q$4,IF(Category=$A$8,IF(Provider=$B13,Responses))))} -> 6 | U13: =Q13*(S13/SUM(S$9:S$42)) -> 2.5276596 | W13: =Q13*(S13/(SUM(S$9:S$42)+SUM(S$48:S$81)+SUM(S$87:S$120)+SUM(S$126:S$159)+SUM(S$165:S$198)+SUM(S$204:S$237))) -> 0.42352941 | Y13: {=SUM(IF(Period=Y$4,IF(Category=$A$8,IF(Provider=$B13,Score))))} -> 70.8 | AA13: {=SUM(IF(Period=Y$4,IF(Category=$A$8,IF(Provider=$B13,Responses))))} -> 12 | AC13: =Y13*(AA13/SUM(AA$9:AA$42)) -> 2.7947368 | AE13: =Y13*(AA13/(SUM(AA$9:AA$42)+SUM(AA$48:AA$81)+SUM(AA$87:AA$120)+SUM(AA$126:AA$159)+SUM(AA$165:AA$198)+SUM(AA$204:AA$237))) -> 0.46861555 | AG13: {=SUM(IF(Period=AG$4,IF(Category=$A$8,IF(Provider=$B13,Score))))} -> 86.1 | AI13: {=SUM(IF(Period=AG$4,IF(Category=$A$8,IF(Provider=$B13,Responses))))} -> 9 | AK13: =AG13*(AI13/SUM(AI$9:AI$42)) -> 3.0269531 | AM13: =AG13*(AI13/(SUM(AI$9:AI$42)+SUM(AI$48:AI$81)+SUM(AI$87:AI$120)+SUM(AI$126:AI$159)+SUM(AI$165:AI$198)+SUM(AI$204:AI$237))) -> 0.50187824 | AO13: {=SUM(IF(Period=AO$4,IF(Category=$A$8,IF(Provider=$B13,Score))))} -> 100 | AQ13: {=SUM(IF(Period=AO$4,IF(Category=$A$8,IF(Provider=$B13,Responses))))} -> 4 | AS13: =AO13*(AQ13/SUM(AQ$9:AQ$42)) -> 2.3255814 | AU13: =AO13*(AQ13/(SUM(AQ$9:AQ$42)+SUM(AQ$48:AQ$81)+SUM(AQ$87:AQ$120)+SUM(AQ$126:AQ$159)+SUM(AQ$165:AQ$198)+SUM(AQ$204:AQ$237))) -> 0.38986355 | AW13: {=SUM(IF(Period=AW$4,IF(Category=$A$8,IF(Provider=$B13,Score))))} -> 83.3 | AY13: {=SUM(IF(Period=AW$4,IF(Category=$A$8,IF(Provider=$B13,Responses))))} -> 6 | BA13: =AW13*(AY13/SUM(AY$9:AY$42)) -> 2.3032258 | BC13: =AW13*(AY13/(SUM(AY$9:AY$42)+SUM(AY$48:AY$81)+SUM(AY$87:AY$120)+SUM(AY$126:AY$159)+SUM(AY$165:AY$198)+SUM(AY$204:AY$237))) -> 0.38387097 | BE13: {=SUM(IF(Period=BE$4,IF(Category=$A$8,IF(Provider=$B13,Score))))} -> 58.3 | BG13: {=SUM(IF(Period=BE$4,IF(Category=$A$8,IF(Provider=$B13,Responses))))} -> 6 | BI13: =BE13*(BG13/SUM(BG$9:BG$42)) -> 1.4885106 | BK13: =BE13*(BG13/(SUM(BG$9:BG$42)+SUM(BG$48:BG$81)+SUM(BG$87:BG$120)+SUM(BG$126:BG$159)+SUM(BG$165:BG$198)+SUM(BG$204:BG$237))) -> 0.24720848 | BM13: {=SUM(IF(Period=BM$4,IF(Category=$A$8,IF(Provider=$B13,Score))))} -> 75 | BO13: {=SUM(IF(Period=BM$4,IF(Category=$A$8,IF(Provider=$B13,Responses))))} -> 7 | BQ13: =BM13*(BO13/SUM(BO$9:BO$42)) -> 2.262931 | BS13: =BM13*(BO13/(SUM(BO$9:BO$42)+SUM(BO$48:BO$81)+SUM(BO$87:BO$120)+SUM(BO$126:BO$159)+SUM(BO$165:BO$198)+SUM(BO$204:BO$237))) -> 0.37878788 | BU13: {=SUM(IF(Period=BU$4,IF(Category=$A$8,IF(Provider=$B13,Score))))} -> 85.7 | BW13: {=SUM(IF(Period=BU$4,IF(Category=$A$8,IF(Provider=$B13,Responses))))} -> 7 | BY13: =BU13*(BW13/SUM(BW$9:BW$42)) -> 2.4789256 | CA13: =BU13*(BW13/(SUM(BW$9:BW$42)+SUM(BW$48:BW$81)+SUM(BW$87:BW$120)+SUM(BW$126:BW$159)+SUM(BW$165:BW$198)+SUM(BW$204:BW$237))) -> 0.41458189
B14: ANTONY FRIEDMAN | C14: 0 | E14: 0 | G14: 0 | I14: {=SUM(IF(Period=I$4,IF(Category=$A$8,IF(Provider=$B14,Score))))} -> 50 | K14: {=SUM(IF(Period=I$4,IF(Category=$A$8,IF(Provider=$B14,Responses))))} -> 4 | M14: =I14*(K14/SUM(K$9:K$42)) -> 1 | O14: =I14*(K14/(SUM(K$9:K$42)+SUM(K$48:K$81)+SUM(K$87:K$120)+SUM(K$126:K$159)+SUM(K$165:K$198)+SUM(K$204:K$237))) -> 0.16542597 | Q14: {=SUM(IF(Period=Q$4,IF(Category=$A$8,IF(Provider=$B14,Score))))} -> 35 | S14: {=SUM(IF(Period=Q$4,IF(Category=$A$8,IF(Provider=$B14,Responses))))} -> 10 | U14: =Q14*(S14/SUM(S$9:S$42)) -> 1.8617021 | W14: =Q14*(S14/(SUM(S$9:S$42)+SUM(S$48:S$81)+SUM(S$87:S$120)+SUM(S$126:S$159)+SUM(S$165:S$198)+SUM(S$204:S$237))) -> 0.31194296 | Y14: {=SUM(IF(Period=Y$4,IF(Category=$A$8,IF(Provider=$B14,Score))))} -> 70 | AA14: {=SUM(IF(Period=Y$4,IF(Category=$A$8,IF(Provider=$B14,Responses))))} -> 5 | AC14: =Y14*(AA14/SUM(AA$9:AA$42)) -> 1.1513158 | AE14: =Y14*(AA14/(SUM(AA$9:AA$42)+SUM(AA$48:AA$81)+SUM(AA$87:AA$120)+SUM(AA$126:AA$159)+SUM(AA$165:AA$198)+SUM(AA$204:AA$237))) -> 0.19305019 | AG14: {=SUM(IF(Period=AG$4,IF(Category=$A$8,IF(Provider=$B14,Score))))} -> 75 | AI14: {=SUM(IF(Period=AG$4,IF(Category=$A$8,IF(Provider=$B14,Responses))))} -> 1 | AK14: =AG14*(AI14/SUM(AI$9:AI$42)) -> 0.29296875 | AM14: =AG14*(AI14/(SUM(AI$9:AI$42)+SUM(AI$48:AI$81)+SUM(AI$87:AI$120)+SUM(AI$126:AI$159)+SUM(AI$165:AI$198)+SUM(AI$204:AI$237))) -> 0.04857513 | AO14: {=SUM(IF(Period=AO$4,IF(Category=$A$8,IF(Provider=$B14,Score))))} -> 79.2 | AQ14: {=SUM(IF(Period=AO$4,IF(Category=$A$8,IF(Provider=$B14,Responses))))} -> 6 | AS14: =AO14*(AQ14/SUM(AQ$9:AQ$42)) -> 2.7627907 | AU14: =AO14*(AQ14/(SUM(AQ$9:AQ$42)+SUM(AQ$48:AQ$81)+SUM(AQ$87:AQ$120)+SUM(AQ$126:AQ$159)+SUM(AQ$165:AQ$198)+SUM(AQ$204:AQ$237))) -> 0.46315789 | AW14: {=SUM(IF(Period=AW$4,IF(Category=$A$8,IF(Provider=$B14,Score))))} -> 62.5 | AY14: {=SUM(IF(Period=AW$4,IF(Category=$A$8,IF(Provider=$B14,Responses))))} -> 8 | BA14: =AW14*(AY14/SUM(AY$9:AY$42)) -> 2.3041475 | BC14: =AW14*(AY14/(SUM(AY$9:AY$42)+SUM(AY$48:AY$81)+SUM(AY$87:AY$120)+SUM(AY$126:AY$159)+SUM(AY$165:AY$198)+SUM(AY$204:AY$237))) -> 0.38402458 | BE14: {=SUM(IF(Period=BE$4,IF(Category=$A$8,IF(Provider=$B14,Score))))} -> 58.3 | BG14: {=SUM(IF(Period=BE$4,IF(Category=$A$8,IF(Provider=$B14,Responses))))} -> 15 | BI14: =BE14*(BG14/SUM(BG$9:BG$42)) -> 3.7212766 | BK14: =BE14*(BG14/(SUM(BG$9:BG$42)+SUM(BG$48:BG$81)+SUM(BG$87:BG$120)+SUM(BG$126:BG$159)+SUM(BG$165:BG$198)+SUM(BG$204:BG$237))) -> 0.6180212 | BM14: {=SUM(IF(Period=BM$4,IF(Category=$A$8,IF(Provider=$B14,Score))))} -> 81.8 | BO14: {=SUM(IF(Period=BM$4,IF(Category=$A$8,IF(Provider=$B14,Responses))))} -> 11 | BQ14: =BM14*(BO14/SUM(BO$9:BO$42)) -> 3.8784483 | BS14: =BM14*(BO14/(SUM(BO$9:BO$42)+SUM(BO$48:BO$81)+SUM(BO$87:BO$120)+SUM(BO$126:BO$159)+SUM(BO$165:BO$198)+SUM(BO$204:BO$237))) -> 0.64920635 | BU14: {=SUM(IF(Period=BU$4,IF(Category=$A$8,IF(Provider=$B14,Score))))} -> 65.6 | BW14: {=SUM(IF(Period=BU$4,IF(Category=$A$8,IF(Provider=$B14,Responses))))} -> 8 | BY14: =BU14*(BW14/SUM(BW$9:BW$42)) -> 2.168595 | CA14: =BU14*(BW14/(SUM(BW$9:BW$42)+SUM(BW$48:BW$81)+SUM(BW$87:BW$120)+SUM(BW$126:BW$159)+SUM(BW$165:BW$198)+SUM(BW$204:BW$237))) -> 0.36268141
B15: CHARLES SANZ | C15: 0 | E15: 0 | G15: 0 | I15: {=SUM(IF(Period=I$4,IF(Category=$A$8,IF(Provider=$B15,Score))))} -> 81.3 | K15: {=SUM(IF(Period=I$4,IF(Category=$A$8,IF(Provider=$B15,Responses))))} -> 4 | M15: =I15*(K15/SUM(K$9:K$42)) -> 1.626 | O15: =I15*(K15/(SUM(K$9:K$42)+SUM(K$48:K$81)+SUM(K$87:K$120)+SUM(K$126:K$159)+SUM(K$165:K$198)+SUM(K$204:K$237))) -> 0.26898263 | Q15: {=SUM(IF(Period=Q$4,IF(Category=$A$8,IF(Provider=$B15,Score))))} -> 83.3 | S15: {=SUM(IF(Period=Q$4,IF(Category=$A$8,IF(Provider=$B15,Responses))))} -> 3 | U15: =Q15*(S15/SUM(S$9:S$42)) -> 1.3292553 | W15: =Q15*(S15/(SUM(S$9:S$42)+SUM(S$48:S$81)+SUM(S$87:S$120)+SUM(S$126:S$159)+SUM(S$165:S$198)+SUM(S$204:S$237))) -> 0.22272727 | Y15: {=SUM(IF(Period=Y$4,IF(Category=$A$8,IF(Provider=$B15,Score))))} -> 96.9 | AA15: {=SUM(IF(Period=Y$4,IF(Category=$A$8,IF(Provider=$B15,Responses))))} -> 8 | AC15: =Y15*(AA15/SUM(AA$9:AA$42)) -> 2.55 | AE15: =Y15*(AA15/(SUM(AA$9:AA$42)+SUM(AA$48:AA$81)+SUM(AA$87:AA$120)+SUM(AA$126:AA$159)+SUM(AA$165:AA$198)+SUM(AA$204:AA$237))) -> 0.4275786 | AG15: {=SUM(IF(Period=AG$4,IF(Category=$A$8,IF(Provider=$B15,Score))))} -> 90.6 | AI15: {=SUM(IF(Period=AG$4,IF(Category=$A$8,IF(Provider=$B15,Responses))))} -> 8 | AK15: =AG15*(AI15/SUM(AI$9:AI$42)) -> 2.83125 | AM15: =AG15*(AI15/(SUM(AI$9:AI$42)+SUM(AI$48:AI$81)+SUM(AI$87:AI$120)+SUM(AI$126:AI$159)+SUM(AI$165:AI$198)+SUM(AI$204:AI$237))) -> 0.46943005 | AO15: {=SUM(IF(Period=AO$4,IF(Category=$A$8,IF(Provider=$B15,Score))))} -> 83.3 | AQ15: {=SUM(IF(Period=AO$4,IF(Category=$A$8,IF(Provider=$B15,Responses))))} -> 3 | AS15: =AO15*(AQ15/SUM(AQ$9:AQ$42)) -> 1.452907 | AU15: =AO15*(AQ15/(SUM(AQ$9:AQ$42)+SUM(AQ$48:AQ$81)+SUM(AQ$87:AQ$120)+SUM(AQ$126:AQ$159)+SUM(AQ$165:AQ$198)+SUM(AQ$204:AQ$237))) -> 0.24356725 | AW15: {=SUM(IF(Period=AW$4,IF(Category=$A$8,IF(Provider=$B15,Score))))} -> 91.7 | AY15: {=SUM(IF(Period=AW$4,IF(Category=$A$8,IF(Provider=$B15,Responses))))} -> 3 | BA15: =AW15*(AY15/SUM(AY$9:AY$42)) -> 1.2677419 | BC15: =AW15*(AY15/(SUM(AY$9:AY$42)+SUM(AY$48:AY$81)+SUM(AY$87:AY$120)+SUM(AY$126:AY$159)+SUM(AY$165:AY$198)+SUM(AY$204:AY$237))) -> 0.21129032 | BE15: {=SUM(IF(Period=BE$4,IF(Category=$A$8,IF(Provider=$B15,Score))))} -> 69.2 | BG15: {=SUM(IF(Period=BE$4,IF(Category=$A$8,IF(Provider=$B15,Responses))))} -> 13 | BI15: =BE15*(BG15/SUM(BG$9:BG$42)) -> 3.8280851 | BK15: =BE15*(BG15/(SUM(BG$9:BG$42)+SUM(BG$48:BG$81)+SUM(BG$87:BG$120)+SUM(BG$126:BG$159)+SUM(BG$165:BG$198)+SUM(BG$204:BG$237))) -> 0.63575972 | BM15: {=SUM(IF(Period=BM$4,IF(Category=$A$8,IF(Provider=$B15,Score))))} -> 95.8 | BO15: {=SUM(IF(Period=BM$4,IF(Category=$A$8,IF(Provider=$B15,Responses))))} -> 12 | BQ15: =BM15*(BO15/SUM(BO$9:BO$42)) -> 4.9551724 | BS15: =BM15*(BO15/(SUM(BO$9:BO$42)+SUM(BO$48:BO$81)+SUM(BO$87:BO$120)+SUM(BO$126:BO$159)+SUM(BO$165:BO$198)+SUM(BO$204:BO$237))) -> 0.82943723 | BU15: {=SUM(IF(Period=BU$4,IF(Category=$A$8,IF(Provider=$B15,Score))))} -> 100 | BW15: {=SUM(IF(Period=BU$4,IF(Category=$A$8,IF(Provider=$B15,Responses))))} -> 6 | BY15: =BU15*(BW15/SUM(BW$9:BW$42)) -> 2.4793388 | CA15: =BU15*(BW15/(SUM(BW$9:BW$42)+SUM(BW$48:BW$81)+SUM(BW$87:BW$120)+SUM(BW$126:BW$159)+SUM(BW$165:BW$198)+SUM(BW$204:BW$237))) -> 0.414651
B16: CHRISTIAN KOKINAKOS | C16: 0 | E16: 0 | G16: 0 | I16: {=SUM(IF(Period=I$4,IF(Category=$A$8,IF(Provider=$B16,Score))))} -> 85 | K16: {=SUM(IF(Period=I$4,IF(Category=$A$8,IF(Provider=$B16,Responses))))} -> 5 | M16: =I16*(K16/SUM(K$9:K$42)) -> 2.125 | O16: =I16*(K16/(SUM(K$9:K$42)+SUM(K$48:K$81)+SUM(K$87:K$120)+SUM(K$126:K$159)+SUM(K$165:K$198)+SUM(K$204:K$237))) -> 0.35153019 | Q16: {=SUM(IF(Period=Q$4,IF(Category=$A$8,IF(Provider=$B16,Score))))} -> 83.3 | S16: {=SUM(IF(Period=Q$4,IF(Category=$A$8,IF(Provider=$B16,Responses))))} -> 3 | U16: =Q16*(S16/SUM(S$9:S$42)) -> 1.3292553 | W16: =Q16*(S16/(SUM(S$9:S$42)+SUM(S$48:S$81)+SUM(S$87:S$120)+SUM(S$126:S$159)+SUM(S$165:S$198)+SUM(S$204:S$237))) -> 0.22272727 | Y16: {=SUM(IF(Period=Y$4,IF(Category=$A$8,IF(Provider=$B16,Score))))} -> 0 | AA16: {=SUM(IF(Period=Y$4,IF(Category=$A$8,IF(Provider=$B16,Responses))))} -> 0 | AC16: =Y16*(AA16/SUM(AA$9:AA$42)) -> 0 | AE16: =Y16*(AA16/(SUM(AA$9:AA$42)+SUM(AA$48:AA$81)+SUM(AA$87:AA$120)+SUM(AA$126:AA$159)+SUM(AA$165:AA$198)+SUM(AA$204:AA$237))) -> 0 | AG16: {=SUM(IF(Period=AG$4,IF(Category=$A$8,IF(Provider=$B16,Score))))} -> 0 | AI16: {=SUM(IF(Period=AG$4,IF(Category=$A$8,IF(Provider=$B16,Responses))))} -> 0 | AK16: =AG16*(AI16/SUM(AI$9:AI$42)) -> 0 | AM16: =AG16*(AI16/(SUM(AI$9:AI$42)+SUM(AI$48:AI$81)+SUM(AI$87:AI$120)+SUM(AI$126:AI$159)+SUM(AI$165:AI$198)+SUM(AI$204:AI$237))) -> 0 | AO16: {=SUM(IF(Period=AO$4,IF(Category=$A$8,IF(Provider=$B16,Score))))} -> 0 | AQ16: {=SUM(IF(Period=AO$4,IF(Category=$A$8,IF(Provider=$B16,Responses))))} -> 0 | AS16: =AO16*(AQ16/SUM(AQ$9:AQ$42)) -> 0 | AU16: =AO16*(AQ16/(SUM(AQ$9:AQ$42)+SUM(AQ$48:AQ$81)+SUM(AQ$87:AQ$120)+SUM(AQ$126:AQ$159)+SUM(AQ$165:AQ$198)+SUM(AQ$204:AQ$237))) -> 0 | AW16: {=SUM(IF(Period=AW$4,IF(Category=$A$8,IF(Provider=$B16,Score))))} -> 0 | AY16: {=SUM(IF(Period=AW$4,IF(Category=$A$8,IF(Provider=$B16,Responses))))} -> 0 | BA16: =AW16*(AY16/SUM(AY$9:AY$42)) -> 0 | BC16: =AW16*(AY16/(SUM(AY$9:AY$42)+SUM(AY$48:AY$81)+SUM(AY$87:AY$120)+SUM(AY$126:AY$159)+SUM(AY$165:AY$198)+SUM(AY$204:AY$237))) -> 0 | BE16: {=SUM(IF(Period=BE$4,IF(Category=$A$8,IF(Provider=$B16,Score))))} -> 0 | BG16: {=SUM(IF(Period=BE$4,IF(Category=$A$8,IF(Provider=$B16,Responses))))} -> 0 | BI16: =BE16*(BG16/SUM(BG$9:BG$42)) -> 0 | BK16: =BE16*(BG16/(SUM(BG$9:BG$42)+SUM(BG$48:BG$81)+SUM(BG$87:BG$120)+SUM(BG$126:BG$159)+SUM(BG$165:BG$198)+SUM(BG$204:BG$237))) -> 0 | BM16: {=SUM(IF(Period=BM$4,IF(Category=$A$8,IF(Provider=$B16,Score))))} -> 0 | BO16: {=SUM(IF(Period=BM$4,IF(Category=$A$8,IF(Provider=$B16,Responses))))} -> 0 | BQ16: =BM16*(BO16/SUM(BO$9:BO$42)) -> 0 | BS16: =BM16*(BO16/(SUM(BO$9:BO$42)+SUM(BO$48:BO$81)+SUM(BO$87:BO$120)+SUM(BO$126:BO$159)+SUM(BO$165:BO$198)+SUM(BO$204:BO$237))) -> 0 | BU16: {=SUM(IF(Period=BU$4,IF(Category=$A$8,IF(Provider=$B16,Score))))} -> 0 | BW16: {=SUM(IF(Period=BU$4,IF(Category=$A$8,IF(Provider=$B16,Responses))))} -> 0 | BY16: =BU16*(BW16/SUM(BW$9:BW$42)) -> 0 | CA16: =BU16*(BW16/(SUM(BW$9:BW$42)+SUM(BW$48:BW$81)+SUM(BW$87:BW$120)+SUM(BW$126:BW$159)+SUM(BW$165:BW$198)+SUM(BW$204:BW$237))) -> 0
B17: DANIEL D'AMORE | C17: 0 | E17: 0 | G17: 0 | I17: {=SUM(IF(Period=I$4,IF(Category=$A$8,IF(Provider=$B17,Score))))} -> 75 | K17: {=SUM(IF(Period=I$4,IF(Category=$A$8,IF(Provider=$B17,Responses))))} -> 8 | M17: =I17*(K17/SUM(K$9:K$42)) -> 3 | O17: =I17*(K17/(SUM(K$9:K$42)+SUM(K$48:K$81)+SUM(K$87:K$120)+SUM(K$126:K$159)+SUM(K$165:K$198)+SUM(K$204:K$237))) -> 0.49627792 | Q17: {=SUM(IF(Period=Q$4,IF(Category=$A$8,IF(Provider=$B17,Score))))} -> 65 | S17: {=SUM(IF(Period=Q$4,IF(Category=$A$8,IF(Provider=$B17,Responses))))} -> 5 | U17: =Q17*(S17/SUM(S$9:S$42)) -> 1.7287234 | W17: =Q17*(S17/(SUM(S$9:S$42)+SUM(S$48:S$81)+SUM(S$87:S$120)+SUM(S$126:S$159)+SUM(S$165:S$198)+SUM(S$204:S$237))) -> 0.28966132 | Y17: {=SUM(IF(Period=Y$4,IF(Category=$A$8,IF(Provider=$B17,Score))))} -> 77.1 | AA17: {=SUM(IF(Period=Y$4,IF(Category=$A$8,IF(Provider=$B17,Responses))))} -> 12 | AC17: =Y17*(AA17/SUM(AA$9:AA$42)) -> 3.0434211 | AE17: =Y17*(AA17/(SUM(AA$9:AA$42)+SUM(AA$48:AA$81)+SUM(AA$87:AA$120)+SUM(AA$126:AA$159)+SUM(AA$165:AA$198)+SUM(AA$204:AA$237))) -> 0.5103144 | AG17: {=SUM(IF(Period=AG$4,IF(Category=$A$8,IF(Provider=$B17,Score))))} -> 91.7 | AI17: {=SUM(IF(Period=AG$4,IF(Category=$A$8,IF(Provider=$B17,Responses))))} -> 9 | AK17: =AG17*(AI17/SUM(AI$9:AI$42)) -> 3.2238281 | AM17: =AG17*(AI17/(SUM(AI$9:AI$42)+SUM(AI$48:AI$81)+SUM(AI$87:AI$120)+SUM(AI$126:AI$159)+SUM(AI$165:AI$198)+SUM(AI$204:AI$237))) -> 0.53452073 | AO17: {=SUM(IF(Period=AO$4,IF(Category=$A$8,IF(Provider=$B17,Score))))} -> 81.3 | AQ17: {=SUM(IF(Period=AO$4,IF(Category=$A$8,IF(Provider=$B17,Responses))))} -> 12 | AS17: =AO17*(AQ17/SUM(AQ$9:AQ$42)) -> 5.672093 | AU17: =AO17*(AQ17/(SUM(AQ$9:AQ$42)+SUM(AQ$48:AQ$81)+SUM(AQ$87:AQ$120)+SUM(AQ$126:AQ$159)+SUM(AQ$165:AQ$198)+SUM(AQ$204:AQ$237))) -> 0.95087719 | AW17: {=SUM(IF(Period=AW$4,IF(Category=$A$8,IF(Provider=$B17,Score))))} -> 78.1 | AY17: {=SUM(IF(Period=AW$4,IF(Category=$A$8,IF(Provider=$B17,Responses))))} -> 8 | BA17: =AW17*(AY17/SUM(AY$9:AY$42)) -> 2.8792627 | BC17: =AW17*(AY17/(SUM(AY$9:AY$42)+SUM(AY$48:AY$81)+SUM(AY$87:AY$120)+SUM(AY$126:AY$159)+SUM(AY$165:AY$198)+SUM(AY$204:AY$237))) -> 0.47987711 | BE17: {=SUM(IF(Period=BE$4,IF(Category=$A$8,IF(Provider=$B17,Score))))} -> 68.8 | BG17: {=SUM(IF(Period=BE$4,IF(Category=$A$8,IF(Provider=$B17,Responses))))} -> 4 | BI17: =BE17*(BG17/SUM(BG$9:BG$42)) -> 1.1710638 | BK17: =BE17*(BG17/(SUM(BG$9:BG$42)+SUM(BG$48:BG$81)+SUM(BG$87:BG$120)+SUM(BG$126:BG$159)+SUM(BG$165:BG$198)+SUM(BG$204:BG$237))) -> 0.19448763 | BM17: {=SUM(IF(Period=BM$4,IF(Category=$A$8,IF(Provider=$B17,Score))))} -> 73.1 | BO17: {=SUM(IF(Period=BM$4,IF(Category=$A$8,IF(Provider=$B17,Responses))))} -> 13 | BQ17: =BM17*(BO17/SUM(BO$9:BO$42)) -> 4.0961207 | BS17: =BM17*(BO17/(SUM(BO$9:BO$42)+SUM(BO$48:BO$81)+SUM(BO$87:BO$120)+SUM(BO$126:BO$159)+SUM(BO$165:BO$198)+SUM(BO$204:BO$237))) -> 0.68564214 | BU17: {=SUM(IF(Period=BU$4,IF(Category=$A$8,IF(Provider=$B17,Score))))} -> 69.4 | BW17: {=SUM(IF(Period=BU$4,IF(Category=$A$8,IF(Provider=$B17,Responses))))} -> 9 | BY17: =BU17*(BW17/SUM(BW$9:BW$42)) -> 2.5809917 | CA17: =BU17*(BW17/(SUM(BW$9:BW$42)+SUM(BW$48:BW$81)+SUM(BW$87:BW$120)+SUM(BW$126:BW$159)+SUM(BW$165:BW$198)+SUM(BW$204:BW$237))) -> 0.43165169
B18: DAVID MISHKIN | C18: 0 | E18: 0 | G18: 0 | I18: {=SUM(IF(Period=I$4,IF(Category=$A$8,IF(Provider=$B18,Score))))} -> 87.5 | K18: {=SUM(IF(Period=I$4,IF(Category=$A$8,IF(Provider=$B18,Responses))))} -> 8 | M18: =I18*(K18/SUM(K$9:K$42)) -> 3.5 | O18: =I18*(K18/(SUM(K$9:K$42)+SUM(K$48:K$81)+SUM(K$87:K$120)+SUM(K$126:K$159)+SUM(K$165:K$198)+SUM(K$204:K$237))) -> 0.5789909 | Q18: {=SUM(IF(Period=Q$4,IF(Category=$A$8,IF(Provider=$B18,Score))))} -> 63.9 | S18: {=SUM(IF(Period=Q$4,IF(Category=$A$8,IF(Provider=$B18,Responses))))} -> 9 | U18: =Q18*(S18/SUM(S$9:S$42)) -> 3.0590426 | W18: =Q18*(S18/(SUM(S$9:S$42)+SUM(S$48:S$81)+SUM(S$87:S$120)+SUM(S$126:S$159)+SUM(S$165:S$198)+SUM(S$204:S$237))) -> 0.51256684 | Y18: {=SUM(IF(Period=Y$4,IF(Category=$A$8,IF(Provider=$B18,Score))))} -> 76.9 | AA18: {=SUM(IF(Period=Y$4,IF(Category=$A$8,IF(Provider=$B18,Responses))))} -> 13 | AC18: =Y18*(AA18/SUM(AA$9:AA$42)) -> 3.2884868 | AE18: =Y18*(AA18/(SUM(AA$9:AA$42)+SUM(AA$48:AA$81)+SUM(AA$87:AA$120)+SUM(AA$126:AA$159)+SUM(AA$165:AA$198)+SUM(AA$204:AA$237))) -> 0.55140651 | AG18: {=SUM(IF(Period=AG$4,IF(Category=$A$8,IF(Provider=$B18,Score))))} -> 95 | AI18: {=SUM(IF(Period=AG$4,IF(Category=$A$8,IF(Provider=$B18,Responses))))} -> 10 | AK18: =AG18*(AI18/SUM(AI$9:AI$42)) -> 3.7109375 | AM18: =AG18*(AI18/(SUM(AI$9:AI$42)+SUM(AI$48:AI$81)+SUM(AI$87:AI$120)+SUM(AI$126:AI$159)+SUM(AI$165:AI$198)+SUM(AI$204:AI$237))) -> 0.61528497 | AO18: {=SUM(IF(Period=AO$4,IF(Category=$A$8,IF(Provider=$B18,Score))))} -> 96.9 | AQ18: {=SUM(IF(Period=AO$4,IF(Category=$A$8,IF(Provider=$B18,Responses))))} -> 8 | AS18: =AO18*(AQ18/SUM(AQ$9:AQ$42)) -> 4.5069767 | AU18: =AO18*(AQ18/(SUM(AQ$9:AQ$42)+SUM(AQ$48:AQ$81)+SUM(AQ$87:AQ$120)+SUM(AQ$126:AQ$159)+SUM(AQ$165:AQ$198)+SUM(AQ$204:AQ$237))) -> 0.75555556 | AW18: {=SUM(IF(Period=AW$4,IF(Category=$A$8,IF(Provider=$B18,Score))))} -> 89.3 | AY18: {=SUM(IF(Period=AW$4,IF(Category=$A$8,IF(Provider=$B18,Responses))))} -> 14 | BA18: =AW18*(AY18/SUM(AY$9:AY$42)) -> 5.7612903 | BC18: =AW18*(AY18/(SUM(AY$9:AY$42)+SUM(AY$48:AY$81)+SUM(AY$87:AY$120)+SUM(AY$126:AY$159)+SUM(AY$165:AY$198)+SUM(AY$204:AY$237))) -> 0.96021505 | BE18: {=SUM(IF(Period=BE$4,IF(Category=$A$8,IF(Provider=$B18,Score))))} -> 100 | BG18: {=SUM(IF(Period=BE$4,IF(Category=$A$8,IF(Provider=$B18,Responses))))} -> 11 | BI18: =BE18*(BG18/SUM(BG$9:BG$42)) -> 4.6808511 | BK18: =BE18*(BG18/(SUM(BG$9:BG$42)+SUM(BG$48:BG$81)+SUM(BG$87:BG$120)+SUM(BG$126:BG$159)+SUM(BG$165:BG$198)+SUM(BG$204:BG$237))) -> 0.77738516 | BM18: {=SUM(IF(Period=BM$4,IF(Category=$A$8,IF(Provider=$B18,Score))))} -> 92.9 | BO18: {=SUM(IF(Period=BM$4,IF(Category=$A$8,IF(Provider=$B18,Responses))))} -> 7 | BQ18: =BM18*(BO18/SUM(BO$9:BO$42)) -> 2.8030172 | BS18: =BM18*(BO18/(SUM(BO$9:BO$42)+SUM(BO$48:BO$81)+SUM(BO$87:BO$120)+SUM(BO$126:BO$159)+SUM(BO$165:BO$198)+SUM(BO$204:BO$237))) -> 0.46919192 | BU18: {=SUM(IF(Period=BU$4,IF(Category=$A$8,IF(Provider=$B18,Score))))} -> 83.9 | BW18: {=SUM(IF(Period=BU$4,IF(Category=$A$8,IF(Provider=$B18,Responses))))} -> 14 | BY18: =BU18*(BW18/SUM(BW$9:BW$42)) -> 4.853719 | CA18: =BU18*(BW18/(SUM(BW$9:BW$42)+SUM(BW$48:BW$81)+SUM(BW$87:BW$120)+SUM(BW$126:BW$159)+SUM(BW$165:BW$198)+SUM(BW$204:BW$237))) -> 0.81174845
B19: ELAINE DIAZ | C19: 0 | E19: 0 | G19: 0 | I19: {=SUM(IF(Period=I$4,IF(Category=$A$8,IF(Provider=$B19,Score))))} -> 81.3 | K19: {=SUM(IF(Period=I$4,IF(Category=$A$8,IF(Provider=$B19,Responses))))} -> 4 | M19: =I19*(K19/SUM(K$9:K$42)) -> 1.626 | O19: =I19*(K19/(SUM(K$9:K$42)+SUM(K$48:K$81)+SUM(K$87:K$120)+SUM(K$126:K$159)+SUM(K$165:K$198)+SUM(K$204:K$237))) -> 0.26898263 | Q19: {=SUM(IF(Period=Q$4,IF(Category=$A$8,IF(Provider=$B19,Score))))} -> 81.3 | S19: {=SUM(IF(Period=Q$4,IF(Category=$A$8,IF(Provider=$B19,Responses))))} -> 4 | U19: =Q19*(S19/SUM(S$9:S$42)) -> 1.7297872 | W19: =Q19*(S19/(SUM(S$9:S$42)+SUM(S$48:S$81)+SUM(S$87:S$120)+SUM(S$126:S$159)+SUM(S$165:S$198)+SUM(S$204:S$237))) -> 0.28983957 | Y19: {=SUM(IF(Period=Y$4,IF(Category=$A$8,IF(Provider=$B19,Score))))} -> 80 | AA19: {=SUM(IF(Period=Y$4,IF(Category=$A$8,IF(Provider=$B19,Responses))))} -> 5 | AC19: =Y19*(AA19/SUM(AA$9:AA$42)) -> 1.3157895 | AE19: =Y19*(AA19/(SUM(AA$9:AA$42)+SUM(AA$48:AA$81)+SUM(AA$87:AA$120)+SUM(AA$126:AA$159)+SUM(AA$165:AA$198)+SUM(AA$204:AA$237))) -> 0.22062879 | AG19: {=SUM(IF(Period=AG$4,IF(Category=$A$8,IF(Provider=$B19,Score))))} -> 93.8 | AI19: {=SUM(IF(Period=AG$4,IF(Category=$A$8,IF(Provider=$B19,Responses))))} -> 4 | AK19: =AG19*(AI19/SUM(AI$9:AI$42)) -> 1.465625 | AM19: =AG19*(AI19/(SUM(AI$9:AI$42)+SUM(AI$48:AI$81)+SUM(AI$87:AI$120)+SUM(AI$126:AI$159)+SUM(AI$165:AI$198)+SUM(AI$204:AI$237))) -> 0.24300518 | AO19: {=SUM(IF(Period=AO$4,IF(Category=$A$8,IF(Provider=$B19,Score))))} -> 37.5 | AQ19: {=SUM(IF(Period=AO$4,IF(Category=$A$8,IF(Provider=$B19,Responses))))} -> 2 | AS19: =AO19*(AQ19/SUM(AQ$9:AQ$42)) -> 0.43604651 | AU19: =AO19*(AQ19/(SUM(AQ$9:AQ$42)+SUM(AQ$48:AQ$81)+SUM(AQ$87:AQ$120)+SUM(AQ$126:AQ$159)+SUM(AQ$165:AQ$198)+SUM(AQ$204:AQ$237))) -> 0.073099415 | AW19: {=SUM(IF(Period=AW$4,IF(Category=$A$8,IF(Provider=$B19,Score))))} -> 80 | AY19: {=SUM(IF(Period=AW$4,IF(Category=$A$8,IF(Provider=$B19,Responses))))} -> 5 | BA19: =AW19*(AY19/SUM(AY$9:AY$42)) -> 1.843318 | BC19: =AW19*(AY19/(SUM(AY$9:AY$42)+SUM(AY$48:AY$81)+SUM(AY$87:AY$120)+SUM(AY$126:AY$159)+SUM(AY$165:AY$198)+SUM(AY$204:AY$237))) -> 0.30721966 | BE19: {=SUM(IF(Period=BE$4,IF(Category=$A$8,IF(Provider=$B19,Score))))} -> 100 | BG19: {=SUM(IF(Period=BE$4,IF(Category=$A$8,IF(Provider=$B19,Responses))))} -> 2 | BI19: =BE19*(BG19/SUM(BG$9:BG$42)) -> 0.85106383 | BK19: =BE19*(BG19/(SUM(BG$9:BG$42)+SUM(BG$48:BG$81)+SUM(BG$87:BG$120)+SUM(BG$126:BG$159)+SUM(BG$165:BG$198)+SUM(BG$204:BG$237))) -> 0.14134276 | BM19: {=SUM(IF(Period=BM$4,IF(Category=$A$8,IF(Provider=$B19,Score))))} -> 91.7 | BO19: {=SUM(IF(Period=BM$4,IF(Category=$A$8,IF(Provider=$B19,Responses))))} -> 3 | BQ19: =BM19*(BO19/SUM(BO$9:BO$42)) -> 1.1857759 | BS19: =BM19*(BO19/(SUM(BO$9:BO$42)+SUM(BO$48:BO$81)+SUM(BO$87:BO$120)+SUM(BO$126:BO$159)+SUM(BO$165:BO$198)+SUM(BO$204:BO$237))) -> 0.19848485 | BU19: {=SUM(IF(Period=BU$4,IF(Category=$A$8,IF(Provider=$B19,Score))))} -> 75 | BW19: {=SUM(IF(Period=BU$4,IF(Category=$A$8,IF(Provider=$B19,Responses))))} -> 7 | BY19: =BU19*(BW19/SUM(BW$9:BW$42)) -> 2.1694215 | CA19: =BU19*(BW19/(SUM(BW$9:BW$42)+SUM(BW$48:BW$81)+SUM(BW$87:BW$120)+SUM(BW$126:BW$159)+SUM(BW$165:BW$198)+SUM(BW$204:BW$237))) -> 0.36281963
B20: EVA ESCATEL | C20: 0 | E20: 0 | G20: 0 | I20: {=SUM(IF(Period=I$4,IF(Category=$A$8,IF(Provider=$B20,Score))))} -> 79.6 | K20: {=SUM(IF(Period=I$4,IF(Category=$A$8,IF(Provider=$B20,Responses))))} -> 11 | M20: =I20*(K20/SUM(K$9:K$42)) -> 4.378 | O20: =I20*(K20/(SUM(K$9:K$42)+SUM(K$48:K$81)+SUM(K$87:K$120)+SUM(K$126:K$159)+SUM(K$165:K$198)+SUM(K$204:K$237))) -> 0.7242349 | Q20: {=SUM(IF(Period=Q$4,IF(Category=$A$8,IF(Provider=$B20,Score))))} -> 86.1 | S20: {=SUM(IF(Period=Q$4,IF(Category=$A$8,IF(Provider=$B20,Responses))))} -> 9 | U20: =Q20*(S20/SUM(S$9:S$42)) -> 4.1218085 | W20: =Q20*(S20/(SUM(S$9:S$42)+SUM(S$48:S$81)+SUM(S$87:S$120)+SUM(S$126:S$159)+SUM(S$165:S$198)+SUM(S$204:S$237))) -> 0.69064171 | Y20: {=SUM(IF(Period=Y$4,IF(Category=$A$8,IF(Provider=$B20,Score))))} -> 76.4 | AA20: {=SUM(IF(Period=Y$4,IF(Category=$A$8,IF(Provider=$B20,Responses))))} -> 18 | AC20: =Y20*(AA20/SUM(AA$9:AA$42)) -> 4.5236842 | AE20: =Y20*(AA20/(SUM(AA$9:AA$42)+SUM(AA$48:AA$81)+SUM(AA$87:AA$120)+SUM(AA$126:AA$159)+SUM(AA$165:AA$198)+SUM(AA$204:AA$237))) -> 0.75852179 | AG20: {=SUM(IF(Period=AG$4,IF(Category=$A$8,IF(Provider=$B20,Score))))} -> 81.3 | AI20: {=SUM(IF(Period=AG$4,IF(Category=$A$8,IF(Provider=$B20,Responses))))} -> 16 | AK20: =AG20*(AI20/SUM(AI$9:AI$42)) -> 5.08125 | AM20: =AG20*(AI20/(SUM(AI$9:AI$42)+SUM(AI$48:AI$81)+SUM(AI$87:AI$120)+SUM(AI$126:AI$159)+SUM(AI$165:AI$198)+SUM(AI$204:AI$237))) -> 0.84248705 | AO20: {=SUM(IF(Period=AO$4,IF(Category=$A$8,IF(Provider=$B20,Score))))} -> 83.3 | AQ20: {=SUM(IF(Period=AO$4,IF(Category=$A$8,IF(Provider=$B20,Responses))))} -> 12 | AS20: =AO20*(AQ20/SUM(AQ$9:AQ$42)) -> 5.8116279 | AU20: =AO20*(AQ20/(SUM(AQ$9:AQ$42)+SUM(AQ$48:AQ$81)+SUM(AQ$87:AQ$120)+SUM(AQ$126:AQ$159)+SUM(AQ$165:AQ$198)+SUM(AQ$204:AQ$237))) -> 0.97426901 | AW20: {=SUM(IF(Period=AW$4,IF(Category=$A$8,IF(Provider=$B20,Score))))} -> 92.5 | AY20: {=SUM(IF(Period=AW$4,IF(Category=$A$8,IF(Provider=$B20,Responses))))} -> 10 | BA20: =AW20*(AY20/SUM(AY$9:AY$42)) -> 4.2626728 | BC20: =AW20*(AY20/(SUM(AY$9:AY$42)+SUM(AY$48:AY$81)+SUM(AY$87:AY$120)+SUM(AY$126:AY$159)+SUM(AY$165:AY$198)+SUM(AY$204:AY$237))) -> 0.71044547 | BE20: {=SUM(IF(Period=BE$4,IF(Category=$A$8,IF(Provider=$B20,Score))))} -> 90.6 | BG20: {=SUM(IF(Period=BE$4,IF(Category=$A$8,IF(Provider=$B20,Responses))))} -> 8 | BI20: =BE20*(BG20/SUM(BG$9:BG$42)) -> 3.0842553 | BK20: =BE20*(BG20/(SUM(BG$9:BG$42)+SUM(BG$48:BG$81)+SUM(BG$87:BG$120)+SUM(BG$126:BG$159)+SUM(BG$165:BG$198)+SUM(BG$204:BG$237))) -> 0.51222615 | BM20: {=SUM(IF(Period=BM$4,IF(Category=$A$8,IF(Provider=$B20,Score))))} -> 97.2 | BO20: {=SUM(IF(Period=BM$4,IF(Category=$A$8,IF(Provider=$B20,Responses))))} -> 9 | BQ20: =BM20*(BO20/SUM(BO$9:BO$42)) -> 3.7706897 | BS20: =BM20*(BO20/(SUM(BO$9:BO$42)+SUM(BO$48:BO$81)+SUM(BO$87:BO$120)+SUM(BO$126:BO$159)+SUM(BO$165:BO$198)+SUM(BO$204:BO$237))) -> 0.63116883 | BU20: {=SUM(IF(Period=BU$4,IF(Category=$A$8,IF(Provider=$B20,Score))))} -> 92.9 | BW20: {=SUM(IF(Period=BU$4,IF(Category=$A$8,IF(Provider=$B20,Responses))))} -> 7 | BY20: =BU20*(BW20/SUM(BW$9:BW$42)) -> 2.6871901 | CA20: =BU20*(BW20/(SUM(BW$9:BW$42)+SUM(BW$48:BW$81)+SUM(BW$87:BW$120)+SUM(BW$126:BW$159)+SUM(BW$165:BW$198)+SUM(BW$204:BW$237))) -> 0.44941258
... B42: NAME NOT GIVEN | C42: 0 | E42: 0 | G42: 0 | I42: {=SUM(IF(Period=I$4,IF(Category=$A$8,IF(Provider=$B42,Score))))} -> 0 | K42: {=SUM(IF(Period=I$4,IF(Category=$A$8,IF(Provider=$B42,Responses))))} -> 0 | M42: =I42*(K42/SUM(K$9:K$42)) -> 0 | O42: =I42*(K42/(SUM(K$9:K$42)+SUM(K$48:K$81)+SUM(K$87:K$120)+SUM(K$126:K$159)+SUM(K$165:K$198)+SUM(K$204:K$237))) -> 0 | Q42: {=SUM(IF(Period=Q$4,IF(Category=$A$8,IF(Provider=$B42,Score))))} -> 0 | S42: {=SUM(IF(Period=Q$4,IF(Category=$A$8,IF(Provider=$B42,Responses))))} -> 0 | U42: =Q42*(S42/SUM(S$9:S$42)) -> 0 | W42: =Q42*(S42/(SUM(S$9:S$42)+SUM(S$48:S$81)+SUM(S$87:S$120)+SUM(S$126:S$159)+SUM(S$165:S$198)+SUM(S$204:S$237))) -> 0 | Y42: {=SUM(IF(Period=Y$4,IF(Category=$A$8,IF(Provider=$B42,Score))))} -> 0 | AA42: {=SUM(IF(Period=Y$4,IF(Category=$A$8,IF(Provider=$B42,Responses))))} -> 0 | AC42: =Y42*(AA42/SUM(AA$9:AA$42)) -> 0 | AE42: =Y42*(AA42/(SUM(AA$9:AA$42)+SUM(AA$48:AA$81)+SUM(AA$87:AA$120)+SUM(AA$126:AA$159)+SUM(AA$165:AA$198)+SUM(AA$204:AA$237))) -> 0 | AG42: {=SUM(IF(Period=AG$4,IF(Category=$A$8,IF(Provider=$B42,Score))))} -> 75 | AI42: {=SUM(IF(Period=AG$4,IF(Category=$A$8,IF(Provider=$B42,Responses))))} -> 1 | AK42: =AG42*(AI42/SUM(AI$9:AI$42)) -> 0.29296875 | AM42: =AG42*(AI42/(SUM(AI$9:AI$42)+SUM(AI$48:AI$81)+SUM(AI$87:AI$120)+SUM(AI$126:AI$159)+SUM(AI$165:AI$198)+SUM(AI$204:AI$237))) -> 0.04857513 | AO42: {=SUM(IF(Period=AO$4,IF(Category=$A$8,IF(Provider=$B42,Score))))} -> 0 | AQ42: {=SUM(IF(Period=AO$4,IF(Category=$A$8,IF(Provider=$B42,Responses))))} -> 0 | AS42: =AO42*(AQ42/SUM(AQ$9:AQ$42)) -> 0 | AU42: =AO42*(AQ42/(SUM(AQ$9:AQ$42)+SUM(AQ$48:AQ$81)+SUM(AQ$87:AQ$120)+SUM(AQ$126:AQ$159)+SUM(AQ$165:AQ$198)+SUM(AQ$204:AQ$237))) -> 0 | AW42: {=SUM(IF(Period=AW$4,IF(Category=$A$8,IF(Provider=$B42,Score))))} -> 0 | AY42: {=SUM(IF(Period=AW$4,IF(Category=$A$8,IF(Provider=$B42,Responses))))} -> 0 | BA42: =AW42*(AY42/SUM(AY$9:AY$42)) -> 0 | BC42: =AW42*(AY42/(SUM(AY$9:AY$42)+SUM(AY$48:AY$81)+SUM(AY$87:AY$120)+SUM(AY$126:AY$159)+SUM(AY$165:AY$198)+SUM(AY$204:AY$237))) -> 0 | BE42: {=SUM(IF(Period=BE$4,IF(Category=$A$8,IF(Provider=$B42,Score))))} -> 0 | BG42: {=SUM(IF(Period=BE$4,IF(Category=$A$8,IF(Provider=$B42,Responses))))} -> 0 | BI42: =BE42*(BG42/SUM(BG$9:BG$42)) -> 0 | BK42: =BE42*(BG42/(SUM(BG$9:BG$42)+SUM(BG$48:BG$81)+SUM(BG$87:BG$120)+SUM(BG$126:BG$159)+SUM(BG$165:BG$198)+SUM(BG$204:BG$237))) -> 0 | BM42: {=SUM(IF(Period=BM$4,IF(Category=$A$8,IF(Provider=$B42,Score))))} -> 0 | BO42: {=SUM(IF(Period=BM$4,IF(Category=$A$8,IF(Provider=$B42,Responses))))} -> 0 | BQ42: =BM42*(BO42/SUM(BO$9:BO$42)) -> 0 | BS42: =BM42*(BO42/(SUM(BO$9:BO$42)+SUM(BO$48:BO$81)+SUM(BO$87:BO$120)+SUM(BO$126:BO$159)+SUM(BO$165:BO$198)+SUM(BO$204:BO$237))) -> 0 | BU42: {=SUM(IF(Period=BU$4,IF(Category=$A$8,IF(Provider=$B42,Score))))} -> 0 | BW42: {=SUM(IF(Period=BU$4,IF(Category=$A$8,IF(Provider=$B42,Responses))))} -> 0 | BY42: =BU42*(BW42/SUM(BW$9:BW$42)) -> 0 | CA42: =BU42*(BW42/(SUM(BW$9:BW$42)+SUM(BW$48:BW$81)+SUM(BW$87:BW$120)+SUM(BW$126:BW$159)+SUM(BW$165:BW$198)+SUM(BW$204:BW$237))) -> 0
B43: Average for Category: | C43: 0 | E43: 0 | G43: 0 | I43: =SUM(M9:M42) -> 72.256 | K43: =AVERAGEIF(K9:K42,"<>0") -> 6.25 | Q43: =SUM(U9:U42) -> 76.200532 | S43: =AVERAGEIF(S9:S42,"<>0") -> 6.2666667 | Y43: =SUM(AC9:AC42) -> 76.067763 | AA43: =AVERAGEIF(AA9:AA42,"<>0") -> 9.8064516 | AG43: =SUM(AK9:AK42) -> 80.762891 | AI43: =AVERAGEIF(AI9:AI42,"<>0") -> 7.7575758 | AO43: =SUM(AS9:AS42) -> 76.900581 | AQ43: =AVERAGEIF(AQ9:AQ42,"<>0") -> 5.7333333 | AW43: =SUM(BA9:BA42) -> 79.611982 | AY43: =AVERAGEIF(AY9:AY42,"<>0") -> 6.78125 | BE43: =SUM(BI9:BI42) -> 80.208085 | BG43: =AVERAGEIF(BG9:BG42,"<>0") -> 7.5806452 | BM43: =SUM(BQ9:BQ42) -> 84.273707 | BO43: =AVERAGEIF(BO9:BO42,"<>0") -> 7.25 | BU43: =SUM(BY9:BY42) -> 78.926446 | BW43: =AVERAGEIF(BW9:BW42,"<>0") -> 7.5625
B44: Median Values: | I44: {=MEDIAN(IF(I9:I42<>0,I9:I42))} -> 78.2 | K44: {=MEDIAN(IF(K9:K42<>0,K9:K42))} -> 6 | Q44: {=MEDIAN(IF(Q9:Q42<>0,Q9:Q42))} -> 80.65 | S44: {=MEDIAN(IF(S9:S42<>0,S9:S42))} -> 6 | Y44: {=MEDIAN(IF(Y9:Y42<>0,Y9:Y42))} -> 77.1 | AA44: {=MEDIAN(IF(AA9:AA42<>0,AA9:AA42))} -> 9 | AG44: {=MEDIAN(IF(AG9:AG42<>0,AG9:AG42))} -> 81.3 | AI44: {=MEDIAN(IF(AI9:AI42<>0,AI9:AI42))} -> 8 | AO44: {=MEDIAN(IF(AO9:AO42<>0,AO9:AO42))} -> 80.25 | AQ44: {=MEDIAN(IF(AQ9:AQ42<>0,AQ9:AQ42))} -> 5.5 | AW44: {=MEDIAN(IF(AW9:AW42<>0,AW9:AW42))} -> 80.65 | AY44: {=MEDIAN(IF(AY9:AY42<>0,AY9:AY42))} -> 6 | BE44: {=MEDIAN(IF(BE9:BE42<>0,BE9:BE42))} -> 83.3 | BG44: {=MEDIAN(IF(BG9:BG42<>0,BG9:BG42))} -> 8 | BM44: {=MEDIAN(IF(BM9:BM42<>0,BM9:BM42))} -> 87.1 | BO44: {=MEDIAN(IF(BO9:BO42<>0,BO9:BO42))} -> 7 | BU44: {=MEDIAN(IF(BU9:BU42<>0,BU9:BU42))} -> 79.3 | BW44: {=MEDIAN(IF(BW9:BW42<>0,BW9:BW42))} -> 7
B45: Subtotal n: | K45: =SUM(K9:K42) -> 200 | S45: =SUM(S9:S42) -> 188 | AA45: =SUM(AA9:AA42) -> 304 | AI45: =SUM(AI9:AI42) -> 256 | AQ45: =SUM(AQ9:AQ42) -> 172 | AY45: =SUM(AY9:AY42) -> 217 | BG45: =SUM(BG9:BG42) -> 235 | BO45: =SUM(BO9:BO42) -> 232 | BW45: =SUM(BW9:BW42) -> 242
A47: Doctor took time to listen
B48: ALAN ITZKOWITZ | C48: 0 | E48: 0 | G48: 0 | I48: {=SUM(IF(Period=I$4,IF(Category=$A$47,IF(Provider=$B48,Score))))} -> 89.3 | K48: {=SUM(IF(Period=I$4,IF(Category=$A$47,IF(Provider=$B48,Responses))))} -> 7 | M48: =I48*(K48/SUM(K$48:K$81)) -> 3.0945545 | O48: =I48*(K48/(SUM(K$9:K$42)+SUM(K$48:K$81)+SUM(K$87:K$120)+SUM(K$126:K$159)+SUM(K$165:K$198)+SUM(K$204:K$237))) -> 0.51703888 | Q48: {=SUM(IF(Period=Q$4,IF(Category=$A$47,IF(Provider=$B48,Score))))} -> 81.3 | S48: {=SUM(IF(Period=Q$4,IF(Category=$A$47,IF(Provider=$B48,Responses))))} -> 4 | U48: =Q48*(S48/SUM(S$48:S$81)) -> 1.7297872 | W48: =Q48*(S48/(SUM(S$9:S$42)+SUM(S$48:S$81)+SUM(S$87:S$120)+SUM(S$126:S$159)+SUM(S$165:S$198)+SUM(S$204:S$237))) -> 0.28983957 | Y48: {=SUM(IF(Period=Y$4,IF(Category=$A$47,IF(Provider=$B48,Score))))} -> 87.5 | AA48: {=SUM(IF(Period=Y$4,IF(Category=$A$47,IF(Provider=$B48,Responses))))} -> 14 | AC48: =Y48*(AA48/SUM(AA$48:AA$81)) -> 4.0562914 | AE48: =Y48*(AA48/(SUM(AA$9:AA$42)+SUM(AA$48:AA$81)+SUM(AA$87:AA$120)+SUM(AA$126:AA$159)+SUM(AA$165:AA$198)+SUM(AA$204:AA$237))) -> 0.67567568 | AG48: {=SUM(IF(Period=AG$4,IF(Category=$A$47,IF(Provider=$B48,Score))))} -> 100 | AI48: {=SUM(IF(Period=AG$4,IF(Category=$A$47,IF(Provider=$B48,Responses))))} -> 3 | AK48: =AG48*(AI48/SUM(AI$48:AI$81)) -> 1.1627907 | AM48: =AG48*(AI48/(SUM(AI$9:AI$42)+SUM(AI$48:AI$81)+SUM(AI$87:AI$120)+SUM(AI$126:AI$159)+SUM(AI$165:AI$198)+SUM(AI$204:AI$237))) -> 0.19430052 | AO48: {=SUM(IF(Period=AO$4,IF(Category=$A$47,IF(Provider=$B48,Score))))} -> 100 | AQ48: {=SUM(IF(Period=AO$4,IF(Category=$A$47,IF(Provider=$B48,Responses))))} -> 2 | AS48: =AO48*(AQ48/SUM(AQ$48:AQ$81)) -> 1.1695906 | AU48: =AO48*(AQ48/(SUM(AQ$9:AQ$42)+SUM(AQ$48:AQ$81)+SUM(AQ$87:AQ$120)+SUM(AQ$126:AQ$159)+SUM(AQ$165:AQ$198)+SUM(AQ$204:AQ$237))) -> 0.19493177 | AW48: {=SUM(IF(Period=AW$4,IF(Category=$A$47,IF(Provider=$B48,Score))))} -> 90 | AY48: {=SUM(IF(Period=AW$4,IF(Category=$A$47,IF(Provider=$B48,Responses))))} -> 5 | BA48: =AW48*(AY48/SUM(AY$48:AY$81)) -> 2.0737327 | BC48: =AW48*(AY48/(SUM(AY$9:AY$42)+SUM(AY$48:AY$81)+SUM(AY$87:AY$120)+SUM(AY$126:AY$159)+SUM(AY$165:AY$198)+SUM(AY$204:AY$237))) -> 0.34562212 | BE48: {=SUM(IF(Period=BE$4,IF(Category=$A$47,IF(Provider=$B48,Score))))} -> 88.9 | BG48: {=SUM(IF(Period=BE$4,IF(Category=$A$47,IF(Provider=$B48,Responses))))} -> 9 | BI48: =BE48*(BG48/SUM(BG$48:BG$81)) -> 3.4046809 | BK48: =BE48*(BG48/(SUM(BG$9:BG$42)+SUM(BG$48:BG$81)+SUM(BG$87:BG$120)+SUM(BG$126:BG$159)+SUM(BG$165:BG$198)+SUM(BG$204:BG$237))) -> 0.5654417 | BM48: {=SUM(IF(Period=BM$4,IF(Category=$A$47,IF(Provider=$B48,Score))))} -> 100 | BO48: {=SUM(IF(Period=BM$4,IF(Category=$A$47,IF(Provider=$B48,Responses))))} -> 6 | BQ48: =BM48*(BO48/SUM(BO$48:BO$81)) -> 2.5974026 | BS48: =BM48*(BO48/(SUM(BO$9:BO$42)+SUM(BO$48:BO$81)+SUM(BO$87:BO$120)+SUM(BO$126:BO$159)+SUM(BO$165:BO$198)+SUM(BO$204:BO$237))) -> 0.43290043 | BU48: {=SUM(IF(Period=BU$4,IF(Category=$A$47,IF(Provider=$B48,Score))))} -> 90 | BW48: {=SUM(IF(Period=BU$4,IF(Category=$A$47,IF(Provider=$B48,Responses))))} -> 5 | BY48: =BU48*(BW48/SUM(BW$48:BW$81)) -> 1.8907563 | CA48: =BU48*(BW48/(SUM(BW$9:BW$42)+SUM(BW$48:BW$81)+SUM(BW$87:BW$120)+SUM(BW$126:BW$159)+SUM(BW$165:BW$198)+SUM(BW$204:BW$237))) -> 0.31098825
B49: ALEX PALMA | C49: 0 | E49: 0 | G49: 0 | I49: {=SUM(IF(Period=I$4,IF(Category=$A$47,IF(Provider=$B49,Score))))} -> 82.1 | K49: {=SUM(IF(Period=I$4,IF(Category=$A$47,IF(Provider=$B49,Responses))))} -> 7 | M49: =I49*(K49/SUM(K$48:K$81)) -> 2.8450495 | O49: =I49*(K49/(SUM(K$9:K$42)+SUM(K$48:K$81)+SUM(K$87:K$120)+SUM(K$126:K$159)+SUM(K$165:K$198)+SUM(K$204:K$237))) -> 0.47535153 | Q49: {=SUM(IF(Period=Q$4,IF(Category=$A$47,IF(Provider=$B49,Score))))} -> 92.5 | S49: {=SUM(IF(Period=Q$4,IF(Category=$A$47,IF(Provider=$B49,Responses))))} -> 10 | U49: =Q49*(S49/SUM(S$48:S$81)) -> 4.9202128 | W49: =Q49*(S49/(SUM(S$9:S$42)+SUM(S$48:S$81)+SUM(S$87:S$120)+SUM(S$126:S$159)+SUM(S$165:S$198)+SUM(S$204:S$237))) -> 0.82442068 | Y49: {=SUM(IF(Period=Y$4,IF(Category=$A$47,IF(Provider=$B49,Score))))} -> 83.3 | AA49: {=SUM(IF(Period=Y$4,IF(Category=$A$47,IF(Provider=$B49,Responses))))} -> 9 | AC49: =Y49*(AA49/SUM(AA$48:AA$81)) -> 2.4824503 | AE49: =Y49*(AA49/(SUM(AA$9:AA$42)+SUM(AA$48:AA$81)+SUM(AA$87:AA$120)+SUM(AA$126:AA$159)+SUM(AA$165:AA$198)+SUM(AA$204:AA$237))) -> 0.41351351 | AG49: {=SUM(IF(Period=AG$4,IF(Category=$A$47,IF(Provider=$B49,Score))))} -> 100 | AI49: {=SUM(IF(Period=AG$4,IF(Category=$A$47,IF(Provider=$B49,Responses))))} -> 6 | AK49: =AG49*(AI49/SUM(AI$48:AI$81)) -> 2.3255814 | AM49: =AG49*(AI49/(SUM(AI$9:AI$42)+SUM(AI$48:AI$81)+SUM(AI$87:AI$120)+SUM(AI$126:AI$159)+SUM(AI$165:AI$198)+SUM(AI$204:AI$237))) -> 0.38860104 | AO49: {=SUM(IF(Period=AO$4,IF(Category=$A$47,IF(Provider=$B49,Score))))} -> 31.3 | AQ49: {=SUM(IF(Period=AO$4,IF(Category=$A$47,IF(Provider=$B49,Responses))))} -> 4 | AS49: =AO49*(AQ49/SUM(AQ$48:AQ$81)) -> 0.73216374 | AU49: =AO49*(AQ49/(SUM(AQ$9:AQ$42)+SUM(AQ$48:AQ$81)+SUM(AQ$87:AQ$120)+SUM(AQ$126:AQ$159)+SUM(AQ$165:AQ$198)+SUM(AQ$204:AQ$237))) -> 0.12202729 | AW49: {=SUM(IF(Period=AW$4,IF(Category=$A$47,IF(Provider=$B49,Score))))} -> 85.7 | AY49: {=SUM(IF(Period=AW$4,IF(Category=$A$47,IF(Provider=$B49,Responses))))} -> 7 | BA49: =AW49*(AY49/SUM(AY$48:AY$81)) -> 2.7645161 | BC49: =AW49*(AY49/(SUM(AY$9:AY$42)+SUM(AY$48:AY$81)+SUM(AY$87:AY$120)+SUM(AY$126:AY$159)+SUM(AY$165:AY$198)+SUM(AY$204:AY$237))) -> 0.46075269 | BE49: {=SUM(IF(Period=BE$4,IF(Category=$A$47,IF(Provider=$B49,Score))))} -> 100 | BG49: {=SUM(IF(Period=BE$4,IF(Category=$A$47,IF(Provider=$B49,Responses))))} -> 8 | BI49: =BE49*(BG49/SUM(BG$48:BG$81)) -> 3.4042553 | BK49: =BE49*(BG49/(SUM(BG$9:BG$42)+SUM(BG$48:BG$81)+SUM(BG$87:BG$120)+SUM(BG$126:BG$159)+SUM(BG$165:BG$198)+SUM(BG$204:BG$237))) -> 0.56537102 | BM49: {=SUM(IF(Period=BM$4,IF(Category=$A$47,IF(Provider=$B49,Score))))} -> 87.5 | BO49: {=SUM(IF(Period=BM$4,IF(Category=$A$47,IF(Provider=$B49,Responses))))} -> 6 | BQ49: =BM49*(BO49/SUM(BO$48:BO$81)) -> 2.2727273 | BS49: =BM49*(BO49/(SUM(BO$9:BO$42)+SUM(BO$48:BO$81)+SUM(BO$87:BO$120)+SUM(BO$126:BO$159)+SUM(BO$165:BO$198)+SUM(BO$204:BO$237))) -> 0.37878788 | BU49: {=SUM(IF(Period=BU$4,IF(Category=$A$47,IF(Provider=$B49,Score))))} -> 84.1 | BW49: {=SUM(IF(Period=BU$4,IF(Category=$A$47,IF(Provider=$B49,Responses))))} -> 11 | BY49: =BU49*(BW49/SUM(BW$48:BW$81)) -> 3.8869748 | CA49: =BU49*(BW49/(SUM(BW$9:BW$42)+SUM(BW$48:BW$81)+SUM(BW$87:BW$120)+SUM(BW$126:BW$159)+SUM(BW$165:BW$198)+SUM(BW$204:BW$237))) -> 0.63932274
B50: ALEXANDER GARCIA | C50: 0 | E50: 0 | G50: 0 | I50: {=SUM(IF(Period=I$4,IF(Category=$A$47,IF(Provider=$B50,Score))))} -> 92.9 | K50: {=SUM(IF(Period=I$4,IF(Category=$A$47,IF(Provider=$B50,Responses))))} -> 7 | M50: =I50*(K50/SUM(K$48:K$81)) -> 3.2193069 | O50: =I50*(K50/(SUM(K$9:K$42)+SUM(K$48:K$81)+SUM(K$87:K$120)+SUM(K$126:K$159)+SUM(K$165:K$198)+SUM(K$204:K$237))) -> 0.53788255 | Q50: {=SUM(IF(Period=Q$4,IF(Category=$A$47,IF(Provider=$B50,Score))))} -> 91.7 | S50: {=SUM(IF(Period=Q$4,IF(Category=$A$47,IF(Provider=$B50,Responses))))} -> 6 | U50: =Q50*(S50/SUM(S$48:S$81)) -> 2.9265957 | W50: =Q50*(S50/(SUM(S$9:S$42)+SUM(S$48:S$81)+SUM(S$87:S$120)+SUM(S$126:S$159)+SUM(S$165:S$198)+SUM(S$204:S$237))) -> 0.49037433 | Y50: {=SUM(IF(Period=Y$4,IF(Category=$A$47,IF(Provider=$B50,Score))))} -> 81.3 | AA50: {=SUM(IF(Period=Y$4,IF(Category=$A$47,IF(Provider=$B50,Responses))))} -> 8 | AC50: =Y50*(AA50/SUM(AA$48:AA$81)) -> 2.1536424 | AE50: =Y50*(AA50/(SUM(AA$9:AA$42)+SUM(AA$48:AA$81)+SUM(AA$87:AA$120)+SUM(AA$126:AA$159)+SUM(AA$165:AA$198)+SUM(AA$204:AA$237))) -> 0.35874242 | AG50: {=SUM(IF(Period=AG$4,IF(Category=$A$47,IF(Provider=$B50,Score))))} -> 96.4 | AI50: {=SUM(IF(Period=AG$4,IF(Category=$A$47,IF(Provider=$B50,Responses))))} -> 7 | AK50: =AG50*(AI50/SUM(AI$48:AI$81)) -> 2.6155039 | AM50: =AG50*(AI50/(SUM(AI$9:AI$42)+SUM(AI$48:AI$81)+SUM(AI$87:AI$120)+SUM(AI$126:AI$159)+SUM(AI$165:AI$198)+SUM(AI$204:AI$237))) -> 0.43704663 | AO50: {=SUM(IF(Period=AO$4,IF(Category=$A$47,IF(Provider=$B50,Score))))} -> 68.8 | AQ50: {=SUM(IF(Period=AO$4,IF(Category=$A$47,IF(Provider=$B50,Responses))))} -> 8 | AS50: =AO50*(AQ50/SUM(AQ$48:AQ$81)) -> 3.2187135 | AU50: =AO50*(AQ50/(SUM(AQ$9:AQ$42)+SUM(AQ$48:AQ$81)+SUM(AQ$87:AQ$120)+SUM(AQ$126:AQ$159)+SUM(AQ$165:AQ$198)+SUM(AQ$204:AQ$237))) -> 0.53645224 | AW50: {=SUM(IF(Period=AW$4,IF(Category=$A$47,IF(Provider=$B50,Score))))} -> 95.8 | AY50: {=SUM(IF(Period=AW$4,IF(Category=$A$47,IF(Provider=$B50,Responses))))} -> 6 | BA50: =AW50*(AY50/SUM(AY$48:AY$81)) -> 2.6488479 | BC50: =AW50*(AY50/(SUM(AY$9:AY$42)+SUM(AY$48:AY$81)+SUM(AY$87:AY$120)+SUM(AY$126:AY$159)+SUM(AY$165:AY$198)+SUM(AY$204:AY$237))) -> 0.44147465 | BE50: {=SUM(IF(Period=BE$4,IF(Category=$A$47,IF(Provider=$B50,Score))))} -> 87.5 | BG50: {=SUM(IF(Period=BE$4,IF(Category=$A$47,IF(Provider=$B50,Responses))))} -> 8 | BI50: =BE50*(BG50/SUM(BG$48:BG$81)) -> 2.9787234 | BK50: =BE50*(BG50/(SUM(BG$9:BG$42)+SUM(BG$48:BG$81)+SUM(BG$87:BG$120)+SUM(BG$126:BG$159)+SUM(BG$165:BG$198)+SUM(BG$204:BG$237))) -> 0.49469965 | BM50: {=SUM(IF(Period=BM$4,IF(Category=$A$47,IF(Provider=$B50,Score))))} -> 68.8 | BO50: {=SUM(IF(Period=BM$4,IF(Category=$A$47,IF(Provider=$B50,Responses))))} -> 8 | BQ50: =BM50*(BO50/SUM(BO$48:BO$81)) -> 2.382684 | BS50: =BM50*(BO50/(SUM(BO$9:BO$42)+SUM(BO$48:BO$81)+SUM(BO$87:BO$120)+SUM(BO$126:BO$159)+SUM(BO$165:BO$198)+SUM(BO$204:BO$237))) -> 0.397114 | BU50: {=SUM(IF(Period=BU$4,IF(Category=$A$47,IF(Provider=$B50,Score))))} -> 79.2 | BW50: {=SUM(IF(Period=BU$4,IF(Category=$A$47,IF(Provider=$B50,Responses))))} -> 6 | BY50: =BU50*(BW50/SUM(BW$48:BW$81)) -> 1.9966387 | CA50: =BU50*(BW50/(SUM(BW$9:BW$42)+SUM(BW$48:BW$81)+SUM(BW$87:BW$120)+SUM(BW$126:BW$159)+SUM(BW$165:BW$198)+SUM(BW$204:BW$237))) -> 0.32840359
B51: ANDREA J BETANCOURT | C51: 0 | E51: 0 | G51: 0 | I51: {=SUM(IF(Period=I$4,IF(Category=$A$47,IF(Provider=$B51,Score))))} -> 68.8 | K51: {=SUM(IF(Period=I$4,IF(Category=$A$47,IF(Provider=$B51,Responses))))} -> 4 | M51: =I51*(K51/SUM(K$48:K$81)) -> 1.3623762 | O51: =I51*(K51/(SUM(K$9:K$42)+SUM(K$48:K$81)+SUM(K$87:K$120)+SUM(K$126:K$159)+SUM(K$165:K$198)+SUM(K$204:K$237))) -> 0.22762614 | Q51: {=SUM(IF(Period=Q$4,IF(Category=$A$47,IF(Provider=$B51,Score))))} -> 85.7 | S51: {=SUM(IF(Period=Q$4,IF(Category=$A$47,IF(Provider=$B51,Responses))))} -> 7 | U51: =Q51*(S51/SUM(S$48:S$81)) -> 3.1909574 | W51: =Q51*(S51/(SUM(S$9:S$42)+SUM(S$48:S$81)+SUM(S$87:S$120)+SUM(S$126:S$159)+SUM(S$165:S$198)+SUM(S$204:S$237))) -> 0.53467023 | Y51: {=SUM(IF(Period=Y$4,IF(Category=$A$47,IF(Provider=$B51,Score))))} -> 81.8 | AA51: {=SUM(IF(Period=Y$4,IF(Category=$A$47,IF(Provider=$B51,Responses))))} -> 11 | AC51: =Y51*(AA51/SUM(AA$48:AA$81)) -> 2.9794702 | AE51: =Y51*(AA51/(SUM(AA$9:AA$42)+SUM(AA$48:AA$81)+SUM(AA$87:AA$120)+SUM(AA$126:AA$159)+SUM(AA$165:AA$198)+SUM(AA$204:AA$237))) -> 0.49630447 | AG51: {=SUM(IF(Period=AG$4,IF(Category=$A$47,IF(Provider=$B51,Score))))} -> 75 | AI51: {=SUM(IF(Period=AG$4,IF(Category=$A$47,IF(Provider=$B51,Responses))))} -> 5 | AK51: =AG51*(AI51/SUM(AI$48:AI$81)) -> 1.4534884 | AM51: =AG51*(AI51/(SUM(AI$9:AI$42)+SUM(AI$48:AI$81)+SUM(AI$87:AI$120)+SUM(AI$126:AI$159)+SUM(AI$165:AI$198)+SUM(AI$204:AI$237))) -> 0.24287565 | AO51: {=SUM(IF(Period=AO$4,IF(Category=$A$47,IF(Provider=$B51,Score))))} -> 88.9 | AQ51: {=SUM(IF(Period=AO$4,IF(Category=$A$47,IF(Provider=$B51,Responses))))} -> 9 | AS51: =AO51*(AQ51/SUM(AQ$48:AQ$81)) -> 4.6789474 | AU51: =AO51*(AQ51/(SUM(AQ$9:AQ$42)+SUM(AQ$48:AQ$81)+SUM(AQ$87:AQ$120)+SUM(AQ$126:AQ$159)+SUM(AQ$165:AQ$198)+SUM(AQ$204:AQ$237))) -> 0.77982456 | AW51: {=SUM(IF(Period=AW$4,IF(Category=$A$47,IF(Provider=$B51,Score))))} -> 62.5 | AY51: {=SUM(IF(Period=AW$4,IF(Category=$A$47,IF(Provider=$B51,Responses))))} -> 2 | BA51: =AW51*(AY51/SUM(AY$48:AY$81)) -> 0.57603687 | BC51: =AW51*(AY51/(SUM(AY$9:AY$42)+SUM(AY$48:AY$81)+SUM(AY$87:AY$120)+SUM(AY$126:AY$159)+SUM(AY$165:AY$198)+SUM(AY$204:AY$237))) -> 0.096006144 | BE51: {=SUM(IF(Period=BE$4,IF(Category=$A$47,IF(Provider=$B51,Score))))} -> 75 | BG51: {=SUM(IF(Period=BE$4,IF(Category=$A$47,IF(Provider=$B51,Responses))))} -> 2 | BI51: =BE51*(BG51/SUM(BG$48:BG$81)) -> 0.63829787 | BK51: =BE51*(BG51/(SUM(BG$9:BG$42)+SUM(BG$48:BG$81)+SUM(BG$87:BG$120)+SUM(BG$126:BG$159)+SUM(BG$165:BG$198)+SUM(BG$204:BG$237))) -> 0.10600707 | BM51: {=SUM(IF(Period=BM$4,IF(Category=$A$47,IF(Provider=$B51,Score))))} -> 89.3 | BO51: {=SUM(IF(Period=BM$4,IF(Category=$A$47,IF(Provider=$B51,Responses))))} -> 7 | BQ51: =BM51*(BO51/SUM(BO$48:BO$81)) -> 2.7060606 | BS51: =BM51*(BO51/(SUM(BO$9:BO$42)+SUM(BO$48:BO$81)+SUM(BO$87:BO$120)+SUM(BO$126:BO$159)+SUM(BO$165:BO$198)+SUM(BO$204:BO$237))) -> 0.4510101 | BU51: {=SUM(IF(Period=BU$4,IF(Category=$A$47,IF(Provider=$B51,Score))))} -> 93.8 | BW51: {=SUM(IF(Period=BU$4,IF(Category=$A$47,IF(Provider=$B51,Responses))))} -> 8 | BY51: =BU51*(BW51/SUM(BW$48:BW$81)) -> 3.1529412 | CA51: =BU51*(BW51/(SUM(BW$9:BW$42)+SUM(BW$48:BW$81)+SUM(BW$87:BW$120)+SUM(BW$126:BW$159)+SUM(BW$165:BW$198)+SUM(BW$204:BW$237))) -> 0.51859019
B52: ANDREW MASON | C52: 0 | E52: 0 | G52: 0 | I52: {=SUM(IF(Period=I$4,IF(Category=$A$47,IF(Provider=$B52,Score))))} -> 85.7 | K52: {=SUM(IF(Period=I$4,IF(Category=$A$47,IF(Provider=$B52,Responses))))} -> 7 | M52: =I52*(K52/SUM(K$48:K$81)) -> 2.969802 | O52: =I52*(K52/(SUM(K$9:K$42)+SUM(K$48:K$81)+SUM(K$87:K$120)+SUM(K$126:K$159)+SUM(K$165:K$198)+SUM(K$204:K$237))) -> 0.4961952 | Q52: {=SUM(IF(Period=Q$4,IF(Category=$A$47,IF(Provider=$B52,Score))))} -> 83.3 | S52: {=SUM(IF(Period=Q$4,IF(Category=$A$47,IF(Provider=$B52,Responses))))} -> 6 | U52: =Q52*(S52/SUM(S$48:S$81)) -> 2.6585106 | W52: =Q52*(S52/(SUM(S$9:S$42)+SUM(S$48:S$81)+SUM(S$87:S$120)+SUM(S$126:S$159)+SUM(S$165:S$198)+SUM(S$204:S$237))) -> 0.44545455 | Y52: {=SUM(IF(Period=Y$4,IF(Category=$A$47,IF(Provider=$B52,Score))))} -> 81.3 | AA52: {=SUM(IF(Period=Y$4,IF(Category=$A$47,IF(Provider=$B52,Responses))))} -> 12 | AC52: =Y52*(AA52/SUM(AA$48:AA$81)) -> 3.2304636 | AE52: =Y52*(AA52/(SUM(AA$9:AA$42)+SUM(AA$48:AA$81)+SUM(AA$87:AA$120)+SUM(AA$126:AA$159)+SUM(AA$165:AA$198)+SUM(AA$204:AA$237))) -> 0.53811362 | AG52: {=SUM(IF(Period=AG$4,IF(Category=$A$47,IF(Provider=$B52,Score))))} -> 88.9 | AI52: {=SUM(IF(Period=AG$4,IF(Category=$A$47,IF(Provider=$B52,Responses))))} -> 9 | AK52: =AG52*(AI52/SUM(AI$48:AI$81)) -> 3.1011628 | AM52: =AG52*(AI52/(SUM(AI$9:AI$42)+SUM(AI$48:AI$81)+SUM(AI$87:AI$120)+SUM(AI$126:AI$159)+SUM(AI$165:AI$198)+SUM(AI$204:AI$237))) -> 0.51819948 | AO52: {=SUM(IF(Period=AO$4,IF(Category=$A$47,IF(Provider=$B52,Score))))} -> 100 | AQ52: {=SUM(IF(Period=AO$4,IF(Category=$A$47,IF(Provider=$B52,Responses))))} -> 4 | AS52: =AO52*(AQ52/SUM(AQ$48:AQ$81)) -> 2.3391813 | AU52: =AO52*(AQ52/(SUM(AQ$9:AQ$42)+SUM(AQ$48:AQ$81)+SUM(AQ$87:AQ$120)+SUM(AQ$126:AQ$159)+SUM(AQ$165:AQ$198)+SUM(AQ$204:AQ$237))) -> 0.38986355 | AW52: {=SUM(IF(Period=AW$4,IF(Category=$A$47,IF(Provider=$B52,Score))))} -> 83.3 | AY52: {=SUM(IF(Period=AW$4,IF(Category=$A$47,IF(Provider=$B52,Responses))))} -> 6 | BA52: =AW52*(AY52/SUM(AY$48:AY$81)) -> 2.3032258 | BC52: =AW52*(AY52/(SUM(AY$9:AY$42)+SUM(AY$48:AY$81)+SUM(AY$87:AY$120)+SUM(AY$126:AY$159)+SUM(AY$165:AY$198)+SUM(AY$204:AY$237))) -> 0.38387097 | BE52: {=SUM(IF(Period=BE$4,IF(Category=$A$47,IF(Provider=$B52,Score))))} -> 62.5 | BG52: {=SUM(IF(Period=BE$4,IF(Category=$A$47,IF(Provider=$B52,Responses))))} -> 6 | BI52: =BE52*(BG52/SUM(BG$48:BG$81)) -> 1.5957447 | BK52: =BE52*(BG52/(SUM(BG$9:BG$42)+SUM(BG$48:BG$81)+SUM(BG$87:BG$120)+SUM(BG$126:BG$159)+SUM(BG$165:BG$198)+SUM(BG$204:BG$237))) -> 0.26501767 | BM52: {=SUM(IF(Period=BM$4,IF(Category=$A$47,IF(Provider=$B52,Score))))} -> 75 | BO52: {=SUM(IF(Period=BM$4,IF(Category=$A$47,IF(Provider=$B52,Responses))))} -> 7 | BQ52: =BM52*(BO52/SUM(BO$48:BO$81)) -> 2.2727273 | BS52: =BM52*(BO52/(SUM(BO$9:BO$42)+SUM(BO$48:BO$81)+SUM(BO$87:BO$120)+SUM(BO$126:BO$159)+SUM(BO$165:BO$198)+SUM(BO$204:BO$237))) -> 0.37878788 | BU52: {=SUM(IF(Period=BU$4,IF(Category=$A$47,IF(Provider=$B52,Score))))} -> 96.4 | BW52: {=SUM(IF(Period=BU$4,IF(Category=$A$47,IF(Provider=$B52,Responses))))} -> 7 | BY52: =BU52*(BW52/SUM(BW$48:BW$81)) -> 2.8352941 | CA52: =BU52*(BW52/(SUM(BW$9:BW$42)+SUM(BW$48:BW$81)+SUM(BW$87:BW$120)+SUM(BW$126:BW$159)+SUM(BW$165:BW$198)+SUM(BW$204:BW$237))) -> 0.46634416
B53: ANTONY FRIEDMAN | C53: 0 | E53: 0 | G53: 0 | I53: {=SUM(IF(Period=I$4,IF(Category=$A$47,IF(Provider=$B53,Score))))} -> 56.3 | K53: {=SUM(IF(Period=I$4,IF(Category=$A$47,IF(Provider=$B53,Responses))))} -> 4 | M53: =I53*(K53/SUM(K$48:K$81)) -> 1.1148515 | O53: =I53*(K53/(SUM(K$9:K$42)+SUM(K$48:K$81)+SUM(K$87:K$120)+SUM(K$126:K$159)+SUM(K$165:K$198)+SUM(K$204:K$237))) -> 0.18626964 | Q53: {=SUM(IF(Period=Q$4,IF(Category=$A$47,IF(Provider=$B53,Score))))} -> 45 | S53: {=SUM(IF(Period=Q$4,IF(Category=$A$47,IF(Provider=$B53,Responses))))} -> 10 | U53: =Q53*(S53/SUM(S$48:S$81)) -> 2.393617 | W53: =Q53*(S53/(SUM(S$9:S$42)+SUM(S$48:S$81)+SUM(S$87:S$120)+SUM(S$126:S$159)+SUM(S$165:S$198)+SUM(S$204:S$237))) -> 0.40106952 | Y53: {=SUM(IF(Period=Y$4,IF(Category=$A$47,IF(Provider=$B53,Score))))} -> 70 | AA53: {=SUM(IF(Period=Y$4,IF(Category=$A$47,IF(Provider=$B53,Responses))))} -> 5 | AC53: =Y53*(AA53/SUM(AA$48:AA$81)) -> 1.1589404 | AE53: =Y53*(AA53/(SUM(AA$9:AA$42)+SUM(AA$48:AA$81)+SUM(AA$87:AA$120)+SUM(AA$126:AA$159)+SUM(AA$165:AA$198)+SUM(AA$204:AA$237))) -> 0.19305019 | AG53: {=SUM(IF(Period=AG$4,IF(Category=$A$47,IF(Provider=$B53,Score))))} -> 75 | AI53: {=SUM(IF(Period=AG$4,IF(Category=$A$47,IF(Provider=$B53,Responses))))} -> 1 | AK53: =AG53*(AI53/SUM(AI$48:AI$81)) -> 0.29069767 | AM53: =AG53*(AI53/(SUM(AI$9:AI$42)+SUM(AI$48:AI$81)+SUM(AI$87:AI$120)+SUM(AI$126:AI$159)+SUM(AI$165:AI$198)+SUM(AI$204:AI$237))) -> 0.04857513 | AO53: {=SUM(IF(Period=AO$4,IF(Category=$A$47,IF(Provider=$B53,Score))))} -> 75 | AQ53: {=SUM(IF(Period=AO$4,IF(Category=$A$47,IF(Provider=$B53,Responses))))} -> 6 | AS53: =AO53*(AQ53/SUM(AQ$48:AQ$81)) -> 2.6315789 | AU53: =AO53*(AQ53/(SUM(AQ$9:AQ$42)+SUM(AQ$48:AQ$81)+SUM(AQ$87:AQ$120)+SUM(AQ$126:AQ$159)+SUM(AQ$165:AQ$198)+SUM(AQ$204:AQ$237))) -> 0.43859649 | AW53: {=SUM(IF(Period=AW$4,IF(Category=$A$47,IF(Provider=$B53,Score))))} -> 68.8 | AY53: {=SUM(IF(Period=AW$4,IF(Category=$A$47,IF(Provider=$B53,Responses))))} -> 8 | BA53: =AW53*(AY53/SUM(AY$48:AY$81)) -> 2.5364055 | BC53: =AW53*(AY53/(SUM(AY$9:AY$42)+SUM(AY$48:AY$81)+SUM(AY$87:AY$120)+SUM(AY$126:AY$159)+SUM(AY$165:AY$198)+SUM(AY$204:AY$237))) -> 0.42273425 | BE53: {=SUM(IF(Period=BE$4,IF(Category=$A$47,IF(Provider=$B53,Score))))} -> 60 | BG53: {=SUM(IF(Period=BE$4,IF(Category=$A$47,IF(Provider=$B53,Responses))))} -> 15 | BI53: =BE53*(BG53/SUM(BG$48:BG$81)) -> 3.8297872 | BK53: =BE53*(BG53/(SUM(BG$9:BG$42)+SUM(BG$48:BG$81)+SUM(BG$87:BG$120)+SUM(BG$126:BG$159)+SUM(BG$165:BG$198)+SUM(BG$204:BG$237))) -> 0.6360424 | BM53: {=SUM(IF(Period=BM$4,IF(Category=$A$47,IF(Provider=$B53,Score))))} -> 84.1 | BO53: {=SUM(IF(Period=BM$4,IF(Category=$A$47,IF(Provider=$B53,Responses))))} -> 11 | BQ53: =BM53*(BO53/SUM(BO$48:BO$81)) -> 4.0047619 | BS53: =BM53*(BO53/(SUM(BO$9:BO$42)+SUM(BO$48:BO$81)+SUM(BO$87:BO$120)+SUM(BO$126:BO$159)+SUM(BO$165:BO$198)+SUM(BO$204:BO$237))) -> 0.66746032 | BU53: {=SUM(IF(Period=BU$4,IF(Category=$A$47,IF(Provider=$B53,Score))))} -> 65.6 | BW53: {=SUM(IF(Period=BU$4,IF(Category=$A$47,IF(Provider=$B53,Responses))))} -> 8 | BY53: =BU53*(BW53/SUM(BW$48:BW$81)) -> 2.205042 | CA53: =BU53*(BW53/(SUM(BW$9:BW$42)+SUM(BW$48:BW$81)+SUM(BW$87:BW$120)+SUM(BW$126:BW$159)+SUM(BW$165:BW$198)+SUM(BW$204:BW$237))) -> 0.36268141
B54: CHARLES SANZ | C54: 0 | E54: 0 | G54: 0 | I54: {=SUM(IF(Period=I$4,IF(Category=$A$47,IF(Provider=$B54,Score))))} -> 87.5 | K54: {=SUM(IF(Period=I$4,IF(Category=$A$47,IF(Provider=$B54,Responses))))} -> 4 | M54: =I54*(K54/SUM(K$48:K$81)) -> 1.7326733 | O54: =I54*(K54/(SUM(K$9:K$42)+SUM(K$48:K$81)+SUM(K$87:K$120)+SUM(K$126:K$159)+SUM(K$165:K$198)+SUM(K$204:K$237))) -> 0.28949545 | Q54: {=SUM(IF(Period=Q$4,IF(Category=$A$47,IF(Provider=$B54,Score))))} -> 83.3 | S54: {=SUM(IF(Period=Q$4,IF(Category=$A$47,IF(Provider=$B54,Responses))))} -> 3 | U54: =Q54*(S54/SUM(S$48:S$81)) -> 1.3292553 | W54: =Q54*(S54/(SUM(S$9:S$42)+SUM(S$48:S$81)+SUM(S$87:S$120)+SUM(S$126:S$159)+SUM(S$165:S$198)+SUM(S$204:S$237))) -> 0.22272727 | Y54: {=SUM(IF(Period=Y$4,IF(Category=$A$47,IF(Provider=$B54,Score))))} -> 96.9 | AA54: {=SUM(IF(Period=Y$4,IF(Category=$A$47,IF(Provider=$B54,Responses))))} -> 8 | AC54: =Y54*(AA54/SUM(AA$48:AA$81)) -> 2.5668874 | AE54: =Y54*(AA54/(SUM(AA$9:AA$42)+SUM(AA$48:AA$81)+SUM(AA$87:AA$120)+SUM(AA$126:AA$159)+SUM(AA$165:AA$198)+SUM(AA$204:AA$237))) -> 0.4275786 | AG54: {=SUM(IF(Period=AG$4,IF(Category=$A$47,IF(Provider=$B54,Score))))} -> 90.6 | AI54: {=SUM(IF(Period=AG$4,IF(Category=$A$47,IF(Provider=$B54,Responses))))} -> 8 | AK54: =AG54*(AI54/SUM(AI$48:AI$81)) -> 2.8093023 | AM54: =AG54*(AI54/(SUM(AI$9:AI$42)+SUM(AI$48:AI$81)+SUM(AI$87:AI$120)+SUM(AI$126:AI$159)+SUM(AI$165:AI$198)+SUM(AI$204:AI$237))) -> 0.46943005 | AO54: {=SUM(IF(Period=AO$4,IF(Category=$A$47,IF(Provider=$B54,Score))))} -> 83.3 | AQ54: {=SUM(IF(Period=AO$4,IF(Category=$A$47,IF(Provider=$B54,Responses))))} -> 3 | AS54: =AO54*(AQ54/SUM(AQ$48:AQ$81)) -> 1.4614035 | AU54: =AO54*(AQ54/(SUM(AQ$9:AQ$42)+SUM(AQ$48:AQ$81)+SUM(AQ$87:AQ$120)+SUM(AQ$126:AQ$159)+SUM(AQ$165:AQ$198)+SUM(AQ$204:AQ$237))) -> 0.24356725 | AW54: {=SUM(IF(Period=AW$4,IF(Category=$A$47,IF(Provider=$B54,Score))))} -> 91.7 | AY54: {=SUM(IF(Period=AW$4,IF(Category=$A$47,IF(Provider=$B54,Responses))))} -> 3 | BA54: =AW54*(AY54/SUM(AY$48:AY$81)) -> 1.2677419 | BC54: =AW54*(AY54/(SUM(AY$9:AY$42)+SUM(AY$48:AY$81)+SUM(AY$87:AY$120)+SUM(AY$126:AY$159)+SUM(AY$165:AY$198)+SUM(AY$204:AY$237))) -> 0.21129032 | BE54: {=SUM(IF(Period=BE$4,IF(Category=$A$47,IF(Provider=$B54,Score))))} -> 70.8 | BG54: {=SUM(IF(Period=BE$4,IF(Category=$A$47,IF(Provider=$B54,Responses))))} -> 12 | BI54: =BE54*(BG54/SUM(BG$48:BG$81)) -> 3.6153191 | BK54: =BE54*(BG54/(SUM(BG$9:BG$42)+SUM(BG$48:BG$81)+SUM(BG$87:BG$120)+SUM(BG$126:BG$159)+SUM(BG$165:BG$198)+SUM(BG$204:BG$237))) -> 0.60042403 | BM54: {=SUM(IF(Period=BM$4,IF(Category=$A$47,IF(Provider=$B54,Score))))} -> 95.8 | BO54: {=SUM(IF(Period=BM$4,IF(Category=$A$47,IF(Provider=$B54,Responses))))} -> 12 | BQ54: =BM54*(BO54/SUM(BO$48:BO$81)) -> 4.9766234 | BS54: =BM54*(BO54/(SUM(BO$9:BO$42)+SUM(BO$48:BO$81)+SUM(BO$87:BO$120)+SUM(BO$126:BO$159)+SUM(BO$165:BO$198)+SUM(BO$204:BO$237))) -> 0.82943723 | BU54: {=SUM(IF(Period=BU$4,IF(Category=$A$47,IF(Provider=$B54,Score))))} -> 100 | BW54: {=SUM(IF(Period=BU$4,IF(Category=$A$47,IF(Provider=$B54,Responses))))} -> 6 | BY54: =BU54*(BW54/SUM(BW$48:BW$81)) -> 2.5210084 | CA54: =BU54*(BW54/(SUM(BW$9:BW$42)+SUM(BW$48:BW$81)+SUM(BW$87:BW$120)+SUM(BW$126:BW$159)+SUM(BW$165:BW$198)+SUM(BW$204:BW$237))) -> 0.414651
B55: CHRISTIAN KOKINAKOS | C55: 0 | E55: 0 | G55: 0 | I55: {=SUM(IF(Period=I$4,IF(Category=$A$47,IF(Provider=$B55,Score))))} -> 95 | K55: {=SUM(IF(Period=I$4,IF(Category=$A$47,IF(Provider=$B55,Responses))))} -> 5 | M55: =I55*(K55/SUM(K$48:K$81)) -> 2.3514851 | O55: =I55*(K55/(SUM(K$9:K$42)+SUM(K$48:K$81)+SUM(K$87:K$120)+SUM(K$126:K$159)+SUM(K$165:K$198)+SUM(K$204:K$237))) -> 0.39288668 | Q55: {=SUM(IF(Period=Q$4,IF(Category=$A$47,IF(Provider=$B55,Score))))} -> 75 | S55: {=SUM(IF(Period=Q$4,IF(Category=$A$47,IF(Provider=$B55,Responses))))} -> 3 | U55: =Q55*(S55/SUM(S$48:S$81)) -> 1.1968085 | W55: =Q55*(S55/(SUM(S$9:S$42)+SUM(S$48:S$81)+SUM(S$87:S$120)+SUM(S$126:S$159)+SUM(S$165:S$198)+SUM(S$204:S$237))) -> 0.20053476 | Y55: {=SUM(IF(Period=Y$4,IF(Category=$A$47,IF(Provider=$B55,Score))))} -> 0 | AA55: {=SUM(IF(Period=Y$4,IF(Category=$A$47,IF(Provider=$B55,Responses))))} -> 0 | AC55: =Y55*(AA55/SUM(AA$48:AA$81)) -> 0 | AE55: =Y55*(AA55/(SUM(AA$9:AA$42)+SUM(AA$48:AA$81)+SUM(AA$87:AA$120)+SUM(AA$126:AA$159)+SUM(AA$165:AA$198)+SUM(AA$204:AA$237))) -> 0 | AG55: {=SUM(IF(Period=AG$4,IF(Category=$A$47,IF(Provider=$B55,Score))))} -> 0 | AI55: {=SUM(IF(Period=AG$4,IF(Category=$A$47,IF(Provider=$B55,Responses))))} -> 0 | AK55: =AG55*(AI55/SUM(AI$48:AI$81)) -> 0 | AM55: =AG55*(AI55/(SUM(AI$9:AI$42)+SUM(AI$48:AI$81)+SUM(AI$87:AI$120)+SUM(AI$126:AI$159)+SUM(AI$165:AI$198)+SUM(AI$204:AI$237))) -> 0 | AO55: {=SUM(IF(Period=AO$4,IF(Category=$A$47,IF(Provider=$B55,Score))))} -> 0 | AQ55: {=SUM(IF(Period=AO$4,IF(Category=$A$47,IF(Provider=$B55,Responses))))} -> 0 | AS55: =AO55*(AQ55/SUM(AQ$48:AQ$81)) -> 0 | AU55: =AO55*(AQ55/(SUM(AQ$9:AQ$42)+SUM(AQ$48:AQ$81)+SUM(AQ$87:AQ$120)+SUM(AQ$126:AQ$159)+SUM(AQ$165:AQ$198)+SUM(AQ$204:AQ$237))) -> 0 | AW55: {=SUM(IF(Period=AW$4,IF(Category=$A$47,IF(Provider=$B55,Score))))} -> 0 | AY55: {=SUM(IF(Period=AW$4,IF(Category=$A$47,IF(Provider=$B55,Responses))))} -> 0 | BA55: =AW55*(AY55/SUM(AY$48:AY$81)) -> 0 | BC55: =AW55*(AY55/(SUM(AY$9:AY$42)+SUM(AY$48:AY$81)+SUM(AY$87:AY$120)+SUM(AY$126:AY$159)+SUM(AY$165:AY$198)+SUM(AY$204:AY$237))) -> 0 | BE55: {=SUM(IF(Period=BE$4,IF(Category=$A$47,IF(Provider=$B55,Score))))} -> 0 | BG55: {=SUM(IF(Period=BE$4,IF(Category=$A$47,IF(Provider=$B55,Responses))))} -> 0 | BI55: =BE55*(BG55/SUM(BG$48:BG$81)) -> 0 | BK55: =BE55*(BG55/(SUM(BG$9:BG$42)+SUM(BG$48:BG$81)+SUM(BG$87:BG$120)+SUM(BG$126:BG$159)+SUM(BG$165:BG$198)+SUM(BG$204:BG$237))) -> 0 | BM55: {=SUM(IF(Period=BM$4,IF(Category=$A$47,IF(Provider=$B55,Score))))} -> 0 | BO55: {=SUM(IF(Period=BM$4,IF(Category=$A$47,IF(Provider=$B55,Responses))))} -> 0 | BQ55: =BM55*(BO55/SUM(BO$48:BO$81)) -> 0 | BS55: =BM55*(BO55/(SUM(BO$9:BO$42)+SUM(BO$48:BO$81)+SUM(BO$87:BO$120)+SUM(BO$126:BO$159)+SUM(BO$165:BO$198)+SUM(BO$204:BO$237))) -> 0 | BU55: {=SUM(IF(Period=BU$4,IF(Category=$A$47,IF(Provider=$B55,Score))))} -> 0 | BW55: {=SUM(IF(Period=BU$4,IF(Category=$A$47,IF(Provider=$B55,Responses))))} -> 0 | BY55: =BU55*(BW55/SUM(BW$48:BW$81)) -> 0 | CA55: =BU55*(BW55/(SUM(BW$9:BW$42)+SUM(BW$48:BW$81)+SUM(BW$87:BW$120)+SUM(BW$126:BW$159)+SUM(BW$165:BW$198)+SUM(BW$204:BW$237))) -> 0
B56: DANIEL D'AMORE | C56: 0 | E56: 0 | G56: 0 | I56: {=SUM(IF(Period=I$4,IF(Category=$A$47,IF(Provider=$B56,Score))))} -> 75 | K56: {=SUM(IF(Period=I$4,IF(Category=$A$47,IF(Provider=$B56,Responses))))} -> 8 | M56: =I56*(K56/SUM(K$48:K$81)) -> 2.970297 | O56: =I56*(K56/(SUM(K$9:K$42)+SUM(K$48:K$81)+SUM(K$87:K$120)+SUM(K$126:K$159)+SUM(K$165:K$198)+SUM(K$204:K$237))) -> 0.49627792 | Q56: {=SUM(IF(Period=Q$4,IF(Category=$A$47,IF(Provider=$B56,Score))))} -> 70 | S56: {=SUM(IF(Period=Q$4,IF(Category=$A$47,IF(Provider=$B56,Responses))))} -> 5 | U56: =Q56*(S56/SUM(S$48:S$81)) -> 1.8617021 | W56: =Q56*(S56/(SUM(S$9:S$42)+SUM(S$48:S$81)+SUM(S$87:S$120)+SUM(S$126:S$159)+SUM(S$165:S$198)+SUM(S$204:S$237))) -> 0.31194296 | Y56: {=SUM(IF(Period=Y$4,IF(Category=$A$47,IF(Provider=$B56,Score))))} -> 79.2 | AA56: {=SUM(IF(Period=Y$4,IF(Category=$A$47,IF(Provider=$B56,Responses))))} -> 12 | AC56: =Y56*(AA56/SUM(AA$48:AA$81)) -> 3.1470199 | AE56: =Y56*(AA56/(SUM(AA$9:AA$42)+SUM(AA$48:AA$81)+SUM(AA$87:AA$120)+SUM(AA$126:AA$159)+SUM(AA$165:AA$198)+SUM(AA$204:AA$237))) -> 0.52421401 | AG56: {=SUM(IF(Period=AG$4,IF(Category=$A$47,IF(Provider=$B56,Score))))} -> 91.7 | AI56: {=SUM(IF(Period=AG$4,IF(Category=$A$47,IF(Provider=$B56,Responses))))} -> 9 | AK56: =AG56*(AI56/SUM(AI$48:AI$81)) -> 3.1988372 | AM56: =AG56*(AI56/(SUM(AI$9:AI$42)+SUM(AI$48:AI$81)+SUM(AI$87:AI$120)+SUM(AI$126:AI$159)+SUM(AI$165:AI$198)+SUM(AI$204:AI$237))) -> 0.53452073 | AO56: {=SUM(IF(Period=AO$4,IF(Category=$A$47,IF(Provider=$B56,Score))))} -> 81.3 | AQ56: {=SUM(IF(Period=AO$4,IF(Category=$A$47,IF(Provider=$B56,Responses))))} -> 12 | AS56: =AO56*(AQ56/SUM(AQ$48:AQ$81)) -> 5.7052632 | AU56: =AO56*(AQ56/(SUM(AQ$9:AQ$42)+SUM(AQ$48:AQ$81)+SUM(AQ$87:AQ$120)+SUM(AQ$126:AQ$159)+SUM(AQ$165:AQ$198)+SUM(AQ$204:AQ$237))) -> 0.95087719 | AW56: {=SUM(IF(Period=AW$4,IF(Category=$A$47,IF(Provider=$B56,Score))))} -> 84.4 | AY56: {=SUM(IF(Period=AW$4,IF(Category=$A$47,IF(Provider=$B56,Responses))))} -> 8 | BA56: =AW56*(AY56/SUM(AY$48:AY$81)) -> 3.1115207 | BC56: =AW56*(AY56/(SUM(AY$9:AY$42)+SUM(AY$48:AY$81)+SUM(AY$87:AY$120)+SUM(AY$126:AY$159)+SUM(AY$165:AY$198)+SUM(AY$204:AY$237))) -> 0.51858679 | BE56: {=SUM(IF(Period=BE$4,IF(Category=$A$47,IF(Provider=$B56,Score))))} -> 75 | BG56: {=SUM(IF(Period=BE$4,IF(Category=$A$47,IF(Provider=$B56,Responses))))} -> 4 | BI56: =BE56*(BG56/SUM(BG$48:BG$81)) -> 1.2765957 | BK56: =BE56*(BG56/(SUM(BG$9:BG$42)+SUM(BG$48:BG$81)+SUM(BG$87:BG$120)+SUM(BG$126:BG$159)+SUM(BG$165:BG$198)+SUM(BG$204:BG$237))) -> 0.21201413 | BM56: {=SUM(IF(Period=BM$4,IF(Category=$A$47,IF(Provider=$B56,Score))))} -> 78.9 | BO56: {=SUM(IF(Period=BM$4,IF(Category=$A$47,IF(Provider=$B56,Responses))))} -> 13 | BQ56: =BM56*(BO56/SUM(BO$48:BO$81)) -> 4.4402597 | BS56: =BM56*(BO56/(SUM(BO$9:BO$42)+SUM(BO$48:BO$81)+SUM(BO$87:BO$120)+SUM(BO$126:BO$159)+SUM(BO$165:BO$198)+SUM(BO$204:BO$237))) -> 0.74004329 | BU56: {=SUM(IF(Period=BU$4,IF(Category=$A$47,IF(Provider=$B56,Score))))} -> 71.9 | BW56: {=SUM(IF(Period=BU$4,IF(Category=$A$47,IF(Provider=$B56,Responses))))} -> 8 | BY56: =BU56*(BW56/SUM(BW$48:BW$81)) -> 2.4168067 | CA56: =BU56*(BW56/(SUM(BW$9:BW$42)+SUM(BW$48:BW$81)+SUM(BW$87:BW$120)+SUM(BW$126:BW$159)+SUM(BW$165:BW$198)+SUM(BW$204:BW$237))) -> 0.39751209
B57: DAVID MISHKIN | C57: 0 | E57: 0 | G57: 0 | I57: {=SUM(IF(Period=I$4,IF(Category=$A$47,IF(Provider=$B57,Score))))} -> 90.6 | K57: {=SUM(IF(Period=I$4,IF(Category=$A$47,IF(Provider=$B57,Responses))))} -> 8 | M57: =I57*(K57/SUM(K$48:K$81)) -> 3.5881188 | O57: =I57*(K57/(SUM(K$9:K$42)+SUM(K$48:K$81)+SUM(K$87:K$120)+SUM(K$126:K$159)+SUM(K$165:K$198)+SUM(K$204:K$237))) -> 0.59950372 | Q57: {=SUM(IF(Period=Q$4,IF(Category=$A$47,IF(Provider=$B57,Score))))} -> 63.9 | S57: {=SUM(IF(Period=Q$4,IF(Category=$A$47,IF(Provider=$B57,Responses))))} -> 9 | U57: =Q57*(S57/SUM(S$48:S$81)) -> 3.0590426 | W57: =Q57*(S57/(SUM(S$9:S$42)+SUM(S$48:S$81)+SUM(S$87:S$120)+SUM(S$126:S$159)+SUM(S$165:S$198)+SUM(S$204:S$237))) -> 0.51256684 | Y57: {=SUM(IF(Period=Y$4,IF(Category=$A$47,IF(Provider=$B57,Score))))} -> 76.9 | AA57: {=SUM(IF(Period=Y$4,IF(Category=$A$47,IF(Provider=$B57,Responses))))} -> 13 | AC57: =Y57*(AA57/SUM(AA$48:AA$81)) -> 3.3102649 | AE57: =Y57*(AA57/(SUM(AA$9:AA$42)+SUM(AA$48:AA$81)+SUM(AA$87:AA$120)+SUM(AA$126:AA$159)+SUM(AA$165:AA$198)+SUM(AA$204:AA$237))) -> 0.55140651 | AG57: {=SUM(IF(Period=AG$4,IF(Category=$A$47,IF(Provider=$B57,Score))))} -> 95 | AI57: {=SUM(IF(Period=AG$4,IF(Category=$A$47,IF(Provider=$B57,Responses))))} -> 10 | AK57: =AG57*(AI57/SUM(AI$48:AI$81)) -> 3.6821705 | AM57: =AG57*(AI57/(SUM(AI$9:AI$42)+SUM(AI$48:AI$81)+SUM(AI$87:AI$120)+SUM(AI$126:AI$159)+SUM(AI$165:AI$198)+SUM(AI$204:AI$237))) -> 0.61528497 | AO57: {=SUM(IF(Period=AO$4,IF(Category=$A$47,IF(Provider=$B57,Score))))} -> 100 | AQ57: {=SUM(IF(Period=AO$4,IF(Category=$A$47,IF(Provider=$B57,Responses))))} -> 8 | AS57: =AO57*(AQ57/SUM(AQ$48:AQ$81)) -> 4.6783626 | AU57: =AO57*(AQ57/(SUM(AQ$9:AQ$42)+SUM(AQ$48:AQ$81)+SUM(AQ$87:AQ$120)+SUM(AQ$126:AQ$159)+SUM(AQ$165:AQ$198)+SUM(AQ$204:AQ$237))) -> 0.7797271 | AW57: {=SUM(IF(Period=AW$4,IF(Category=$A$47,IF(Provider=$B57,Score))))} -> 92.9 | AY57: {=SUM(IF(Period=AW$4,IF(Category=$A$47,IF(Provider=$B57,Responses))))} -> 14 | BA57: =AW57*(AY57/SUM(AY$48:AY$81)) -> 5.9935484 | BC57: =AW57*(AY57/(SUM(AY$9:AY$42)+SUM(AY$48:AY$81)+SUM(AY$87:AY$120)+SUM(AY$126:AY$159)+SUM(AY$165:AY$198)+SUM(AY$204:AY$237))) -> 0.99892473 | BE57: {=SUM(IF(Period=BE$4,IF(Category=$A$47,IF(Provider=$B57,Score))))} -> 97.5 | BG57: {=SUM(IF(Period=BE$4,IF(Category=$A$47,IF(Provider=$B57,Responses))))} -> 10 | BI57: =BE57*(BG57/SUM(BG$48:BG$81)) -> 4.1489362 | BK57: =BE57*(BG57/(SUM(BG$9:BG$42)+SUM(BG$48:BG$81)+SUM(BG$87:BG$120)+SUM(BG$126:BG$159)+SUM(BG$165:BG$198)+SUM(BG$204:BG$237))) -> 0.68904594 | BM57: {=SUM(IF(Period=BM$4,IF(Category=$A$47,IF(Provider=$B57,Score))))} -> 89.3 | BO57: {=SUM(IF(Period=BM$4,IF(Category=$A$47,IF(Provider=$B57,Responses))))} -> 7 | BQ57: =BM57*(BO57/SUM(BO$48:BO$81)) -> 2.7060606 | BS57: =BM57*(BO57/(SUM(BO$9:BO$42)+SUM(BO$48:BO$81)+SUM(BO$87:BO$120)+SUM(BO$126:BO$159)+SUM(BO$165:BO$198)+SUM(BO$204:BO$237))) -> 0.4510101 | BU57: {=SUM(IF(Period=BU$4,IF(Category=$A$47,IF(Provider=$B57,Score))))} -> 89.3 | BW57: {=SUM(IF(Period=BU$4,IF(Category=$A$47,IF(Provider=$B57,Responses))))} -> 14 | BY57: =BU57*(BW57/SUM(BW$48:BW$81)) -> 5.2529412 | CA57: =BU57*(BW57/(SUM(BW$9:BW$42)+SUM(BW$48:BW$81)+SUM(BW$87:BW$120)+SUM(BW$126:BW$159)+SUM(BW$165:BW$198)+SUM(BW$204:BW$237))) -> 0.86399447
B58: ELAINE DIAZ | C58: 0 | E58: 0 | G58: 0 | I58: {=SUM(IF(Period=I$4,IF(Category=$A$47,IF(Provider=$B58,Score))))} -> 87.5 | K58: {=SUM(IF(Period=I$4,IF(Category=$A$47,IF(Provider=$B58,Responses))))} -> 4 | M58: =I58*(K58/SUM(K$48:K$81)) -> 1.7326733 | O58: =I58*(K58/(SUM(K$9:K$42)+SUM(K$48:K$81)+SUM(K$87:K$120)+SUM(K$126:K$159)+SUM(K$165:K$198)+SUM(K$204:K$237))) -> 0.28949545 | Q58: {=SUM(IF(Period=Q$4,IF(Category=$A$47,IF(Provider=$B58,Score))))} -> 100 | S58: {=SUM(IF(Period=Q$4,IF(Category=$A$47,IF(Provider=$B58,Responses))))} -> 4 | U58: =Q58*(S58/SUM(S$48:S$81)) -> 2.1276596 | W58: =Q58*(S58/(SUM(S$9:S$42)+SUM(S$48:S$81)+SUM(S$87:S$120)+SUM(S$126:S$159)+SUM(S$165:S$198)+SUM(S$204:S$237))) -> 0.35650624 | Y58: {=SUM(IF(Period=Y$4,IF(Category=$A$47,IF(Provider=$B58,Score))))} -> 90 | AA58: {=SUM(IF(Period=Y$4,IF(Category=$A$47,IF(Provider=$B58,Responses))))} -> 5 | AC58: =Y58*(AA58/SUM(AA$48:AA$81)) -> 1.4900662 | AE58: =Y58*(AA58/(SUM(AA$9:AA$42)+SUM(AA$48:AA$81)+SUM(AA$87:AA$120)+SUM(AA$126:AA$159)+SUM(AA$165:AA$198)+SUM(AA$204:AA$237))) -> 0.24820739 | AG58: {=SUM(IF(Period=AG$4,IF(Category=$A$47,IF(Provider=$B58,Score))))} -> 93.8 | AI58: {=SUM(IF(Period=AG$4,IF(Category=$A$47,IF(Provider=$B58,Responses))))} -> 4 | AK58: =AG58*(AI58/SUM(AI$48:AI$81)) -> 1.4542636 | AM58: =AG58*(AI58/(SUM(AI$9:AI$42)+SUM(AI$48:AI$81)+SUM(AI$87:AI$120)+SUM(AI$126:AI$159)+SUM(AI$165:AI$198)+SUM(AI$204:AI$237))) -> 0.24300518 | AO58: {=SUM(IF(Period=AO$4,IF(Category=$A$47,IF(Provider=$B58,Score))))} -> 37.5 | AQ58: {=SUM(IF(Period=AO$4,IF(Category=$A$47,IF(Provider=$B58,Responses))))} -> 2 | AS58: =AO58*(AQ58/SUM(AQ$48:AQ$81)) -> 0.43859649 | AU58: =AO58*(AQ58/(SUM(AQ$9:AQ$42)+SUM(AQ$48:AQ$81)+SUM(AQ$87:AQ$120)+SUM(AQ$126:AQ$159)+SUM(AQ$165:AQ$198)+SUM(AQ$204:AQ$237))) -> 0.073099415 | AW58: {=SUM(IF(Period=AW$4,IF(Category=$A$47,IF(Provider=$B58,Score))))} -> 80 | AY58: {=SUM(IF(Period=AW$4,IF(Category=$A$47,IF(Provider=$B58,Responses))))} -> 5 | BA58: =AW58*(AY58/SUM(AY$48:AY$81)) -> 1.843318 | BC58: =AW58*(AY58/(SUM(AY$9:AY$42)+SUM(AY$48:AY$81)+SUM(AY$87:AY$120)+SUM(AY$126:AY$159)+SUM(AY$165:AY$198)+SUM(AY$204:AY$237))) -> 0.30721966 | BE58: {=SUM(IF(Period=BE$4,IF(Category=$A$47,IF(Provider=$B58,Score))))} -> 100 | BG58: {=SUM(IF(Period=BE$4,IF(Category=$A$47,IF(Provider=$B58,Responses))))} -> 2 | BI58: =BE58*(BG58/SUM(BG$48:BG$81)) -> 0.85106383 | BK58: =BE58*(BG58/(SUM(BG$9:BG$42)+SUM(BG$48:BG$81)+SUM(BG$87:BG$120)+SUM(BG$126:BG$159)+SUM(BG$165:BG$198)+SUM(BG$204:BG$237))) -> 0.14134276 | BM58: {=SUM(IF(Period=BM$4,IF(Category=$A$47,IF(Provider=$B58,Score))))} -> 100 | BO58: {=SUM(IF(Period=BM$4,IF(Category=$A$47,IF(Provider=$B58,Responses))))} -> 3 | BQ58: =BM58*(BO58/SUM(BO$48:BO$81)) -> 1.2987013 | BS58: =BM58*(BO58/(SUM(BO$9:BO$42)+SUM(BO$48:BO$81)+SUM(BO$87:BO$120)+SUM(BO$126:BO$159)+SUM(BO$165:BO$198)+SUM(BO$204:BO$237))) -> 0.21645022 | BU58: {=SUM(IF(Period=BU$4,IF(Category=$A$47,IF(Provider=$B58,Score))))} -> 75 | BW58: {=SUM(IF(Period=BU$4,IF(Category=$A$47,IF(Provider=$B58,Responses))))} -> 7 | BY58: =BU58*(BW58/SUM(BW$48:BW$81)) -> 2.2058824 | CA58: =BU58*(BW58/(SUM(BW$9:BW$42)+SUM(BW$48:BW$81)+SUM(BW$87:BW$120)+SUM(BW$126:BW$159)+SUM(BW$165:BW$198)+SUM(BW$204:BW$237))) -> 0.36281963
B59: EVA ESCATEL | C59: 0 | E59: 0 | G59: 0 | I59: {=SUM(IF(Period=I$4,IF(Category=$A$47,IF(Provider=$B59,Score))))} -> 81.8 | K59: {=SUM(IF(Period=I$4,IF(Category=$A$47,IF(Provider=$B59,Responses))))} -> 11 | M59: =I59*(K59/SUM(K$48:K$81)) -> 4.4544554 | O59: =I59*(K59/(SUM(K$9:K$42)+SUM(K$48:K$81)+SUM(K$87:K$120)+SUM(K$126:K$159)+SUM(K$165:K$198)+SUM(K$204:K$237))) -> 0.74425145 | Q59: {=SUM(IF(Period=Q$4,IF(Category=$A$47,IF(Provider=$B59,Score))))} -> 86.1 | S59: {=SUM(IF(Period=Q$4,IF(Category=$A$47,IF(Provider=$B59,Responses))))} -> 9 | U59: =Q59*(S59/SUM(S$48:S$81)) -> 4.1218085 | W59: =Q59*(S59/(SUM(S$9:S$42)+SUM(S$48:S$81)+SUM(S$87:S$120)+SUM(S$126:S$159)+SUM(S$165:S$198)+SUM(S$204:S$237))) -> 0.69064171 | Y59: {=SUM(IF(Period=Y$4,IF(Category=$A$47,IF(Provider=$B59,Score))))} -> 83.3 | AA59: {=SUM(IF(Period=Y$4,IF(Category=$A$47,IF(Provider=$B59,Responses))))} -> 18 | AC59: =Y59*(AA59/SUM(AA$48:AA$81)) -> 4.9649007 | AE59: =Y59*(AA59/(SUM(AA$9:AA$42)+SUM(AA$48:AA$81)+SUM(AA$87:AA$120)+SUM(AA$126:AA$159)+SUM(AA$165:AA$198)+SUM(AA$204:AA$237))) -> 0.82702703 | AG59: {=SUM(IF(Period=AG$4,IF(Category=$A$47,IF(Provider=$B59,Score))))} -> 85.9 | AI59: {=SUM(IF(Period=AG$4,IF(Category=$A$47,IF(Provider=$B59,Responses))))} -> 16 | AK59: =AG59*(AI59/SUM(AI$48:AI$81)) -> 5.3271318 | AM59: =AG59*(AI59/(SUM(AI$9:AI$42)+SUM(AI$48:AI$81)+SUM(AI$87:AI$120)+SUM(AI$126:AI$159)+SUM(AI$165:AI$198)+SUM(AI$204:AI$237))) -> 0.89015544 | AO59: {=SUM(IF(Period=AO$4,IF(Category=$A$47,IF(Provider=$B59,Score))))} -> 87.5 | AQ59: {=SUM(IF(Period=AO$4,IF(Category=$A$47,IF(Provider=$B59,Responses))))} -> 12 | AS59: =AO59*(AQ59/SUM(AQ$48:AQ$81)) -> 6.1403509 | AU59: =AO59*(AQ59/(SUM(AQ$9:AQ$42)+SUM(AQ$48:AQ$81)+SUM(AQ$87:AQ$120)+SUM(AQ$126:AQ$159)+SUM(AQ$165:AQ$198)+SUM(AQ$204:AQ$237))) -> 1.0233918 | AW59: {=SUM(IF(Period=AW$4,IF(Category=$A$47,IF(Provider=$B59,Score))))} -> 92.5 | AY59: {=SUM(IF(Period=AW$4,IF(Category=$A$47,IF(Provider=$B59,Responses))))} -> 10 | BA59: =AW59*(AY59/SUM(AY$48:AY$81)) -> 4.2626728 | BC59: =AW59*(AY59/(SUM(AY$9:AY$42)+SUM(AY$48:AY$81)+SUM(AY$87:AY$120)+SUM(AY$126:AY$159)+SUM(AY$165:AY$198)+SUM(AY$204:AY$237))) -> 0.71044547 | BE59: {=SUM(IF(Period=BE$4,IF(Category=$A$47,IF(Provider=$B59,Score))))} -> 93.8 | BG59: {=SUM(IF(Period=BE$4,IF(Category=$A$47,IF(Provider=$B59,Responses))))} -> 8 | BI59: =BE59*(BG59/SUM(BG$48:BG$81)) -> 3.1931915 | BK59: =BE59*(BG59/(SUM(BG$9:BG$42)+SUM(BG$48:BG$81)+SUM(BG$87:BG$120)+SUM(BG$126:BG$159)+SUM(BG$165:BG$198)+SUM(BG$204:BG$237))) -> 0.53031802 | BM59: {=SUM(IF(Period=BM$4,IF(Category=$A$47,IF(Provider=$B59,Score))))} -> 100 | BO59: {=SUM(IF(Period=BM$4,IF(Category=$A$47,IF(Provider=$B59,Responses))))} -> 9 | BQ59: =BM59*(BO59/SUM(BO$48:BO$81)) -> 3.8961039 | BS59: =BM59*(BO59/(SUM(BO$9:BO$42)+SUM(BO$48:BO$81)+SUM(BO$87:BO$120)+SUM(BO$126:BO$159)+SUM(BO$165:BO$198)+SUM(BO$204:BO$237))) -> 0.64935065 | BU59: {=SUM(IF(Period=BU$4,IF(Category=$A$47,IF(Provider=$B59,Score))))} -> 92.9 | BW59: {=SUM(IF(Period=BU$4,IF(Category=$A$47,IF(Provider=$B59,Responses))))} -> 7 | BY59: =BU59*(BW59/SUM(BW$48:BW$81)) -> 2.7323529 | CA59: =BU59*(BW59/(SUM(BW$9:BW$42)+SUM(BW$48:BW$81)+SUM(BW$87:BW$120)+SUM(BW$126:BW$159)+SUM(BW$165:BW$198)+SUM(BW$204:BW$237))) -> 0.44941258
... B81: NAME NOT GIVEN | C81: 0 | E81: 0 | G81: 0 | I81: {=SUM(IF(Period=I$4,IF(Category=$A$47,IF(Provider=$B81,Score))))} -> 0 | K81: {=SUM(IF(Period=I$4,IF(Category=$A$47,IF(Provider=$B81,Responses))))} -> 0 | M81: =I81*(K81/SUM(K$48:K$81)) -> 0 | O81: =I81*(K81/(SUM(K$9:K$42)+SUM(K$48:K$81)+SUM(K$87:K$120)+SUM(K$126:K$159)+SUM(K$165:K$198)+SUM(K$204:K$237))) -> 0 | Q81: {=SUM(IF(Period=Q$4,IF(Category=$A$47,IF(Provider=$B81,Score))))} -> 0 | S81: {=SUM(IF(Period=Q$4,IF(Category=$A$47,IF(Provider=$B81,Responses))))} -> 0 | U81: =Q81*(S81/SUM(S$48:S$81)) -> 0 | W81: =Q81*(S81/(SUM(S$9:S$42)+SUM(S$48:S$81)+SUM(S$87:S$120)+SUM(S$126:S$159)+SUM(S$165:S$198)+SUM(S$204:S$237))) -> 0 | Y81: {=SUM(IF(Period=Y$4,IF(Category=$A$47,IF(Provider=$B81,Score))))} -> 0 | AA81: {=SUM(IF(Period=Y$4,IF(Category=$A$47,IF(Provider=$B81,Responses))))} -> 0 | AC81: =Y81*(AA81/SUM(AA$48:AA$81)) -> 0 | AE81: =Y81*(AA81/(SUM(AA$9:AA$42)+SUM(AA$48:AA$81)+SUM(AA$87:AA$120)+SUM(AA$126:AA$159)+SUM(AA$165:AA$198)+SUM(AA$204:AA$237))) -> 0 | AG81: {=SUM(IF(Period=AG$4,IF(Category=$A$47,IF(Provider=$B81,Score))))} -> 75 | AI81: {=SUM(IF(Period=AG$4,IF(Category=$A$47,IF(Provider=$B81,Responses))))} -> 1 | AK81: =AG81*(AI81/SUM(AI$48:AI$81)) -> 0.29069767 | AM81: =AG81*(AI81/(SUM(AI$9:AI$42)+SUM(AI$48:AI$81)+SUM(AI$87:AI$120)+SUM(AI$126:AI$159)+SUM(AI$165:AI$198)+SUM(AI$204:AI$237))) -> 0.04857513 | AO81: {=SUM(IF(Period=AO$4,IF(Category=$A$47,IF(Provider=$B81,Score))))} -> 0 | AQ81: {=SUM(IF(Period=AO$4,IF(Category=$A$47,IF(Provider=$B81,Responses))))} -> 0 | AS81: =AO81*(AQ81/SUM(AQ$48:AQ$81)) -> 0 | AU81: =AO81*(AQ81/(SUM(AQ$9:AQ$42)+SUM(AQ$48:AQ$81)+SUM(AQ$87:AQ$120)+SUM(AQ$126:AQ$159)+SUM(AQ$165:AQ$198)+SUM(AQ$204:AQ$237))) -> 0 | AW81: {=SUM(IF(Period=AW$4,IF(Category=$A$47,IF(Provider=$B81,Score))))} -> 0 | AY81: {=SUM(IF(Period=AW$4,IF(Category=$A$47,IF(Provider=$B81,Responses))))} -> 0 | BA81: =AW81*(AY81/SUM(AY$48:AY$81)) -> 0 | BC81: =AW81*(AY81/(SUM(AY$9:AY$42)+SUM(AY$48:AY$81)+SUM(AY$87:AY$120)+SUM(AY$126:AY$159)+SUM(AY$165:AY$198)+SUM(AY$204:AY$237))) -> 0 | BE81: {=SUM(IF(Period=BE$4,IF(Category=$A$47,IF(Provider=$B81,Score))))} -> 0 | BG81: {=SUM(IF(Period=BE$4,IF(Category=$A$47,IF(Provider=$B81,Responses))))} -> 0 | BI81: =BE81*(BG81/SUM(BG$48:BG$81)) -> 0 | BK81: =BE81*(BG81/(SUM(BG$9:BG$42)+SUM(BG$48:BG$81)+SUM(BG$87:BG$120)+SUM(BG$126:BG$159)+SUM(BG$165:BG$198)+SUM(BG$204:BG$237))) -> 0 | BM81: {=SUM(IF(Period=BM$4,IF(Category=$A$47,IF(Provider=$B81,Score))))} -> 0 | BO81: {=SUM(IF(Period=BM$4,IF(Category=$A$47,IF(Provider=$B81,Responses))))} -> 0 | BQ81: =BM81*(BO81/SUM(BO$48:BO$81)) -> 0 | BS81: =BM81*(BO81/(SUM(BO$9:BO$42)+SUM(BO$48:BO$81)+SUM(BO$87:BO$120)+SUM(BO$126:BO$159)+SUM(BO$165:BO$198)+SUM(BO$204:BO$237))) -> 0 | BU81: {=SUM(IF(Period=BU$4,IF(Category=$A$47,IF(Provider=$B81,Score))))} -> 0 | BW81: {=SUM(IF(Period=BU$4,IF(Category=$A$47,IF(Provider=$B81,Responses))))} -> 0 | BY81: =BU81*(BW81/SUM(BW$48:BW$81)) -> 0 | CA81: =BU81*(BW81/(SUM(BW$9:BW$42)+SUM(BW$48:BW$81)+SUM(BW$87:BW$120)+SUM(BW$126:BW$159)+SUM(BW$165:BW$198)+SUM(BW$204:BW$237))) -> 0
B82: Average for Category: | C82: 0 | E82: 0 | G82: 0 | I82: =SUM(M48:M81) -> 74.631188 | K82: =AVERAGEIF(K48:K81,"<>0") -> 6.3125 | Q82: =SUM(U48:U81) -> 78.197872 | S82: =AVERAGEIF(S48:S81,"<>0") -> 6.2666667 | Y82: =SUM(AC48:AC81) -> 79.886424 | AA82: =AVERAGEIF(AA48:AA81,"<>0") -> 9.7419355 | AG82: =SUM(AK48:AK81) -> 83.618605 | AI82: =AVERAGEIF(AI48:AI81,"<>0") -> 7.8181818 | AO82: =SUM(AS48:AS81) -> 79.535088 | AQ82: =AVERAGEIF(AQ48:AQ81,"<>0") -> 5.7 | AW82: =SUM(BA48:BA81) -> 81.114286 | AY82: =AVERAGEIF(AY48:AY81,"<>0") -> 6.78125 | BE82: =SUM(BI48:BI81) -> 82.773191 | BG82: =AVERAGEIF(BG48:BG81,"<>0") -> 7.5806452 | BM82: =SUM(BQ48:BQ81) -> 85.184416 | BO82: =AVERAGEIF(BO48:BO81,"<>0") -> 7.21875 | BU82: =SUM(BY48:BY81) -> 82.67563 | BW82: =AVERAGEIF(BW48:BW81,"<>0") -> 7.4375
B83: Median Values: | I83: {=MEDIAN(IF(I48:I81<>0,I48:I81))} -> 76.4 | K83: {=MEDIAN(IF(K48:K81<>0,K48:K81))} -> 6.5 | Q83: {=MEDIAN(IF(Q48:Q81<>0,Q48:Q81))} -> 82.3 | S83: {=MEDIAN(IF(S48:S81<>0,S48:S81))} -> 6 | Y83: {=MEDIAN(IF(Y48:Y81<>0,Y48:Y81))} -> 82.4 | AA83: {=MEDIAN(IF(AA48:AA81<>0,AA48:AA81))} -> 9 | AG83: {=MEDIAN(IF(AG48:AG81<>0,AG48:AG81))} -> 87.5 | AI83: {=MEDIAN(IF(AI48:AI81<>0,AI48:AI81))} -> 8 | AO83: {=MEDIAN(IF(AO48:AO81<>0,AO48:AO81))} -> 83.3 | AQ83: {=MEDIAN(IF(AQ48:AQ81<>0,AQ48:AQ81))} -> 5.5 | AW83: {=MEDIAN(IF(AW48:AW81<>0,AW48:AW81))} -> 82.7 | AY83: {=MEDIAN(IF(AY48:AY81<>0,AY48:AY81))} -> 6 | BE83: {=MEDIAN(IF(BE48:BE81<>0,BE48:BE81))} -> 84.4 | BG83: {=MEDIAN(IF(BG48:BG81<>0,BG48:BG81))} -> 8 | BM83: {=MEDIAN(IF(BM48:BM81<>0,BM48:BM81))} -> 87.1 | BO83: {=MEDIAN(IF(BO48:BO81<>0,BO48:BO81))} -> 7 | BU83: {=MEDIAN(IF(BU48:BU81<>0,BU48:BU81))} -> 84.25 | BW83: {=MEDIAN(IF(BW48:BW81<>0,BW48:BW81))} -> 7
B84: Subtotal n: | K84: =SUM(K48:K81) -> 202 | S84: =SUM(S48:S81) -> 188 | AA84: =SUM(AA48:AA81) -> 302 | AI84: =SUM(AI48:AI81) -> 258 | AQ84: =SUM(AQ48:AQ81) -> 171 | AY84: =SUM(AY48:AY81) -> 217 | BG84: =SUM(BG48:BG81) -> 235 | BO84: =SUM(BO48:BO81) -> 231 | BW84: =SUM(BW48:BW81) -> 238
A86: Doctors concern for comfort
B87: ALAN ITZKOWITZ | C87: 0 | E87: 0 | G87: 0 | I87: {=SUM(IF(Period=I$4,IF(Category=$A$86,IF(Provider=$B87,Score))))} -> 89.3 | K87: {=SUM(IF(Period=I$4,IF(Category=$A$86,IF(Provider=$B87,Responses))))} -> 7 | M87: =I87*(K87/SUM(K$87:K$120)) -> 3.1255 | O87: =I87*(K87/(SUM(K$9:K$42)+SUM(K$48:K$81)+SUM(K$87:K$120)+SUM(K$126:K$159)+SUM(K$165:K$198)+SUM(K$204:K$237))) -> 0.51703888 | Q87: {=SUM(IF(Period=Q$4,IF(Category=$A$86,IF(Provider=$B87,Score))))} -> 75 | S87: {=SUM(IF(Period=Q$4,IF(Category=$A$86,IF(Provider=$B87,Responses))))} -> 4 | U87: =Q87*(S87/SUM(S$87:S$120)) -> 1.6393443 | W87: =Q87*(S87/(SUM(S$9:S$42)+SUM(S$48:S$81)+SUM(S$87:S$120)+SUM(S$126:S$159)+SUM(S$165:S$198)+SUM(S$204:S$237))) -> 0.26737968 | Y87: {=SUM(IF(Period=Y$4,IF(Category=$A$86,IF(Provider=$B87,Score))))} -> 87.5 | AA87: {=SUM(IF(Period=Y$4,IF(Category=$A$86,IF(Provider=$B87,Responses))))} -> 14 | AC87: =Y87*(AA87/SUM(AA$87:AA$120)) -> 4.0833333 | AE87: =Y87*(AA87/(SUM(AA$9:AA$42)+SUM(AA$48:AA$81)+SUM(AA$87:AA$120)+SUM(AA$126:AA$159)+SUM(AA$165:AA$198)+SUM(AA$204:AA$237))) -> 0.67567568 | AG87: {=SUM(IF(Period=AG$4,IF(Category=$A$86,IF(Provider=$B87,Score))))} -> 100 | AI87: {=SUM(IF(Period=AG$4,IF(Category=$A$86,IF(Provider=$B87,Responses))))} -> 3 | AK87: =AG87*(AI87/SUM(AI$87:AI$120)) -> 1.1673152 | AM87: =AG87*(AI87/(SUM(AI$9:AI$42)+SUM(AI$48:AI$81)+SUM(AI$87:AI$120)+SUM(AI$126:AI$159)+SUM(AI$165:AI$198)+SUM(AI$204:AI$237))) -> 0.19430052 | AO87: {=SUM(IF(Period=AO$4,IF(Category=$A$86,IF(Provider=$B87,Score))))} -> 100 | AQ87: {=SUM(IF(Period=AO$4,IF(Category=$A$86,IF(Provider=$B87,Responses))))} -> 1 | AS87: =AO87*(AQ87/SUM(AQ$87:AQ$120)) -> 0.59171598 | AU87: =AO87*(AQ87/(SUM(AQ$9:AQ$42)+SUM(AQ$48:AQ$81)+SUM(AQ$87:AQ$120)+SUM(AQ$126:AQ$159)+SUM(AQ$165:AQ$198)+SUM(AQ$204:AQ$237))) -> 0.097465887 | AW87: {=SUM(IF(Period=AW$4,IF(Category=$A$86,IF(Provider=$B87,Score))))} -> 90 | AY87: {=SUM(IF(Period=AW$4,IF(Category=$A$86,IF(Provider=$B87,Responses))))} -> 5 | BA87: =AW87*(AY87/SUM(AY$87:AY$120)) -> 2.0930233 | BC87: =AW87*(AY87/(SUM(AY$9:AY$42)+SUM(AY$48:AY$81)+SUM(AY$87:AY$120)+SUM(AY$126:AY$159)+SUM(AY$165:AY$198)+SUM(AY$204:AY$237))) -> 0.34562212 | BE87: {=SUM(IF(Period=BE$4,IF(Category=$A$86,IF(Provider=$B87,Score))))} -> 83.3 | BG87: {=SUM(IF(Period=BE$4,IF(Category=$A$86,IF(Provider=$B87,Responses))))} -> 9 | BI87: =BE87*(BG87/SUM(BG$87:BG$120)) -> 3.1902128 | BK87: =BE87*(BG87/(SUM(BG$9:BG$42)+SUM(BG$48:BG$81)+SUM(BG$87:BG$120)+SUM(BG$126:BG$159)+SUM(BG$165:BG$198)+SUM(BG$204:BG$237))) -> 0.52982332 | BM87: {=SUM(IF(Period=BM$4,IF(Category=$A$86,IF(Provider=$B87,Score))))} -> 100 | BO87: {=SUM(IF(Period=BM$4,IF(Category=$A$86,IF(Provider=$B87,Responses))))} -> 6 | BQ87: =BM87*(BO87/SUM(BO$87:BO$120)) -> 2.6431718 | BS87: =BM87*(BO87/(SUM(BO$9:BO$42)+SUM(BO$48:BO$81)+SUM(BO$87:BO$120)+SUM(BO$126:BO$159)+SUM(BO$165:BO$198)+SUM(BO$204:BO$237))) -> 0.43290043 | BU87: {=SUM(IF(Period=BU$4,IF(Category=$A$86,IF(Provider=$B87,Score))))} -> 90 | BW87: {=SUM(IF(Period=BU$4,IF(Category=$A$86,IF(Provider=$B87,Responses))))} -> 5 | BY87: =BU87*(BW87/SUM(BW$87:BW$120)) -> 1.875 | CA87: =BU87*(BW87/(SUM(BW$9:BW$42)+SUM(BW$48:BW$81)+SUM(BW$87:BW$120)+SUM(BW$126:BW$159)+SUM(BW$165:BW$198)+SUM(BW$204:BW$237))) -> 0.31098825
B88: ALEX PALMA | C88: 0 | E88: 0 | G88: 0 | I88: {=SUM(IF(Period=I$4,IF(Category=$A$86,IF(Provider=$B88,Score))))} -> 78.6 | K88: {=SUM(IF(Period=I$4,IF(Category=$A$86,IF(Provider=$B88,Responses))))} -> 7 | M88: =I88*(K88/SUM(K$87:K$120)) -> 2.751 | O88: =I88*(K88/(SUM(K$9:K$42)+SUM(K$48:K$81)+SUM(K$87:K$120)+SUM(K$126:K$159)+SUM(K$165:K$198)+SUM(K$204:K$237))) -> 0.45508685 | Q88: {=SUM(IF(Period=Q$4,IF(Category=$A$86,IF(Provider=$B88,Score))))} -> 95 | S88: {=SUM(IF(Period=Q$4,IF(Category=$A$86,IF(Provider=$B88,Responses))))} -> 10 | U88: =Q88*(S88/SUM(S$87:S$120)) -> 5.1912568 | W88: =Q88*(S88/(SUM(S$9:S$42)+SUM(S$48:S$81)+SUM(S$87:S$120)+SUM(S$126:S$159)+SUM(S$165:S$198)+SUM(S$204:S$237))) -> 0.84670232 | Y88: {=SUM(IF(Period=Y$4,IF(Category=$A$86,IF(Provider=$B88,Score))))} -> 83.3 | AA88: {=SUM(IF(Period=Y$4,IF(Category=$A$86,IF(Provider=$B88,Responses))))} -> 9 | AC88: =Y88*(AA88/SUM(AA$87:AA$120)) -> 2.499 | AE88: =Y88*(AA88/(SUM(AA$9:AA$42)+SUM(AA$48:AA$81)+SUM(AA$87:AA$120)+SUM(AA$126:AA$159)+SUM(AA$165:AA$198)+SUM(AA$204:AA$237))) -> 0.41351351 | AG88: {=SUM(IF(Period=AG$4,IF(Category=$A$86,IF(Provider=$B88,Score))))} -> 100 | AI88: {=SUM(IF(Period=AG$4,IF(Category=$A$86,IF(Provider=$B88,Responses))))} -> 6 | AK88: =AG88*(AI88/SUM(AI$87:AI$120)) -> 2.3346304 | AM88: =AG88*(AI88/(SUM(AI$9:AI$42)+SUM(AI$48:AI$81)+SUM(AI$87:AI$120)+SUM(AI$126:AI$159)+SUM(AI$165:AI$198)+SUM(AI$204:AI$237))) -> 0.38860104 | AO88: {=SUM(IF(Period=AO$4,IF(Category=$A$86,IF(Provider=$B88,Score))))} -> 37.5 | AQ88: {=SUM(IF(Period=AO$4,IF(Category=$A$86,IF(Provider=$B88,Responses))))} -> 4 | AS88: =AO88*(AQ88/SUM(AQ$87:AQ$120)) -> 0.88757396 | AU88: =AO88*(AQ88/(SUM(AQ$9:AQ$42)+SUM(AQ$48:AQ$81)+SUM(AQ$87:AQ$120)+SUM(AQ$126:AQ$159)+SUM(AQ$165:AQ$198)+SUM(AQ$204:AQ$237))) -> 0.14619883 | AW88: {=SUM(IF(Period=AW$4,IF(Category=$A$86,IF(Provider=$B88,Score))))} -> 89.3 | AY88: {=SUM(IF(Period=AW$4,IF(Category=$A$86,IF(Provider=$B88,Responses))))} -> 7 | BA88: =AW88*(AY88/SUM(AY$87:AY$120)) -> 2.9074419 | BC88: =AW88*(AY88/(SUM(AY$9:AY$42)+SUM(AY$48:AY$81)+SUM(AY$87:AY$120)+SUM(AY$126:AY$159)+SUM(AY$165:AY$198)+SUM(AY$204:AY$237))) -> 0.48010753 | BE88: {=SUM(IF(Period=BE$4,IF(Category=$A$86,IF(Provider=$B88,Score))))} -> 96.9 | BG88: {=SUM(IF(Period=BE$4,IF(Category=$A$86,IF(Provider=$B88,Responses))))} -> 8 | BI88: =BE88*(BG88/SUM(BG$87:BG$120)) -> 3.2987234 | BK88: =BE88*(BG88/(SUM(BG$9:BG$42)+SUM(BG$48:BG$81)+SUM(BG$87:BG$120)+SUM(BG$126:BG$159)+SUM(BG$165:BG$198)+SUM(BG$204:BG$237))) -> 0.54784452 | BM88: {=SUM(IF(Period=BM$4,IF(Category=$A$86,IF(Provider=$B88,Score))))} -> 91.7 | BO88: {=SUM(IF(Period=BM$4,IF(Category=$A$86,IF(Provider=$B88,Responses))))} -> 6 | BQ88: =BM88*(BO88/SUM(BO$87:BO$120)) -> 2.4237885 | BS88: =BM88*(BO88/(SUM(BO$9:BO$42)+SUM(BO$48:BO$81)+SUM(BO$87:BO$120)+SUM(BO$126:BO$159)+SUM(BO$165:BO$198)+SUM(BO$204:BO$237))) -> 0.3969697 | BU88: {=SUM(IF(Period=BU$4,IF(Category=$A$86,IF(Provider=$B88,Score))))} -> 79.6 | BW88: {=SUM(IF(Period=BU$4,IF(Category=$A$86,IF(Provider=$B88,Responses))))} -> 11 | BY88: =BU88*(BW88/SUM(BW$87:BW$120)) -> 3.6483333 | CA88: =BU88*(BW88/(SUM(BW$9:BW$42)+SUM(BW$48:BW$81)+SUM(BW$87:BW$120)+SUM(BW$126:BW$159)+SUM(BW$165:BW$198)+SUM(BW$204:BW$237))) -> 0.60511403
B89: ALEXANDER GARCIA | C89: 0 | E89: 0 | G89: 0 | I89: {=SUM(IF(Period=I$4,IF(Category=$A$86,IF(Provider=$B89,Score))))} -> 96.4 | K89: {=SUM(IF(Period=I$4,IF(Category=$A$86,IF(Provider=$B89,Responses))))} -> 7 | M89: =I89*(K89/SUM(K$87:K$120)) -> 3.374 | O89: =I89*(K89/(SUM(K$9:K$42)+SUM(K$48:K$81)+SUM(K$87:K$120)+SUM(K$126:K$159)+SUM(K$165:K$198)+SUM(K$204:K$237))) -> 0.55814723 | Q89: {=SUM(IF(Period=Q$4,IF(Category=$A$86,IF(Provider=$B89,Score))))} -> 91.7 | S89: {=SUM(IF(Period=Q$4,IF(Category=$A$86,IF(Provider=$B89,Responses))))} -> 6 | U89: =Q89*(S89/SUM(S$87:S$120)) -> 3.0065574 | W89: =Q89*(S89/(SUM(S$9:S$42)+SUM(S$48:S$81)+SUM(S$87:S$120)+SUM(S$126:S$159)+SUM(S$165:S$198)+SUM(S$204:S$237))) -> 0.49037433 | Y89: {=SUM(IF(Period=Y$4,IF(Category=$A$86,IF(Provider=$B89,Score))))} -> 86.1 | AA89: {=SUM(IF(Period=Y$4,IF(Category=$A$86,IF(Provider=$B89,Responses))))} -> 9 | AC89: =Y89*(AA89/SUM(AA$87:AA$120)) -> 2.583 | AE89: =Y89*(AA89/(SUM(AA$9:AA$42)+SUM(AA$48:AA$81)+SUM(AA$87:AA$120)+SUM(AA$126:AA$159)+SUM(AA$165:AA$198)+SUM(AA$204:AA$237))) -> 0.42741313 | AG89: {=SUM(IF(Period=AG$4,IF(Category=$A$86,IF(Provider=$B89,Score))))} -> 100 | AI89: {=SUM(IF(Period=AG$4,IF(Category=$A$86,IF(Provider=$B89,Responses))))} -> 6 | AK89: =AG89*(AI89/SUM(AI$87:AI$120)) -> 2.3346304 | AM89: =AG89*(AI89/(SUM(AI$9:AI$42)+SUM(AI$48:AI$81)+SUM(AI$87:AI$120)+SUM(AI$126:AI$159)+SUM(AI$165:AI$198)+SUM(AI$204:AI$237))) -> 0.38860104 | AO89: {=SUM(IF(Period=AO$4,IF(Category=$A$86,IF(Provider=$B89,Score))))} -> 57.1 | AQ89: {=SUM(IF(Period=AO$4,IF(Category=$A$86,IF(Provider=$B89,Responses))))} -> 7 | AS89: =AO89*(AQ89/SUM(AQ$87:AQ$120)) -> 2.3650888 | AU89: =AO89*(AQ89/(SUM(AQ$9:AQ$42)+SUM(AQ$48:AQ$81)+SUM(AQ$87:AQ$120)+SUM(AQ$126:AQ$159)+SUM(AQ$165:AQ$198)+SUM(AQ$204:AQ$237))) -> 0.38957115 | AW89: {=SUM(IF(Period=AW$4,IF(Category=$A$86,IF(Provider=$B89,Score))))} -> 95.8 | AY89: {=SUM(IF(Period=AW$4,IF(Category=$A$86,IF(Provider=$B89,Responses))))} -> 6 | BA89: =AW89*(AY89/SUM(AY$87:AY$120)) -> 2.6734884 | BC89: =AW89*(AY89/(SUM(AY$9:AY$42)+SUM(AY$48:AY$81)+SUM(AY$87:AY$120)+SUM(AY$126:AY$159)+SUM(AY$165:AY$198)+SUM(AY$204:AY$237))) -> 0.44147465 | BE89: {=SUM(IF(Period=BE$4,IF(Category=$A$86,IF(Provider=$B89,Score))))} -> 87.5 | BG89: {=SUM(IF(Period=BE$4,IF(Category=$A$86,IF(Provider=$B89,Responses))))} -> 8 | BI89: =BE89*(BG89/SUM(BG$87:BG$120)) -> 2.9787234 | BK89: =BE89*(BG89/(SUM(BG$9:BG$42)+SUM(BG$48:BG$81)+SUM(BG$87:BG$120)+SUM(BG$126:BG$159)+SUM(BG$165:BG$198)+SUM(BG$204:BG$237))) -> 0.49469965 | BM89: {=SUM(IF(Period=BM$4,IF(Category=$A$86,IF(Provider=$B89,Score))))} -> 65.6 | BO89: {=SUM(IF(Period=BM$4,IF(Category=$A$86,IF(Provider=$B89,Responses))))} -> 8 | BQ89: =BM89*(BO89/SUM(BO$87:BO$120)) -> 2.3118943 | BS89: =BM89*(BO89/(SUM(BO$9:BO$42)+SUM(BO$48:BO$81)+SUM(BO$87:BO$120)+SUM(BO$126:BO$159)+SUM(BO$165:BO$198)+SUM(BO$204:BO$237))) -> 0.37864358 | BU89: {=SUM(IF(Period=BU$4,IF(Category=$A$86,IF(Provider=$B89,Score))))} -> 75 | BW89: {=SUM(IF(Period=BU$4,IF(Category=$A$86,IF(Provider=$B89,Responses))))} -> 6 | BY89: =BU89*(BW89/SUM(BW$87:BW$120)) -> 1.875 | CA89: =BU89*(BW89/(SUM(BW$9:BW$42)+SUM(BW$48:BW$81)+SUM(BW$87:BW$120)+SUM(BW$126:BW$159)+SUM(BW$165:BW$198)+SUM(BW$204:BW$237))) -> 0.31098825
B90: ANDREA J BETANCOURT | C90: 0 | E90: 0 | G90: 0 | I90: {=SUM(IF(Period=I$4,IF(Category=$A$86,IF(Provider=$B90,Score))))} -> 62.5 | K90: {=SUM(IF(Period=I$4,IF(Category=$A$86,IF(Provider=$B90,Responses))))} -> 4 | M90: =I90*(K90/SUM(K$87:K$120)) -> 1.25 | O90: =I90*(K90/(SUM(K$9:K$42)+SUM(K$48:K$81)+SUM(K$87:K$120)+SUM(K$126:K$159)+SUM(K$165:K$198)+SUM(K$204:K$237))) -> 0.20678246 | Q90: {=SUM(IF(Period=Q$4,IF(Category=$A$86,IF(Provider=$B90,Score))))} -> 85 | S90: {=SUM(IF(Period=Q$4,IF(Category=$A$86,IF(Provider=$B90,Responses))))} -> 5 | U90: =Q90*(S90/SUM(S$87:S$120)) -> 2.3224044 | W90: =Q90*(S90/(SUM(S$9:S$42)+SUM(S$48:S$81)+SUM(S$87:S$120)+SUM(S$126:S$159)+SUM(S$165:S$198)+SUM(S$204:S$237))) -> 0.37878788 | Y90: {=SUM(IF(Period=Y$4,IF(Category=$A$86,IF(Provider=$B90,Score))))} -> 75 | AA90: {=SUM(IF(Period=Y$4,IF(Category=$A$86,IF(Provider=$B90,Responses))))} -> 11 | AC90: =Y90*(AA90/SUM(AA$87:AA$120)) -> 2.75 | AE90: =Y90*(AA90/(SUM(AA$9:AA$42)+SUM(AA$48:AA$81)+SUM(AA$87:AA$120)+SUM(AA$126:AA$159)+SUM(AA$165:AA$198)+SUM(AA$204:AA$237))) -> 0.45504688 | AG90: {=SUM(IF(Period=AG$4,IF(Category=$A$86,IF(Provider=$B90,Score))))} -> 85 | AI90: {=SUM(IF(Period=AG$4,IF(Category=$A$86,IF(Provider=$B90,Responses))))} -> 5 | AK90: =AG90*(AI90/SUM(AI$87:AI$120)) -> 1.6536965 | AM90: =AG90*(AI90/(SUM(AI$9:AI$42)+SUM(AI$48:AI$81)+SUM(AI$87:AI$120)+SUM(AI$126:AI$159)+SUM(AI$165:AI$198)+SUM(AI$204:AI$237))) -> 0.27525907 | AO90: {=SUM(IF(Period=AO$4,IF(Category=$A$86,IF(Provider=$B90,Score))))} -> 86.1 | AQ90: {=SUM(IF(Period=AO$4,IF(Category=$A$86,IF(Provider=$B90,Responses))))} -> 9 | AS90: =AO90*(AQ90/SUM(AQ$87:AQ$120)) -> 4.5852071 | AU90: =AO90*(AQ90/(SUM(AQ$9:AQ$42)+SUM(AQ$48:AQ$81)+SUM(AQ$87:AQ$120)+SUM(AQ$126:AQ$159)+SUM(AQ$165:AQ$198)+SUM(AQ$204:AQ$237))) -> 0.75526316 | AW90: {=SUM(IF(Period=AW$4,IF(Category=$A$86,IF(Provider=$B90,Score))))} -> 62.5 | AY90: {=SUM(IF(Period=AW$4,IF(Category=$A$86,IF(Provider=$B90,Responses))))} -> 2 | BA90: =AW90*(AY90/SUM(AY$87:AY$120)) -> 0.58139535 | BC90: =AW90*(AY90/(SUM(AY$9:AY$42)+SUM(AY$48:AY$81)+SUM(AY$87:AY$120)+SUM(AY$126:AY$159)+SUM(AY$165:AY$198)+SUM(AY$204:AY$237))) -> 0.096006144 | BE90: {=SUM(IF(Period=BE$4,IF(Category=$A$86,IF(Provider=$B90,Score))))} -> 75 | BG90: {=SUM(IF(Period=BE$4,IF(Category=$A$86,IF(Provider=$B90,Responses))))} -> 2 | BI90: =BE90*(BG90/SUM(BG$87:BG$120)) -> 0.63829787 | BK90: =BE90*(BG90/(SUM(BG$9:BG$42)+SUM(BG$48:BG$81)+SUM(BG$87:BG$120)+SUM(BG$126:BG$159)+SUM(BG$165:BG$198)+SUM(BG$204:BG$237))) -> 0.10600707 | BM90: {=SUM(IF(Period=BM$4,IF(Category=$A$86,IF(Provider=$B90,Score))))} -> 87.5 | BO90: {=SUM(IF(Period=BM$4,IF(Category=$A$86,IF(Provider=$B90,Responses))))} -> 6 | BQ90: =BM90*(BO90/SUM(BO$87:BO$120)) -> 2.3127753 | BS90: =BM90*(BO90/(SUM(BO$9:BO$42)+SUM(BO$48:BO$81)+SUM(BO$87:BO$120)+SUM(BO$126:BO$159)+SUM(BO$165:BO$198)+SUM(BO$204:BO$237))) -> 0.37878788 | BU90: {=SUM(IF(Period=BU$4,IF(Category=$A$86,IF(Provider=$B90,Score))))} -> 96.9 | BW90: {=SUM(IF(Period=BU$4,IF(Category=$A$86,IF(Provider=$B90,Responses))))} -> 8 | BY90: =BU90*(BW90/SUM(BW$87:BW$120)) -> 3.23 | CA90: =BU90*(BW90/(SUM(BW$9:BW$42)+SUM(BW$48:BW$81)+SUM(BW$87:BW$120)+SUM(BW$126:BW$159)+SUM(BW$165:BW$198)+SUM(BW$204:BW$237))) -> 0.53572909
B91: ANDREW MASON | C91: 0 | E91: 0 | G91: 0 | I91: {=SUM(IF(Period=I$4,IF(Category=$A$86,IF(Provider=$B91,Score))))} -> 78.6 | K91: {=SUM(IF(Period=I$4,IF(Category=$A$86,IF(Provider=$B91,Responses))))} -> 7 | M91: =I91*(K91/SUM(K$87:K$120)) -> 2.751 | O91: =I91*(K91/(SUM(K$9:K$42)+SUM(K$48:K$81)+SUM(K$87:K$120)+SUM(K$126:K$159)+SUM(K$165:K$198)+SUM(K$204:K$237))) -> 0.45508685 | Q91: {=SUM(IF(Period=Q$4,IF(Category=$A$86,IF(Provider=$B91,Score))))} -> 75 | S91: {=SUM(IF(Period=Q$4,IF(Category=$A$86,IF(Provider=$B91,Responses))))} -> 6 | U91: =Q91*(S91/SUM(S$87:S$120)) -> 2.4590164 | W91: =Q91*(S91/(SUM(S$9:S$42)+SUM(S$48:S$81)+SUM(S$87:S$120)+SUM(S$126:S$159)+SUM(S$165:S$198)+SUM(S$204:S$237))) -> 0.40106952 | Y91: {=SUM(IF(Period=Y$4,IF(Category=$A$86,IF(Provider=$B91,Score))))} -> 68.8 | AA91: {=SUM(IF(Period=Y$4,IF(Category=$A$86,IF(Provider=$B91,Responses))))} -> 12 | AC91: =Y91*(AA91/SUM(AA$87:AA$120)) -> 2.752 | AE91: =Y91*(AA91/(SUM(AA$9:AA$42)+SUM(AA$48:AA$81)+SUM(AA$87:AA$120)+SUM(AA$126:AA$159)+SUM(AA$165:AA$198)+SUM(AA$204:AA$237))) -> 0.45537783 | AG91: {=SUM(IF(Period=AG$4,IF(Category=$A$86,IF(Provider=$B91,Score))))} -> 86.1 | AI91: {=SUM(IF(Period=AG$4,IF(Category=$A$86,IF(Provider=$B91,Responses))))} -> 9 | AK91: =AG91*(AI91/SUM(AI$87:AI$120)) -> 3.0151751 | AM91: =AG91*(AI91/(SUM(AI$9:AI$42)+SUM(AI$48:AI$81)+SUM(AI$87:AI$120)+SUM(AI$126:AI$159)+SUM(AI$165:AI$198)+SUM(AI$204:AI$237))) -> 0.50187824 | AO91: {=SUM(IF(Period=AO$4,IF(Category=$A$86,IF(Provider=$B91,Score))))} -> 100 | AQ91: {=SUM(IF(Period=AO$4,IF(Category=$A$86,IF(Provider=$B91,Responses))))} -> 4 | AS91: =AO91*(AQ91/SUM(AQ$87:AQ$120)) -> 2.3668639 | AU91: =AO91*(AQ91/(SUM(AQ$9:AQ$42)+SUM(AQ$48:AQ$81)+SUM(AQ$87:AQ$120)+SUM(AQ$126:AQ$159)+SUM(AQ$165:AQ$198)+SUM(AQ$204:AQ$237))) -> 0.38986355 | AW91: {=SUM(IF(Period=AW$4,IF(Category=$A$86,IF(Provider=$B91,Score))))} -> 79.2 | AY91: {=SUM(IF(Period=AW$4,IF(Category=$A$86,IF(Provider=$B91,Responses))))} -> 6 | BA91: =AW91*(AY91/SUM(AY$87:AY$120)) -> 2.2102326 | BC91: =AW91*(AY91/(SUM(AY$9:AY$42)+SUM(AY$48:AY$81)+SUM(AY$87:AY$120)+SUM(AY$126:AY$159)+SUM(AY$165:AY$198)+SUM(AY$204:AY$237))) -> 0.36497696 | BE91: {=SUM(IF(Period=BE$4,IF(Category=$A$86,IF(Provider=$B91,Score))))} -> 54.2 | BG91: {=SUM(IF(Period=BE$4,IF(Category=$A$86,IF(Provider=$B91,Responses))))} -> 6 | BI91: =BE91*(BG91/SUM(BG$87:BG$120)) -> 1.3838298 | BK91: =BE91*(BG91/(SUM(BG$9:BG$42)+SUM(BG$48:BG$81)+SUM(BG$87:BG$120)+SUM(BG$126:BG$159)+SUM(BG$165:BG$198)+SUM(BG$204:BG$237))) -> 0.22982332 | BM91: {=SUM(IF(Period=BM$4,IF(Category=$A$86,IF(Provider=$B91,Score))))} -> 67.9 | BO91: {=SUM(IF(Period=BM$4,IF(Category=$A$86,IF(Provider=$B91,Responses))))} -> 7 | BQ91: =BM91*(BO91/SUM(BO$87:BO$120)) -> 2.0938326 | BS91: =BM91*(BO91/(SUM(BO$9:BO$42)+SUM(BO$48:BO$81)+SUM(BO$87:BO$120)+SUM(BO$126:BO$159)+SUM(BO$165:BO$198)+SUM(BO$204:BO$237))) -> 0.34292929 | BU91: {=SUM(IF(Period=BU$4,IF(Category=$A$86,IF(Provider=$B91,Score))))} -> 82.1 | BW91: {=SUM(IF(Period=BU$4,IF(Category=$A$86,IF(Provider=$B91,Responses))))} -> 7 | BY91: =BU91*(BW91/SUM(BW$87:BW$120)) -> 2.3945833 | CA91: =BU91*(BW91/(SUM(BW$9:BW$42)+SUM(BW$48:BW$81)+SUM(BW$87:BW$120)+SUM(BW$126:BW$159)+SUM(BW$165:BW$198)+SUM(BW$204:BW$237))) -> 0.39716655
B92: ANTONY FRIEDMAN | C92: 0 | E92: 0 | G92: 0 | I92: {=SUM(IF(Period=I$4,IF(Category=$A$86,IF(Provider=$B92,Score))))} -> 50 | K92: {=SUM(IF(Period=I$4,IF(Category=$A$86,IF(Provider=$B92,Responses))))} -> 4 | M92: =I92*(K92/SUM(K$87:K$120)) -> 1 | O92: =I92*(K92/(SUM(K$9:K$42)+SUM(K$48:K$81)+SUM(K$87:K$120)+SUM(K$126:K$159)+SUM(K$165:K$198)+SUM(K$204:K$237))) -> 0.16542597 | Q92: {=SUM(IF(Period=Q$4,IF(Category=$A$86,IF(Provider=$B92,Score))))} -> 35 | S92: {=SUM(IF(Period=Q$4,IF(Category=$A$86,IF(Provider=$B92,Responses))))} -> 10 | U92: =Q92*(S92/SUM(S$87:S$120)) -> 1.9125683 | W92: =Q92*(S92/(SUM(S$9:S$42)+SUM(S$48:S$81)+SUM(S$87:S$120)+SUM(S$126:S$159)+SUM(S$165:S$198)+SUM(S$204:S$237))) -> 0.31194296 | Y92: {=SUM(IF(Period=Y$4,IF(Category=$A$86,IF(Provider=$B92,Score))))} -> 65 | AA92: {=SUM(IF(Period=Y$4,IF(Category=$A$86,IF(Provider=$B92,Responses))))} -> 5 | AC92: =Y92*(AA92/SUM(AA$87:AA$120)) -> 1.0833333 | AE92: =Y92*(AA92/(SUM(AA$9:AA$42)+SUM(AA$48:AA$81)+SUM(AA$87:AA$120)+SUM(AA$126:AA$159)+SUM(AA$165:AA$198)+SUM(AA$204:AA$237))) -> 0.17926089 | AG92: {=SUM(IF(Period=AG$4,IF(Category=$A$86,IF(Provider=$B92,Score))))} -> 75 | AI92: {=SUM(IF(Period=AG$4,IF(Category=$A$86,IF(Provider=$B92,Responses))))} -> 1 | AK92: =AG92*(AI92/SUM(AI$87:AI$120)) -> 0.29182879 | AM92: =AG92*(AI92/(SUM(AI$9:AI$42)+SUM(AI$48:AI$81)+SUM(AI$87:AI$120)+SUM(AI$126:AI$159)+SUM(AI$165:AI$198)+SUM(AI$204:AI$237))) -> 0.04857513 | AO92: {=SUM(IF(Period=AO$4,IF(Category=$A$86,IF(Provider=$B92,Score))))} -> 87.5 | AQ92: {=SUM(IF(Period=AO$4,IF(Category=$A$86,IF(Provider=$B92,Responses))))} -> 6 | AS92: =AO92*(AQ92/SUM(AQ$87:AQ$120)) -> 3.1065089 | AU92: =AO92*(AQ92/(SUM(AQ$9:AQ$42)+SUM(AQ$48:AQ$81)+SUM(AQ$87:AQ$120)+SUM(AQ$126:AQ$159)+SUM(AQ$165:AQ$198)+SUM(AQ$204:AQ$237))) -> 0.51169591 | AW92: {=SUM(IF(Period=AW$4,IF(Category=$A$86,IF(Provider=$B92,Score))))} -> 62.5 | AY92: {=SUM(IF(Period=AW$4,IF(Category=$A$86,IF(Provider=$B92,Responses))))} -> 8 | BA92: =AW92*(AY92/SUM(AY$87:AY$120)) -> 2.3255814 | BC92: =AW92*(AY92/(SUM(AY$9:AY$42)+SUM(AY$48:AY$81)+SUM(AY$87:AY$120)+SUM(AY$126:AY$159)+SUM(AY$165:AY$198)+SUM(AY$204:AY$237))) -> 0.38402458 | BE92: {=SUM(IF(Period=BE$4,IF(Category=$A$86,IF(Provider=$B92,Score))))} -> 56.7 | BG92: {=SUM(IF(Period=BE$4,IF(Category=$A$86,IF(Provider=$B92,Responses))))} -> 15 | BI92: =BE92*(BG92/SUM(BG$87:BG$120)) -> 3.6191489 | BK92: =BE92*(BG92/(SUM(BG$9:BG$42)+SUM(BG$48:BG$81)+SUM(BG$87:BG$120)+SUM(BG$126:BG$159)+SUM(BG$165:BG$198)+SUM(BG$204:BG$237))) -> 0.60106007 | BM92: {=SUM(IF(Period=BM$4,IF(Category=$A$86,IF(Provider=$B92,Score))))} -> 80 | BO92: {=SUM(IF(Period=BM$4,IF(Category=$A$86,IF(Provider=$B92,Responses))))} -> 10 | BQ92: =BM92*(BO92/SUM(BO$87:BO$120)) -> 3.5242291 | BS92: =BM92*(BO92/(SUM(BO$9:BO$42)+SUM(BO$48:BO$81)+SUM(BO$87:BO$120)+SUM(BO$126:BO$159)+SUM(BO$165:BO$198)+SUM(BO$204:BO$237))) -> 0.57720058 | BU92: {=SUM(IF(Period=BU$4,IF(Category=$A$86,IF(Provider=$B92,Score))))} -> 65.6 | BW92: {=SUM(IF(Period=BU$4,IF(Category=$A$86,IF(Provider=$B92,Responses))))} -> 8 | BY92: =BU92*(BW92/SUM(BW$87:BW$120)) -> 2.1866667 | CA92: =BU92*(BW92/(SUM(BW$9:BW$42)+SUM(BW$48:BW$81)+SUM(BW$87:BW$120)+SUM(BW$126:BW$159)+SUM(BW$165:BW$198)+SUM(BW$204:BW$237))) -> 0.36268141
B93: CHARLES SANZ | C93: 0 | E93: 0 | G93: 0 | I93: {=SUM(IF(Period=I$4,IF(Category=$A$86,IF(Provider=$B93,Score))))} -> 87.5 | K93: {=SUM(IF(Period=I$4,IF(Category=$A$86,IF(Provider=$B93,Responses))))} -> 4 | M93: =I93*(K93/SUM(K$87:K$120)) -> 1.75 | O93: =I93*(K93/(SUM(K$9:K$42)+SUM(K$48:K$81)+SUM(K$87:K$120)+SUM(K$126:K$159)+SUM(K$165:K$198)+SUM(K$204:K$237))) -> 0.28949545 | Q93: {=SUM(IF(Period=Q$4,IF(Category=$A$86,IF(Provider=$B93,Score))))} -> 91.7 | S93: {=SUM(IF(Period=Q$4,IF(Category=$A$86,IF(Provider=$B93,Responses))))} -> 3 | U93: =Q93*(S93/SUM(S$87:S$120)) -> 1.5032787 | W93: =Q93*(S93/(SUM(S$9:S$42)+SUM(S$48:S$81)+SUM(S$87:S$120)+SUM(S$126:S$159)+SUM(S$165:S$198)+SUM(S$204:S$237))) -> 0.24518717 | Y93: {=SUM(IF(Period=Y$4,IF(Category=$A$86,IF(Provider=$B93,Score))))} -> 90.6 | AA93: {=SUM(IF(Period=Y$4,IF(Category=$A$86,IF(Provider=$B93,Responses))))} -> 8 | AC93: =Y93*(AA93/SUM(AA$87:AA$120)) -> 2.416 | AE93: =Y93*(AA93/(SUM(AA$9:AA$42)+SUM(AA$48:AA$81)+SUM(AA$87:AA$120)+SUM(AA$126:AA$159)+SUM(AA$165:AA$198)+SUM(AA$204:AA$237))) -> 0.39977937 | AG93: {=SUM(IF(Period=AG$4,IF(Category=$A$86,IF(Provider=$B93,Score))))} -> 90.6 | AI93: {=SUM(IF(Period=AG$4,IF(Category=$A$86,IF(Provider=$B93,Responses))))} -> 8 | AK93: =AG93*(AI93/SUM(AI$87:AI$120)) -> 2.8202335 | AM93: =AG93*(AI93/(SUM(AI$9:AI$42)+SUM(AI$48:AI$81)+SUM(AI$87:AI$120)+SUM(AI$126:AI$159)+SUM(AI$165:AI$198)+SUM(AI$204:AI$237))) -> 0.46943005 | AO93: {=SUM(IF(Period=AO$4,IF(Category=$A$86,IF(Provider=$B93,Score))))} -> 83.3 | AQ93: {=SUM(IF(Period=AO$4,IF(Category=$A$86,IF(Provider=$B93,Responses))))} -> 3 | AS93: =AO93*(AQ93/SUM(AQ$87:AQ$120)) -> 1.4786982 | AU93: =AO93*(AQ93/(SUM(AQ$9:AQ$42)+SUM(AQ$48:AQ$81)+SUM(AQ$87:AQ$120)+SUM(AQ$126:AQ$159)+SUM(AQ$165:AQ$198)+SUM(AQ$204:AQ$237))) -> 0.24356725 | AW93: {=SUM(IF(Period=AW$4,IF(Category=$A$86,IF(Provider=$B93,Score))))} -> 91.7 | AY93: {=SUM(IF(Period=AW$4,IF(Category=$A$86,IF(Provider=$B93,Responses))))} -> 3 | BA93: =AW93*(AY93/SUM(AY$87:AY$120)) -> 1.2795349 | BC93: =AW93*(AY93/(SUM(AY$9:AY$42)+SUM(AY$48:AY$81)+SUM(AY$87:AY$120)+SUM(AY$126:AY$159)+SUM(AY$165:AY$198)+SUM(AY$204:AY$237))) -> 0.21129032 | BE93: {=SUM(IF(Period=BE$4,IF(Category=$A$86,IF(Provider=$B93,Score))))} -> 67.3 | BG93: {=SUM(IF(Period=BE$4,IF(Category=$A$86,IF(Provider=$B93,Responses))))} -> 13 | BI93: =BE93*(BG93/SUM(BG$87:BG$120)) -> 3.7229787 | BK93: =BE93*(BG93/(SUM(BG$9:BG$42)+SUM(BG$48:BG$81)+SUM(BG$87:BG$120)+SUM(BG$126:BG$159)+SUM(BG$165:BG$198)+SUM(BG$204:BG$237))) -> 0.61830389 | BM93: {=SUM(IF(Period=BM$4,IF(Category=$A$86,IF(Provider=$B93,Score))))} -> 93.8 | BO93: {=SUM(IF(Period=BM$4,IF(Category=$A$86,IF(Provider=$B93,Responses))))} -> 12 | BQ93: =BM93*(BO93/SUM(BO$87:BO$120)) -> 4.9585903 | BS93: =BM93*(BO93/(SUM(BO$9:BO$42)+SUM(BO$48:BO$81)+SUM(BO$87:BO$120)+SUM(BO$126:BO$159)+SUM(BO$165:BO$198)+SUM(BO$204:BO$237))) -> 0.81212121 | BU93: {=SUM(IF(Period=BU$4,IF(Category=$A$86,IF(Provider=$B93,Score))))} -> 100 | BW93: {=SUM(IF(Period=BU$4,IF(Category=$A$86,IF(Provider=$B93,Responses))))} -> 5 | BY93: =BU93*(BW93/SUM(BW$87:BW$120)) -> 2.0833333 | CA93: =BU93*(BW93/(SUM(BW$9:BW$42)+SUM(BW$48:BW$81)+SUM(BW$87:BW$120)+SUM(BW$126:BW$159)+SUM(BW$165:BW$198)+SUM(BW$204:BW$237))) -> 0.3455425
B94: CHRISTIAN KOKINAKOS | C94: 0 | E94: 0 | G94: 0 | I94: {=SUM(IF(Period=I$4,IF(Category=$A$86,IF(Provider=$B94,Score))))} -> 80 | K94: {=SUM(IF(Period=I$4,IF(Category=$A$86,IF(Provider=$B94,Responses))))} -> 5 | M94: =I94*(K94/SUM(K$87:K$120)) -> 2 | O94: =I94*(K94/(SUM(K$9:K$42)+SUM(K$48:K$81)+SUM(K$87:K$120)+SUM(K$126:K$159)+SUM(K$165:K$198)+SUM(K$204:K$237))) -> 0.33085194 | Q94: {=SUM(IF(Period=Q$4,IF(Category=$A$86,IF(Provider=$B94,Score))))} -> 75 | S94: {=SUM(IF(Period=Q$4,IF(Category=$A$86,IF(Provider=$B94,Responses))))} -> 3 | U94: =Q94*(S94/SUM(S$87:S$120)) -> 1.2295082 | W94: =Q94*(S94/(SUM(S$9:S$42)+SUM(S$48:S$81)+SUM(S$87:S$120)+SUM(S$126:S$159)+SUM(S$165:S$198)+SUM(S$204:S$237))) -> 0.20053476 | Y94: {=SUM(IF(Period=Y$4,IF(Category=$A$86,IF(Provider=$B94,Score))))} -> 0 | AA94: {=SUM(IF(Period=Y$4,IF(Category=$A$86,IF(Provider=$B94,Responses))))} -> 0 | AC94: =Y94*(AA94/SUM(AA$87:AA$120)) -> 0 | AE94: =Y94*(AA94/(SUM(AA$9:AA$42)+SUM(AA$48:AA$81)+SUM(AA$87:AA$120)+SUM(AA$126:AA$159)+SUM(AA$165:AA$198)+SUM(AA$204:AA$237))) -> 0 | AG94: {=SUM(IF(Period=AG$4,IF(Category=$A$86,IF(Provider=$B94,Score))))} -> 0 | AI94: {=SUM(IF(Period=AG$4,IF(Category=$A$86,IF(Provider=$B94,Responses))))} -> 0 | AK94: =AG94*(AI94/SUM(AI$87:AI$120)) -> 0 | AM94: =AG94*(AI94/(SUM(AI$9:AI$42)+SUM(AI$48:AI$81)+SUM(AI$87:AI$120)+SUM(AI$126:AI$159)+SUM(AI$165:AI$198)+SUM(AI$204:AI$237))) -> 0 | AO94: {=SUM(IF(Period=AO$4,IF(Category=$A$86,IF(Provider=$B94,Score))))} -> 0 | AQ94: {=SUM(IF(Period=AO$4,IF(Category=$A$86,IF(Provider=$B94,Responses))))} -> 0 | AS94: =AO94*(AQ94/SUM(AQ$87:AQ$120)) -> 0 | AU94: =AO94*(AQ94/(SUM(AQ$9:AQ$42)+SUM(AQ$48:AQ$81)+SUM(AQ$87:AQ$120)+SUM(AQ$126:AQ$159)+SUM(AQ$165:AQ$198)+SUM(AQ$204:AQ$237))) -> 0 | AW94: {=SUM(IF(Period=AW$4,IF(Category=$A$86,IF(Provider=$B94,Score))))} -> 0 | AY94: {=SUM(IF(Period=AW$4,IF(Category=$A$86,IF(Provider=$B94,Responses))))} -> 0 | BA94: =AW94*(AY94/SUM(AY$87:AY$120)) -> 0 | BC94: =AW94*(AY94/(SUM(AY$9:AY$42)+SUM(AY$48:AY$81)+SUM(AY$87:AY$120)+SUM(AY$126:AY$159)+SUM(AY$165:AY$198)+SUM(AY$204:AY$237))) -> 0 | BE94: {=SUM(IF(Period=BE$4,IF(Category=$A$86,IF(Provider=$B94,Score))))} -> 0 | BG94: {=SUM(IF(Period=BE$4,IF(Category=$A$86,IF(Provider=$B94,Responses))))} -> 0 | BI94: =BE94*(BG94/SUM(BG$87:BG$120)) -> 0 | BK94: =BE94*(BG94/(SUM(BG$9:BG$42)+SUM(BG$48:BG$81)+SUM(BG$87:BG$120)+SUM(BG$126:BG$159)+SUM(BG$165:BG$198)+SUM(BG$204:BG$237))) -> 0 | BM94: {=SUM(IF(Period=BM$4,IF(Category=$A$86,IF(Provider=$B94,Score))))} -> 0 | BO94: {=SUM(IF(Period=BM$4,IF(Category=$A$86,IF(Provider=$B94,Responses))))} -> 0 | BQ94: =BM94*(BO94/SUM(BO$87:BO$120)) -> 0 | BS94: =BM94*(BO94/(SUM(BO$9:BO$42)+SUM(BO$48:BO$81)+SUM(BO$87:BO$120)+SUM(BO$126:BO$159)+SUM(BO$165:BO$198)+SUM(BO$204:BO$237))) -> 0 | BU94: {=SUM(IF(Period=BU$4,IF(Category=$A$86,IF(Provider=$B94,Score))))} -> 0 | BW94: {=SUM(IF(Period=BU$4,IF(Category=$A$86,IF(Provider=$B94,Responses))))} -> 0 | BY94: =BU94*(BW94/SUM(BW$87:BW$120)) -> 0 | CA94: =BU94*(BW94/(SUM(BW$9:BW$42)+SUM(BW$48:BW$81)+SUM(BW$87:BW$120)+SUM(BW$126:BW$159)+SUM(BW$165:BW$198)+SUM(BW$204:BW$237))) -> 0
B95: DANIEL D'AMORE | C95: 0 | E95: 0 | G95: 0 | I95: {=SUM(IF(Period=I$4,IF(Category=$A$86,IF(Provider=$B95,Score))))} -> 71.9 | K95: {=SUM(IF(Period=I$4,IF(Category=$A$86,IF(Provider=$B95,Responses))))} -> 8 | M95: =I95*(K95/SUM(K$87:K$120)) -> 2.876 | O95: =I95*(K95/(SUM(K$9:K$42)+SUM(K$48:K$81)+SUM(K$87:K$120)+SUM(K$126:K$159)+SUM(K$165:K$198)+SUM(K$204:K$237))) -> 0.4757651 | Q95: {=SUM(IF(Period=Q$4,IF(Category=$A$86,IF(Provider=$B95,Score))))} -> 65 | S95: {=SUM(IF(Period=Q$4,IF(Category=$A$86,IF(Provider=$B95,Responses))))} -> 5 | U95: =Q95*(S95/SUM(S$87:S$120)) -> 1.7759563 | W95: =Q95*(S95/(SUM(S$9:S$42)+SUM(S$48:S$81)+SUM(S$87:S$120)+SUM(S$126:S$159)+SUM(S$165:S$198)+SUM(S$204:S$237))) -> 0.28966132 | Y95: {=SUM(IF(Period=Y$4,IF(Category=$A$86,IF(Provider=$B95,Score))))} -> 75 | AA95: {=SUM(IF(Period=Y$4,IF(Category=$A$86,IF(Provider=$B95,Responses))))} -> 11 | AC95: =Y95*(AA95/SUM(AA$87:AA$120)) -> 2.75 | AE95: =Y95*(AA95/(SUM(AA$9:AA$42)+SUM(AA$48:AA$81)+SUM(AA$87:AA$120)+SUM(AA$126:AA$159)+SUM(AA$165:AA$198)+SUM(AA$204:AA$237))) -> 0.45504688 | AG95: {=SUM(IF(Period=AG$4,IF(Category=$A$86,IF(Provider=$B95,Score))))} -> 94.4 | AI95: {=SUM(IF(Period=AG$4,IF(Category=$A$86,IF(Provider=$B95,Responses))))} -> 9 | AK95: =AG95*(AI95/SUM(AI$87:AI$120)) -> 3.3058366 | AM95: =AG95*(AI95/(SUM(AI$9:AI$42)+SUM(AI$48:AI$81)+SUM(AI$87:AI$120)+SUM(AI$126:AI$159)+SUM(AI$165:AI$198)+SUM(AI$204:AI$237))) -> 0.55025907 | AO95: {=SUM(IF(Period=AO$4,IF(Category=$A$86,IF(Provider=$B95,Score))))} -> 83.3 | AQ95: {=SUM(IF(Period=AO$4,IF(Category=$A$86,IF(Provider=$B95,Responses))))} -> 12 | AS95: =AO95*(AQ95/SUM(AQ$87:AQ$120)) -> 5.9147929 | AU95: =AO95*(AQ95/(SUM(AQ$9:AQ$42)+SUM(AQ$48:AQ$81)+SUM(AQ$87:AQ$120)+SUM(AQ$126:AQ$159)+SUM(AQ$165:AQ$198)+SUM(AQ$204:AQ$237))) -> 0.97426901 | AW95: {=SUM(IF(Period=AW$4,IF(Category=$A$86,IF(Provider=$B95,Score))))} -> 84.4 | AY95: {=SUM(IF(Period=AW$4,IF(Category=$A$86,IF(Provider=$B95,Responses))))} -> 8 | BA95: =AW95*(AY95/SUM(AY$87:AY$120)) -> 3.1404651 | BC95: =AW95*(AY95/(SUM(AY$9:AY$42)+SUM(AY$48:AY$81)+SUM(AY$87:AY$120)+SUM(AY$126:AY$159)+SUM(AY$165:AY$198)+SUM(AY$204:AY$237))) -> 0.51858679 | BE95: {=SUM(IF(Period=BE$4,IF(Category=$A$86,IF(Provider=$B95,Score))))} -> 68.8 | BG95: {=SUM(IF(Period=BE$4,IF(Category=$A$86,IF(Provider=$B95,Responses))))} -> 4 | BI95: =BE95*(BG95/SUM(BG$87:BG$120)) -> 1.1710638 | BK95: =BE95*(BG95/(SUM(BG$9:BG$42)+SUM(BG$48:BG$81)+SUM(BG$87:BG$120)+SUM(BG$126:BG$159)+SUM(BG$165:BG$198)+SUM(BG$204:BG$237))) -> 0.19448763 | BM95: {=SUM(IF(Period=BM$4,IF(Category=$A$86,IF(Provider=$B95,Score))))} -> 71.2 | BO95: {=SUM(IF(Period=BM$4,IF(Category=$A$86,IF(Provider=$B95,Responses))))} -> 13 | BQ95: =BM95*(BO95/SUM(BO$87:BO$120)) -> 4.077533 | BS95: =BM95*(BO95/(SUM(BO$9:BO$42)+SUM(BO$48:BO$81)+SUM(BO$87:BO$120)+SUM(BO$126:BO$159)+SUM(BO$165:BO$198)+SUM(BO$204:BO$237))) -> 0.66782107 | BU95: {=SUM(IF(Period=BU$4,IF(Category=$A$86,IF(Provider=$B95,Score))))} -> 69.4 | BW95: {=SUM(IF(Period=BU$4,IF(Category=$A$86,IF(Provider=$B95,Responses))))} -> 9 | BY95: =BU95*(BW95/SUM(BW$87:BW$120)) -> 2.6025 | CA95: =BU95*(BW95/(SUM(BW$9:BW$42)+SUM(BW$48:BW$81)+SUM(BW$87:BW$120)+SUM(BW$126:BW$159)+SUM(BW$165:BW$198)+SUM(BW$204:BW$237))) -> 0.43165169
B96: DAVID MISHKIN | C96: 0 | E96: 0 | G96: 0 | I96: {=SUM(IF(Period=I$4,IF(Category=$A$86,IF(Provider=$B96,Score))))} -> 93.8 | K96: {=SUM(IF(Period=I$4,IF(Category=$A$86,IF(Provider=$B96,Responses))))} -> 8 | M96: =I96*(K96/SUM(K$87:K$120)) -> 3.752 | O96: =I96*(K96/(SUM(K$9:K$42)+SUM(K$48:K$81)+SUM(K$87:K$120)+SUM(K$126:K$159)+SUM(K$165:K$198)+SUM(K$204:K$237))) -> 0.62067825 | Q96: {=SUM(IF(Period=Q$4,IF(Category=$A$86,IF(Provider=$B96,Score))))} -> 62.5 | S96: {=SUM(IF(Period=Q$4,IF(Category=$A$86,IF(Provider=$B96,Responses))))} -> 8 | U96: =Q96*(S96/SUM(S$87:S$120)) -> 2.7322404 | W96: =Q96*(S96/(SUM(S$9:S$42)+SUM(S$48:S$81)+SUM(S$87:S$120)+SUM(S$126:S$159)+SUM(S$165:S$198)+SUM(S$204:S$237))) -> 0.4456328 | Y96: {=SUM(IF(Period=Y$4,IF(Category=$A$86,IF(Provider=$B96,Score))))} -> 76.9 | AA96: {=SUM(IF(Period=Y$4,IF(Category=$A$86,IF(Provider=$B96,Responses))))} -> 13 | AC96: =Y96*(AA96/SUM(AA$87:AA$120)) -> 3.3323333 | AE96: =Y96*(AA96/(SUM(AA$9:AA$42)+SUM(AA$48:AA$81)+SUM(AA$87:AA$120)+SUM(AA$126:AA$159)+SUM(AA$165:AA$198)+SUM(AA$204:AA$237))) -> 0.55140651 | AG96: {=SUM(IF(Period=AG$4,IF(Category=$A$86,IF(Provider=$B96,Score))))} -> 87.5 | AI96: {=SUM(IF(Period=AG$4,IF(Category=$A$86,IF(Provider=$B96,Responses))))} -> 10 | AK96: =AG96*(AI96/SUM(AI$87:AI$120)) -> 3.4046693 | AM96: =AG96*(AI96/(SUM(AI$9:AI$42)+SUM(AI$48:AI$81)+SUM(AI$87:AI$120)+SUM(AI$126:AI$159)+SUM(AI$165:AI$198)+SUM(AI$204:AI$237))) -> 0.56670984 | AO96: {=SUM(IF(Period=AO$4,IF(Category=$A$86,IF(Provider=$B96,Score))))} -> 100 | AQ96: {=SUM(IF(Period=AO$4,IF(Category=$A$86,IF(Provider=$B96,Responses))))} -> 8 | AS96: =AO96*(AQ96/SUM(AQ$87:AQ$120)) -> 4.7337278 | AU96: =AO96*(AQ96/(SUM(AQ$9:AQ$42)+SUM(AQ$48:AQ$81)+SUM(AQ$87:AQ$120)+SUM(AQ$126:AQ$159)+SUM(AQ$165:AQ$198)+SUM(AQ$204:AQ$237))) -> 0.7797271 | AW96: {=SUM(IF(Period=AW$4,IF(Category=$A$86,IF(Provider=$B96,Score))))} -> 89.3 | AY96: {=SUM(IF(Period=AW$4,IF(Category=$A$86,IF(Provider=$B96,Responses))))} -> 14 | BA96: =AW96*(AY96/SUM(AY$87:AY$120)) -> 5.8148837 | BC96: =AW96*(AY96/(SUM(AY$9:AY$42)+SUM(AY$48:AY$81)+SUM(AY$87:AY$120)+SUM(AY$126:AY$159)+SUM(AY$165:AY$198)+SUM(AY$204:AY$237))) -> 0.96021505 | BE96: {=SUM(IF(Period=BE$4,IF(Category=$A$86,IF(Provider=$B96,Score))))} -> 95.5 | BG96: {=SUM(IF(Period=BE$4,IF(Category=$A$86,IF(Provider=$B96,Responses))))} -> 11 | BI96: =BE96*(BG96/SUM(BG$87:BG$120)) -> 4.4702128 | BK96: =BE96*(BG96/(SUM(BG$9:BG$42)+SUM(BG$48:BG$81)+SUM(BG$87:BG$120)+SUM(BG$126:BG$159)+SUM(BG$165:BG$198)+SUM(BG$204:BG$237))) -> 0.74240283 | BM96: {=SUM(IF(Period=BM$4,IF(Category=$A$86,IF(Provider=$B96,Score))))} -> 92.9 | BO96: {=SUM(IF(Period=BM$4,IF(Category=$A$86,IF(Provider=$B96,Responses))))} -> 7 | BQ96: =BM96*(BO96/SUM(BO$87:BO$120)) -> 2.8647577 | BS96: =BM96*(BO96/(SUM(BO$9:BO$42)+SUM(BO$48:BO$81)+SUM(BO$87:BO$120)+SUM(BO$126:BO$159)+SUM(BO$165:BO$198)+SUM(BO$204:BO$237))) -> 0.46919192 | BU96: {=SUM(IF(Period=BU$4,IF(Category=$A$86,IF(Provider=$B96,Score))))} -> 87.5 | BW96: {=SUM(IF(Period=BU$4,IF(Category=$A$86,IF(Provider=$B96,Responses))))} -> 14 | BY96: =BU96*(BW96/SUM(BW$87:BW$120)) -> 5.1041667 | CA96: =BU96*(BW96/(SUM(BW$9:BW$42)+SUM(BW$48:BW$81)+SUM(BW$87:BW$120)+SUM(BW$126:BW$159)+SUM(BW$165:BW$198)+SUM(BW$204:BW$237))) -> 0.84657913
B97: ELAINE DIAZ | C97: 0 | E97: 0 | G97: 0 | I97: {=SUM(IF(Period=I$4,IF(Category=$A$86,IF(Provider=$B97,Score))))} -> 93.8 | K97: {=SUM(IF(Period=I$4,IF(Category=$A$86,IF(Provider=$B97,Responses))))} -> 4 | M97: =I97*(K97/SUM(K$87:K$120)) -> 1.876 | O97: =I97*(K97/(SUM(K$9:K$42)+SUM(K$48:K$81)+SUM(K$87:K$120)+SUM(K$126:K$159)+SUM(K$165:K$198)+SUM(K$204:K$237))) -> 0.31033912 | Q97: {=SUM(IF(Period=Q$4,IF(Category=$A$86,IF(Provider=$B97,Score))))} -> 81.3 | S97: {=SUM(IF(Period=Q$4,IF(Category=$A$86,IF(Provider=$B97,Responses))))} -> 4 | U97: =Q97*(S97/SUM(S$87:S$120)) -> 1.7770492 | W97: =Q97*(S97/(SUM(S$9:S$42)+SUM(S$48:S$81)+SUM(S$87:S$120)+SUM(S$126:S$159)+SUM(S$165:S$198)+SUM(S$204:S$237))) -> 0.28983957 | Y97: {=SUM(IF(Period=Y$4,IF(Category=$A$86,IF(Provider=$B97,Score))))} -> 80 | AA97: {=SUM(IF(Period=Y$4,IF(Category=$A$86,IF(Provider=$B97,Responses))))} -> 5 | AC97: =Y97*(AA97/SUM(AA$87:AA$120)) -> 1.3333333 | AE97: =Y97*(AA97/(SUM(AA$9:AA$42)+SUM(AA$48:AA$81)+SUM(AA$87:AA$120)+SUM(AA$126:AA$159)+SUM(AA$165:AA$198)+SUM(AA$204:AA$237))) -> 0.22062879 | AG97: {=SUM(IF(Period=AG$4,IF(Category=$A$86,IF(Provider=$B97,Score))))} -> 93.8 | AI97: {=SUM(IF(Period=AG$4,IF(Category=$A$86,IF(Provider=$B97,Responses))))} -> 4 | AK97: =AG97*(AI97/SUM(AI$87:AI$120)) -> 1.4599222 | AM97: =AG97*(AI97/(SUM(AI$9:AI$42)+SUM(AI$48:AI$81)+SUM(AI$87:AI$120)+SUM(AI$126:AI$159)+SUM(AI$165:AI$198)+SUM(AI$204:AI$237))) -> 0.24300518 | AO97: {=SUM(IF(Period=AO$4,IF(Category=$A$86,IF(Provider=$B97,Score))))} -> 75 | AQ97: {=SUM(IF(Period=AO$4,IF(Category=$A$86,IF(Provider=$B97,Responses))))} -> 2 | AS97: =AO97*(AQ97/SUM(AQ$87:AQ$120)) -> 0.88757396 | AU97: =AO97*(AQ97/(SUM(AQ$9:AQ$42)+SUM(AQ$48:AQ$81)+SUM(AQ$87:AQ$120)+SUM(AQ$126:AQ$159)+SUM(AQ$165:AQ$198)+SUM(AQ$204:AQ$237))) -> 0.14619883 | AW97: {=SUM(IF(Period=AW$4,IF(Category=$A$86,IF(Provider=$B97,Score))))} -> 80 | AY97: {=SUM(IF(Period=AW$4,IF(Category=$A$86,IF(Provider=$B97,Responses))))} -> 5 | BA97: =AW97*(AY97/SUM(AY$87:AY$120)) -> 1.8604651 | BC97: =AW97*(AY97/(SUM(AY$9:AY$42)+SUM(AY$48:AY$81)+SUM(AY$87:AY$120)+SUM(AY$126:AY$159)+SUM(AY$165:AY$198)+SUM(AY$204:AY$237))) -> 0.30721966 | BE97: {=SUM(IF(Period=BE$4,IF(Category=$A$86,IF(Provider=$B97,Score))))} -> 100 | BG97: {=SUM(IF(Period=BE$4,IF(Category=$A$86,IF(Provider=$B97,Responses))))} -> 2 | BI97: =BE97*(BG97/SUM(BG$87:BG$120)) -> 0.85106383 | BK97: =BE97*(BG97/(SUM(BG$9:BG$42)+SUM(BG$48:BG$81)+SUM(BG$87:BG$120)+SUM(BG$126:BG$159)+SUM(BG$165:BG$198)+SUM(BG$204:BG$237))) -> 0.14134276 | BM97: {=SUM(IF(Period=BM$4,IF(Category=$A$86,IF(Provider=$B97,Score))))} -> 91.7 | BO97: {=SUM(IF(Period=BM$4,IF(Category=$A$86,IF(Provider=$B97,Responses))))} -> 3 | BQ97: =BM97*(BO97/SUM(BO$87:BO$120)) -> 1.2118943 | BS97: =BM97*(BO97/(SUM(BO$9:BO$42)+SUM(BO$48:BO$81)+SUM(BO$87:BO$120)+SUM(BO$126:BO$159)+SUM(BO$165:BO$198)+SUM(BO$204:BO$237))) -> 0.19848485 | BU97: {=SUM(IF(Period=BU$4,IF(Category=$A$86,IF(Provider=$B97,Score))))} -> 75 | BW97: {=SUM(IF(Period=BU$4,IF(Category=$A$86,IF(Provider=$B97,Responses))))} -> 7 | BY97: =BU97*(BW97/SUM(BW$87:BW$120)) -> 2.1875 | CA97: =BU97*(BW97/(SUM(BW$9:BW$42)+SUM(BW$48:BW$81)+SUM(BW$87:BW$120)+SUM(BW$126:BW$159)+SUM(BW$165:BW$198)+SUM(BW$204:BW$237))) -> 0.36281963
B98: EVA ESCATEL | C98: 0 | E98: 0 | G98: 0 | I98: {=SUM(IF(Period=I$4,IF(Category=$A$86,IF(Provider=$B98,Score))))} -> 75 | K98: {=SUM(IF(Period=I$4,IF(Category=$A$86,IF(Provider=$B98,Responses))))} -> 11 | M98: =I98*(K98/SUM(K$87:K$120)) -> 4.125 | O98: =I98*(K98/(SUM(K$9:K$42)+SUM(K$48:K$81)+SUM(K$87:K$120)+SUM(K$126:K$159)+SUM(K$165:K$198)+SUM(K$204:K$237))) -> 0.68238213 | Q98: {=SUM(IF(Period=Q$4,IF(Category=$A$86,IF(Provider=$B98,Score))))} -> 86.1 | S98: {=SUM(IF(Period=Q$4,IF(Category=$A$86,IF(Provider=$B98,Responses))))} -> 9 | U98: =Q98*(S98/SUM(S$87:S$120)) -> 4.2344262 | W98: =Q98*(S98/(SUM(S$9:S$42)+SUM(S$48:S$81)+SUM(S$87:S$120)+SUM(S$126:S$159)+SUM(S$165:S$198)+SUM(S$204:S$237))) -> 0.69064171 | Y98: {=SUM(IF(Period=Y$4,IF(Category=$A$86,IF(Provider=$B98,Score))))} -> 77.8 | AA98: {=SUM(IF(Period=Y$4,IF(Category=$A$86,IF(Provider=$B98,Responses))))} -> 18 | AC98: =Y98*(AA98/SUM(AA$87:AA$120)) -> 4.668 | AE98: =Y98*(AA98/(SUM(AA$9:AA$42)+SUM(AA$48:AA$81)+SUM(AA$87:AA$120)+SUM(AA$126:AA$159)+SUM(AA$165:AA$198)+SUM(AA$204:AA$237))) -> 0.7724214 | AG98: {=SUM(IF(Period=AG$4,IF(Category=$A$86,IF(Provider=$B98,Score))))} -> 84.4 | AI98: {=SUM(IF(Period=AG$4,IF(Category=$A$86,IF(Provider=$B98,Responses))))} -> 16 | AK98: =AG98*(AI98/SUM(AI$87:AI$120)) -> 5.2544747 | AM98: =AG98*(AI98/(SUM(AI$9:AI$42)+SUM(AI$48:AI$81)+SUM(AI$87:AI$120)+SUM(AI$126:AI$159)+SUM(AI$165:AI$198)+SUM(AI$204:AI$237))) -> 0.8746114 | AO98: {=SUM(IF(Period=AO$4,IF(Category=$A$86,IF(Provider=$B98,Score))))} -> 81.3 | AQ98: {=SUM(IF(Period=AO$4,IF(Category=$A$86,IF(Provider=$B98,Responses))))} -> 12 | AS98: =AO98*(AQ98/SUM(AQ$87:AQ$120)) -> 5.7727811 | AU98: =AO98*(AQ98/(SUM(AQ$9:AQ$42)+SUM(AQ$48:AQ$81)+SUM(AQ$87:AQ$120)+SUM(AQ$126:AQ$159)+SUM(AQ$165:AQ$198)+SUM(AQ$204:AQ$237))) -> 0.95087719 | AW98: {=SUM(IF(Period=AW$4,IF(Category=$A$86,IF(Provider=$B98,Score))))} -> 92.5 | AY98: {=SUM(IF(Period=AW$4,IF(Category=$A$86,IF(Provider=$B98,Responses))))} -> 10 | BA98: =AW98*(AY98/SUM(AY$87:AY$120)) -> 4.3023256 | BC98: =AW98*(AY98/(SUM(AY$9:AY$42)+SUM(AY$48:AY$81)+SUM(AY$87:AY$120)+SUM(AY$126:AY$159)+SUM(AY$165:AY$198)+SUM(AY$204:AY$237))) -> 0.71044547 | BE98: {=SUM(IF(Period=BE$4,IF(Category=$A$86,IF(Provider=$B98,Score))))} -> 93.8 | BG98: {=SUM(IF(Period=BE$4,IF(Category=$A$86,IF(Provider=$B98,Responses))))} -> 8 | BI98: =BE98*(BG98/SUM(BG$87:BG$120)) -> 3.1931915 | BK98: =BE98*(BG98/(SUM(BG$9:BG$42)+SUM(BG$48:BG$81)+SUM(BG$87:BG$120)+SUM(BG$126:BG$159)+SUM(BG$165:BG$198)+SUM(BG$204:BG$237))) -> 0.53031802 | BM98: {=SUM(IF(Period=BM$4,IF(Category=$A$86,IF(Provider=$B98,Score))))} -> 97.2 | BO98: {=SUM(IF(Period=BM$4,IF(Category=$A$86,IF(Provider=$B98,Responses))))} -> 9 | BQ98: =BM98*(BO98/SUM(BO$87:BO$120)) -> 3.8537445 | BS98: =BM98*(BO98/(SUM(BO$9:BO$42)+SUM(BO$48:BO$81)+SUM(BO$87:BO$120)+SUM(BO$126:BO$159)+SUM(BO$165:BO$198)+SUM(BO$204:BO$237))) -> 0.63116883 | BU98: {=SUM(IF(Period=BU$4,IF(Category=$A$86,IF(Provider=$B98,Score))))} -> 82.1 | BW98: {=SUM(IF(Period=BU$4,IF(Category=$A$86,IF(Provider=$B98,Responses))))} -> 7 | BY98: =BU98*(BW98/SUM(BW$87:BW$120)) -> 2.3945833 | CA98: =BU98*(BW98/(SUM(BW$9:BW$42)+SUM(BW$48:BW$81)+SUM(BW$87:BW$120)+SUM(BW$126:BW$159)+SUM(BW$165:BW$198)+SUM(BW$204:BW$237))) -> 0.39716655
... B120: NAME NOT GIVEN | C120: 0 | E120: 0 | G120: 0 | I120: {=SUM(IF(Period=I$4,IF(Category=$A$86,IF(Provider=$B120,Score))))} -> 0 | K120: {=SUM(IF(Period=I$4,IF(Category=$A$86,IF(Provider=$B120,Responses))))} -> 0 | M120: =I120*(K120/SUM(K$87:K$120)) -> 0 | O120: =I120*(K120/(SUM(K$9:K$42)+SUM(K$48:K$81)+SUM(K$87:K$120)+SUM(K$126:K$159)+SUM(K$165:K$198)+SUM(K$204:K$237))) -> 0 | Q120: {=SUM(IF(Period=Q$4,IF(Category=$A$86,IF(Provider=$B120,Score))))} -> 0 | S120: {=SUM(IF(Period=Q$4,IF(Category=$A$86,IF(Provider=$B120,Responses))))} -> 0 | U120: =Q120*(S120/SUM(S$87:S$120)) -> 0 | W120: =Q120*(S120/(SUM(S$9:S$42)+SUM(S$48:S$81)+SUM(S$87:S$120)+SUM(S$126:S$159)+SUM(S$165:S$198)+SUM(S$204:S$237))) -> 0 | Y120: {=SUM(IF(Period=Y$4,IF(Category=$A$86,IF(Provider=$B120,Score))))} -> 0 | AA120: {=SUM(IF(Period=Y$4,IF(Category=$A$86,IF(Provider=$B120,Responses))))} -> 0 | AC120: =Y120*(AA120/SUM(AA$87:AA$120)) -> 0 | AE120: =Y120*(AA120/(SUM(AA$9:AA$42)+SUM(AA$48:AA$81)+SUM(AA$87:AA$120)+SUM(AA$126:AA$159)+SUM(AA$165:AA$198)+SUM(AA$204:AA$237))) -> 0 | AG120: {=SUM(IF(Period=AG$4,IF(Category=$A$86,IF(Provider=$B120,Score))))} -> 75 | AI120: {=SUM(IF(Period=AG$4,IF(Category=$A$86,IF(Provider=$B120,Responses))))} -> 1 | AK120: =AG120*(AI120/SUM(AI$87:AI$120)) -> 0.29182879 | AM120: =AG120*(AI120/(SUM(AI$9:AI$42)+SUM(AI$48:AI$81)+SUM(AI$87:AI$120)+SUM(AI$126:AI$159)+SUM(AI$165:AI$198)+SUM(AI$204:AI$237))) -> 0.04857513 | AO120: {=SUM(IF(Period=AO$4,IF(Category=$A$86,IF(Provider=$B120,Score))))} -> 0 | AQ120: {=SUM(IF(Period=AO$4,IF(Category=$A$86,IF(Provider=$B120,Responses))))} -> 0 | AS120: =AO120*(AQ120/SUM(AQ$87:AQ$120)) -> 0 | AU120: =AO120*(AQ120/(SUM(AQ$9:AQ$42)+SUM(AQ$48:AQ$81)+SUM(AQ$87:AQ$120)+SUM(AQ$126:AQ$159)+SUM(AQ$165:AQ$198)+SUM(AQ$204:AQ$237))) -> 0 | AW120: {=SUM(IF(Period=AW$4,IF(Category=$A$86,IF(Provider=$B120,Score))))} -> 0 | AY120: {=SUM(IF(Period=AW$4,IF(Category=$A$86,IF(Provider=$B120,Responses))))} -> 0 | BA120: =AW120*(AY120/SUM(AY$87:AY$120)) -> 0 | BC120: =AW120*(AY120/(SUM(AY$9:AY$42)+SUM(AY$48:AY$81)+SUM(AY$87:AY$120)+SUM(AY$126:AY$159)+SUM(AY$165:AY$198)+SUM(AY$204:AY$237))) -> 0 | BE120: {=SUM(IF(Period=BE$4,IF(Category=$A$86,IF(Provider=$B120,Score))))} -> 0 | BG120: {=SUM(IF(Period=BE$4,IF(Category=$A$86,IF(Provider=$B120,Responses))))} -> 0 | BI120: =BE120*(BG120/SUM(BG$87:BG$120)) -> 0 | BK120: =BE120*(BG120/(SUM(BG$9:BG$42)+SUM(BG$48:BG$81)+SUM(BG$87:BG$120)+SUM(BG$126:BG$159)+SUM(BG$165:BG$198)+SUM(BG$204:BG$237))) -> 0 | BM120: {=SUM(IF(Period=BM$4,IF(Category=$A$86,IF(Provider=$B120,Score))))} -> 0 | BO120: {=SUM(IF(Period=BM$4,IF(Category=$A$86,IF(Provider=$B120,Responses))))} -> 0 | BQ120: =BM120*(BO120/SUM(BO$87:BO$120)) -> 0 | BS120: =BM120*(BO120/(SUM(BO$9:BO$42)+SUM(BO$48:BO$81)+SUM(BO$87:BO$120)+SUM(BO$126:BO$159)+SUM(BO$165:BO$198)+SUM(BO$204:BO$237))) -> 0 | BU120: {=SUM(IF(Period=BU$4,IF(Category=$A$86,IF(Provider=$B120,Score))))} -> 0 | BW120: {=SUM(IF(Period=BU$4,IF(Category=$A$86,IF(Provider=$B120,Responses))))} -> 0 | BY120: =BU120*(BW120/SUM(BW$87:BW$120)) -> 0 | CA120: =BU120*(BW120/(SUM(BW$9:BW$42)+SUM(BW$48:BW$81)+SUM(BW$87:BW$120)+SUM(BW$126:BW$159)+SUM(BW$165:BW$198)+SUM(BW$204:BW$237))) -> 0
B121: Average for Category: | C121: 0 | E121: 0 | G121: 0 | I121: =SUM(M87:M120) -> 72.5055 | K121: =AVERAGEIF(K87:K120,"<>0") -> 6.25 | Q121: =SUM(U87:U120) -> 75.413115 | S121: =AVERAGEIF(S87:S120,"<>0") -> 6.1 | Y121: =SUM(AC87:AC120) -> 76.000667 | AA121: =AVERAGEIF(AA87:AA120,"<>0") -> 9.6774194 | AG121: =SUM(AK87:AK120) -> 81.123346 | AI121: =AVERAGEIF(AI87:AI120,"<>0") -> 7.7878788 | AO121: =SUM(AS87:AS120) -> 78.107101 | AQ121: =AVERAGEIF(AQ87:AQ120,"<>0") -> 5.6333333 | AW121: =SUM(BA87:BA120) -> 79.778605 | AY121: =AVERAGEIF(AY87:AY120,"<>0") -> 6.71875 | BE121: =SUM(BI87:BI120) -> 80.333191 | BG121: =AVERAGEIF(BG87:BG120,"<>0") -> 7.5806452 | BM121: =SUM(BQ87:BQ120) -> 83.044934 | BO121: =AVERAGEIF(BO87:BO120,"<>0") -> 7.09375 | BU121: =SUM(BY87:BY120) -> 78.654167 | BW121: =AVERAGEIF(BW87:BW120,"<>0") -> 7.5
B122: Median Values: | I122: {=MEDIAN(IF(I87:I120<>0,I87:I120))} -> 76.8 | K122: {=MEDIAN(IF(K87:K120<>0,K87:K120))} -> 6.5 | Q122: {=MEDIAN(IF(Q87:Q120<>0,Q87:Q120))} -> 80.65 | S122: {=MEDIAN(IF(S87:S120<>0,S87:S120))} -> 5.5 | Y122: {=MEDIAN(IF(Y87:Y120<>0,Y87:Y120))} -> 75 | AA122: {=MEDIAN(IF(AA87:AA120<>0,AA87:AA120))} -> 9 | AG122: {=MEDIAN(IF(AG87:AG120<>0,AG87:AG120))} -> 82.5 | AI122: {=MEDIAN(IF(AI87:AI120<>0,AI87:AI120))} -> 8 | AO122: {=MEDIAN(IF(AO87:AO120<>0,AO87:AO120))} -> 82.55 | AQ122: {=MEDIAN(IF(AQ87:AQ120<>0,AQ87:AQ120))} -> 5.5 | AW122: {=MEDIAN(IF(AW87:AW120<>0,AW87:AW120))} -> 81.3 | AY122: {=MEDIAN(IF(AY87:AY120<>0,AY87:AY120))} -> 6 | BE122: {=MEDIAN(IF(BE87:BE120<>0,BE87:BE120))} -> 83.3 | BG122: {=MEDIAN(IF(BG87:BG120<>0,BG87:BG120))} -> 7 | BM122: {=MEDIAN(IF(BM87:BM120<>0,BM87:BM120))} -> 84.9 | BO122: {=MEDIAN(IF(BO87:BO120<>0,BO87:BO120))} -> 7 | BU122: {=MEDIAN(IF(BU87:BU120<>0,BU87:BU120))} -> 79.8 | BW122: {=MEDIAN(IF(BW87:BW120<>0,BW87:BW120))} -> 7
B123: Subtotal n: | K123: =SUM(K87:K120) -> 200 | S123: =SUM(S87:S120) -> 183 | AA123: =SUM(AA87:AA120) -> 300 | AI123: =SUM(AI87:AI120) -> 257 | AQ123: =SUM(AQ87:AQ120) -> 169 | AY123: =SUM(AY87:AY120) -> 215 | BG123: =SUM(BG87:BG120) -> 235 | BO123: =SUM(BO87:BO120) -> 227 | BW123: =SUM(BW87:BW120) -> 240
A125: Doctors courtesy
B126: ALAN ITZKOWITZ | C126: 0 | E126: 0 | G126: 0 | I126: {=SUM(IF(Period=I$4,IF(Category=$A$125,IF(Provider=$B126,Score))))} -> 85.7 | K126: {=SUM(IF(Period=I$4,IF(Category=$A$125,IF(Provider=$B126,Responses))))} -> 7 | M126: =I126*(K126/SUM(K$126:K$159)) -> 2.969802 | O126: =I126*(K126/(SUM(K$9:K$42)+SUM(K$48:K$81)+SUM(K$87:K$120)+SUM(K$126:K$159)+SUM(K$165:K$198)+SUM(K$204:K$237))) -> 0.4961952 | Q126: {=SUM(IF(Period=Q$4,IF(Category=$A$125,IF(Provider=$B126,Score))))} -> 87.5 | S126: {=SUM(IF(Period=Q$4,IF(Category=$A$125,IF(Provider=$B126,Responses))))} -> 4 | U126: =Q126*(S126/SUM(S$126:S$159)) -> 1.8716578 | W126: =Q126*(S126/(SUM(S$9:S$42)+SUM(S$48:S$81)+SUM(S$87:S$120)+SUM(S$126:S$159)+SUM(S$165:S$198)+SUM(S$204:S$237))) -> 0.31194296 | Y126: {=SUM(IF(Period=Y$4,IF(Category=$A$125,IF(Provider=$B126,Score))))} -> 91.1 | AA126: {=SUM(IF(Period=Y$4,IF(Category=$A$125,IF(Provider=$B126,Responses))))} -> 14 | AC126: =Y126*(AA126/SUM(AA$126:AA$159)) -> 4.2092409 | AE126: =Y126*(AA126/(SUM(AA$9:AA$42)+SUM(AA$48:AA$81)+SUM(AA$87:AA$120)+SUM(AA$126:AA$159)+SUM(AA$165:AA$198)+SUM(AA$204:AA$237))) -> 0.7034749 | AG126: {=SUM(IF(Period=AG$4,IF(Category=$A$125,IF(Provider=$B126,Score))))} -> 100 | AI126: {=SUM(IF(Period=AG$4,IF(Category=$A$125,IF(Provider=$B126,Responses))))} -> 3 | AK126: =AG126*(AI126/SUM(AI$126:AI$159)) -> 1.1673152 | AM126: =AG126*(AI126/(SUM(AI$9:AI$42)+SUM(AI$48:AI$81)+SUM(AI$87:AI$120)+SUM(AI$126:AI$159)+SUM(AI$165:AI$198)+SUM(AI$204:AI$237))) -> 0.19430052 | AO126: {=SUM(IF(Period=AO$4,IF(Category=$A$125,IF(Provider=$B126,Score))))} -> 100 | AQ126: {=SUM(IF(Period=AO$4,IF(Category=$A$125,IF(Provider=$B126,Responses))))} -> 2 | AS126: =AO126*(AQ126/SUM(AQ$126:AQ$159)) -> 1.1695906 | AU126: =AO126*(AQ126/(SUM(AQ$9:AQ$42)+SUM(AQ$48:AQ$81)+SUM(AQ$87:AQ$120)+SUM(AQ$126:AQ$159)+SUM(AQ$165:AQ$198)+SUM(AQ$204:AQ$237))) -> 0.19493177 | AW126: {=SUM(IF(Period=AW$4,IF(Category=$A$125,IF(Provider=$B126,Score))))} -> 95 | AY126: {=SUM(IF(Period=AW$4,IF(Category=$A$125,IF(Provider=$B126,Responses))))} -> 5 | BA126: =AW126*(AY126/SUM(AY$126:AY$159)) -> 2.1889401 | BC126: =AW126*(AY126/(SUM(AY$9:AY$42)+SUM(AY$48:AY$81)+SUM(AY$87:AY$120)+SUM(AY$126:AY$159)+SUM(AY$165:AY$198)+SUM(AY$204:AY$237))) -> 0.36482335 | BE126: {=SUM(IF(Period=BE$4,IF(Category=$A$125,IF(Provider=$B126,Score))))} -> 91.7 | BG126: {=SUM(IF(Period=BE$4,IF(Category=$A$125,IF(Provider=$B126,Responses))))} -> 9 | BI126: =BE126*(BG126/SUM(BG$126:BG$159)) -> 3.4970339 | BK126: =BE126*(BG126/(SUM(BG$9:BG$42)+SUM(BG$48:BG$81)+SUM(BG$87:BG$120)+SUM(BG$126:BG$159)+SUM(BG$165:BG$198)+SUM(BG$204:BG$237))) -> 0.58325088 | BM126: {=SUM(IF(Period=BM$4,IF(Category=$A$125,IF(Provider=$B126,Score))))} -> 100 | BO126: {=SUM(IF(Period=BM$4,IF(Category=$A$125,IF(Provider=$B126,Responses))))} -> 6 | BQ126: =BM126*(BO126/SUM(BO$126:BO$159)) -> 2.5862069 | BS126: =BM126*(BO126/(SUM(BO$9:BO$42)+SUM(BO$48:BO$81)+SUM(BO$87:BO$120)+SUM(BO$126:BO$159)+SUM(BO$165:BO$198)+SUM(BO$204:BO$237))) -> 0.43290043 | BU126: {=SUM(IF(Period=BU$4,IF(Category=$A$125,IF(Provider=$B126,Score))))} -> 85 | BW126: {=SUM(IF(Period=BU$4,IF(Category=$A$125,IF(Provider=$B126,Responses))))} -> 5 | BY126: =BU126*(BW126/SUM(BW$126:BW$159)) -> 1.7634855 | CA126: =BU126*(BW126/(SUM(BW$9:BW$42)+SUM(BW$48:BW$81)+SUM(BW$87:BW$120)+SUM(BW$126:BW$159)+SUM(BW$165:BW$198)+SUM(BW$204:BW$237))) -> 0.29371113
B127: ALEX PALMA | C127: 0 | E127: 0 | G127: 0 | I127: {=SUM(IF(Period=I$4,IF(Category=$A$125,IF(Provider=$B127,Score))))} -> 82.1 | K127: {=SUM(IF(Period=I$4,IF(Category=$A$125,IF(Provider=$B127,Responses))))} -> 7 | M127: =I127*(K127/SUM(K$126:K$159)) -> 2.8450495 | O127: =I127*(K127/(SUM(K$9:K$42)+SUM(K$48:K$81)+SUM(K$87:K$120)+SUM(K$126:K$159)+SUM(K$165:K$198)+SUM(K$204:K$237))) -> 0.47535153 | Q127: {=SUM(IF(Period=Q$4,IF(Category=$A$125,IF(Provider=$B127,Score))))} -> 92.5 | S127: {=SUM(IF(Period=Q$4,IF(Category=$A$125,IF(Provider=$B127,Responses))))} -> 10 | U127: =Q127*(S127/SUM(S$126:S$159)) -> 4.9465241 | W127: =Q127*(S127/(SUM(S$9:S$42)+SUM(S$48:S$81)+SUM(S$87:S$120)+SUM(S$126:S$159)+SUM(S$165:S$198)+SUM(S$204:S$237))) -> 0.82442068 | Y127: {=SUM(IF(Period=Y$4,IF(Category=$A$125,IF(Provider=$B127,Score))))} -> 83.3 | AA127: {=SUM(IF(Period=Y$4,IF(Category=$A$125,IF(Provider=$B127,Responses))))} -> 9 | AC127: =Y127*(AA127/SUM(AA$126:AA$159)) -> 2.4742574 | AE127: =Y127*(AA127/(SUM(AA$9:AA$42)+SUM(AA$48:AA$81)+SUM(AA$87:AA$120)+SUM(AA$126:AA$159)+SUM(AA$165:AA$198)+SUM(AA$204:AA$237))) -> 0.41351351 | AG127: {=SUM(IF(Period=AG$4,IF(Category=$A$125,IF(Provider=$B127,Score))))} -> 100 | AI127: {=SUM(IF(Period=AG$4,IF(Category=$A$125,IF(Provider=$B127,Responses))))} -> 6 | AK127: =AG127*(AI127/SUM(AI$126:AI$159)) -> 2.3346304 | AM127: =AG127*(AI127/(SUM(AI$9:AI$42)+SUM(AI$48:AI$81)+SUM(AI$87:AI$120)+SUM(AI$126:AI$159)+SUM(AI$165:AI$198)+SUM(AI$204:AI$237))) -> 0.38860104 | AO127: {=SUM(IF(Period=AO$4,IF(Category=$A$125,IF(Provider=$B127,Score))))} -> 43.8 | AQ127: {=SUM(IF(Period=AO$4,IF(Category=$A$125,IF(Provider=$B127,Responses))))} -> 4 | AS127: =AO127*(AQ127/SUM(AQ$126:AQ$159)) -> 1.0245614 | AU127: =AO127*(AQ127/(SUM(AQ$9:AQ$42)+SUM(AQ$48:AQ$81)+SUM(AQ$87:AQ$120)+SUM(AQ$126:AQ$159)+SUM(AQ$165:AQ$198)+SUM(AQ$204:AQ$237))) -> 0.17076023 | AW127: {=SUM(IF(Period=AW$4,IF(Category=$A$125,IF(Provider=$B127,Score))))} -> 89.3 | AY127: {=SUM(IF(Period=AW$4,IF(Category=$A$125,IF(Provider=$B127,Responses))))} -> 7 | BA127: =AW127*(AY127/SUM(AY$126:AY$159)) -> 2.8806452 | BC127: =AW127*(AY127/(SUM(AY$9:AY$42)+SUM(AY$48:AY$81)+SUM(AY$87:AY$120)+SUM(AY$126:AY$159)+SUM(AY$165:AY$198)+SUM(AY$204:AY$237))) -> 0.48010753 | BE127: {=SUM(IF(Period=BE$4,IF(Category=$A$125,IF(Provider=$B127,Score))))} -> 100 | BG127: {=SUM(IF(Period=BE$4,IF(Category=$A$125,IF(Provider=$B127,Responses))))} -> 8 | BI127: =BE127*(BG127/SUM(BG$126:BG$159)) -> 3.3898305 | BK127: =BE127*(BG127/(SUM(BG$9:BG$42)+SUM(BG$48:BG$81)+SUM(BG$87:BG$120)+SUM(BG$126:BG$159)+SUM(BG$165:BG$198)+SUM(BG$204:BG$237))) -> 0.56537102 | BM127: {=SUM(IF(Period=BM$4,IF(Category=$A$125,IF(Provider=$B127,Score))))} -> 91.7 | BO127: {=SUM(IF(Period=BM$4,IF(Category=$A$125,IF(Provider=$B127,Responses))))} -> 6 | BQ127: =BM127*(BO127/SUM(BO$126:BO$159)) -> 2.3715517 | BS127: =BM127*(BO127/(SUM(BO$9:BO$42)+SUM(BO$48:BO$81)+SUM(BO$87:BO$120)+SUM(BO$126:BO$159)+SUM(BO$165:BO$198)+SUM(BO$204:BO$237))) -> 0.3969697 | BU127: {=SUM(IF(Period=BU$4,IF(Category=$A$125,IF(Provider=$B127,Score))))} -> 86.4 | BW127: {=SUM(IF(Period=BU$4,IF(Category=$A$125,IF(Provider=$B127,Responses))))} -> 11 | BY127: =BU127*(BW127/SUM(BW$126:BW$159)) -> 3.9435685 | CA127: =BU127*(BW127/(SUM(BW$9:BW$42)+SUM(BW$48:BW$81)+SUM(BW$87:BW$120)+SUM(BW$126:BW$159)+SUM(BW$165:BW$198)+SUM(BW$204:BW$237))) -> 0.65680719
B128: ALEXANDER GARCIA | C128: 0 | E128: 0 | G128: 0 | I128: {=SUM(IF(Period=I$4,IF(Category=$A$125,IF(Provider=$B128,Score))))} -> 92.9 | K128: {=SUM(IF(Period=I$4,IF(Category=$A$125,IF(Provider=$B128,Responses))))} -> 7 | M128: =I128*(K128/SUM(K$126:K$159)) -> 3.2193069 | O128: =I128*(K128/(SUM(K$9:K$42)+SUM(K$48:K$81)+SUM(K$87:K$120)+SUM(K$126:K$159)+SUM(K$165:K$198)+SUM(K$204:K$237))) -> 0.53788255 | Q128: {=SUM(IF(Period=Q$4,IF(Category=$A$125,IF(Provider=$B128,Score))))} -> 91.7 | S128: {=SUM(IF(Period=Q$4,IF(Category=$A$125,IF(Provider=$B128,Responses))))} -> 6 | U128: =Q128*(S128/SUM(S$126:S$159)) -> 2.942246 | W128: =Q128*(S128/(SUM(S$9:S$42)+SUM(S$48:S$81)+SUM(S$87:S$120)+SUM(S$126:S$159)+SUM(S$165:S$198)+SUM(S$204:S$237))) -> 0.49037433 | Y128: {=SUM(IF(Period=Y$4,IF(Category=$A$125,IF(Provider=$B128,Score))))} -> 86.1 | AA128: {=SUM(IF(Period=Y$4,IF(Category=$A$125,IF(Provider=$B128,Responses))))} -> 9 | AC128: =Y128*(AA128/SUM(AA$126:AA$159)) -> 2.5574257 | AE128: =Y128*(AA128/(SUM(AA$9:AA$42)+SUM(AA$48:AA$81)+SUM(AA$87:AA$120)+SUM(AA$126:AA$159)+SUM(AA$165:AA$198)+SUM(AA$204:AA$237))) -> 0.42741313 | AG128: {=SUM(IF(Period=AG$4,IF(Category=$A$125,IF(Provider=$B128,Score))))} -> 100 | AI128: {=SUM(IF(Period=AG$4,IF(Category=$A$125,IF(Provider=$B128,Responses))))} -> 7 | AK128: =AG128*(AI128/SUM(AI$126:AI$159)) -> 2.7237354 | AM128: =AG128*(AI128/(SUM(AI$9:AI$42)+SUM(AI$48:AI$81)+SUM(AI$87:AI$120)+SUM(AI$126:AI$159)+SUM(AI$165:AI$198)+SUM(AI$204:AI$237))) -> 0.45336788 | AO128: {=SUM(IF(Period=AO$4,IF(Category=$A$125,IF(Provider=$B128,Score))))} -> 71.9 | AQ128: {=SUM(IF(Period=AO$4,IF(Category=$A$125,IF(Provider=$B128,Responses))))} -> 8 | AS128: =AO128*(AQ128/SUM(AQ$126:AQ$159)) -> 3.3637427 | AU128: =AO128*(AQ128/(SUM(AQ$9:AQ$42)+SUM(AQ$48:AQ$81)+SUM(AQ$87:AQ$120)+SUM(AQ$126:AQ$159)+SUM(AQ$165:AQ$198)+SUM(AQ$204:AQ$237))) -> 0.56062378 | AW128: {=SUM(IF(Period=AW$4,IF(Category=$A$125,IF(Provider=$B128,Score))))} -> 100 | AY128: {=SUM(IF(Period=AW$4,IF(Category=$A$125,IF(Provider=$B128,Responses))))} -> 6 | BA128: =AW128*(AY128/SUM(AY$126:AY$159)) -> 2.764977 | BC128: =AW128*(AY128/(SUM(AY$9:AY$42)+SUM(AY$48:AY$81)+SUM(AY$87:AY$120)+SUM(AY$126:AY$159)+SUM(AY$165:AY$198)+SUM(AY$204:AY$237))) -> 0.46082949 | BE128: {=SUM(IF(Period=BE$4,IF(Category=$A$125,IF(Provider=$B128,Score))))} -> 87.5 | BG128: {=SUM(IF(Period=BE$4,IF(Category=$A$125,IF(Provider=$B128,Responses))))} -> 8 | BI128: =BE128*(BG128/SUM(BG$126:BG$159)) -> 2.9661017 | BK128: =BE128*(BG128/(SUM(BG$9:BG$42)+SUM(BG$48:BG$81)+SUM(BG$87:BG$120)+SUM(BG$126:BG$159)+SUM(BG$165:BG$198)+SUM(BG$204:BG$237))) -> 0.49469965 | BM128: {=SUM(IF(Period=BM$4,IF(Category=$A$125,IF(Provider=$B128,Score))))} -> 78.1 | BO128: {=SUM(IF(Period=BM$4,IF(Category=$A$125,IF(Provider=$B128,Responses))))} -> 8 | BQ128: =BM128*(BO128/SUM(BO$126:BO$159)) -> 2.6931034 | BS128: =BM128*(BO128/(SUM(BO$9:BO$42)+SUM(BO$48:BO$81)+SUM(BO$87:BO$120)+SUM(BO$126:BO$159)+SUM(BO$165:BO$198)+SUM(BO$204:BO$237))) -> 0.45079365 | BU128: {=SUM(IF(Period=BU$4,IF(Category=$A$125,IF(Provider=$B128,Score))))} -> 79.2 | BW128: {=SUM(IF(Period=BU$4,IF(Category=$A$125,IF(Provider=$B128,Responses))))} -> 6 | BY128: =BU128*(BW128/SUM(BW$126:BW$159)) -> 1.9717842 | CA128: =BU128*(BW128/(SUM(BW$9:BW$42)+SUM(BW$48:BW$81)+SUM(BW$87:BW$120)+SUM(BW$126:BW$159)+SUM(BW$165:BW$198)+SUM(BW$204:BW$237))) -> 0.32840359
B129: ANDREA J BETANCOURT | C129: 0 | E129: 0 | G129: 0 | I129: {=SUM(IF(Period=I$4,IF(Category=$A$125,IF(Provider=$B129,Score))))} -> 68.8 | K129: {=SUM(IF(Period=I$4,IF(Category=$A$125,IF(Provider=$B129,Responses))))} -> 4 | M129: =I129*(K129/SUM(K$126:K$159)) -> 1.3623762 | O129: =I129*(K129/(SUM(K$9:K$42)+SUM(K$48:K$81)+SUM(K$87:K$120)+SUM(K$126:K$159)+SUM(K$165:K$198)+SUM(K$204:K$237))) -> 0.22762614 | Q129: {=SUM(IF(Period=Q$4,IF(Category=$A$125,IF(Provider=$B129,Score))))} -> 92.9 | S129: {=SUM(IF(Period=Q$4,IF(Category=$A$125,IF(Provider=$B129,Responses))))} -> 7 | U129: =Q129*(S129/SUM(S$126:S$159)) -> 3.4775401 | W129: =Q129*(S129/(SUM(S$9:S$42)+SUM(S$48:S$81)+SUM(S$87:S$120)+SUM(S$126:S$159)+SUM(S$165:S$198)+SUM(S$204:S$237))) -> 0.57959002 | Y129: {=SUM(IF(Period=Y$4,IF(Category=$A$125,IF(Provider=$B129,Score))))} -> 86.4 | AA129: {=SUM(IF(Period=Y$4,IF(Category=$A$125,IF(Provider=$B129,Responses))))} -> 11 | AC129: =Y129*(AA129/SUM(AA$126:AA$159)) -> 3.1366337 | AE129: =Y129*(AA129/(SUM(AA$9:AA$42)+SUM(AA$48:AA$81)+SUM(AA$87:AA$120)+SUM(AA$126:AA$159)+SUM(AA$165:AA$198)+SUM(AA$204:AA$237))) -> 0.52421401 | AG129: {=SUM(IF(Period=AG$4,IF(Category=$A$125,IF(Provider=$B129,Score))))} -> 75 | AI129: {=SUM(IF(Period=AG$4,IF(Category=$A$125,IF(Provider=$B129,Responses))))} -> 5 | AK129: =AG129*(AI129/SUM(AI$126:AI$159)) -> 1.459144 | AM129: =AG129*(AI129/(SUM(AI$9:AI$42)+SUM(AI$48:AI$81)+SUM(AI$87:AI$120)+SUM(AI$126:AI$159)+SUM(AI$165:AI$198)+SUM(AI$204:AI$237))) -> 0.24287565 | AO129: {=SUM(IF(Period=AO$4,IF(Category=$A$125,IF(Provider=$B129,Score))))} -> 91.7 | AQ129: {=SUM(IF(Period=AO$4,IF(Category=$A$125,IF(Provider=$B129,Responses))))} -> 9 | AS129: =AO129*(AQ129/SUM(AQ$126:AQ$159)) -> 4.8263158 | AU129: =AO129*(AQ129/(SUM(AQ$9:AQ$42)+SUM(AQ$48:AQ$81)+SUM(AQ$87:AQ$120)+SUM(AQ$126:AQ$159)+SUM(AQ$165:AQ$198)+SUM(AQ$204:AQ$237))) -> 0.80438596 | AW129: {=SUM(IF(Period=AW$4,IF(Category=$A$125,IF(Provider=$B129,Score))))} -> 75 | AY129: {=SUM(IF(Period=AW$4,IF(Category=$A$125,IF(Provider=$B129,Responses))))} -> 2 | BA129: =AW129*(AY129/SUM(AY$126:AY$159)) -> 0.69124424 | BC129: =AW129*(AY129/(SUM(AY$9:AY$42)+SUM(AY$48:AY$81)+SUM(AY$87:AY$120)+SUM(AY$126:AY$159)+SUM(AY$165:AY$198)+SUM(AY$204:AY$237))) -> 0.11520737 | BE129: {=SUM(IF(Period=BE$4,IF(Category=$A$125,IF(Provider=$B129,Score))))} -> 87.5 | BG129: {=SUM(IF(Period=BE$4,IF(Category=$A$125,IF(Provider=$B129,Responses))))} -> 2 | BI129: =BE129*(BG129/SUM(BG$126:BG$159)) -> 0.74152542 | BK129: =BE129*(BG129/(SUM(BG$9:BG$42)+SUM(BG$48:BG$81)+SUM(BG$87:BG$120)+SUM(BG$126:BG$159)+SUM(BG$165:BG$198)+SUM(BG$204:BG$237))) -> 0.12367491 | BM129: {=SUM(IF(Period=BM$4,IF(Category=$A$125,IF(Provider=$B129,Score))))} -> 89.3 | BO129: {=SUM(IF(Period=BM$4,IF(Category=$A$125,IF(Provider=$B129,Responses))))} -> 7 | BQ129: =BM129*(BO129/SUM(BO$126:BO$159)) -> 2.6943966 | BS129: =BM129*(BO129/(SUM(BO$9:BO$42)+SUM(BO$48:BO$81)+SUM(BO$87:BO$120)+SUM(BO$126:BO$159)+SUM(BO$165:BO$198)+SUM(BO$204:BO$237))) -> 0.4510101 | BU129: {=SUM(IF(Period=BU$4,IF(Category=$A$125,IF(Provider=$B129,Score))))} -> 96.9 | BW129: {=SUM(IF(Period=BU$4,IF(Category=$A$125,IF(Provider=$B129,Responses))))} -> 8 | BY129: =BU129*(BW129/SUM(BW$126:BW$159)) -> 3.2165975 | CA129: =BU129*(BW129/(SUM(BW$9:BW$42)+SUM(BW$48:BW$81)+SUM(BW$87:BW$120)+SUM(BW$126:BW$159)+SUM(BW$165:BW$198)+SUM(BW$204:BW$237))) -> 0.53572909
B130: ANDREW MASON | C130: 0 | E130: 0 | G130: 0 | I130: {=SUM(IF(Period=I$4,IF(Category=$A$125,IF(Provider=$B130,Score))))} -> 85.7 | K130: {=SUM(IF(Period=I$4,IF(Category=$A$125,IF(Provider=$B130,Responses))))} -> 7 | M130: =I130*(K130/SUM(K$126:K$159)) -> 2.969802 | O130: =I130*(K130/(SUM(K$9:K$42)+SUM(K$48:K$81)+SUM(K$87:K$120)+SUM(K$126:K$159)+SUM(K$165:K$198)+SUM(K$204:K$237))) -> 0.4961952 | Q130: {=SUM(IF(Period=Q$4,IF(Category=$A$125,IF(Provider=$B130,Score))))} -> 79.2 | S130: {=SUM(IF(Period=Q$4,IF(Category=$A$125,IF(Provider=$B130,Responses))))} -> 6 | U130: =Q130*(S130/SUM(S$126:S$159)) -> 2.5411765 | W130: =Q130*(S130/(SUM(S$9:S$42)+SUM(S$48:S$81)+SUM(S$87:S$120)+SUM(S$126:S$159)+SUM(S$165:S$198)+SUM(S$204:S$237))) -> 0.42352941 | Y130: {=SUM(IF(Period=Y$4,IF(Category=$A$125,IF(Provider=$B130,Score))))} -> 89.6 | AA130: {=SUM(IF(Period=Y$4,IF(Category=$A$125,IF(Provider=$B130,Responses))))} -> 12 | AC130: =Y130*(AA130/SUM(AA$126:AA$159)) -> 3.5485149 | AE130: =Y130*(AA130/(SUM(AA$9:AA$42)+SUM(AA$48:AA$81)+SUM(AA$87:AA$120)+SUM(AA$126:AA$159)+SUM(AA$165:AA$198)+SUM(AA$204:AA$237))) -> 0.59305019 | AG130: {=SUM(IF(Period=AG$4,IF(Category=$A$125,IF(Provider=$B130,Score))))} -> 94.4 | AI130: {=SUM(IF(Period=AG$4,IF(Category=$A$125,IF(Provider=$B130,Responses))))} -> 9 | AK130: =AG130*(AI130/SUM(AI$126:AI$159)) -> 3.3058366 | AM130: =AG130*(AI130/(SUM(AI$9:AI$42)+SUM(AI$48:AI$81)+SUM(AI$87:AI$120)+SUM(AI$126:AI$159)+SUM(AI$165:AI$198)+SUM(AI$204:AI$237))) -> 0.55025907 | AO130: {=SUM(IF(Period=AO$4,IF(Category=$A$125,IF(Provider=$B130,Score))))} -> 100 | AQ130: {=SUM(IF(Period=AO$4,IF(Category=$A$125,IF(Provider=$B130,Responses))))} -> 4 | AS130: =AO130*(AQ130/SUM(AQ$126:AQ$159)) -> 2.3391813 | AU130: =AO130*(AQ130/(SUM(AQ$9:AQ$42)+SUM(AQ$48:AQ$81)+SUM(AQ$87:AQ$120)+SUM(AQ$126:AQ$159)+SUM(AQ$165:AQ$198)+SUM(AQ$204:AQ$237))) -> 0.38986355 | AW130: {=SUM(IF(Period=AW$4,IF(Category=$A$125,IF(Provider=$B130,Score))))} -> 83.3 | AY130: {=SUM(IF(Period=AW$4,IF(Category=$A$125,IF(Provider=$B130,Responses))))} -> 6 | BA130: =AW130*(AY130/SUM(AY$126:AY$159)) -> 2.3032258 | BC130: =AW130*(AY130/(SUM(AY$9:AY$42)+SUM(AY$48:AY$81)+SUM(AY$87:AY$120)+SUM(AY$126:AY$159)+SUM(AY$165:AY$198)+SUM(AY$204:AY$237))) -> 0.38387097 | BE130: {=SUM(IF(Period=BE$4,IF(Category=$A$125,IF(Provider=$B130,Score))))} -> 75 | BG130: {=SUM(IF(Period=BE$4,IF(Category=$A$125,IF(Provider=$B130,Responses))))} -> 6 | BI130: =BE130*(BG130/SUM(BG$126:BG$159)) -> 1.9067797 | BK130: =BE130*(BG130/(SUM(BG$9:BG$42)+SUM(BG$48:BG$81)+SUM(BG$87:BG$120)+SUM(BG$126:BG$159)+SUM(BG$165:BG$198)+SUM(BG$204:BG$237))) -> 0.3180212 | BM130: {=SUM(IF(Period=BM$4,IF(Category=$A$125,IF(Provider=$B130,Score))))} -> 75 | BO130: {=SUM(IF(Period=BM$4,IF(Category=$A$125,IF(Provider=$B130,Responses))))} -> 7 | BQ130: =BM130*(BO130/SUM(BO$126:BO$159)) -> 2.262931 | BS130: =BM130*(BO130/(SUM(BO$9:BO$42)+SUM(BO$48:BO$81)+SUM(BO$87:BO$120)+SUM(BO$126:BO$159)+SUM(BO$165:BO$198)+SUM(BO$204:BO$237))) -> 0.37878788 | BU130: {=SUM(IF(Period=BU$4,IF(Category=$A$125,IF(Provider=$B130,Score))))} -> 100 | BW130: {=SUM(IF(Period=BU$4,IF(Category=$A$125,IF(Provider=$B130,Responses))))} -> 7 | BY130: =BU130*(BW130/SUM(BW$126:BW$159)) -> 2.9045643 | CA130: =BU130*(BW130/(SUM(BW$9:BW$42)+SUM(BW$48:BW$81)+SUM(BW$87:BW$120)+SUM(BW$126:BW$159)+SUM(BW$165:BW$198)+SUM(BW$204:BW$237))) -> 0.4837595
B131: ANTONY FRIEDMAN | C131: 0 | E131: 0 | G131: 0 | I131: {=SUM(IF(Period=I$4,IF(Category=$A$125,IF(Provider=$B131,Score))))} -> 50 | K131: {=SUM(IF(Period=I$4,IF(Category=$A$125,IF(Provider=$B131,Responses))))} -> 4 | M131: =I131*(K131/SUM(K$126:K$159)) -> 0.99009901 | O131: =I131*(K131/(SUM(K$9:K$42)+SUM(K$48:K$81)+SUM(K$87:K$120)+SUM(K$126:K$159)+SUM(K$165:K$198)+SUM(K$204:K$237))) -> 0.16542597 | Q131: {=SUM(IF(Period=Q$4,IF(Category=$A$125,IF(Provider=$B131,Score))))} -> 55 | S131: {=SUM(IF(Period=Q$4,IF(Category=$A$125,IF(Provider=$B131,Responses))))} -> 10 | U131: =Q131*(S131/SUM(S$126:S$159)) -> 2.9411765 | W131: =Q131*(S131/(SUM(S$9:S$42)+SUM(S$48:S$81)+SUM(S$87:S$120)+SUM(S$126:S$159)+SUM(S$165:S$198)+SUM(S$204:S$237))) -> 0.49019608 | Y131: {=SUM(IF(Period=Y$4,IF(Category=$A$125,IF(Provider=$B131,Score))))} -> 75 | AA131: {=SUM(IF(Period=Y$4,IF(Category=$A$125,IF(Provider=$B131,Responses))))} -> 5 | AC131: =Y131*(AA131/SUM(AA$126:AA$159)) -> 1.2376238 | AE131: =Y131*(AA131/(SUM(AA$9:AA$42)+SUM(AA$48:AA$81)+SUM(AA$87:AA$120)+SUM(AA$126:AA$159)+SUM(AA$165:AA$198)+SUM(AA$204:AA$237))) -> 0.20683949 | AG131: {=SUM(IF(Period=AG$4,IF(Category=$A$125,IF(Provider=$B131,Score))))} -> 75 | AI131: {=SUM(IF(Period=AG$4,IF(Category=$A$125,IF(Provider=$B131,Responses))))} -> 1 | AK131: =AG131*(AI131/SUM(AI$126:AI$159)) -> 0.29182879 | AM131: =AG131*(AI131/(SUM(AI$9:AI$42)+SUM(AI$48:AI$81)+SUM(AI$87:AI$120)+SUM(AI$126:AI$159)+SUM(AI$165:AI$198)+SUM(AI$204:AI$237))) -> 0.04857513 | AO131: {=SUM(IF(Period=AO$4,IF(Category=$A$125,IF(Provider=$B131,Score))))} -> 87.5 | AQ131: {=SUM(IF(Period=AO$4,IF(Category=$A$125,IF(Provider=$B131,Responses))))} -> 6 | AS131: =AO131*(AQ131/SUM(AQ$126:AQ$159)) -> 3.0701754 | AU131: =AO131*(AQ131/(SUM(AQ$9:AQ$42)+SUM(AQ$48:AQ$81)+SUM(AQ$87:AQ$120)+SUM(AQ$126:AQ$159)+SUM(AQ$165:AQ$198)+SUM(AQ$204:AQ$237))) -> 0.51169591 | AW131: {=SUM(IF(Period=AW$4,IF(Category=$A$125,IF(Provider=$B131,Score))))} -> 71.9 | AY131: {=SUM(IF(Period=AW$4,IF(Category=$A$125,IF(Provider=$B131,Responses))))} -> 8 | BA131: =AW131*(AY131/SUM(AY$126:AY$159)) -> 2.6506912 | BC131: =AW131*(AY131/(SUM(AY$9:AY$42)+SUM(AY$48:AY$81)+SUM(AY$87:AY$120)+SUM(AY$126:AY$159)+SUM(AY$165:AY$198)+SUM(AY$204:AY$237))) -> 0.44178187 | BE131: {=SUM(IF(Period=BE$4,IF(Category=$A$125,IF(Provider=$B131,Score))))} -> 58.3 | BG131: {=SUM(IF(Period=BE$4,IF(Category=$A$125,IF(Provider=$B131,Responses))))} -> 15 | BI131: =BE131*(BG131/SUM(BG$126:BG$159)) -> 3.7055085 | BK131: =BE131*(BG131/(SUM(BG$9:BG$42)+SUM(BG$48:BG$81)+SUM(BG$87:BG$120)+SUM(BG$126:BG$159)+SUM(BG$165:BG$198)+SUM(BG$204:BG$237))) -> 0.6180212 | BM131: {=SUM(IF(Period=BM$4,IF(Category=$A$125,IF(Provider=$B131,Score))))} -> 86.4 | BO131: {=SUM(IF(Period=BM$4,IF(Category=$A$125,IF(Provider=$B131,Responses))))} -> 11 | BQ131: =BM131*(BO131/SUM(BO$126:BO$159)) -> 4.0965517 | BS131: =BM131*(BO131/(SUM(BO$9:BO$42)+SUM(BO$48:BO$81)+SUM(BO$87:BO$120)+SUM(BO$126:BO$159)+SUM(BO$165:BO$198)+SUM(BO$204:BO$237))) -> 0.68571429 | BU131: {=SUM(IF(Period=BU$4,IF(Category=$A$125,IF(Provider=$B131,Score))))} -> 68.8 | BW131: {=SUM(IF(Period=BU$4,IF(Category=$A$125,IF(Provider=$B131,Responses))))} -> 8 | BY131: =BU131*(BW131/SUM(BW$126:BW$159)) -> 2.2838174 | CA131: =BU131*(BW131/(SUM(BW$9:BW$42)+SUM(BW$48:BW$81)+SUM(BW$87:BW$120)+SUM(BW$126:BW$159)+SUM(BW$165:BW$198)+SUM(BW$204:BW$237))) -> 0.38037319
B132: CHARLES SANZ | C132: 0 | E132: 0 | G132: 0 | I132: {=SUM(IF(Period=I$4,IF(Category=$A$125,IF(Provider=$B132,Score))))} -> 93.8 | K132: {=SUM(IF(Period=I$4,IF(Category=$A$125,IF(Provider=$B132,Responses))))} -> 4 | M132: =I132*(K132/SUM(K$126:K$159)) -> 1.8574257 | O132: =I132*(K132/(SUM(K$9:K$42)+SUM(K$48:K$81)+SUM(K$87:K$120)+SUM(K$126:K$159)+SUM(K$165:K$198)+SUM(K$204:K$237))) -> 0.31033912 | Q132: {=SUM(IF(Period=Q$4,IF(Category=$A$125,IF(Provider=$B132,Score))))} -> 91.7 | S132: {=SUM(IF(Period=Q$4,IF(Category=$A$125,IF(Provider=$B132,Responses))))} -> 3 | U132: =Q132*(S132/SUM(S$126:S$159)) -> 1.471123 | W132: =Q132*(S132/(SUM(S$9:S$42)+SUM(S$48:S$81)+SUM(S$87:S$120)+SUM(S$126:S$159)+SUM(S$165:S$198)+SUM(S$204:S$237))) -> 0.24518717 | Y132: {=SUM(IF(Period=Y$4,IF(Category=$A$125,IF(Provider=$B132,Score))))} -> 96.9 | AA132: {=SUM(IF(Period=Y$4,IF(Category=$A$125,IF(Provider=$B132,Responses))))} -> 8 | AC132: =Y132*(AA132/SUM(AA$126:AA$159)) -> 2.5584158 | AE132: =Y132*(AA132/(SUM(AA$9:AA$42)+SUM(AA$48:AA$81)+SUM(AA$87:AA$120)+SUM(AA$126:AA$159)+SUM(AA$165:AA$198)+SUM(AA$204:AA$237))) -> 0.4275786 | AG132: {=SUM(IF(Period=AG$4,IF(Category=$A$125,IF(Provider=$B132,Score))))} -> 90.6 | AI132: {=SUM(IF(Period=AG$4,IF(Category=$A$125,IF(Provider=$B132,Responses))))} -> 8 | AK132: =AG132*(AI132/SUM(AI$126:AI$159)) -> 2.8202335 | AM132: =AG132*(AI132/(SUM(AI$9:AI$42)+SUM(AI$48:AI$81)+SUM(AI$87:AI$120)+SUM(AI$126:AI$159)+SUM(AI$165:AI$198)+SUM(AI$204:AI$237))) -> 0.46943005 | AO132: {=SUM(IF(Period=AO$4,IF(Category=$A$125,IF(Provider=$B132,Score))))} -> 83.3 | AQ132: {=SUM(IF(Period=AO$4,IF(Category=$A$125,IF(Provider=$B132,Responses))))} -> 3 | AS132: =AO132*(AQ132/SUM(AQ$126:AQ$159)) -> 1.4614035 | AU132: =AO132*(AQ132/(SUM(AQ$9:AQ$42)+SUM(AQ$48:AQ$81)+SUM(AQ$87:AQ$120)+SUM(AQ$126:AQ$159)+SUM(AQ$165:AQ$198)+SUM(AQ$204:AQ$237))) -> 0.24356725 | AW132: {=SUM(IF(Period=AW$4,IF(Category=$A$125,IF(Provider=$B132,Score))))} -> 100 | AY132: {=SUM(IF(Period=AW$4,IF(Category=$A$125,IF(Provider=$B132,Responses))))} -> 3 | BA132: =AW132*(AY132/SUM(AY$126:AY$159)) -> 1.3824885 | BC132: =AW132*(AY132/(SUM(AY$9:AY$42)+SUM(AY$48:AY$81)+SUM(AY$87:AY$120)+SUM(AY$126:AY$159)+SUM(AY$165:AY$198)+SUM(AY$204:AY$237))) -> 0.23041475 | BE132: {=SUM(IF(Period=BE$4,IF(Category=$A$125,IF(Provider=$B132,Score))))} -> 78.9 | BG132: {=SUM(IF(Period=BE$4,IF(Category=$A$125,IF(Provider=$B132,Responses))))} -> 13 | BI132: =BE132*(BG132/SUM(BG$126:BG$159)) -> 4.3461864 | BK132: =BE132*(BG132/(SUM(BG$9:BG$42)+SUM(BG$48:BG$81)+SUM(BG$87:BG$120)+SUM(BG$126:BG$159)+SUM(BG$165:BG$198)+SUM(BG$204:BG$237))) -> 0.72487633 | BM132: {=SUM(IF(Period=BM$4,IF(Category=$A$125,IF(Provider=$B132,Score))))} -> 100 | BO132: {=SUM(IF(Period=BM$4,IF(Category=$A$125,IF(Provider=$B132,Responses))))} -> 12 | BQ132: =BM132*(BO132/SUM(BO$126:BO$159)) -> 5.1724138 | BS132: =BM132*(BO132/(SUM(BO$9:BO$42)+SUM(BO$48:BO$81)+SUM(BO$87:BO$120)+SUM(BO$126:BO$159)+SUM(BO$165:BO$198)+SUM(BO$204:BO$237))) -> 0.86580087 | BU132: {=SUM(IF(Period=BU$4,IF(Category=$A$125,IF(Provider=$B132,Score))))} -> 95.8 | BW132: {=SUM(IF(Period=BU$4,IF(Category=$A$125,IF(Provider=$B132,Responses))))} -> 6 | BY132: =BU132*(BW132/SUM(BW$126:BW$159)) -> 2.3850622 | CA132: =BU132*(BW132/(SUM(BW$9:BW$42)+SUM(BW$48:BW$81)+SUM(BW$87:BW$120)+SUM(BW$126:BW$159)+SUM(BW$165:BW$198)+SUM(BW$204:BW$237))) -> 0.39723566
B133: CHRISTIAN KOKINAKOS | C133: 0 | E133: 0 | G133: 0 | I133: {=SUM(IF(Period=I$4,IF(Category=$A$125,IF(Provider=$B133,Score))))} -> 90 | K133: {=SUM(IF(Period=I$4,IF(Category=$A$125,IF(Provider=$B133,Responses))))} -> 5 | M133: =I133*(K133/SUM(K$126:K$159)) -> 2.2277228 | O133: =I133*(K133/(SUM(K$9:K$42)+SUM(K$48:K$81)+SUM(K$87:K$120)+SUM(K$126:K$159)+SUM(K$165:K$198)+SUM(K$204:K$237))) -> 0.37220844 | Q133: {=SUM(IF(Period=Q$4,IF(Category=$A$125,IF(Provider=$B133,Score))))} -> 83.3 | S133: {=SUM(IF(Period=Q$4,IF(Category=$A$125,IF(Provider=$B133,Responses))))} -> 3 | U133: =Q133*(S133/SUM(S$126:S$159)) -> 1.3363636 | W133: =Q133*(S133/(SUM(S$9:S$42)+SUM(S$48:S$81)+SUM(S$87:S$120)+SUM(S$126:S$159)+SUM(S$165:S$198)+SUM(S$204:S$237))) -> 0.22272727 | Y133: {=SUM(IF(Period=Y$4,IF(Category=$A$125,IF(Provider=$B133,Score))))} -> 0 | AA133: {=SUM(IF(Period=Y$4,IF(Category=$A$125,IF(Provider=$B133,Responses))))} -> 0 | AC133: =Y133*(AA133/SUM(AA$126:AA$159)) -> 0 | AE133: =Y133*(AA133/(SUM(AA$9:AA$42)+SUM(AA$48:AA$81)+SUM(AA$87:AA$120)+SUM(AA$126:AA$159)+SUM(AA$165:AA$198)+SUM(AA$204:AA$237))) -> 0 | AG133: {=SUM(IF(Period=AG$4,IF(Category=$A$125,IF(Provider=$B133,Score))))} -> 0 | AI133: {=SUM(IF(Period=AG$4,IF(Category=$A$125,IF(Provider=$B133,Responses))))} -> 0 | AK133: =AG133*(AI133/SUM(AI$126:AI$159)) -> 0 | AM133: =AG133*(AI133/(SUM(AI$9:AI$42)+SUM(AI$48:AI$81)+SUM(AI$87:AI$120)+SUM(AI$126:AI$159)+SUM(AI$165:AI$198)+SUM(AI$204:AI$237))) -> 0 | AO133: {=SUM(IF(Period=AO$4,IF(Category=$A$125,IF(Provider=$B133,Score))))} -> 0 | AQ133: {=SUM(IF(Period=AO$4,IF(Category=$A$125,IF(Provider=$B133,Responses))))} -> 0 | AS133: =AO133*(AQ133/SUM(AQ$126:AQ$159)) -> 0 | AU133: =AO133*(AQ133/(SUM(AQ$9:AQ$42)+SUM(AQ$48:AQ$81)+SUM(AQ$87:AQ$120)+SUM(AQ$126:AQ$159)+SUM(AQ$165:AQ$198)+SUM(AQ$204:AQ$237))) -> 0 | AW133: {=SUM(IF(Period=AW$4,IF(Category=$A$125,IF(Provider=$B133,Score))))} -> 0 | AY133: {=SUM(IF(Period=AW$4,IF(Category=$A$125,IF(Provider=$B133,Responses))))} -> 0 | BA133: =AW133*(AY133/SUM(AY$126:AY$159)) -> 0 | BC133: =AW133*(AY133/(SUM(AY$9:AY$42)+SUM(AY$48:AY$81)+SUM(AY$87:AY$120)+SUM(AY$126:AY$159)+SUM(AY$165:AY$198)+SUM(AY$204:AY$237))) -> 0 | BE133: {=SUM(IF(Period=BE$4,IF(Category=$A$125,IF(Provider=$B133,Score))))} -> 0 | BG133: {=SUM(IF(Period=BE$4,IF(Category=$A$125,IF(Provider=$B133,Responses))))} -> 0 | BI133: =BE133*(BG133/SUM(BG$126:BG$159)) -> 0 | BK133: =BE133*(BG133/(SUM(BG$9:BG$42)+SUM(BG$48:BG$81)+SUM(BG$87:BG$120)+SUM(BG$126:BG$159)+SUM(BG$165:BG$198)+SUM(BG$204:BG$237))) -> 0 | BM133: {=SUM(IF(Period=BM$4,IF(Category=$A$125,IF(Provider=$B133,Score))))} -> 0 | BO133: {=SUM(IF(Period=BM$4,IF(Category=$A$125,IF(Provider=$B133,Responses))))} -> 0 | BQ133: =BM133*(BO133/SUM(BO$126:BO$159)) -> 0 | BS133: =BM133*(BO133/(SUM(BO$9:BO$42)+SUM(BO$48:BO$81)+SUM(BO$87:BO$120)+SUM(BO$126:BO$159)+SUM(BO$165:BO$198)+SUM(BO$204:BO$237))) -> 0 | BU133: {=SUM(IF(Period=BU$4,IF(Category=$A$125,IF(Provider=$B133,Score))))} -> 0 | BW133: {=SUM(IF(Period=BU$4,IF(Category=$A$125,IF(Provider=$B133,Responses))))} -> 0 | BY133: =BU133*(BW133/SUM(BW$126:BW$159)) -> 0 | CA133: =BU133*(BW133/(SUM(BW$9:BW$42)+SUM(BW$48:BW$81)+SUM(BW$87:BW$120)+SUM(BW$126:BW$159)+SUM(BW$165:BW$198)+SUM(BW$204:BW$237))) -> 0
B134: DANIEL D'AMORE | C134: 0 | E134: 0 | G134: 0 | I134: {=SUM(IF(Period=I$4,IF(Category=$A$125,IF(Provider=$B134,Score))))} -> 78.1 | K134: {=SUM(IF(Period=I$4,IF(Category=$A$125,IF(Provider=$B134,Responses))))} -> 8 | M134: =I134*(K134/SUM(K$126:K$159)) -> 3.0930693 | O134: =I134*(K134/(SUM(K$9:K$42)+SUM(K$48:K$81)+SUM(K$87:K$120)+SUM(K$126:K$159)+SUM(K$165:K$198)+SUM(K$204:K$237))) -> 0.51679074 | Q134: {=SUM(IF(Period=Q$4,IF(Category=$A$125,IF(Provider=$B134,Score))))} -> 68.8 | S134: {=SUM(IF(Period=Q$4,IF(Category=$A$125,IF(Provider=$B134,Responses))))} -> 4 | U134: =Q134*(S134/SUM(S$126:S$159)) -> 1.4716578 | W134: =Q134*(S134/(SUM(S$9:S$42)+SUM(S$48:S$81)+SUM(S$87:S$120)+SUM(S$126:S$159)+SUM(S$165:S$198)+SUM(S$204:S$237))) -> 0.24527629 | Y134: {=SUM(IF(Period=Y$4,IF(Category=$A$125,IF(Provider=$B134,Score))))} -> 85.4 | AA134: {=SUM(IF(Period=Y$4,IF(Category=$A$125,IF(Provider=$B134,Responses))))} -> 12 | AC134: =Y134*(AA134/SUM(AA$126:AA$159)) -> 3.3821782 | AE134: =Y134*(AA134/(SUM(AA$9:AA$42)+SUM(AA$48:AA$81)+SUM(AA$87:AA$120)+SUM(AA$126:AA$159)+SUM(AA$165:AA$198)+SUM(AA$204:AA$237))) -> 0.56525097 | AG134: {=SUM(IF(Period=AG$4,IF(Category=$A$125,IF(Provider=$B134,Score))))} -> 91.7 | AI134: {=SUM(IF(Period=AG$4,IF(Category=$A$125,IF(Provider=$B134,Responses))))} -> 9 | AK134: =AG134*(AI134/SUM(AI$126:AI$159)) -> 3.211284 | AM134: =AG134*(AI134/(SUM(AI$9:AI$42)+SUM(AI$48:AI$81)+SUM(AI$87:AI$120)+SUM(AI$126:AI$159)+SUM(AI$165:AI$198)+SUM(AI$204:AI$237))) -> 0.53452073 | AO134: {=SUM(IF(Period=AO$4,IF(Category=$A$125,IF(Provider=$B134,Score))))} -> 89.6 | AQ134: {=SUM(IF(Period=AO$4,IF(Category=$A$125,IF(Provider=$B134,Responses))))} -> 12 | AS134: =AO134*(AQ134/SUM(AQ$126:AQ$159)) -> 6.2877193 | AU134: =AO134*(AQ134/(SUM(AQ$9:AQ$42)+SUM(AQ$48:AQ$81)+SUM(AQ$87:AQ$120)+SUM(AQ$126:AQ$159)+SUM(AQ$165:AQ$198)+SUM(AQ$204:AQ$237))) -> 1.0479532 | AW134: {=SUM(IF(Period=AW$4,IF(Category=$A$125,IF(Provider=$B134,Score))))} -> 90.6 | AY134: {=SUM(IF(Period=AW$4,IF(Category=$A$125,IF(Provider=$B134,Responses))))} -> 8 | BA134: =AW134*(AY134/SUM(AY$126:AY$159)) -> 3.3400922 | BC134: =AW134*(AY134/(SUM(AY$9:AY$42)+SUM(AY$48:AY$81)+SUM(AY$87:AY$120)+SUM(AY$126:AY$159)+SUM(AY$165:AY$198)+SUM(AY$204:AY$237))) -> 0.55668203 | BE134: {=SUM(IF(Period=BE$4,IF(Category=$A$125,IF(Provider=$B134,Score))))} -> 75 | BG134: {=SUM(IF(Period=BE$4,IF(Category=$A$125,IF(Provider=$B134,Responses))))} -> 4 | BI134: =BE134*(BG134/SUM(BG$126:BG$159)) -> 1.2711864 | BK134: =BE134*(BG134/(SUM(BG$9:BG$42)+SUM(BG$48:BG$81)+SUM(BG$87:BG$120)+SUM(BG$126:BG$159)+SUM(BG$165:BG$198)+SUM(BG$204:BG$237))) -> 0.21201413 | BM134: {=SUM(IF(Period=BM$4,IF(Category=$A$125,IF(Provider=$B134,Score))))} -> 76.9 | BO134: {=SUM(IF(Period=BM$4,IF(Category=$A$125,IF(Provider=$B134,Responses))))} -> 13 | BQ134: =BM134*(BO134/SUM(BO$126:BO$159)) -> 4.3090517 | BS134: =BM134*(BO134/(SUM(BO$9:BO$42)+SUM(BO$48:BO$81)+SUM(BO$87:BO$120)+SUM(BO$126:BO$159)+SUM(BO$165:BO$198)+SUM(BO$204:BO$237))) -> 0.72128427 | BU134: {=SUM(IF(Period=BU$4,IF(Category=$A$125,IF(Provider=$B134,Score))))} -> 77.8 | BW134: {=SUM(IF(Period=BU$4,IF(Category=$A$125,IF(Provider=$B134,Responses))))} -> 9 | BY134: =BU134*(BW134/SUM(BW$126:BW$159)) -> 2.9053942 | CA134: =BU134*(BW134/(SUM(BW$9:BW$42)+SUM(BW$48:BW$81)+SUM(BW$87:BW$120)+SUM(BW$126:BW$159)+SUM(BW$165:BW$198)+SUM(BW$204:BW$237))) -> 0.48389772
B135: DAVID MISHKIN | C135: 0 | E135: 0 | G135: 0 | I135: {=SUM(IF(Period=I$4,IF(Category=$A$125,IF(Provider=$B135,Score))))} -> 93.8 | K135: {=SUM(IF(Period=I$4,IF(Category=$A$125,IF(Provider=$B135,Responses))))} -> 8 | M135: =I135*(K135/SUM(K$126:K$159)) -> 3.7148515 | O135: =I135*(K135/(SUM(K$9:K$42)+SUM(K$48:K$81)+SUM(K$87:K$120)+SUM(K$126:K$159)+SUM(K$165:K$198)+SUM(K$204:K$237))) -> 0.62067825 | Q135: {=SUM(IF(Period=Q$4,IF(Category=$A$125,IF(Provider=$B135,Score))))} -> 75 | S135: {=SUM(IF(Period=Q$4,IF(Category=$A$125,IF(Provider=$B135,Responses))))} -> 9 | U135: =Q135*(S135/SUM(S$126:S$159)) -> 3.6096257 | W135: =Q135*(S135/(SUM(S$9:S$42)+SUM(S$48:S$81)+SUM(S$87:S$120)+SUM(S$126:S$159)+SUM(S$165:S$198)+SUM(S$204:S$237))) -> 0.60160428 | Y135: {=SUM(IF(Period=Y$4,IF(Category=$A$125,IF(Provider=$B135,Score))))} -> 80.8 | AA135: {=SUM(IF(Period=Y$4,IF(Category=$A$125,IF(Provider=$B135,Responses))))} -> 13 | AC135: =Y135*(AA135/SUM(AA$126:AA$159)) -> 3.4666667 | AE135: =Y135*(AA135/(SUM(AA$9:AA$42)+SUM(AA$48:AA$81)+SUM(AA$87:AA$120)+SUM(AA$126:AA$159)+SUM(AA$165:AA$198)+SUM(AA$204:AA$237))) -> 0.57937121 | AG135: {=SUM(IF(Period=AG$4,IF(Category=$A$125,IF(Provider=$B135,Score))))} -> 100 | AI135: {=SUM(IF(Period=AG$4,IF(Category=$A$125,IF(Provider=$B135,Responses))))} -> 10 | AK135: =AG135*(AI135/SUM(AI$126:AI$159)) -> 3.8910506 | AM135: =AG135*(AI135/(SUM(AI$9:AI$42)+SUM(AI$48:AI$81)+SUM(AI$87:AI$120)+SUM(AI$126:AI$159)+SUM(AI$165:AI$198)+SUM(AI$204:AI$237))) -> 0.64766839 | AO135: {=SUM(IF(Period=AO$4,IF(Category=$A$125,IF(Provider=$B135,Score))))} -> 100 | AQ135: {=SUM(IF(Period=AO$4,IF(Category=$A$125,IF(Provider=$B135,Responses))))} -> 8 | AS135: =AO135*(AQ135/SUM(AQ$126:AQ$159)) -> 4.6783626 | AU135: =AO135*(AQ135/(SUM(AQ$9:AQ$42)+SUM(AQ$48:AQ$81)+SUM(AQ$87:AQ$120)+SUM(AQ$126:AQ$159)+SUM(AQ$165:AQ$198)+SUM(AQ$204:AQ$237))) -> 0.7797271 | AW135: {=SUM(IF(Period=AW$4,IF(Category=$A$125,IF(Provider=$B135,Score))))} -> 96.4 | AY135: {=SUM(IF(Period=AW$4,IF(Category=$A$125,IF(Provider=$B135,Responses))))} -> 14 | BA135: =AW135*(AY135/SUM(AY$126:AY$159)) -> 6.2193548 | BC135: =AW135*(AY135/(SUM(AY$9:AY$42)+SUM(AY$48:AY$81)+SUM(AY$87:AY$120)+SUM(AY$126:AY$159)+SUM(AY$165:AY$198)+SUM(AY$204:AY$237))) -> 1.0365591 | BE135: {=SUM(IF(Period=BE$4,IF(Category=$A$125,IF(Provider=$B135,Score))))} -> 100 | BG135: {=SUM(IF(Period=BE$4,IF(Category=$A$125,IF(Provider=$B135,Responses))))} -> 11 | BI135: =BE135*(BG135/SUM(BG$126:BG$159)) -> 4.6610169 | BK135: =BE135*(BG135/(SUM(BG$9:BG$42)+SUM(BG$48:BG$81)+SUM(BG$87:BG$120)+SUM(BG$126:BG$159)+SUM(BG$165:BG$198)+SUM(BG$204:BG$237))) -> 0.77738516 | BM135: {=SUM(IF(Period=BM$4,IF(Category=$A$125,IF(Provider=$B135,Score))))} -> 92.9 | BO135: {=SUM(IF(Period=BM$4,IF(Category=$A$125,IF(Provider=$B135,Responses))))} -> 7 | BQ135: =BM135*(BO135/SUM(BO$126:BO$159)) -> 2.8030172 | BS135: =BM135*(BO135/(SUM(BO$9:BO$42)+SUM(BO$48:BO$81)+SUM(BO$87:BO$120)+SUM(BO$126:BO$159)+SUM(BO$165:BO$198)+SUM(BO$204:BO$237))) -> 0.46919192 | BU135: {=SUM(IF(Period=BU$4,IF(Category=$A$125,IF(Provider=$B135,Score))))} -> 94.6 | BW135: {=SUM(IF(Period=BU$4,IF(Category=$A$125,IF(Provider=$B135,Responses))))} -> 14 | BY135: =BU135*(BW135/SUM(BW$126:BW$159)) -> 5.4954357 | CA135: =BU135*(BW135/(SUM(BW$9:BW$42)+SUM(BW$48:BW$81)+SUM(BW$87:BW$120)+SUM(BW$126:BW$159)+SUM(BW$165:BW$198)+SUM(BW$204:BW$237))) -> 0.91527298
B136: ELAINE DIAZ | C136: 0 | E136: 0 | G136: 0 | I136: {=SUM(IF(Period=I$4,IF(Category=$A$125,IF(Provider=$B136,Score))))} -> 93.8 | K136: {=SUM(IF(Period=I$4,IF(Category=$A$125,IF(Provider=$B136,Responses))))} -> 4 | M136: =I136*(K136/SUM(K$126:K$159)) -> 1.8574257 | O136: =I136*(K136/(SUM(K$9:K$42)+SUM(K$48:K$81)+SUM(K$87:K$120)+SUM(K$126:K$159)+SUM(K$165:K$198)+SUM(K$204:K$237))) -> 0.31033912 | Q136: {=SUM(IF(Period=Q$4,IF(Category=$A$125,IF(Provider=$B136,Score))))} -> 100 | S136: {=SUM(IF(Period=Q$4,IF(Category=$A$125,IF(Provider=$B136,Responses))))} -> 4 | U136: =Q136*(S136/SUM(S$126:S$159)) -> 2.1390374 | W136: =Q136*(S136/(SUM(S$9:S$42)+SUM(S$48:S$81)+SUM(S$87:S$120)+SUM(S$126:S$159)+SUM(S$165:S$198)+SUM(S$204:S$237))) -> 0.35650624 | Y136: {=SUM(IF(Period=Y$4,IF(Category=$A$125,IF(Provider=$B136,Score))))} -> 95 | AA136: {=SUM(IF(Period=Y$4,IF(Category=$A$125,IF(Provider=$B136,Responses))))} -> 5 | AC136: =Y136*(AA136/SUM(AA$126:AA$159)) -> 1.5676568 | AE136: =Y136*(AA136/(SUM(AA$9:AA$42)+SUM(AA$48:AA$81)+SUM(AA$87:AA$120)+SUM(AA$126:AA$159)+SUM(AA$165:AA$198)+SUM(AA$204:AA$237))) -> 0.26199669 | AG136: {=SUM(IF(Period=AG$4,IF(Category=$A$125,IF(Provider=$B136,Score))))} -> 93.8 | AI136: {=SUM(IF(Period=AG$4,IF(Category=$A$125,IF(Provider=$B136,Responses))))} -> 4 | AK136: =AG136*(AI136/SUM(AI$126:AI$159)) -> 1.4599222 | AM136: =AG136*(AI136/(SUM(AI$9:AI$42)+SUM(AI$48:AI$81)+SUM(AI$87:AI$120)+SUM(AI$126:AI$159)+SUM(AI$165:AI$198)+SUM(AI$204:AI$237))) -> 0.24300518 | AO136: {=SUM(IF(Period=AO$4,IF(Category=$A$125,IF(Provider=$B136,Score))))} -> 75 | AQ136: {=SUM(IF(Period=AO$4,IF(Category=$A$125,IF(Provider=$B136,Responses))))} -> 2 | AS136: =AO136*(AQ136/SUM(AQ$126:AQ$159)) -> 0.87719298 | AU136: =AO136*(AQ136/(SUM(AQ$9:AQ$42)+SUM(AQ$48:AQ$81)+SUM(AQ$87:AQ$120)+SUM(AQ$126:AQ$159)+SUM(AQ$165:AQ$198)+SUM(AQ$204:AQ$237))) -> 0.14619883 | AW136: {=SUM(IF(Period=AW$4,IF(Category=$A$125,IF(Provider=$B136,Score))))} -> 80 | AY136: {=SUM(IF(Period=AW$4,IF(Category=$A$125,IF(Provider=$B136,Responses))))} -> 5 | BA136: =AW136*(AY136/SUM(AY$126:AY$159)) -> 1.843318 | BC136: =AW136*(AY136/(SUM(AY$9:AY$42)+SUM(AY$48:AY$81)+SUM(AY$87:AY$120)+SUM(AY$126:AY$159)+SUM(AY$165:AY$198)+SUM(AY$204:AY$237))) -> 0.30721966 | BE136: {=SUM(IF(Period=BE$4,IF(Category=$A$125,IF(Provider=$B136,Score))))} -> 87.5 | BG136: {=SUM(IF(Period=BE$4,IF(Category=$A$125,IF(Provider=$B136,Responses))))} -> 2 | BI136: =BE136*(BG136/SUM(BG$126:BG$159)) -> 0.74152542 | BK136: =BE136*(BG136/(SUM(BG$9:BG$42)+SUM(BG$48:BG$81)+SUM(BG$87:BG$120)+SUM(BG$126:BG$159)+SUM(BG$165:BG$198)+SUM(BG$204:BG$237))) -> 0.12367491 | BM136: {=SUM(IF(Period=BM$4,IF(Category=$A$125,IF(Provider=$B136,Score))))} -> 100 | BO136: {=SUM(IF(Period=BM$4,IF(Category=$A$125,IF(Provider=$B136,Responses))))} -> 3 | BQ136: =BM136*(BO136/SUM(BO$126:BO$159)) -> 1.2931034 | BS136: =BM136*(BO136/(SUM(BO$9:BO$42)+SUM(BO$48:BO$81)+SUM(BO$87:BO$120)+SUM(BO$126:BO$159)+SUM(BO$165:BO$198)+SUM(BO$204:BO$237))) -> 0.21645022 | BU136: {=SUM(IF(Period=BU$4,IF(Category=$A$125,IF(Provider=$B136,Score))))} -> 78.6 | BW136: {=SUM(IF(Period=BU$4,IF(Category=$A$125,IF(Provider=$B136,Responses))))} -> 7 | BY136: =BU136*(BW136/SUM(BW$126:BW$159)) -> 2.2829876 | CA136: =BU136*(BW136/(SUM(BW$9:BW$42)+SUM(BW$48:BW$81)+SUM(BW$87:BW$120)+SUM(BW$126:BW$159)+SUM(BW$165:BW$198)+SUM(BW$204:BW$237))) -> 0.38023497
B137: EVA ESCATEL | C137: 0 | E137: 0 | G137: 0 | I137: {=SUM(IF(Period=I$4,IF(Category=$A$125,IF(Provider=$B137,Score))))} -> 88.6 | K137: {=SUM(IF(Period=I$4,IF(Category=$A$125,IF(Provider=$B137,Responses))))} -> 11 | M137: =I137*(K137/SUM(K$126:K$159)) -> 4.8247525 | O137: =I137*(K137/(SUM(K$9:K$42)+SUM(K$48:K$81)+SUM(K$87:K$120)+SUM(K$126:K$159)+SUM(K$165:K$198)+SUM(K$204:K$237))) -> 0.80612076 | Q137: {=SUM(IF(Period=Q$4,IF(Category=$A$125,IF(Provider=$B137,Score))))} -> 86.1 | S137: {=SUM(IF(Period=Q$4,IF(Category=$A$125,IF(Provider=$B137,Responses))))} -> 9 | U137: =Q137*(S137/SUM(S$126:S$159)) -> 4.1438503 | W137: =Q137*(S137/(SUM(S$9:S$42)+SUM(S$48:S$81)+SUM(S$87:S$120)+SUM(S$126:S$159)+SUM(S$165:S$198)+SUM(S$204:S$237))) -> 0.69064171 | Y137: {=SUM(IF(Period=Y$4,IF(Category=$A$125,IF(Provider=$B137,Score))))} -> 84.7 | AA137: {=SUM(IF(Period=Y$4,IF(Category=$A$125,IF(Provider=$B137,Responses))))} -> 18 | AC137: =Y137*(AA137/SUM(AA$126:AA$159)) -> 5.0316832 | AE137: =Y137*(AA137/(SUM(AA$9:AA$42)+SUM(AA$48:AA$81)+SUM(AA$87:AA$120)+SUM(AA$126:AA$159)+SUM(AA$165:AA$198)+SUM(AA$204:AA$237))) -> 0.84092664 | AG137: {=SUM(IF(Period=AG$4,IF(Category=$A$125,IF(Provider=$B137,Score))))} -> 89.1 | AI137: {=SUM(IF(Period=AG$4,IF(Category=$A$125,IF(Provider=$B137,Responses))))} -> 16 | AK137: =AG137*(AI137/SUM(AI$126:AI$159)) -> 5.5470817 | AM137: =AG137*(AI137/(SUM(AI$9:AI$42)+SUM(AI$48:AI$81)+SUM(AI$87:AI$120)+SUM(AI$126:AI$159)+SUM(AI$165:AI$198)+SUM(AI$204:AI$237))) -> 0.92331606 | AO137: {=SUM(IF(Period=AO$4,IF(Category=$A$125,IF(Provider=$B137,Score))))} -> 89.6 | AQ137: {=SUM(IF(Period=AO$4,IF(Category=$A$125,IF(Provider=$B137,Responses))))} -> 12 | AS137: =AO137*(AQ137/SUM(AQ$126:AQ$159)) -> 6.2877193 | AU137: =AO137*(AQ137/(SUM(AQ$9:AQ$42)+SUM(AQ$48:AQ$81)+SUM(AQ$87:AQ$120)+SUM(AQ$126:AQ$159)+SUM(AQ$165:AQ$198)+SUM(AQ$204:AQ$237))) -> 1.0479532 | AW137: {=SUM(IF(Period=AW$4,IF(Category=$A$125,IF(Provider=$B137,Score))))} -> 95 | AY137: {=SUM(IF(Period=AW$4,IF(Category=$A$125,IF(Provider=$B137,Responses))))} -> 10 | BA137: =AW137*(AY137/SUM(AY$126:AY$159)) -> 4.3778802 | BC137: =AW137*(AY137/(SUM(AY$9:AY$42)+SUM(AY$48:AY$81)+SUM(AY$87:AY$120)+SUM(AY$126:AY$159)+SUM(AY$165:AY$198)+SUM(AY$204:AY$237))) -> 0.7296467 | BE137: {=SUM(IF(Period=BE$4,IF(Category=$A$125,IF(Provider=$B137,Score))))} -> 96.9 | BG137: {=SUM(IF(Period=BE$4,IF(Category=$A$125,IF(Provider=$B137,Responses))))} -> 8 | BI137: =BE137*(BG137/SUM(BG$126:BG$159)) -> 3.2847458 | BK137: =BE137*(BG137/(SUM(BG$9:BG$42)+SUM(BG$48:BG$81)+SUM(BG$87:BG$120)+SUM(BG$126:BG$159)+SUM(BG$165:BG$198)+SUM(BG$204:BG$237))) -> 0.54784452 | BM137: {=SUM(IF(Period=BM$4,IF(Category=$A$125,IF(Provider=$B137,Score))))} -> 100 | BO137: {=SUM(IF(Period=BM$4,IF(Category=$A$125,IF(Provider=$B137,Responses))))} -> 9 | BQ137: =BM137*(BO137/SUM(BO$126:BO$159)) -> 3.8793103 | BS137: =BM137*(BO137/(SUM(BO$9:BO$42)+SUM(BO$48:BO$81)+SUM(BO$87:BO$120)+SUM(BO$126:BO$159)+SUM(BO$165:BO$198)+SUM(BO$204:BO$237))) -> 0.64935065 | BU137: {=SUM(IF(Period=BU$4,IF(Category=$A$125,IF(Provider=$B137,Score))))} -> 100 | BW137: {=SUM(IF(Period=BU$4,IF(Category=$A$125,IF(Provider=$B137,Responses))))} -> 7 | BY137: =BU137*(BW137/SUM(BW$126:BW$159)) -> 2.9045643 | CA137: =BU137*(BW137/(SUM(BW$9:BW$42)+SUM(BW$48:BW$81)+SUM(BW$87:BW$120)+SUM(BW$126:BW$159)+SUM(BW$165:BW$198)+SUM(BW$204:BW$237))) -> 0.4837595
... B159: NAME NOT GIVEN | C159: 0 | E159: 0 | G159: 0 | I159: {=SUM(IF(Period=I$4,IF(Category=$A$125,IF(Provider=$B159,Score))))} -> 0 | K159: {=SUM(IF(Period=I$4,IF(Category=$A$125,IF(Provider=$B159,Responses))))} -> 0 | M159: =I159*(K159/SUM(K$126:K$159)) -> 0 | O159: =I159*(K159/(SUM(K$9:K$42)+SUM(K$48:K$81)+SUM(K$87:K$120)+SUM(K$126:K$159)+SUM(K$165:K$198)+SUM(K$204:K$237))) -> 0 | Q159: {=SUM(IF(Period=Q$4,IF(Category=$A$125,IF(Provider=$B159,Score))))} -> 0 | S159: {=SUM(IF(Period=Q$4,IF(Category=$A$125,IF(Provider=$B159,Responses))))} -> 0 | U159: =Q159*(S159/SUM(S$126:S$159)) -> 0 | W159: =Q159*(S159/(SUM(S$9:S$42)+SUM(S$48:S$81)+SUM(S$87:S$120)+SUM(S$126:S$159)+SUM(S$165:S$198)+SUM(S$204:S$237))) -> 0 | Y159: {=SUM(IF(Period=Y$4,IF(Category=$A$125,IF(Provider=$B159,Score))))} -> 0 | AA159: {=SUM(IF(Period=Y$4,IF(Category=$A$125,IF(Provider=$B159,Responses))))} -> 0 | AC159: =Y159*(AA159/SUM(AA$126:AA$159)) -> 0 | AE159: =Y159*(AA159/(SUM(AA$9:AA$42)+SUM(AA$48:AA$81)+SUM(AA$87:AA$120)+SUM(AA$126:AA$159)+SUM(AA$165:AA$198)+SUM(AA$204:AA$237))) -> 0 | AG159: {=SUM(IF(Period=AG$4,IF(Category=$A$125,IF(Provider=$B159,Score))))} -> 100 | AI159: {=SUM(IF(Period=AG$4,IF(Category=$A$125,IF(Provider=$B159,Responses))))} -> 1 | AK159: =AG159*(AI159/SUM(AI$126:AI$159)) -> 0.38910506 | AM159: =AG159*(AI159/(SUM(AI$9:AI$42)+SUM(AI$48:AI$81)+SUM(AI$87:AI$120)+SUM(AI$126:AI$159)+SUM(AI$165:AI$198)+SUM(AI$204:AI$237))) -> 0.064766839 | AO159: {=SUM(IF(Period=AO$4,IF(Category=$A$125,IF(Provider=$B159,Score))))} -> 0 | AQ159: {=SUM(IF(Period=AO$4,IF(Category=$A$125,IF(Provider=$B159,Responses))))} -> 0 | AS159: =AO159*(AQ159/SUM(AQ$126:AQ$159)) -> 0 | AU159: =AO159*(AQ159/(SUM(AQ$9:AQ$42)+SUM(AQ$48:AQ$81)+SUM(AQ$87:AQ$120)+SUM(AQ$126:AQ$159)+SUM(AQ$165:AQ$198)+SUM(AQ$204:AQ$237))) -> 0 | AW159: {=SUM(IF(Period=AW$4,IF(Category=$A$125,IF(Provider=$B159,Score))))} -> 0 | AY159: {=SUM(IF(Period=AW$4,IF(Category=$A$125,IF(Provider=$B159,Responses))))} -> 0 | BA159: =AW159*(AY159/SUM(AY$126:AY$159)) -> 0 | BC159: =AW159*(AY159/(SUM(AY$9:AY$42)+SUM(AY$48:AY$81)+SUM(AY$87:AY$120)+SUM(AY$126:AY$159)+SUM(AY$165:AY$198)+SUM(AY$204:AY$237))) -> 0 | BE159: {=SUM(IF(Period=BE$4,IF(Category=$A$125,IF(Provider=$B159,Score))))} -> 0 | BG159: {=SUM(IF(Period=BE$4,IF(Category=$A$125,IF(Provider=$B159,Responses))))} -> 0 | BI159: =BE159*(BG159/SUM(BG$126:BG$159)) -> 0 | BK159: =BE159*(BG159/(SUM(BG$9:BG$42)+SUM(BG$48:BG$81)+SUM(BG$87:BG$120)+SUM(BG$126:BG$159)+SUM(BG$165:BG$198)+SUM(BG$204:BG$237))) -> 0 | BM159: {=SUM(IF(Period=BM$4,IF(Category=$A$125,IF(Provider=$B159,Score))))} -> 0 | BO159: {=SUM(IF(Period=BM$4,IF(Category=$A$125,IF(Provider=$B159,Responses))))} -> 0 | BQ159: =BM159*(BO159/SUM(BO$126:BO$159)) -> 0 | BS159: =BM159*(BO159/(SUM(BO$9:BO$42)+SUM(BO$48:BO$81)+SUM(BO$87:BO$120)+SUM(BO$126:BO$159)+SUM(BO$165:BO$198)+SUM(BO$204:BO$237))) -> 0 | BU159: {=SUM(IF(Period=BU$4,IF(Category=$A$125,IF(Provider=$B159,Score))))} -> 0 | BW159: {=SUM(IF(Period=BU$4,IF(Category=$A$125,IF(Provider=$B159,Responses))))} -> 0 | BY159: =BU159*(BW159/SUM(BW$126:BW$159)) -> 0 | CA159: =BU159*(BW159/(SUM(BW$9:BW$42)+SUM(BW$48:BW$81)+SUM(BW$87:BW$120)+SUM(BW$126:BW$159)+SUM(BW$165:BW$198)+SUM(BW$204:BW$237))) -> 0
B160: Average for Category: | C160: 0 | E160: 0 | G160: 0 | I160: =SUM(M126:M159) -> 78.476238 | K160: =AVERAGEIF(K126:K159,"<>0") -> 6.3125 | Q160: =SUM(U126:U159) -> 81.55508 | S160: =AVERAGEIF(S126:S159,"<>0") -> 6.2333333 | Y160: =SUM(AC126:AC159) -> 82.515842 | AA160: =AVERAGEIF(AA126:AA159,"<>0") -> 9.7741935 | AG160: =SUM(AK126:AK159) -> 86.577432 | AI160: =AVERAGEIF(AI126:AI159,"<>0") -> 7.7878788 | AO160: =SUM(AS126:AS159) -> 83.045029 | AQ160: =AVERAGEIF(AQ126:AQ159,"<>0") -> 5.7 | AW160: =SUM(BA126:BA159) -> 85.945161 | AY160: =AVERAGEIF(AY126:AY159,"<>0") -> 6.78125 | BE160: =SUM(BI126:BI159) -> 85.377966 | BG160: =AVERAGEIF(BG126:BG159,"<>0") -> 7.6129032 | BM160: =SUM(BQ126:BQ159) -> 88.262931 | BO160: =AVERAGEIF(BO126:BO159,"<>0") -> 7.25 | BU160: =SUM(BY126:BY159) -> 85.590871 | BW160: =AVERAGEIF(BW126:BW159,"<>0") -> 7.53125
B161: Median Values: | I161: {=MEDIAN(IF(I126:I159<>0,I126:I159))} -> 84.15 | K161: {=MEDIAN(IF(K126:K159<>0,K126:K159))} -> 6.5 | Q161: {=MEDIAN(IF(Q126:Q159<>0,Q126:Q159))} -> 86.8 | S161: {=MEDIAN(IF(S126:S159<>0,S126:S159))} -> 6 | Y161: {=MEDIAN(IF(Y126:Y159<>0,Y126:Y159))} -> 84.7 | AA161: {=MEDIAN(IF(AA126:AA159<>0,AA126:AA159))} -> 9 | AG161: {=MEDIAN(IF(AG126:AG159<>0,AG126:AG159))} -> 89.7 | AI161: {=MEDIAN(IF(AI126:AI159<>0,AI126:AI159))} -> 8 | AO161: {=MEDIAN(IF(AO126:AO159<>0,AO126:AO159))} -> 87.5 | AQ161: {=MEDIAN(IF(AQ126:AQ159<>0,AQ126:AQ159))} -> 5 | AW161: {=MEDIAN(IF(AW126:AW159<>0,AW126:AW159))} -> 85.35 | AY161: {=MEDIAN(IF(AY126:AY159<>0,AY126:AY159))} -> 6 | BE161: {=MEDIAN(IF(BE126:BE159<>0,BE126:BE159))} -> 87.5 | BG161: {=MEDIAN(IF(BG126:BG159<>0,BG126:BG159))} -> 8 | BM161: {=MEDIAN(IF(BM126:BM159<>0,BM126:BM159))} -> 88.4 | BO161: {=MEDIAN(IF(BO126:BO159<>0,BO126:BO159))} -> 7 | BU161: {=MEDIAN(IF(BU126:BU159<>0,BU126:BU159))} -> 86.05 | BW161: {=MEDIAN(IF(BW126:BW159<>0,BW126:BW159))} -> 7
B162: Subtotal n: | K162: =SUM(K126:K159) -> 202 | S162: =SUM(S126:S159) -> 187 | AA162: =SUM(AA126:AA159) -> 303 | AI162: =SUM(AI126:AI159) -> 257 | AQ162: =SUM(AQ126:AQ159) -> 171 | AY162: =SUM(AY126:AY159) -> 217 | BG162: =SUM(BG126:BG159) -> 236 | BO162: =SUM(BO126:BO159) -> 232 | BW162: =SUM(BW126:BW159) -> 241
A164: Std Doctors
